[
  {
    "url": "https://jobs.af/jobs/full-stack-developer-4M5yN57sq",
    "title": "Full Stack Developer",
    "company": null,
    "location": "Kabul",
    "closing_date": "2026-01-21",
    "closing_date_raw": "Jan 21, 2026",
    "apply_url": null,
    "description": "๐\nComing Soon The Jobs.af Freelancer Portal\nConnect with top clients and freelancers across Afghanistan all in one place!\nStay Tuned\nJobs\nProcurement Opportunities\nCompanies\nFreelancers\nServices\nProcurement Opportunities\nTrainings\nScholarships\nLogin\nRegister\nFull Stack Developer\nBaheer Group (BG)\nApply Now\nSee all jobs\nFull Stack Developer\nBaheer Group (BG),\n                                        Kabul, Afghanistan\nApply Now\nBachelor's Degree\nKabul, Afghanistan\n(Kabul)\nFull Time\n1712\nAbout\n                                            Baheer Group (BG)\nBaheer Group (BG) is a prominent manufacturer and provider of high-quality papers and paper products, offering premium solutions in Papers, Packaging, Printing, Mines & Energy, and supplying state-of-the-art Printing Machineries. Our commitment to excellence is reflected in our diversified portfolio, which caters to both domestic and international markets. Backed by an extensive Group of Companies, BG consistently surpasses industry standards, specializing in customized products tailored to meet the unique needs of our clients.\nJob Summary\nWe are seeking an experienced Full stack developer to join our team. This role is suited for a developer who has worked on production systems, understands modern development workflows, and can contribute effectively to both backend and frontend development in a professional environment.\nThe ideal candidate is comfortable working with established systems, writing high-quality code, and collaborating with other engineers to deliver reliable and scalable software solutions.\nDuties & Responsibilities\nDesign, develop, and maintain web applications using Laravel on the backend and React (TypeScript, React Query) on the frontend\nBuild and maintain clean, scalable, and maintainable backend services and APIs\nDevelop user-facing features using modern frontend practices\nCollaborate with cross-functional teams to translate business requirements into technical solutions\nReview code, provide constructive feedback, and help maintain high engineering standards\nOptimize application performance, database queries, and system reliability\nWork with Git and GitHub in a collaborative, team-based workflow\nUse Docker for development, testing, and deployment environments\nParticipate in system improvements, refactoring, and technical decision-making\nContribute to documentation and technical knowledge sharing\nJob Requirements\nStrong professional experience with Laravel (PHP) in production environments\nSolid experience with React.js, TypeScript and modern JavaScript development\nStrong knowledge of HTML, CSS, and JavaScript\nExperience designing and consuming RESTful APIs\nGood understanding of relational databases (MySQL, PostgreSQL, or similar)\nProficiency with Git and GitHub (branching strategies, pull requests, code reviews)\nPractical experience using Docker in real projects\nAbility to write clean, readable, and well-structured code\nExperience working in a collaborative, professional software team\nStrong problem-solving skills and attention to detail\nSubmission Guideline\nBaheer Group is an excellent place to grow your career. Don't hesitate to apply. the vacant position.\nPlease note only short-listed candidates will be contacted for an interview.\nMeanwhile: send a copy of your application to the below email while applying\nvp@baheer.af\nFunctional Area\nComputer Science\nCountries\nAfghanistan\nProvinces\nKabul\nSubmission Email\nvp@baheer.af\nApply Now\nPost Date\nDec 21, 2025\nClosing Date\nJan 21, 2026\nReference\nBG25-054\nNumber of Vacancies\n1\nSalary Range\nSalary is negotiable\nYears of Experience\n3 - 4 years\nProbation Period\n3 month\nContract Type\nPermanent\nContract Duration\n1 year\nContract Extensible\nYes\nMinimum Education\nBachelor's Degree\nGender\nMale\nRelated Jobs\nNETLINKS Plaza | Shahr-e-Naw,\nLane 3, Kabul, Afghanistan\nQuick Links\nAbout Us\nAdvertise with Us\nPrivacy Policy\nFor Companies\nPost a Job\nPost a Job\nPost a Job\nPost a Job\nPost RFP\nPost RFP\nPost RFP\nPost RFP\nPost Training\nPost Training\nPost Training\nPost Training\nFor Jobseekers\nBrowse Jobs\nBrowse Companies\nBuild Resume\nContact\ninfo@jobs.af\nContact Us\nยฉ 2012 - 2026 Jobs.af | All Rights Reserved\nPowered by:\nNETLINKS Ltd",
    "details": {
      "Post Date": "Dec 21, 2025",
      "Closing Date": "Jan 21, 2026",
      "Reference": "BG25-054",
      "Number Of Vacancies": "1",
      "Salary Range": "Salary is negotiable",
      "Years Of Experience": "3 - 4 years",
      "Probation Period": "3 month",
      "Contract Type": "Permanent",
      "Contract Duration": "1 year",
      "Contract Extensible": "Yes",
      "Minimum Education": "Bachelor's Degree",
      "Meanwhile": "send a copy of your application to the below email while applying",
      "Functional Area": "Computer Science",
      "Countries": "Afghanistan",
      "Provinces": "Kabul"
    },
    "scraped_at": "2026-01-21T05:00:22Z",
    "apply_emails": [
      "vp@baheer.af"
    ],
    "apply_method": "email"
  },
  {
    "url": "https://jobs.af/jobs/mdyr-ahsaeyh-w-dytabys-jwaz-ha-ryast-tjarty",
    "title": "ูุฏุฑุช ุงุญุตุงุฆู ู ุฏุชุงุจุณ ุฌูุงุฒ ูุงุ ุฑุงุณุช ุชุฌุงุฑุช",
    "company": null,
    "location": "Kabul",
    "closing_date": "2026-01-21",
    "closing_date_raw": "Jan 21, 2026",
    "apply_url": null,
    "description": "๐\nComing Soon The Jobs.af Freelancer Portal\nConnect with top clients and freelancers across Afghanistan all in one place!\nStay Tuned\nJobs\nProcurement Opportunities\nCompanies\nFreelancers\nServices\nProcurement Opportunities\nTrainings\nScholarships\nLogin\nRegister\nูุฏุฑุช ุงุญุตุงุฆู ู ุฏุชุงุจุณ ุฌูุงุฒ ูุงุ ุฑุงุณุช ุชุฌุงุฑุช\nAfghanistan Oil and Gas Sate-Owned Corporation (AOGC) ุดุฑฺฉุช ุงูุงุฑุช ููุช ู ฺฏุงุฒ ุงูุบุงูุณุชุงู\nApply Now\nSee all jobs\nูุฏุฑุช ุงุญุตุงุฆู ู ุฏุชุงุจุณ ุฌูุงุฒ ูุงุ ุฑุงุณุช ุชุฌุงุฑุช\nAfghanistan Oil and Gas Sate-Owned Corporation (AOGC) ุดุฑฺฉุช ุงูุงุฑุช ููุช ู ฺฏุงุฒ ุงูุบุงูุณุชุงู,\n                                        Kabul, Afghanistan\nApply Now\nBachelor's Degree\nKabul, Afghanistan\n(Kabul)\nFull Time\n919\n68\nAbout\n                                            Afghanistan Oil and Gas Sate-Owned Corporation (AOGC) ุดุฑฺฉุช ุงูุงุฑุช ููุช ู ฺฏุงุฒ ุงูุบุงูุณุชุงู\nุฏ ุงูุบุงูุณุชุงู ููุช ุงู ฺซุงุฒ ุงูุงุฑุช ุดุฑฺฉุช ููฺู ูพูฺูุฏูู :\nุฏ ุงูุบุงูุณุชุงู ููุช ุงู ฺซุงุฒ ุงูุงุฑุช ุดุฑฺฉุช ุฏ ูููฺู ฺู ููพุงุฑู ูพู ฑณณฐ ููุฑุฒ ฺฉุงู ฺฉ ุฏ ุฏููุช ุงูุญุตุงุฑุงุชู ุชุฑ ุนููุงู ูุงูุฏ ุฏ ููุชู ุฏ ุณฺฉุชูุฑ ุงฺููุฏู ฺฉฺูู ุฏ ูุฏุฑุช ุงู ฺุงุฑู ูพู ููุฎู ุชุงุณุณ ุดู. ุฏ ุงุฏ ุดุฑฺฉุช ุญูููู ุดุฎุตุช ุฏ ฺฉูููู ูพู ุงูฺุฏู ฺฉ ุฏ ูุฎุช ุฏ ุบูฺุชูู ูพู ูพุงู ฺฉ ูููู ุณุฑู ฺู ฺู ุจุฏููู ฺฉฺ ฺ ุจูุง ุขุฎุฑู ูพู ฑณนธ ููุฑุฒ ฺฉุงู ฺฉ ุฏ ุงุฏ ุดุฑฺฉุช ุญูููู ุดุฎุตุช ูู ุชุตุฏ ฺุฎู ุดุฑฺฉุช ุชู ุจุฏููู ููููุฏ. ุฏ ุงูุบุงูุณุชุงู ููุช ุงู ฺซุงุฒ ุฏููุช ุดุฑฺฉุช ุฏ ุชูู ุงู ฺซุงุฒู ุฏ ูพุฑุ ูพููุฑุ ุฐุฎุฑู ฺฉููู ุงู ุฏ ุชูู ุงู ฺซุงุฒู ุฏ ฺฉูุชุ ฺฉูุชุ ุงู ููุช ุฏ ฺุงุฑู ุงู ุฎุตูุตู ุณฺฉุชูุฑ ุชู ุฏ ุฎุฏูุชููู ุฏ ูฺุงูุฏ ฺฉููู ูพู ุจุฑุฎู ฺฉ ฺฉฺู ุชุฑุณุฑู ฺฉูู.\nJob Summary\nุทุฑุญ ู ุงูฺฉุดุงู ุฏุชุงุจุณ ุฌุงูุน ุงุฒ ุฌูุงุฒ ูุง ุจุฑ ุงุณุงุณ ูุงุฒููุฏ ุดุฑฺฉุช ู ุงุชุฎุงุฐ ุงูุฏุงูุงุช ูุงุฒู ุฏุฑ ุฒููู ู ุญูุธ ู ูฺฏูุฏุงุดุช ุขู.\nDuties & Responsibilities\nยทยุชุฑุชุจ ูพูุงู ฺฉุงุฑ ูุงููุงุฑุ ุฑุจุนูุงุฑ ู ุณุงูุงูู ุฏุฑ ูุทุงุจูุช ุจุง ูพูุงู ุขูุฑุช ูุฑุจูุทู ุฌูุช ุฑุณุฏู ุจู ุงูุฏุงู ุชุนู ุดุฏู ุงุฏุงุฑู\nยทยุจุฑุฑุณ ู ุชุญูู ูุงุฒ ูุง ุงุทูุงุนุงุช ูุฑุชุจุท ุจุง ุฌูุงุฒุฏู\nยทยุทุฑุญ ู ุงูฺฉุดุงู ุฏุชุงุจุณ ุงฺฉุณู ุฌูุงุฒ ูุง ูุทุงุจู ุจุง ูุงุฒููุฏ ูุง ุดุฑฺฉุช ุฏููุช ููุช ู ฺฏุงุฒ ุงูุบุงูุณุชุงู\nยทยุงุฑุฒุงุจ ฺฉูุช ู ุตุญุช ุฏุงุฏู ูุง ููุฌูุฏ ุฏุฑ ุฏุชุงุจุณ ู ฺฉุณุจ ุงุทููุงู ุงุฒ ุฏุฑ ุฏุณุชุฑุณ ุจูุฏู ุขู ุฏุฑ ููุงูุน ูุงุฒ\nยทยุงุฑุงุฆู ุขูุงุฑ ู ุงุทูุงุนุงุช ูุฑุชุจุท ุจู ุฌูุงุฒ ูุง ุจุฑุง ูุฏุฑุงู ู ุขูุฑู ูุงููู\nยทยุจุฑุฑุณ ู ุงุฌุฑุง ุงูุฏุงูุงุช ูุงุฒู ุจุฑุง ุจูุจูุฏ ฺฉูุช ู ุนููฺฉุฑุฏ ุฏุชุงุจุณ\nยทยุงุชุฎุงุฐ ุงูุฏุงูุงุช ูุงุฒู ุฏุฑ ุฌูุช ุญูุธ ู ูฺฏูุฏุงุฑ (ุจฺฉ ุขูพ ฺฏุฑ) ุงุฒ ุฏุชุงุจุณ ุฌูุงุฒ ูุง\nยทยุชุงูู ุฑูุงุจุท ฺฉุงุฑ ุจุง ููุงูุฏฺฏ ูุง ูุฑุจูุท ุฌูุช ุจุฑูุฒ ุฑุณุงู ุฏุชุงุจุณ\nยทยุขููุฒุด ู ุงุฑุชูุงุก ุฏุงูุด ฺฉุงุฑฺฉูุงู ุฏุฑ ุฒููู ุงุณุชูุงุฏู ุงุฒ ุฏุชุงุจุณ ุฌูุงุฒ ูุง\nยทยุงุฑุฒุงุจ ุฎุทุฑุงุช ู ุงุฌุฑุง ุงูุฏุงูุงุช ูุงุฒู ุจุฑุง ุญูุงุธุช ุงุฒ ุฏุงุฏู ูุง ู ุงุฑุงุฆู ูพุดููุงุฏุงุช ุณุงุฒูุฏู ุฏุฑ ุฒููู ุจูุจูุฏ ุฏุชุงุจุณ\nยทยูพุดููุงุฏ ู ุงุฌุฑุง ุชุบุฑุงุช ู ุจูุจูุฏ ูุง ูุงุฒู ุฏุฑ ุฏุชุงุจุณ ุฌูุงุฒุฏู ุชุงูฺฉ ูุง ุชู\nยทยุชุฑุชุจ ูฺฉุงุชุจุ ูพุดููุงุฏุงุชุ ุงุณุชุนูุงูู ูุง ู ุณุงุฑ ุงุณูุงุฏ ูุฏุฑุช ุฌูุช ุชุณุฑุน ุฑููุฏ ุงุฌุฑุงุขุช ฺฉุงุฑ\nยทยุชุฑุชุจ ู ุงุฑุงุฆู ฺฏุฒุงุฑุดุงุช ูุงููุงุฑุ ุฑุจุนูุงุฑุ ุณุงูุงูู ุงุฒ ูุนุงูุช ูุง ู ุฏุณุช ุขูุฑุฏ ูุง ุจู ูุฏุฑ ูุฑุจูุทู\nยทยุงุฌุฑุง ุณุงุฑ ูุธุงู ฺฉู ุชูุณุท ุขูุฑ ูุฑุจูุทู ูุทุงุจู ููุงููุ ููุฑุฑุงุช ู ุงูุฏุงู ุดุฑฺฉุช ุจู ู ุณูพุฑุฏู ู ุดูุฏ\nJob Requirements\nยทยุฏุงุดุชู ุณูุฏ ุชุญุตู ุญุฏ ุงูู ูุณุงูุณ ุฏุฑ ุฑุดุชู ูุง ุงุญุตุงุฆูุ ุชฺฉูุงููฺ ูุนูููุงุชุ ฺฉููพูุชุฑ ุณุงูุณ ู ุง ุณุงุฑ ุฑุดุชู ูุง ูุฑุชุจุท ุจู ูุธูู\nยทยุฏุงุดุชู ุญุฏ ุงูู 1 ุณุงู ุชุฌุฑุจู ฺฉุงุฑ ูุฑุชุจุท ุจู ูุธูู - ุญุงุฒ ุณูุฏ ุชุญุตู ูุงุณุชุฑ ู ุฏูฺฉุชูุฑุง ุงุฒ ุงู ุญฺฉู ูุณุชุซู ู ุจุงุดุฏ\nยทยุฏุงุดุชู ููู ุงููุงู ู ุชููู ูุฏุฑุช ฺฉุงุฑ\nยทยุชูุงูุง ุงุฌุงุฏ ุงุจุชฺฉุงุฑ ู ุฎูุงูุช ุฏุฑ ุฑูุด ูุง ฺฉุงุฑ\nยทยุงูุนุทุงู ูพุฐุฑ ฺฉุงุฑ ู ุงูููุช ุจูุฏ ฺฉุงุฑ ูุง ุฏุฑ ุดุฑุงุท ุฏุดูุงุฑ\nยทยุณุฑุนุช ฺฉุงุฑ ุฏุฑ ฺฏุฒุงุฑุด ฺฏุฑ ู ฺฏุฒุงุฑุด ุฏู\nยทยุชุณูุท ุจู ฺฉ ุงุฒ ุฒุจุงููุง ูุง ุฑุณู(ุฏุฑ ุง ูพุดุชู) ู ุขุดูุง( ุชุญุฑุฑ ู ุชฺฉูู) ุจุง ุฒุจุงู ุงูฺฏูุณ\nยทยุขุดูุง ุจุง ุจุฑูุงููุง ฺฉููพูุชุฑ ูุฑุชุจุท ุจู ูุธูู\nยทยุชูุงูุง ฺฉุงุฑ ุจุดฺฉู ูุฑุฏ ู ุฌูุน\nSubmission Guideline\nุฑูููุง ุซุจุช ูุงู ูุชูุงุถุงู:\nูุชูุงุถุงู ูุญุชุฑู ุจุฑุง ุซุจุช ูุงู ุฑู ฺฏุฒูู apply now ฺฉูฺฉ ูููุฏู ูุนูููุงุช ุฎูุด ุฑุง ุงุฑุณุงู ุจุฏุงุฑูุฏ.\nุฏุฑุฌุฑุงู ุซุจุช ูุงู ููุงุฑุฏ ุฐู ุฑุง ุฏุฑ ูุธุฑ ุฏุงุดุชู ุจุงุดูุฏ:\n๏ผ. ุชูุงู ูุนูููุงุช ุฎูุด ุฑุง ุฏูู ุจุฑูุช ุงุณูุงุฏ ุฏุฑุฌ ููุงูุฏ ุฏุฑ ุตูุฑุช ูุงุฏุฑุณุช ุจูุฏู ูุนูููุงุช ุฏุฑุฌ ุดุฏู ูุชูุงุถ ุงุฒ ูพุฑูุณู\nุญุฐู ูฺฏุฑุฏุฏ.\n2. ฺฉ ูุฑุฏ ุตุฑู ฺฉุจุงุฑ ุซุจุช ูุงู ฺฉุฑุฏู ูุชูุงูุฏ.\n3. ุฏุฑ ูุณูุช ุฏุฑุฌ ุนููุงู ุจุณุช ู ฺฉูุฏ ุจุณุช ุฏูุช ูุงุฒู ููุงุฆุฏ.\nุขุฏุฑุณ: ุฑุงุณุช ุนููู ุดุฑฺฉุช ุงูุงุฑุช ููุช ู ฺฏุงุฒ ุงูุบุงูุณุชุงู ูุงูุน ฺฉูุชู ุฎุฑุฎุงูู ุฌูุงุฑ ูุงุญู ููุฏููุ ฺฉุงุจู- ุงูุบุงูุณุชุงู ุฏุฑุตูุฑุช ุถุฑูุฑุช ุจู ุดูุงุฑู ุฐู ุชูุงุณ ฺฏุฑูุชู ูุชูุงูุฏ:ยฐทดททททตทฐ\nููุช: ุชููุง ุจุฑุง ฺฉุงูุฏุฏุงู ุชูุงุณ ฺฏุฑูุชู ูุดูุฏ ฺฉู ุฏุฑ ุจุณุช ูุชุฐฺฉุฑู ุดุงุฑุช ูุณุช ฺฏุฑุฏูุฏ.\nุงูุชุญุงู ุจุณุช ูุชุฐฺฉุฑู ุฏูุชุฑ ูุฑฺฉุฒ ุฑุงุณุช ุนููู ุดุฑฺฉุช ุงูุงุฑุช ููุช ู ฺฏุงุฒ ุงูุบุงูุณุชุงู ุงุฎุฐ ูฺฏุฑุฏุฏ.\nFunctional Area\nStatistics\nInformation Technology\nComputer Science\nCountries\nAfghanistan\nProvinces\nKabul\nApply Now\nPost Date\nJan 07, 2026\nClosing Date\nJan 21, 2026\nReference\n0181-1403\nNumber of Vacancies\n1\nSalary Range\nAs per company salary scale\nYears of Experience\n1 year\nProbation Period\n3 month\nContract Type\nPermanent\nContract Duration\nNot specified\nContract Extensible\nYes\nMinimum Education\nBachelor's Degree\nGender\nMale\nRelated Jobs\nNETLINKS Plaza | Shahr-e-Naw,\nLane 3, Kabul, Afghanistan\nQuick Links\nAbout Us\nAdvertise with Us\nPrivacy Policy\nFor Companies\nPost a Job\nPost a Job\nPost a Job\nPost a Job\nPost RFP\nPost RFP\nPost RFP\nPost RFP\nPost Training\nPost Training\nPost Training\nPost Training\nFor Jobseekers\nBrowse Jobs\nBrowse Companies\nBuild Resume\nContact\ninfo@jobs.af\nContact Us\nยฉ 2012 - 2026 Jobs.af | All Rights Reserved\nPowered by:\nNETLINKS Ltd",
    "details": {
      "Post Date": "Jan 07, 2026",
      "Closing Date": "Jan 21, 2026",
      "Reference": "0181-1403",
      "Number Of Vacancies": "1",
      "Salary Range": "As per company salary scale",
      "Years Of Experience": "1 year",
      "Probation Period": "3 month",
      "Contract Type": "Permanent",
      "Contract Duration": "Not specified",
      "Contract Extensible": "Yes",
      "Minimum Education": "Bachelor's Degree",
      "ุขุฏุฑุณ": "ุฑุงุณุช ุนููู ุดุฑฺฉุช ุงูุงุฑุช ููุช ู ฺฏุงุฒ ุงูุบุงูุณุชุงู ูุงูุน ฺฉูุชู ุฎุฑุฎุงูู ุฌูุงุฑ ูุงุญู ููุฏููุ ฺฉุงุจู- ุงูุบุงูุณุชุงู ุฏุฑุตูุฑุช ุถุฑูุฑุช ุจู ุดูุงุฑู ุฐู ุชูุงุณ ฺฏุฑูุชู ูุชูุงูุฏ:ยฐทดททททตทฐ",
      "ููุช": "ุชููุง ุจุฑุง ฺฉุงูุฏุฏุงู ุชูุงุณ ฺฏุฑูุชู ูุดูุฏ ฺฉู ุฏุฑ ุจุณุช ูุชุฐฺฉุฑู ุดุงุฑุช ูุณุช ฺฏุฑุฏูุฏ.",
      "Functional Area": "Statistics",
      "Countries": "Afghanistan",
      "Provinces": "Kabul"
    },
    "scraped_at": "2026-01-21T05:00:22Z",
    "apply_emails": [],
    "apply_method": "unknown"
  },
  {
    "url": "https://jobs.af/jobs/ran-back-office-engineer-huawei-otzPc0NUs",
    "title": "RAN Back Office Engineer ( Huawei)",
    "company": null,
    "location": "Kabul",
    "closing_date": "2026-01-22",
    "closing_date_raw": "Jan 22, 2026",
    "apply_url": null,
    "description": "๐\nComing Soon The Jobs.af Freelancer Portal\nConnect with top clients and freelancers across Afghanistan all in one place!\nStay Tuned\nJobs\nProcurement Opportunities\nCompanies\nFreelancers\nServices\nProcurement Opportunities\nTrainings\nScholarships\nLogin\nRegister\nRAN Back Office Engineer ( Huawei)\nI Engineering Group\nApply Now\nSee all jobs\nRAN Back Office Engineer ( Huawei)\nI Engineering Group,\n                                        Kabul, Afghanistan\nApply Now\nBachelor's Degree\nKabul, Afghanistan\n(Kabul)\nFull Time\n1362\nAbout\n                                            I Engineering Group\nieng Group provides EPC and O&M infrastructure services with a focus on the telecom and power industries. The Group's subsidiaries Eki.Struct (tower) and GreenPole (power), along with its affiliated asset management company CREI complement the functions provided by ieng.\nEstablished in 2007, the Group is a leading provider of telecom infrastructure and managed services in Africa and Emerging Markets.\nWe have grown rapidly since our inception in 2007 and are now operational in 19 countries: Afghanistan, Algeria, Cameroon, Central African Republic, Chad, DR Congo, Ethiopia, Ghana, Guinea, Kenya, KSA, Lebanon, Liberia, Myanmar, Nigeria, Pakistan, Philippines, South Sudan and Uganda.\nToday, we maintain over 31,200+ sites for Africaโs largest MNOs and all TowerCos.\nOur vision\nTo become the leading Engineering Procurement and Construction (EPC) and Operation and Maintenance (O&M) contractor in global emerging markets.\n๏ปฟOur Mission\nWe provide EPC and O&M services to the telecom, renewable energy and construction industries in global emerging markets, seamlessly integrating our core competencies with our customersโ businesses, so they benefit from competitive and comprehensive solutions.\nJob Summary\nieng Afghanistan is seeking highly skilled Huawei experts for RAN to join our team. The ideal candidate must have extensive experience with Huawei networks and equipment. This role involves leading network swap, network planning, optimization, troubleshooting, and maintenance efforts to ensure the highest performance and reliability of network.\nAttractive package will be offered\nDuties & Responsibilities\nยทยยยยยยยProvide Analysis and monitoring Network performance by Checking Key Quality Indicators (KQI's)\nยทยยยยยยยMonitor and demarcating service degradation (Voice and Data) by checking performance of the network nodes\nยทยยยยยยยKnowledge of performance counters of RAN and Core KPIโs to make sure that all necessary counters are activated for daily, weekly, monthly and critical outages.\nยทยยยยยยยUsing Big Data analytics to provide trend analysis for KQI/KPI and provide suggestions and solution on performance improvement\nยทยยยยยยยCustomer proactive support using signaling call flows and big data analytics to improve Customer experience.\nยทยยยยยยยInvestigate and analyze individual User complaints for \" CS and PS\" services, international link's (link utilization, call performance)\nยทยยยยยยยMapping between KPI's & KQI's that's related to worst cell/Site/Node analysis to assist relevant team in improving network performance.\nยทยยยยยยยDetect value added cases by analyzing which KPI affect services.\nยทยยยยยยยReviewing and making guidelines for network performance and people management.\nยทยยยยยยยManaging day-to-day Network KPIs and performed required analysis to improve the service delivery\nยทยยยยยยยReview of various reports (Site outage report, KPI reports, Daily CR report, Pending Outage Reports).\nยทยยยยยยยChecking and reviewing of the KPIs and SLA of the TTโs created by Monitoring team.\nยทยยยยยยยTechnical review of the work orders change request which are impacting the NOC monitoring.\nยทยยยยยยยProviding post incident report and Root cause analysis for Major and Critical Incidents and User complaints.\nยทยยยยยยยExpert knowledge of U2020, BSC, RNC, 2G, 3G, LTE/5G technologies and Huawei RAN solutions.\nยทยยยยยยEmpower local RAN team to do complex task and train them daily, weekly and monthly basis.\nยทยยยยยยยProven experience in leading large-scale RAN projects and optimization initiatives.\nยทยยยยยยNetwork deployment and implementation to oversee installation and configuration of RAN components and ensure equipment is step according design and standards.\nยทยยยยCapacity Management to assess network traffic and make sure that each interface has enough capacity to handle peak hours traffic.\nยทยยยยTrouble shooting and Problem Resolution to analyze problem, degradation and other RAN KPIs.\nยทยยยยยUse available or third partiesโ or specialized software tools for network analysis and trouble shooting.\nยทยยยยTechnology Upgrades and Updates, Ability to migrate from vendor to Vendor and advance wireless technology.\nOH&S/QMS Role and Responsibilities:\nReports any hazards or risks in addition to Accidents/Incident to QHSE department.\nBe aware of and complies to i engineeringโs IMS Policy.\nAbides by i engineeringโs Local Legal and Client Requirements.\nAttends and engages in IMS Awareness Sessions.\nEnsures that all IMS procedures are regularly followed and raises the issue when they are not\nJob Requirements\nยทยยยยยยยMinimum 5 years of experience.\nยทยยยยยยยBSc. in /Electrical/IT, Telecom Engineering/Computer Engineering\nยทยยยยยยยExcellent presentation skills.\nยทยยยยยยยMust have strong telecom skills and knowledge of common programs such as Microsoft Office.\nยทยยยยยยยAbility to work under pressure.\n๏ปฟ๏ปฟ๏ปฟ๏ปฟ\nยทยยยยยยยStrong analytical skills with the ability to interpret complex data and make data-driven decisions.\nยทยยยยยยยExcellent communication, presentation, and client-facing abilities.\nSubmission Guideline\nPlease ensure to write the position title and vacancy number in the subject line of your email, and send your CV along with a cover letter. Only shortlisted candidates will be notified.\nFunctional Area\nElectrical Engineering\nCommunication\nInformation Technology\nComputer Science\nTelecome Engineering\nTelecommunication\nCountries\nAfghanistan\nProvinces\nKabul\nSubmission Email\nfanosha@ieng-group.com\nApply Now\nPost Date\nJan 08, 2026\nClosing Date\nJan 22, 2026\nReference\nIeng-RAN-BO-001\nNumber of Vacancies\n1\nSalary Range\nAs per company salary scale\nYears of Experience\n4 - 5 years\nProbation Period\nNot Specified\nContract Type\nLong-term\nContract Duration\nNot specified\nContract Extensible\nYes\nMinimum Education\nBachelor's Degree\nGender\nMale\nRelated Jobs\nNETLINKS Plaza | Shahr-e-Naw,\nLane 3, Kabul, Afghanistan\nQuick Links\nAbout Us\nAdvertise with Us\nPrivacy Policy\nFor Companies\nPost a Job\nPost a Job\nPost a Job\nPost a Job\nPost RFP\nPost RFP\nPost RFP\nPost RFP\nPost Training\nPost Training\nPost Training\nPost Training\nFor Jobseekers\nBrowse Jobs\nBrowse Companies\nBuild Resume\nContact\ninfo@jobs.af\nContact Us\nยฉ 2012 - 2026 Jobs.af | All Rights Reserved\nPowered by:\nNETLINKS Ltd",
    "details": {
      "Post Date": "Jan 08, 2026",
      "Closing Date": "Jan 22, 2026",
      "Reference": "Ieng-RAN-BO-001",
      "Number Of Vacancies": "1",
      "Salary Range": "As per company salary scale",
      "Years Of Experience": "4 - 5 years",
      "Probation Period": "Not Specified",
      "Contract Type": "Long-term",
      "Contract Duration": "Not specified",
      "Contract Extensible": "Yes",
      "Minimum Education": "Bachelor's Degree",
      "Functional Area": "Electrical Engineering",
      "Countries": "Afghanistan",
      "Provinces": "Kabul"
    },
    "scraped_at": "2026-01-21T05:00:22Z",
    "apply_emails": [
      "fanosha@ieng-group.com"
    ],
    "apply_method": "email"
  },
  {
    "url": "https://jobs.af/jobs/aafysr-arshd-shbkh-shft-shb",
    "title": "ุขูุณุฑ ุงุฑุดุฏ ุดุจฺฉู ุดูุช ุดุจ",
    "company": null,
    "location": "Kabul",
    "closing_date": "2026-01-24",
    "closing_date_raw": "Jan 24, 2026",
    "apply_url": null,
    "description": "๐\nComing Soon The Jobs.af Freelancer Portal\nConnect with top clients and freelancers across Afghanistan all in one place!\nStay Tuned\nJobs\nProcurement Opportunities\nCompanies\nFreelancers\nServices\nProcurement Opportunities\nTrainings\nScholarships\nLogin\nRegister\nุขูุณุฑ ุงุฑุดุฏ ุดุจฺฉู ุดูุช ุดุจ\nDa Afghanistan Bank\nApply Now\nSee all jobs\nุขูุณุฑ ุงุฑุดุฏ ุดุจฺฉู ุดูุช ุดุจ\nDa Afghanistan Bank,\n                                        Kabul, Afghanistan\nApply Now\nBachelor's Degree\nKabul, Afghanistan\n(Kabul)\nFull Time\n4158\n210\nAbout\n                                            Da Afghanistan Bank\nุฏ ุงูุบุงูุณุชุงู ุจุงูฺฉ ูุฑุงุฑ ุชุตูุจ ุดูุงุฑู 152 ููุฑุฎ 3/2/1318 ูุฌูุณ ูุฒุฑุงุ ุชุตูุจ ุดูุงุฑู 11 ููุฑุฎ 19/6/1318 ุดูุฑุง ููุ ุชุตูุจ ุชุงุฑุฎ 12/6/1318 ูุฌูุณ ุงุนุงู ู ููุธูุฑ 5280/1317 ุชุงุฑุฎ 17/11/1318 ุญุถูุฑ ุดุงูุงูู ุจู ุณุฑูุงู ุงุจุชุฏุงุฆ ูุจูุบ ฺฉุตุฏ ู ุจุณุช ูููู ุงูุบุงู ุฏุฑ ูพุงุชุฎุช ฺฉุดูุฑ ุดูุฑ ฺฉุงุจู ุงูุชุชุงุญ ุดุฏ ฺฉู ุฏุฑ ุฏุงุฎู ู ุฎุงุฑุฌ ฺฉุดูุฑ ุจุง ุงุฎุชุงุฑุงุช ู ูุธุงู ูุงุฒู ูุชูุงูุณุช ููุงูุฏฺฏ ู ูุฑูุน ุฎูุฏ ุฑุง ุชุฃุณุณ ู ุจุงูฺฉูุง ุณฺฉุชูุฑ ุฑุง ุชุนู ููุงุฏ. ูุธุงู ุจุงูฺฉุฏุงุฑ ุงูุบุงูุณุชุงู ุจุง ุชุฃุณุณ ุจุงูฺฉ ูู ุงูุบุงู ุฏุฑ ุณุงู 1312 ูุฌุฑ ุดูุณ ูพุง ุจู ุนุฑุตู ูุฌูุฏ ฺฏุฐุงุดุช ู ูุจู ุงุฒ ุชุฃุณุณ ุฏ ุงูุบุงูุณุชุงู ุจุงูฺฉุ ุงููุฑ ุจุงูฺฉุฏุงุฑ ุฏููุช ุฑุง ุงู ุจุงูฺฉ ุจู ูพุด ูุจุฑุฏ. ุจุนุฏ ุงุฒ ุชุฃุณุณ ุฏ ุงูุบุงูุณุชุงู ุจุงูฺฉ ูุธุงู ุจุงูฺฉุฏุงุฑ ุฏููุช ุจู ุดููู ฺุงูพ ู ูุดุฑ ูพูู ุงูุบุงู ุจู ุงู ุจุงูฺฉ ููุชูู ฺฏุฑุฏุฏ. ุฏ ุงูุบุงูุณุชุงู ุจุงูฺฉ ุจุญุซ ุจุงูฺฉุฏุงุฑ ุฏููุช ู ุจุงูฺฉ ุชุฌุงุฑุช ุชูุงูุณุช ุชุญููุงุช ู ุงูฺฉุดุงูุงุช ฺุดูฺฏุฑ ู ุจุฒุฑฺฏ ุฑุง ูู ุฏุฑ ุฑุงุจุทู ุจู ฺุงูพ ู ูุดุฑ ูพูู ุงูุบุงู ุจู ูุฌูุฏ ุขูุฑุฏ ู ูู ุฏุฑ ุณูุช ู ุณู ูุธุงู ุจุงูฺฉ ุจู ุฏุณุชุงูุฑุฏ ูุง ูุงุฆู ฺฏุฑุฏุฏ. ูุนุงูุช ุฏ ุงูุบุงูุณุชุงู ุจุงูฺฉ ุฑุง ู ุชูุงู ุจู ุฏู ูุฑุญูู ุชูุณู ุจูุฏ ฺฉุฑุฏ: ุฏุฑ ูุฑุญูู ุงูู ฺฉู ุงุฒ ุณุงู 1318 ุงู ุณุงู 1380 ุฑุง ุงุญุชูุง ู ููุงุฏุ ุฏ ุงูุบุงูุณุชุงู ุจุงูฺฉ ุฏุฑ ูุณูุช ฺุงูพุ ุถุฑุจ ู ูุดุฑ ูพูู ุงูุบุงู ูุทุงุจู ุจู ุชูุงุถุง ุจุงุฒุงุฑุ ุญูุธ ุงุฑุฒุด ูพูู ู ุงููุฑ ุจุงูฺฉุฏุงุฑ ุฏููุช ูุตุฑูู ุจูุฏ ฺฉู ุฏุฑ ูพููู ุงู ูุธุงูุ ุงููุฑ ุชุฌุงุฑุช ุฑุง ูุฒ ุทุจู ูุนุงูุช ูุง ุณุงุฑ ุจุงูฺฉูุง ุชุฌุงุฑ ุงูุบุงูุณุชุงู ุงูุฌุงู ูุฏุงุฏ ฺฉู ู ุชูุงู ุงุฒ ุงูุชุชุงุญ ุญุณุงุจุงุช ูพุณ ุงูุฏุงุฒุ ุฌุงุฑุ ูุนุงุฏุ ุงุฌุฑุง ูุฑูุถ ุจู ููุธูุฑ ุชููู ุณุฑูุงู ฺฏุฐุงุฑ ูุง ู ุงุฌุฑุง ุณุงุฑ ูุฑูุถ ุฏุฑ ุจุฎุด ูุง ุชุฌุงุฑ ุงุฏ ุขูุฑ ฺฉุฑุฏ. ูุฑุญูู ุฏูู ุงุฒ ุณุงู 1381 ุขุบุงุฒ ู ุดูุฏ. ุจุนุฏ ุงุฒ ุชุตูุจ ูุงููู ุงุณุงุณ ุงูุบุงูุณุชุงูุ ุจุงูฺฉ ูุฑฺฉุฒ ุจุฑ ุงุณุงุณ ูุงุฏู ุฏูุงุฒุฏูู ุงู ูุงูููุ ููุญุซ ฺฉ ุจุงูฺฉ ูุณุชูู ุชุณุฌู ฺฏุฑุฏุฏ ู ุจุง ุตูุงุญุช ูุง ฺฉู ุจู ุขู ุชููุถ ุดุฏ ุจู ุฏุณุชุงูุฑุฏ ูุง ูุงุจู ุชูุฌู ุฏุฑ ุนุฑุตู ูุง ฺฏููุงฺฏูู ุฏุณุช ุงูุช. ุฏ ุงูุบุงูุณุชุงู ุจุงูฺฉ ุจุฑ ุงุณุงุณ ููุงูู ุฌุฏุฏ ุจุงูฺฉ ู ูุงู ุชูุงู ุงููุฑ ุชุฌุงุฑุช ุฑุง ุจู ุจุงูฺฉูุง ุฏููุช ู ุฎุตูุต ูุงฺฏุฐุงุฑ ูููุฏ ู ูุณูููุช ุงุนุทุง ุฌูุงุฒ ูุนุงูุช ู ูุธุงุฑุช ุงุฒ ูุคุณุณุงุช ุจุงูฺฉ ู ูุงู ุฑุง ุจุนูุฏู ฺฏุฑูุช. ุจุฑ ุงุณุงุณ ูุงููู ุฏ ุงูุบุงูุณุชุงู ุจุงูฺฉุ ุซุจุงุช ูู ูุฏู ุงููู ู ุงุณุงุณ ุฏ ุงูุบุงูุณุชุงู ุจุงูฺฉ ู ุจุงุดุฏ ู ุจู ุงู ููุธูุฑ ุทุฑุญุ ุชุทุจู ู ุงุชุฎุงุฐ ุณุงุณุช ูุง ูพููุ ุณุงุณุช ุงุฑุฒ ู ุชุฑุชุจุงุช ุงุณุนุงุฑุ ฺุงูพ ุจุงูฺฉููุช ู ุถุฑุจ ูุณฺฉูฺฉุงุช ุงุฒ ูุธุงู ุจุงูฺฉ ูุฑฺฉุฒ ุชุนู ฺฏุฑุฏุฏ ฺฉู ุฏุฑ ฺฉูุงุฑ ุขู ุทุจู ูุงููู ุจู ุญุซ ุจุงูฺฉุฏุงุฑ ู ููุงูุฏู ูุงู ุฏููุชุ ููุงุฏ ุตุฏูุฑ ู ุซุจุช ุฌูุงุฒ ูุนุงูุช ุจุงูฺฉูุงุ ุตุฑุงูุงู ู ุนุฑุถู ฺฉููุฏฺฏุงู ุฎุฏูุงุช ูพูู ู ุงุณูุงุฏ ุจูุงุฏุงุฑ ู ุณุณุชู ูพุฑุฏุงุฎุช ูุตูู ู ุณุงูู ูุฒ ูุนุงูุช ู ููุงุฏ.\nJob Summary\nุนููุงู ูุธูู\n: ุขูุณุฑ ุงุฑุดุฏ ุดุจฺฉู ุดูุช ุดุจ\nุขูุฑุช\n:\nุขูุฑุช ุนููู ุชฺฉูุงููฺ ูุนูููุงุช\nฺฏุฑุฏ\n: ููุชู (\nท\n)\nุชุนุฏุงุฏ ุจุณุช\n: ฺฉ (\nฑ\n)\nุชุงุฑุฎ ุขุบุงุฒ\n: ฑดฐด/ฑฐ/ฒฐ\nุชุงุฑุฎ ุฎุชู\n: ฑดฐด/ฑฑ/ฐด\nููุน ุงุนูุงู\n:\nุฏุงุฎู ู ุฎุงุฑุฌ\nููุน ุงุณุชุฎุฏุงู\n:\nุฏุงุฆู\nDuties & Responsibilities\nูุธุงู ู ูุณุฆููุช ู\nุง\nยทยยยยฺฉุงููฺฏูุฑุดู ุณุณฺฉู ุณูฺ ูุงุ ุณุณฺฉูุฑูุชุฑูุงุ ูุงุฑูุงู ูุง ASA ู Cyber roamุ Sophos ู Update operating server systemยู ุณุงุฑ ุงุฌุฒุง ูุฑุจูุท ุจู ุดุจฺฉู ุฏุฑ ุจุงูฺฉ ูุฑฺฉุฒุ ุดูุฑ ฺุงูฺฏู ูุง ู ุฒูู ูุง ููุช ฺฏุงูู ุฏ ุงูุบุงูุณุชุงู ุจุงูฺฉ\nยทยยยยยุญู ู ุฑุณุฏฺฏ ุจู ูุดฺฉูุงุช ุชุฎูฺฉ ุจุฎุด ุดุจฺฉู ู ุงูุชุฑูุช ุฏูุงุชุฑ ูุฑฺฉุฒุ ุฒูู ูุง ู ููุงูุฏฺฏ ูุง ููุงุช ฺฉู ุงุฒ ุทุฑู ุดุจ ูุนุงูุช ุฏุงุฑูุฏ\nยทยยยยยุชุฑุชุจ ู ุชูุธู ฺฉุงุฑ ูุง ุชุฎูฺฉ ู ูุณูฺฉ ุณุณุชู ูุฏุฑุช ุดุจฺฉูุจ ุฏ ุงูุบุงูุณุชุงู ุจุงูฺฉ ู ุจุฑูุฑุงุฑ ุณุงุฎุชู ุงุฑุชุจุงุท ุจุง ฺฉููพู ูุง ุฎุฏูุงุช ุดุจฺฉู ู ุงูุชุฑูุช ุบุฑุถ ูุณุงุฆู ุชุฎูฺฉ ู ุญู ูุดฺฉูุงุช ุงุฒ ุทุฑู ุดุจ\nยทยยยยุงูุณุชุงูุดู ู ฺฉุงููฺฏูุฑุดู ุณุณุชู ุชูููู ูุง ุฏุงุฎู AVAYA ุจุฑุง ูุฑฺฉุฒ ู ููุงูุฏฺฏ ูุง\nยทยยยยุจุฑ ูุฑุงุฑ ูฺฏูุฏุงุดุชู ุฎุฏูุงุช ุจูุชุฑ ุงูุชุฑูุชุ ุดุจฺฉูุ ููุงููฺฏ ู ููฺฉุงุฑ ุจุง ูุฏุฑ ูุณุชูู\nยทยยยยุชุณูู ฺฏุฑ ู ุชุณูู ุฏู ุงููุฑ ูุฑุจูุท ุจู ุดูุช ุจุง ุญูุธ ูุณุคูุช ฺฉุงุฑ ุฏุฑ ููุขููฺฏ ุจุง ูุฏุฑ ูุณุชูู\nยทยยยยุชุญุฑุฑ ูฺฉุงุชุจุ ูพุดููุงุฏุงุชุ ุงุณุชุนูุงู ูุง ู ุณุงุฑ ูุฑุงุณูุงุช ุงุฏุงุฑ ู ุท ูุฑุงุญู ุขู ุฏุฑ ููุช ูุนู ุทุจู ูุฏุงุช ูุฏุฑ ูุณุชูู ูุขูุฑ ุฐุตูุงุญ\nยทยยยยุชูุธู ู ุญูุธ ูฺฉุงุชุจุ ูพุดููุงุฏุงุชุ ุงุณุชุนูุงู ูุง ู ุณุงุฑ ูุฑุงุณูุงุช ุงุฏุงุฑ ุฏุฑ ุฏูุณู ูุง ู ฺฉุงุฑุชู ูุง ุทูุฑ ุฏูู ู ููุธู ุจู ุดฺฉู ูุงุฑุฏ ู ุณุงูุช ฺฉุงูพ\nยทยยยยุฌูุน ุขูุฑุ ุชูุญุฏ ู ุชุฑุชุจ ฺฏุฒุงุฑุด ูุง ููุชู ูุงุฑุ ูุงููุงุฑุ ุฑุจุนูุงุฑุ ุณุงูุงูู ู ุนูุฏุงูุถุฑูุฑุช ุงุฒ ูพุดุฑูุช ูุนุงูุชูุง ู ุฏุณุช ุขูุฑุฏ ูุง ูุฏุฑุช ูุฑุจูุท\nยทยยยยุชุฑุชุจ ูพูุงู ูุง ฺฉุงุฑ ู ุงุฑุง ฺฏุฒุงุฑุด ฺฉุงุฑ ุจู ูุฏุฑ ูุณุชูู ู ุขูุฑ ุฐุตูุงุญ\nยทยยยุงูุฌุงู ุณุงุฑ ูุธุงู ู ูุณุฆููุช ูุง ฺฉู ุจุชุฃุณ ุงุฒ ุทุฑุฒุงูุนูู ูุงุ ุฏุณุชูุฑุงูุนูู ู ูุฏุงุงุช ููุงู ูุงููู ุทุจู ูุงุญู ู ููุฑุฑุงุช ุงุฑุฌุงุน ูฺฏุฑุฏุฏ\nJob Requirements\nุฏุฑุฌู ุชุญุตู\nยทยยยยยยยูุณุงูุณ ุฏุฑ ุจุฎุด ฺฉููพูุชุฑ ุณุงูุณุ ุชฺฉูุงููฺ ูุนูููุงุช\nุชุฌุฑุจู\nยท\nุฏู (2) ุณุงู ุชุฌุฑุจ ฺฉุงุฑ ูุฑุชุจุท ุจู ูุธูู\nููุงุฑุช ูุง ู ุชูุงูุงุฆ ูุง\nยทยยยยยยุจูุฏุช ุจู ุฒุจุงู ูุง ุฑุณู ฺฉุดูุฑ ู ุงูฺฏูุณ\nยทยยยยยยุฏุงุดุชู ููุงุฑุช ูุง ูุฏุฑุช\nยทยยยยยยูุตุงุญุช ู ุจูุงุบุช ุฏุฑ ฺฏูุชุงุฑ\nยทยยยยยยุขุดูุงุฆ ุจู ููุงูู ู ููุฑุฑุงุช ุจุงูฺฉ\nยทยยยยยยุชูุงูุงุฆ ุฏุฑ ุชุญุฑุฑ ูฺฉุงุชุจุ ูพุดููุงุฏุงุช ู ฺฏุฒุงุฑุดุงุช ฺฉุงุฑ\nยทยยยยยยุขุดูุง ุจุง ุณุณุชู ูุง ุจุงูฺฉ\nยทยยยยยยููู ู ุฏุฑฺฉ ูุณุฆููุช ฺฉุงุฑ ู ุชุดุฎุต ูุดฺฉูุงุช ุฏุฑ ุณุงุญ ฺฉุงุฑ\nยทยยยยยยุญูุธ ูุญุฑูุช ู ุธูู\nยทยยยยยยุขฺฏุงู ุงุฒ ูุธุงู ู ุงูุฏุงู ุฏ ุงูุบุงูุณุชุงู ุจุงูฺฉ\nยทยยยยยยยยุจูุฏุช ุจุง ูุชูุฑฺฉ ูุงูุชูุฑูฺฏ ู ุณุฑูุฑ ูุงูุชูุฑูฺฏ ุชููุฒ\nยทยยยยยยุขุดูุงุฆ ุจุง ุจุฑูุงูู ูุง ฺฉููพูุชุฑ ู ุณุงุฑ ุงุฌุฒุง ุชฺฉูุงููฺฺฉ CCNP, CCNA,N+ AVAYA IP Phone,ุ Cyber roam Firewall\nุตูุงุช ู ุงุฑุฒุด ูุง ุดุฎุต\nยท\nุตุงุฏูุ ุฏุงุฑุง ุจุฑุฎูุฑุฏ ูฺฉุ ุญุงู ุงุญุชุฑุงู ูุชูุงุจูุ ูุจุชฺฉุฑุ ุจุง ุฏุณูพููุ ูพุงุจูุฏ ุจู ูุธูู ู ููุชุ ุนูุงูููุฏ ุจู ฺฉุงุฑ ฺฏุฑููพุ ููฺฉุงุฑุ ูุณุฆููุช ูพุฐุฑุ ุชุตููฺฏุฑ ู ูุณูฺฉ ุฏุฑ ุจุฎุด ฺฉุงุฑ\nSubmission Guideline\nูฺฉุงุช:\nยทยยยยุนูุงูู ููุฏุงู ูุชูุงููุฏ ูุฎุณุช ุฏุฑ ูุจ ุณุงุช\njobs.dab.gov.af\nุจุฑุง ุฎูุฏ ูุฒุฑ ุงุฌุงุฏ ูููุฏู ู ุจุนุฏุง ุจุณุช ููุฑุฏ ูุธุฑ ุฑุง ุงูุชุฎุงุจ ูููุฏู ู ุงุณูุงุฏ ุฎูุงุณุชู ุดุฏู ุฑุง ุจู ูุงุฑูุช PDF ุขูพููุฏ ููุงุฏ.\nยทยยยยุฌูุช ุงุฎุฐ ุงูุชุญุงู ููุท ุจุง ูุชูุงุถุงู ููุชุฎุจ ุชูุงุณ ฺฏุฑูุชู ูุดูุฏ.\nยทยยยยุชุงุฑุฎ ุงูุชุญุงู ุจุนุฏุงู ุจู ุงุทูุงุน ุฑุณุงูุฏู ูุดูุฏ.\nFunctional Area\nInformation Technology\nComputer Science\nNetworking\nCountries\nAfghanistan\nProvinces\nKabul\nApply Now\nPost Date\nJan 10, 2026\nClosing Date\nJan 24, 2026\nReference\nDAB1446052\nNumber of Vacancies\n1\nSalary Range\nAs per company salary scale\nYears of Experience\n2 years\nProbation Period\n3 month\nContract Type\nPermanent\nContract Duration\nNot specified\nContract Extensible\nYes\nMinimum Education\nBachelor's Degree\nGender\nMale\nRelated Jobs\nNETLINKS Plaza | Shahr-e-Naw,\nLane 3, Kabul, Afghanistan\nQuick Links\nAbout Us\nAdvertise with Us\nPrivacy Policy\nFor Companies\nPost a Job\nPost a Job\nPost a Job\nPost a Job\nPost RFP\nPost RFP\nPost RFP\nPost RFP\nPost Training\nPost Training\nPost Training\nPost Training\nFor Jobseekers\nBrowse Jobs\nBrowse Companies\nBuild Resume\nContact\ninfo@jobs.af\nContact Us\nยฉ 2012 - 2026 Jobs.af | All Rights Reserved\nPowered by:\nNETLINKS Ltd",
    "details": {
      "Post Date": "Jan 10, 2026",
      "Closing Date": "Jan 24, 2026",
      "Reference": "DAB1446052",
      "Number Of Vacancies": "1",
      "Salary Range": "As per company salary scale",
      "Years Of Experience": "2 years",
      "Probation Period": "3 month",
      "Contract Type": "Permanent",
      "Contract Duration": "Not specified",
      "Contract Extensible": "Yes",
      "Minimum Education": "Bachelor's Degree",
      "Functional Area": "Information Technology",
      "Countries": "Afghanistan",
      "Provinces": "Kabul"
    },
    "scraped_at": "2026-01-21T05:00:22Z",
    "apply_emails": [],
    "apply_method": "unknown"
  },
  {
    "url": "https://jobs.af/jobs/adhw-ankshaf-mhswlat",
    "title": "ุนุถู ุงูฺฉุดุงู ูุญุตููุงุช",
    "company": null,
    "location": "Kabul",
    "closing_date": "2026-01-24",
    "closing_date_raw": "Jan 24, 2026",
    "apply_url": null,
    "description": "๐\nComing Soon The Jobs.af Freelancer Portal\nConnect with top clients and freelancers across Afghanistan all in one place!\nStay Tuned\nJobs\nProcurement Opportunities\nCompanies\nFreelancers\nServices\nProcurement Opportunities\nTrainings\nScholarships\nLogin\nRegister\nุนุถู ุงูฺฉุดุงู ูุญุตููุงุช\nDa Afghanistan Bank\nApply Now\nSee all jobs\nุนุถู ุงูฺฉุดุงู ูุญุตููุงุช\nDa Afghanistan Bank,\n                                        Kabul, Afghanistan\nApply Now\nBachelor's Degree\nKabul, Afghanistan\n(Kabul)\nFull Time\n2981\n144\nAbout\n                                            Da Afghanistan Bank\nุฏ ุงูุบุงูุณุชุงู ุจุงูฺฉ ูุฑุงุฑ ุชุตูุจ ุดูุงุฑู 152 ููุฑุฎ 3/2/1318 ูุฌูุณ ูุฒุฑุงุ ุชุตูุจ ุดูุงุฑู 11 ููุฑุฎ 19/6/1318 ุดูุฑุง ููุ ุชุตูุจ ุชุงุฑุฎ 12/6/1318 ูุฌูุณ ุงุนุงู ู ููุธูุฑ 5280/1317 ุชุงุฑุฎ 17/11/1318 ุญุถูุฑ ุดุงูุงูู ุจู ุณุฑูุงู ุงุจุชุฏุงุฆ ูุจูุบ ฺฉุตุฏ ู ุจุณุช ูููู ุงูุบุงู ุฏุฑ ูพุงุชุฎุช ฺฉุดูุฑ ุดูุฑ ฺฉุงุจู ุงูุชุชุงุญ ุดุฏ ฺฉู ุฏุฑ ุฏุงุฎู ู ุฎุงุฑุฌ ฺฉุดูุฑ ุจุง ุงุฎุชุงุฑุงุช ู ูุธุงู ูุงุฒู ูุชูุงูุณุช ููุงูุฏฺฏ ู ูุฑูุน ุฎูุฏ ุฑุง ุชุฃุณุณ ู ุจุงูฺฉูุง ุณฺฉุชูุฑ ุฑุง ุชุนู ููุงุฏ. ูุธุงู ุจุงูฺฉุฏุงุฑ ุงูุบุงูุณุชุงู ุจุง ุชุฃุณุณ ุจุงูฺฉ ูู ุงูุบุงู ุฏุฑ ุณุงู 1312 ูุฌุฑ ุดูุณ ูพุง ุจู ุนุฑุตู ูุฌูุฏ ฺฏุฐุงุดุช ู ูุจู ุงุฒ ุชุฃุณุณ ุฏ ุงูุบุงูุณุชุงู ุจุงูฺฉุ ุงููุฑ ุจุงูฺฉุฏุงุฑ ุฏููุช ุฑุง ุงู ุจุงูฺฉ ุจู ูพุด ูุจุฑุฏ. ุจุนุฏ ุงุฒ ุชุฃุณุณ ุฏ ุงูุบุงูุณุชุงู ุจุงูฺฉ ูุธุงู ุจุงูฺฉุฏุงุฑ ุฏููุช ุจู ุดููู ฺุงูพ ู ูุดุฑ ูพูู ุงูุบุงู ุจู ุงู ุจุงูฺฉ ููุชูู ฺฏุฑุฏุฏ. ุฏ ุงูุบุงูุณุชุงู ุจุงูฺฉ ุจุญุซ ุจุงูฺฉุฏุงุฑ ุฏููุช ู ุจุงูฺฉ ุชุฌุงุฑุช ุชูุงูุณุช ุชุญููุงุช ู ุงูฺฉุดุงูุงุช ฺุดูฺฏุฑ ู ุจุฒุฑฺฏ ุฑุง ูู ุฏุฑ ุฑุงุจุทู ุจู ฺุงูพ ู ูุดุฑ ูพูู ุงูุบุงู ุจู ูุฌูุฏ ุขูุฑุฏ ู ูู ุฏุฑ ุณูุช ู ุณู ูุธุงู ุจุงูฺฉ ุจู ุฏุณุชุงูุฑุฏ ูุง ูุงุฆู ฺฏุฑุฏุฏ. ูุนุงูุช ุฏ ุงูุบุงูุณุชุงู ุจุงูฺฉ ุฑุง ู ุชูุงู ุจู ุฏู ูุฑุญูู ุชูุณู ุจูุฏ ฺฉุฑุฏ: ุฏุฑ ูุฑุญูู ุงูู ฺฉู ุงุฒ ุณุงู 1318 ุงู ุณุงู 1380 ุฑุง ุงุญุชูุง ู ููุงุฏุ ุฏ ุงูุบุงูุณุชุงู ุจุงูฺฉ ุฏุฑ ูุณูุช ฺุงูพุ ุถุฑุจ ู ูุดุฑ ูพูู ุงูุบุงู ูุทุงุจู ุจู ุชูุงุถุง ุจุงุฒุงุฑุ ุญูุธ ุงุฑุฒุด ูพูู ู ุงููุฑ ุจุงูฺฉุฏุงุฑ ุฏููุช ูุตุฑูู ุจูุฏ ฺฉู ุฏุฑ ูพููู ุงู ูุธุงูุ ุงููุฑ ุชุฌุงุฑุช ุฑุง ูุฒ ุทุจู ูุนุงูุช ูุง ุณุงุฑ ุจุงูฺฉูุง ุชุฌุงุฑ ุงูุบุงูุณุชุงู ุงูุฌุงู ูุฏุงุฏ ฺฉู ู ุชูุงู ุงุฒ ุงูุชุชุงุญ ุญุณุงุจุงุช ูพุณ ุงูุฏุงุฒุ ุฌุงุฑุ ูุนุงุฏุ ุงุฌุฑุง ูุฑูุถ ุจู ููุธูุฑ ุชููู ุณุฑูุงู ฺฏุฐุงุฑ ูุง ู ุงุฌุฑุง ุณุงุฑ ูุฑูุถ ุฏุฑ ุจุฎุด ูุง ุชุฌุงุฑ ุงุฏ ุขูุฑ ฺฉุฑุฏ. ูุฑุญูู ุฏูู ุงุฒ ุณุงู 1381 ุขุบุงุฒ ู ุดูุฏ. ุจุนุฏ ุงุฒ ุชุตูุจ ูุงููู ุงุณุงุณ ุงูุบุงูุณุชุงูุ ุจุงูฺฉ ูุฑฺฉุฒ ุจุฑ ุงุณุงุณ ูุงุฏู ุฏูุงุฒุฏูู ุงู ูุงูููุ ููุญุซ ฺฉ ุจุงูฺฉ ูุณุชูู ุชุณุฌู ฺฏุฑุฏุฏ ู ุจุง ุตูุงุญุช ูุง ฺฉู ุจู ุขู ุชููุถ ุดุฏ ุจู ุฏุณุชุงูุฑุฏ ูุง ูุงุจู ุชูุฌู ุฏุฑ ุนุฑุตู ูุง ฺฏููุงฺฏูู ุฏุณุช ุงูุช. ุฏ ุงูุบุงูุณุชุงู ุจุงูฺฉ ุจุฑ ุงุณุงุณ ููุงูู ุฌุฏุฏ ุจุงูฺฉ ู ูุงู ุชูุงู ุงููุฑ ุชุฌุงุฑุช ุฑุง ุจู ุจุงูฺฉูุง ุฏููุช ู ุฎุตูุต ูุงฺฏุฐุงุฑ ูููุฏ ู ูุณูููุช ุงุนุทุง ุฌูุงุฒ ูุนุงูุช ู ูุธุงุฑุช ุงุฒ ูุคุณุณุงุช ุจุงูฺฉ ู ูุงู ุฑุง ุจุนูุฏู ฺฏุฑูุช. ุจุฑ ุงุณุงุณ ูุงููู ุฏ ุงูุบุงูุณุชุงู ุจุงูฺฉุ ุซุจุงุช ูู ูุฏู ุงููู ู ุงุณุงุณ ุฏ ุงูุบุงูุณุชุงู ุจุงูฺฉ ู ุจุงุดุฏ ู ุจู ุงู ููุธูุฑ ุทุฑุญุ ุชุทุจู ู ุงุชุฎุงุฐ ุณุงุณุช ูุง ูพููุ ุณุงุณุช ุงุฑุฒ ู ุชุฑุชุจุงุช ุงุณุนุงุฑุ ฺุงูพ ุจุงูฺฉููุช ู ุถุฑุจ ูุณฺฉูฺฉุงุช ุงุฒ ูุธุงู ุจุงูฺฉ ูุฑฺฉุฒ ุชุนู ฺฏุฑุฏุฏ ฺฉู ุฏุฑ ฺฉูุงุฑ ุขู ุทุจู ูุงููู ุจู ุญุซ ุจุงูฺฉุฏุงุฑ ู ููุงูุฏู ูุงู ุฏููุชุ ููุงุฏ ุตุฏูุฑ ู ุซุจุช ุฌูุงุฒ ูุนุงูุช ุจุงูฺฉูุงุ ุตุฑุงูุงู ู ุนุฑุถู ฺฉููุฏฺฏุงู ุฎุฏูุงุช ูพูู ู ุงุณูุงุฏ ุจูุงุฏุงุฑ ู ุณุณุชู ูพุฑุฏุงุฎุช ูุตูู ู ุณุงูู ูุฒ ูุนุงูุช ู ููุงุฏ.\nJob Summary\nุนููุงู ูุธูู\n: ุนุถู ุงูฺฉุดุงู ูุญุตููุงุช\nุขูุฑุช\n:\nุขูุฑุช ุนููู ูุธุงุฑุช ุจุงูฺฉ ู ุฎุฏูุงุช ูุงู\nฺฏุฑุฏ\n: ูุดุชู (\nธ\n)\nุชุนุฏุงุฏ ุจุณุช\n: ฺฉ (\nฑ\n)\nุชุงุฑุฎ ุขุบุงุฒ\n: ฑดฐด/ฑฐ/ฒฐ\nุชุงุฑุฎ ุฎุชู:\nฑดฐด/ฑฑ/ฐด\nููุน ุงุนูุงู\n:\nุฏุงุฎู ู ุฎุงุฑุฌ\nููุน ุงุณุชุฎุฏุงู\n:\nุฏุงุฆู\nDuties & Responsibilities\nูุธุงู ู ูุณุฆููุช ูุง\nุชุทุจู ูพูุงู ฺฉุงุฑุ ูุงููุงุฑุ ุฑุจุนูุงุฑ ู ุณุงูุงูู ุทุจู ูพูุงู ุนููู ู ููฺฉุงุฑ ุฏุฑ ุชุนุฏู ุงุณูุงุฏ ุงุฏุงุฑ ู ุชููู ูุฑุจูุท ุจุง ูุฏุฑ ูุณุชูู\nูุฏุฑุช ููุงุจุนุ ูุนุงูุช ูุง ู ุนููฺฉุฑุฏ ูุง ุชุญุช ฺฉูุชุฑูู ุฏุฑ ูุทุงุจูุช ุจุง ููุงููุ ููุฑุฑุงุชุ ูพุงูุณ ูุง ู ุทุฑุฒุงูุนูู ูุง ุฌูุช ุนุฑุถ ุฎุฏูุงุช ูุทุงุจู ุจู ูพูุงู ฺฉุงุฑ\nุญู ุดูุงุณุงุฆ ู ุฏุฑุงูุช ุงุดุชุจุงูุงุชุ ุงูุฏุงู ุจู ุงุณุฑุน ููุช ุฏุฑ ุชุตุญุญ ุขู ู ููฺฉุงุฑ ุจุง ุณุงุฑ ุดุนุจุงุช ุฐุฑุจุท ุฏุฑ ุฑุงุจุทู ุจู ุญู ูุดฺฉูุงุช ูุฑุจูุท\nุญุตูู ุงุทููุงู ุงุฒ ุชุทุจู ุชุตุงูุจ ูุฆุช ุนุงูู ู ุดูุฑุง ุนุงู ุฏ ุงูุบุงูุณุชุงู ุจุงูฺฉ ุฏุฑ ูุทุงุจูุช ุจู ุงุณูุงุฏ ุชููู\nุทุฑุญุ ุชุฑุชุจ ู ุชุทุจู ูพุงูุณ ูุงุ ูพูุงู ูุง ฺฉุงุฑ ุทุจู ูพูุงู ุนููู ู ููฺฉุงุฑ ุฏุฑ ุชุนุฏู ุงุณูุงุฏ ุชูููุ ููุฑุฑุงุชุ ุทุฑุฒุงูุนูู ูุง ู ูุญุตููุงุช ูุฑุจูุท\nุฌูุน ุขูุฑ ูพุดููุงุฏุงุช ู ุฏุฑ ุฎูุงุณุช ูุง ุจุงูฺฉ ูุง ุชุฌุงุฑ ู ููุงุฏ ูุง ูุฌูุฒุ ุชุญููุ ุงุฑุฒุงุจ ู ุจุฑุฑุณ ุขู ุฏุฑ ูุทุงุจูุช ุจู ุงุณูุงุฏ ุชููู ู ุฏุฑ ุตูุฑุช ูุฒูู ููุขููฺฏ ุขู ุจุง ุขูุฑุช ูุญุชุฑู ุงููุฑ ุญููู ุฌูุช ุงุฎุฐ ูุธุฑุงุช ุญููู\nููฺฉุงุฑ ุฏุฑ ูุณูุช ุชูุณุน ูพุงูุณ ูุงุ ููุฑุฑุงุชุ ููุงุญุ ุทุฑุฒ ุงูุนูู ูุงุ ููุฑูู ูุง ูุนุงุฑ ู ูพูุงู ูุง ฺฉูุชุงู ูุฏุช ู ุงุณุชุฑุงุชฺฺฉ ุจุง ุฏุฑ ูุธุฑ ุฏุงุดุช ุชุฎุฑุฌ ุดุฑุน\nุฌูุน ุขูุฑ ุฏุฑุงูุช ูุงุ ุชุฑุชุจุ ุชูุณุนู ู ุงูฺฉุดุงู ูุญุตููุงุช ููู ุจุงูฺฉ ู ููุฑุฑุงุช ูุฑุจูุท\nุชุฏูุฑ ุฌูุณู ุจุง ุจุงูฺฉ ูุง ุจู ููุธูุฑ ููุขููฺฏ ุณุงุฒ ู ุงุฑุง ุชูุถุญุงุช ุงุฒ ุทุฑุฒ ุงูุนูู ูุญุตููุงุช ุจุงูฺฉุฏุงุฑ ุงุณูุงู\nุงุฑุง ูุนูููุงุชุ ุชุดุฑุญ ู ุชูุถุญ ุชุฎุฑุฌ ูุญุตููุงุช ููู ู ุงุณูุงุฏ ุชููู ูุฑุจูุท ู ุชุดุฑฺฉ ุขู ุจุง ูุฑุงุฌุนู ู ุฌูุงูุจ ุฐุฏุฎู\nููฺฉุงุฑ ู ููุขููฺฏ ุจุง ูุฏุฑุช ูุง ุฐุฑุจุท ุฏ ุงูุบุงูุณุชุงู ุจุงูฺฉ ุจู ููุธูุฑ ุชุจุงุฏู ูุธุฑ ูุณูฺฉ ุฏุฑ ูุณูุช ุชูุณุน ุทุฑุฒุงูุนูู ูุง ฺฉุงุฑ ุงุฒ ุจูุนุฏ ุงุณูุงู\nููุขููฺฏ ู ุชุฃูู ุงุฑุชุจุงุท ุจุง ุจุฎุด ูุง ุฐุฑุจุท ุจู ููุธูุฑ ุชูุณุน ูุญุตููุงุช ู ุชุฎุฑุฌ ุดุฑุน ุฏุฑ ุฑุงุจุทู\nุงุดุชุฑุงฺฉ ุฏุฑ ูุฌุงูุณุ ฺฉุงููุฑุงูุณ ูุงุ ุณููุงุฑูุงุ ูุฑฺฉุดุงูพ ูุงุ ุจุฑูุงูู ูุง ุขููุฒุด ู ุณุงุฑ ุจุฑูุงูู ูุง ุฑุณู ุจู ููุงูุฏฺฏ ุงุฒ ุฏ ุงูุบุงูุณุชุงู ุจุงูฺฉ ุฏุฑ ุฏุงุฎู ู ุฎุงุฑุฌ ุงุฒ ฺฉุดูุฑ ุทุจู ูุฏุงุงุช\nุชุญุฑุฑ ูฺฉุงุชุจุ ูพุดููุงุฏุงุชุ ุงุณุชุนูุงู ูุง ู ุณุงุฑ ูุฑุงุณูุงุช ุงุฏุงุฑ ู ุท ูุฑุงุญู ุขู ุฏุฑ ููุช ูุนู ุทุจู ูุฏุงุช ูุฏุฑ ูุณุชูู ูุขูุฑ ุฐุตูุงุญ\nุชูุธู ู ุญูุธ ูฺฉุงุชุจุ ูพุดููุงุฏุงุชุ ุงุณุชุนูุงู ูุง ู ุณุงุฑ ูุฑุงุณูุงุช ุงุฏุงุฑ ุฏุฑ ุฏูุณู ูุง ู ฺฉุงุฑุชู ูุง ุทูุฑ ุฏูู ู ููุธู ุจู ุดฺฉู ูุงุฑุฏ ู ุณุงูุช ฺฉุงูพ\nุชุฑุชุจ ูพูุงู ูุง ฺฉุงุฑ ู ุงุฑุงฺฏุฒุงุฑุด ฺฉุงุฑ ุจู ูุฏุฑ ูุณุชูู ู ุขูุฑ ุฐุตูุงุญ\nุงูุฌุงู ุณุงุฑ ูุธุงู ู ูุณุฆููุช ูุง ฺฉู ุจุชุฃุณ ุงุฒ ุทุฑุฒุงูุนูู ูุงุ ุฏุณุชูุฑุงูุนูู ู ูุฏุงุงุช ููุงู ูุงููู ุทุจู ูุงุญู ู ููุฑุฑุงุช ุงุฑุฌุงุน ูฺฏุฑุฏ\nJob Requirements\nุฏุฑุฌู ุชุญุตู\nยท\nูุณุงูุณ ุฏุฑ ุจุฎุด ูุง ุงุฏุงุฑู ู ุชุฌุงุฑุชุ ุงูุชุตุงุฏุ ุจุงูฺฉุฏุงุฑ ุงุณูุงูุ ุญูููุ ุดุฑุนุงุชุ ุจุงูฺฉุฏุงุฑ ู ูุงู ู ุงุฏุงุฑู ุนุงูู ู ุจุฏุงุดุชู ุณูุฏ ูุงุณุชุฑ ุฏุฑ ุจุฎุด ูุง ููู ุงูุฐฺฉุฑ ู ุฏุฑ ูููุ ููู ุงููุนุงููุงุชุ ุงุตูู ููู ุชุฎุตุต ุชุฑุฌุญ ุฏุงุฏู ูุดูุฏ\nุชุฌุฑุจู\nยทยยยยยุณู (3) ุณุงู ุชุฌุฑุจ ฺฉุงุฑ ูุฑุชุจุท ุจู ูุธูู\nููุงุฑุช ูุง ู ุชูุงูุงุฆ ูุง\nยทยยยยยยุจูุฏุช ุจู ุฒุจุงู ูุง ุฑุณู ฺฉุดูุฑ ู ุงูฺฏูุณ\nยทยยยยยยุญูุธ ูุญุฑูุช ู ุธูู\nยทยยยยยยูุตุงุญุช ู ุจูุงุบุช ุฏุฑ ฺฏูุชุงุฑ\nยทยยยยยยุฏุงุดุชู ููุงุฑุช ูุง ูุฏุฑุช\nยทยยยยยยุขุดูุงุฆ ุจู ููุงูู ูููุฑุฑุงุช ุจุงูฺฉ\nยทยยยยยยุชูุงูุงุฆ ุฏุฑ ุชุญุฑุฑ ูฺฉุงุชุจุ ูพุดููุงุฏุงุช ู ฺฏุฒุงุฑุดุงุช ฺฉุงุฑ\nยทยยยยยยููู ู ุฏุฑฺฉ ูุณุฆููุช ฺฉุงุฑ ู ุชุดุฎุต ูุดฺฉูุงุช ุฏุฑ ุณุงุญ ฺฉุงุฑ\nยทยยยยยยุขุดูุงุฆ ุจุง ุจุฑูุงูู ูุง ฺฉููพูุชุฑ ู ุณุณุชู ูุง ุจุงูฺฉ ุจุฎุตูุต ุจุงูฺฉุฏุงุฑ ู ุฎุฏูุงุช ูุงู ุงุณูุงู\nุตูุงุช ู ุงุฑุฒุด ูุง ุดุฎุต\nยท\nุตุงุฏูุ ุฏุงุฑุง ุจุฑุฎูุฑุฏ ูฺฉุ ุญุงู ุงุญุชุฑุงู ูุชูุงุจูุ ูุจุชฺฉุฑุ ุจุง ุฏุณูพููุ ูพุงุจูุฏ ุจู ูุธูู ู ููุชุ ุนูุงูููุฏ ุจู ฺฉุงุฑ ฺฏุฑููพุ ููฺฉุงุฑุ ูุณุฆููุช ูพุฐุฑุ ุชุตููฺฏุฑ ู ูุณูฺฉ ุฏุฑ ุจุฎุด ฺฉุงุฑ\nSubmission Guideline\nูฺฉุงุช:\nยทยยยยุนูุงูู ููุฏุงู ูุชูุงููุฏ ูุฎุณุช ุฏุฑ ูุจ ุณุงุช\njobs.dab.gov.af\nุจุฑุง ุฎูุฏ ูุฒุฑ ุงุฌุงุฏ ูููุฏู ู ุจุนุฏุง ุจุณุช ููุฑุฏ ูุธุฑ ุฑุง ุงูุชุฎุงุจ ูููุฏู ู ุงุณูุงุฏ ุฎูุงุณุชู ุดุฏู ุฑุง ุจู ูุงุฑูุช PDF ุขูพููุฏ ููุงุฏ.\nยทยยยยุฌูุช ุงุฎุฐ ุงูุชุญุงู ููุท ุจุง ูุชูุงุถุงู ููุชุฎุจ ุชูุงุณ ฺฏุฑูุชู ูุดูุฏ.\nยทยยยยุชุงุฑุฎ ุงูุชุญุงู ุจุนุฏุงู ุจู ุงุทูุงุน ุฑุณุงูุฏู ูุดูุฏ.\nFunctional Area\nBanking\nEconomic Growth\nLaw\nBusiness Administration\nLLB\nComputer Operator\nPublic Administration\nEconomic-Department of Business Administration.\nCountries\nAfghanistan\nProvinces\nKabul\nApply Now\nPost Date\nJan 10, 2026\nClosing Date\nJan 24, 2026\nReference\nDAB1446051\nNumber of Vacancies\n1\nSalary Range\nAs per company salary scale\nYears of Experience\n3 years\nProbation Period\n3 month\nContract Type\nPermanent\nContract Duration\nNot specified\nContract Extensible\nYes\nMinimum Education\nBachelor's Degree\nGender\nMale\nRelated Jobs\nNETLINKS Plaza | Shahr-e-Naw,\nLane 3, Kabul, Afghanistan\nQuick Links\nAbout Us\nAdvertise with Us\nPrivacy Policy\nFor Companies\nPost a Job\nPost a Job\nPost a Job\nPost a Job\nPost RFP\nPost RFP\nPost RFP\nPost RFP\nPost Training\nPost Training\nPost Training\nPost Training\nFor Jobseekers\nBrowse Jobs\nBrowse Companies\nBuild Resume\nContact\ninfo@jobs.af\nContact Us\nยฉ 2012 - 2026 Jobs.af | All Rights Reserved\nPowered by:\nNETLINKS Ltd",
    "details": {
      "Post Date": "Jan 10, 2026",
      "Closing Date": "Jan 24, 2026",
      "Reference": "DAB1446051",
      "Number Of Vacancies": "1",
      "Salary Range": "As per company salary scale",
      "Years Of Experience": "3 years",
      "Probation Period": "3 month",
      "Contract Type": "Permanent",
      "Contract Duration": "Not specified",
      "Contract Extensible": "Yes",
      "Minimum Education": "Bachelor's Degree",
      "Functional Area": "Banking",
      "Countries": "Afghanistan",
      "Provinces": "Kabul"
    },
    "scraped_at": "2026-01-21T05:00:22Z",
    "apply_emails": [],
    "apply_method": "unknown"
  },
  {
    "url": "https://jobs.af/jobs/hmis-data-assistance",
    "title": "HMIS Data Assistance",
    "company": null,
    "location": "Kunduz",
    "closing_date": "2026-01-25",
    "closing_date_raw": "Jan 25, 2026",
    "apply_url": null,
    "description": "๐\nComing Soon The Jobs.af Freelancer Portal\nConnect with top clients and freelancers across Afghanistan all in one place!\nStay Tuned\nJobs\nProcurement Opportunities\nCompanies\nFreelancers\nServices\nProcurement Opportunities\nTrainings\nScholarships\nLogin\nRegister\nHMIS Data Assistance\nMAGNA\nApply Now\nSee all jobs\nHMIS Data Assistance\nMAGNA,\n                                        Kunduz, Afghanistan\nApply Now\nBachelor's Degree\nKunduz, Afghanistan\n(Kunduz)\nFull Time\n1438\n48\nAbout\n                                            MAGNA\nMAGNA\nis a medical humanitarian organization that has been actively working worldwide and providing humanitarian aid for more than 20 years. Now our projects cover about 15 countries. The largest programs are deployed in\nCongo (DR), Syria, South Sudan, Iraq, Afghanistan and Ukraine\n. We implement our humanitarian aid projects by working directly with the medical institutions and supporting doctors provided direct emergency medical care to patients who need it.\nMAGNA\noperates internationally and provides assistance to children and their families in need, including victims of natural disasters, wars and conflicts. In the field we maintain doctors and medical staff but also technical and other specialists, providing humanitarian assistance and help to treat children and their families.\nMAGNA\nfocusing on\nHealth, Nutrition and MHPSS\nprojects, primarily aimed at saving lives and alleviating the suffering of those in need. Armed conflicts and unstable political situations have a devastating impact on ordinary people. Consequences, often associated with inadequate local health services, commonly include direct violence, forced displacement, epidemics, famine, and psychological trauma. Providing medical assistance to victims of conflicts and crises is MAGNA workersโ top priority. Alleviating suffering from infectious diseases neglected by local structures is another major area of MAGNAโs focus.\nMAGNA\nhas a zero tolerance policy with regard to Sexual Exploitation and Abuse by MAGNAโs personnel against the people they serve. Protection from Sexual Exploitation and Abuse (PSEA) is the responsibility of everyone and all selected candidates will be required to comply with MAGNAโs PSEA Policy at all times. Selected candidates will therefore undergo rigorous reference and background checks against their past behavior related to sexual exploitation and abuse, and may be required to provide additional information further on in the selection process.\nJob Summary\nDefining, coordinating and monitoring all data related activities including data collection, analysis, reporting, monitoring and evaluation processes according to\nMAGNA\nprotocols, standards and procedures in order to ensure quality medical care for patients and their communities and to improve the health condition of the population\nDuties & Responsibilities\nAccountabilities:\n-ยยยยยยData Entry and Monitoring, assist with daily data entry tasks for the health facilities (clinics, hospitals, health centers) and support the establishment of monitoring tools for data collection processes.\n-ยยยยยยData Verification, ensure that all collected data is accurate, consistent, and aligned with the project's indicators. Perform regular checks to ensure the quality and completeness of data.\n-ยยยยยยTechnical Assistance, provide technical support and guidance to the health care providers and data entry team on how to use HMIS tools for data entry. Help resolve issues related to data collection.\n-ยยยยยยData Analysis Support, assist in analyzing collected data to identify trends, gaps, and key performance indicators (KPIs). Support the review and assessment of data to ensure project targets are being met.\n-ยยยยยยReporting and Feedback, assist in the preparation of monthly and quarterly reports on analyzed data. Provide feedback to the health facilities on the status of their data quality and suggest areas for improvement.\n-ยยยยยยCapacity Building Support, assist in identifying and addressing training needs for the health facilities' staff related to HMIS. Participate in on-the-job training sessions to improve skills in data entry, quality control, and analysis.\n-ยยยยยยHR Coordination, support the HR department in monitoring the training and development needs of the data entry staff. Assist in the organization of training or induction programs for new data team members.\n-ยยยยยยSupport Project Teams, attend regular internal meetings and training sessions, such as MAGNA's coordination meetings and trainings, to contribute to team updates and feedback. Participate in the dissemination of project-related information to the team.\n-ยยยยยยData Update and Communication, ensure that all HMIS data collection tools are updated regularly. Assist in sharing relevant updates with team members and healthcare providers to ensure consistent communication of expectations.\n-ยยยยยยReport Preparation, support the preparation and submission of regular data reports to the Ministry of Health (MoPH), donors, and MAGNA. Ensure reports are accurate, complete, and submitted on time.\n-ยยยยยยTeam Collaboration, work closely with the medical team and health supervisors to ensure proper data collection and entry practices. Participate in collaborative team efforts to assess and improve data handling processes.\n-ยยยยยยยยAdditional Tasks, perform any other tasks assigned by the supervisor to support the success of the project, including assisting with other administrative or operational activities as needed\nContext Specific Accountabilities:\n-ยยยยยยยยยยยHe will assist with daily data entry tasks for the health facilities (clinics, hospitals, health centers) and support the establishment of monitoring tools for data collection processes.\n-ยยยยยยยยยยยHe will help review and adapt HMIS data collection tools to meet the projectโs needs and indicators, under the guidance of the HMIS Manager.\n-ยยยยยยยยยยยHe will ensure that all HMIS data collection tools are updated regularly. Assist in sharing relevant updates with team members and healthcare providers to ensure consistent communication of expectations.\n-ยยยยยยยยยยยHe will ensure the regular supply of HMIS tools to the health facilities, and he will maintain the supply of HMIS tools on need based to the health facilities.\n-ยยยยยยยยยยยHe will assist in ensuring that all staff follow the HMIS Standard Operating Procedures (SOPs) for data collection and documentation.\n-ยยยยยยยยยยยHe will assist with the verification and validation of collected data to maintain consistency and quality at all health facility levels.\n-ยยยยยยยยยยยHe will ensure that all collected data is accurate, consistent, and aligned with the project's indicators. Perform regular checks to ensure the quality and completeness of data.\n-ยยยยยยยยยยยHe will help in analyzing key project indicators and comparing collected data with project targets to assess the performance of activities and identify areas for improvement.\n-ยยยยยยยยยยยHe will ensure that all patient data and sensitive information are handled with full respect and maintained confidentially in accordance with privacy guidelines.\nHe will perform any other tasks assigned by the supervisor to support the success of the project, including assisting with other administrative or operational activities as needed\nJob Requirements\nEducation\nMD/ Nursing degree from recognized institute\nExperience\nAt least 2 years of experience in HMIS and Data entry.\nSubmission Guideline\nInterested and Qualified applicants can send their application and CV to the following email:\npersonal-adm-mng@af.magna.org\nNo other type of submission will be accepted.\nPlease mention the vacancy number and position name in the subject line of the email. Otherwise, you will not be shortlisted.\nRegarding MAGNA recruitment process, please note that!\nยทยยยยยยยยMAGNA will conduct its recruitment on the basis of need only.\nยทยยยยยยยยMAGNA commits to a fair and transparent recruitment procedure.\nยทยยยยยยยยOnly HR department will contact you during the recruitment process.\nยทยยยยยยยยMAGNA may keep data of your application for its pool of candidate and might propose to you another position than the one you applied for based on your qualification.\nOnly short-listed candidates whose application responds to the criteria will be contacted & local applicants from the same province are encouraged to apply and will be given priority.\nFunctional Area\nHealth/Medical\nData Entry\nData Collection\nCountries\nAfghanistan\nProvinces\nKunduz\nApply Now\nPost Date\nJan 15, 2026\nClosing Date\nJan 25, 2026\nReference\n26AFG012\nNumber of Vacancies\n1\nSalary Range\nAs per company salary scale\nYears of Experience\n2 years\nProbation Period\n3 month\nContract Type\nProject Based\nContract Duration\n12 month\nContract Extensible\nMaybe\nMinimum Education\nBachelor's Degree\nGender\nAny\nRelated Jobs\nNETLINKS Plaza | Shahr-e-Naw,\nLane 3, Kabul, Afghanistan\nQuick Links\nAbout Us\nAdvertise with Us\nPrivacy Policy\nFor Companies\nPost a Job\nPost a Job\nPost a Job\nPost a Job\nPost RFP\nPost RFP\nPost RFP\nPost RFP\nPost Training\nPost Training\nPost Training\nPost Training\nFor Jobseekers\nBrowse Jobs\nBrowse Companies\nBuild Resume\nContact\ninfo@jobs.af\nContact Us\nยฉ 2012 - 2026 Jobs.af | All Rights Reserved\nPowered by:\nNETLINKS Ltd",
    "details": {
      "Post Date": "Jan 15, 2026",
      "Closing Date": "Jan 25, 2026",
      "Reference": "26AFG012",
      "Number Of Vacancies": "1",
      "Salary Range": "As per company salary scale",
      "Years Of Experience": "2 years",
      "Probation Period": "3 month",
      "Contract Type": "Project Based",
      "Contract Duration": "12 month",
      "Contract Extensible": "Maybe",
      "Minimum Education": "Bachelor's Degree",
      "Functional Area": "Health/Medical",
      "Countries": "Afghanistan",
      "Provinces": "Kunduz"
    },
    "scraped_at": "2026-01-21T05:00:22Z",
    "apply_emails": [
      "personal-adm-mng@af.magna.org"
    ],
    "apply_method": "email"
  },
  {
    "url": "https://jobs.af/jobs/adhw-mslky-kntrwl-jywmtry-layh-hay-jghrafyayy-anwan-wzyfh",
    "title": "ุนุถู ูุณูฺฉ ฺฉูุชุฑูู ุฌููุชุฑ ูุงู ูุง ุฌุบุฑุงูุง",
    "company": null,
    "location": "Kabul",
    "closing_date": "2026-01-27",
    "closing_date_raw": "Jan 27, 2026",
    "apply_url": null,
    "description": "๐\nComing Soon The Jobs.af Freelancer Portal\nConnect with top clients and freelancers across Afghanistan all in one place!\nStay Tuned\nJobs\nProcurement Opportunities\nCompanies\nFreelancers\nServices\nProcurement Opportunities\nTrainings\nScholarships\nLogin\nRegister\nุนุถู ูุณูฺฉ ฺฉูุชุฑูู ุฌููุชุฑ ูุงู ูุง ุฌุบุฑุงูุง\nNational Statistics and Information Authority\nApply Now\nSee all jobs\nุนุถู ูุณูฺฉ ฺฉูุชุฑูู ุฌููุชุฑ ูุงู ูุง ุฌุบุฑุงูุง\nNational Statistics and Information Authority,\n                                        Kabul, Afghanistan\nApply Now\nBachelor's Degree\nKabul, Afghanistan\n(Kabul)\nFull Time\n1284\nAbout\n                                            National Statistics and Information Authority\nุงุฏุงุฑ ูู ุงุญุตุงุฆู ู ูุนูููุงุช\n\nุฏุฏฺฏุงู:\n\nุฏุงุดุชู ุณุณุชู ูุงุญุฏุ ูุนุงุฑุ ูพุงุณุฎฺฏูุ ูุงุจู ุงุนุชูุงุฏ ุฏุฑ ุณุทุญ ูู ู ุจู ุงููููุ ูพูุง ู ูพุงุฏุงุฑ ุงุญุตุงุฆู ู ูุนูููุงุช ุฏุฑ ฺฉุดูุฑ\n\nูุงููุฑุช:\n\nูุฏุฑุช ู ุงูฺฉุดุงู ุณุณุชู ุงุญุตุงุฆู ู ูุนูููุงุช ุจุฑ ุจูุงุฏ ูุงุฒููุฏ ูุง ฺฉุดูุฑ\n\nูุฏุฑุช ู ุงุฑุงู ูุนูููุงุช ุฏููุ ูุณุชูุฏุ ูุงุจู ุงุทููุงูุ ุจู ูููุนุ ุจุง ฺฉูุช ู ูุงุจู ุงุณุชูุงุฏู ุจุฑุง ุทุฑุญ ูพุงูุณ ูุงุ ุณุงุณุช ฺฏุฐุงุฑ ูุง ุุชุตูู ฺฏุฑ ูุงุ ูพูุงูฺฏุฐุงุฑ ูุงุ ุชุญููุงุชุ ุขฺฏุงู ุนุงููุ ุชุงูู ุดูุงูุช ู ุณุงุฑ ููุงุฑุฏ ุงุฒ ูุฑุฌุน ูุงุญุฏ\n\nุชุฃูู ุงุณุชููุงูุช ูุณูฺฉุ ุจฺฉุงุฑ ฺฏุฑ ุฑูุดูุง ุนููุ ูุนุงุฑ ู ุฑุนุงุช ุงุตูู ุจู ุงูููู ุงุญุตุงุฆู ูุง ุฑุณูุ ุชุฃูู ููุงููฺฏ ู ุฌููฺฏุฑ ุงุฒ ุชฺฉุฑุงุฑ ุนูู ุฏุฑ ุชูุงู ูุนุงูุช ูุง ู ุนุฑุถ ุฎุฏูุงุช ุงุญุตุงุฆู \n\nูุฏุฑุช ุณุณุชู ูุง ูุนูููุงุช ุจู ููุธูุฑ ุงุณุชูุงุฏู ููุซุฑ ุ ุจู ูููุน ู ููู ุฌุงูุจู ุงุฒ ุงุฑูุงู ุฌุงุฑูุ ุงุฑูุงู ุจุฒุฑฺฏ ู ูุนูููุงุช ุฌุบุฑุงูุง ุฏุฑ ุชูู ุงุญุตุงุฆู ูุง ุฑุณู ููฺูุงู ุชุฑูุฌุ ุชููุช ู ูพุงู ฺฏุฐุงุฑ ุงุญุตุงุฆู ูุง ุซุจุช.\n\nูุธุงู ู ุตูุงุญุช ูุง:\n\nุงุฌุงุฏุ ูุฏุฑุช ู ุงูฺฉุดุงู ุณุณุชู ูุงุญุฏ ุงุญุตุงุฆู ู ูุนูููุงุช ุฏุฑ ฺฉุดูุฑ\n\nุฌูุน ุขูุฑุ ุชูุญุฏุ ุชุญูู ู ูุดุฑ ูุนูููุงุช ุฏููุ ูุณุชูุฏุ ูุงุจู ุงุทููุงูุ ุจู ูููุน ู ุจุง ฺฉูุช ุงุญุตุงุฆู ุฏุฑ ุฑุงุจุทู ุจู ูููุณุ ุงููุฑ ุชุฌุงุฑุชุ ุตูุนุชุ ุฒุฑุงุนุชุ ูุงูุ ุงุฌุชูุงุนุ ุงูุชุตุงุฏุ ุตุญุ ูุญุท ู ูุถุน ูุนุงูุช ูุง ุนููู ูุฑุฏู\n\nุชุฃูู ููุงููฺฏุ ุฌููฺฏุฑ ุงุฒ ุชฺฉุฑุงุฑ ุนููุ ุงูุณุฌุงู ู ูุธุงุฑุช ุงุฒ ุชูุงู ูุนุงูุช ูุง ู ุนุฑุถ ุฎุฏูุงุช ุงุญุตุงุฆู ู ูุนูููุงุช ุฏุฑ ฺฉุดูุฑ\n\nูุฑุฌุน ูุงุญุฏ ูุดุฑ ูุนูููุงุช ู ุงุญุตุงุฆู ูุง ุฑุณู ุฏุฑ ฺฉุดูุฑ ู ุงุชุฎุงุฐ ุชุตูู ุฏุฑููุฑุฏ ุดู ุฌูุน ุขูุฑุ ุชูุญุฏุ ุชุญูู ู ฺฺฏููฺฏ ุฒูุงู ูุดุฑ ูุนูููุงุช ุงุญุตุงุฆู\n\nุงุฌุฑุง ุชูุงู ูุนุงูุช ูุง ุงุญุตุงุฆู ุจู ุดููู ุณุฑู ูุงุ ุณุฑ ุดูุงุฑ ูุงุ ุณูุฌุด ูุญุงุณุจุงุช ูู ู ุดุงุฎุต ููุ ุชุดุฎุต ู ุชุซุจุช ูุงุฒููุฏ ูุง ูุนูููุงุช ู ุงุญุตุงุฆู ุฏุฑ ฺฉุดูุฑ\n\nุชุซุจุช ู ุงุฑุงุฆู ุขุฎุฑู ุฑูู ูููุณ ฺฉู ฺฉุดูุฑ ุฏุฑ ูุฑ ุณุงู ุจุง ุณุชูุงุฏู ุงุฒ ุฑูุด ูุง ุนูู ุงุญุตุงุฆู\n\nููฺฉุงุฑ ุจุง ูุฒุงุฑุช ูุง ู ุงุฏุงุฑุงุช ุฏููุช ุฏุฑ ุฌูุน ุขูุฑุ ุชูุญุฏุ ุชุญูู ูุนูููุงุช ุงุญุตุงุฆู ู ูุนูููุงุช ุฌุบุฑุงูุง\n\nุชุฃูู ุงุณุชููุงูุช ูุณูฺฉุ ุงูฺฉุดุงู ู ุชุฌูุฒ ุชุตุงููุ ุชุนุงุฑูุ ุงุตููุ ุณุชูุฏุฑุฏ ูุง ู ุฑูุดูุง ุนูู ููุงุณุจ ุฌูุช ุงุณุชูุงุฏู ุฏุฑ ุชูุงู ูุนุงูุช ูุง ู ุนุฑุถ ุฎุฏูุงุช ุงุญุตุงุฆู ุฏุฑ ฺฉุดูุฑ\n\nุงุฌุงุฏุ ูุฏุฑุช ู ุงูฺฉุดุงู ุณุณุชู ูุนูููุงุช ุฌุบุฑุงูุง ูุงุญุฏ ุจู ููุธูุฑ ุฌููฺฏุฑ ุงุฒ ุชฺฉุฑุงุฑ ุนูู ู ูุฏุฑุช ูุคุซุฑ ูุนูููุงุช ุฌุบุฑุงูุง ุฏุฑ ฺฉุดูุฑ ู ูุณุงุนุฏ ุณุงุฎุชู ุฒููู ุฏุณุชุฑุณ ุขุณุงู ุจู ูุนูููุงุช ูุฐฺฉูุฑ ุจุฑุง ููู ุงุณุชูุงุฏู ฺฉููุฏฺฏุงู ุจู ุงุณุชุซูุง ูุนูููุงุช ูุญุฑู\n\nุชุญูู ู ุงุฑุชูุง ุธุฑูุช ุงุญุตุงุฆู ุฏุฑ ฺฉุดูุฑ ู ุชุฃูู ุฑูุงุจุท ฺฉุงุฑ ุจุง ุงุฏุงุฑุงุช ูุณูฺฉ ุจู ุงูููู ู ุงุณุชูุงุฏู ุงุฒ ุชุฌุงุฑุจ ูููู ุขููุง\n\nุงุฌุงุฏ ุณุณุชู ู ุฒุฑุจูุง ุฌูุช ุงุณุชูุงุฏู ู ุชุญูู ุงุฑูุงู ุจุฒุฑฺฏุ ุงูฺฉุดุงู ู ุฑูุชู ุจู ุณูุช ุงุญุตุงุฆู ูุง ุซุจุช ู ุณุฑูุงู ฺฏุฐุงุฑ ุจุดุชุฑ ุจุงูุง ุขู ุฏุฑ ุฏุฑุงุฒ ูุฏุช\nJob Summary\nุจุฑุฑุณ ุฌููุชุฑ ู ุฏูุช ูุง ูููุนุช ูุงู ูุง ูุนูููุงุช ุฌุบุฑุงูุงุ ุชุดุฎุต ู ฺฏุฒุงุฑุด ุฏู ุฎุทุงูุง ูฺฉุงูุ ุชููพูููฺฺฉ ู ุณุงุฎุชุงุฑ ูุงู ูุง ุฌุบุฑุงูุง ุจู ูุฏู ุชุงูู ุฏูุช ู ุณุงุฒฺฏุงุฑ ูฺฉุงู ูุนูููุงุช ุฌุบุฑุงูุง.\nDuties & Responsibilities\nูุธุงู ุงุณุงุณ\nุจุฑุฑุณ ุฌููุชุฑ ูุงู ูุง ูฺฉุชูุฑ ู ุฑุณุชุฑ ุจู ูุฏู ุชุดุฎุต ุฎุทุง ูุง ูฺฉุงู ูุงููุฏ ุฌุงุจุฌุงุ ูููพูุดุงู ูุงุฏุฑุณุชุ ุฎุทูุท ุจุงุฒุ ุฎูุง ู ุงุชุตุงู.\nููุงุณู ูููุนุช ูฺฉุงู ูุงู ูุง ุจุง ููุงุจุน ูุฑุฌุน ูุงููุฏ ุชุตุงูุฑ ูุงููุงุฑู ุงุ GPS Points ู ููุดู ูุง ุจุณ ููพ.\nุงุฌุฑุง ุนููู ูุง ุชููพูููฺฺฉ ุดูุงุณุง ุฎูุงูุงุ ูููพูุดุงู ุงุถุงู ู ุฎุทูุท ุจุงุฒ ุฑู ูุงู ูุง ุฌุบุฑุงูุง.\nุชูู ู ุจุฑูุฒ ูฺฏูุฏุงุดุชู ุฏุชุงุจุณ ูุงู ูุง ุฌุบุฑุงูุง ุฏุฑ ูุทุงุจูุช ุจุง ููุฑู ูุง ู ูุงูุจ ูุง ูุฑุจูุทู\nุชูู ฺฏุฒุงุฑุด ูุง ฺฉูุช ุฌููุชุฑ ูุงู ูุง ุฌุบุฑุงูุง.\nูุธุงู ูุฏุฑุช\nุชูู ู ุชุฑุชุจ ูพูุงู ฺฉุงุฑ ูุงููุงุฑุ ุฑุจุนูุงุฑ ู ุณุงูุงูู ุฏุฑ ูุทุงุจูุช ุจุง ูพูุงู ุขูุฑุชุ ุฌูุช ุจุฏุณุช ุขูุฑุฏู ุงูุฏุงู ุชุนู ุดุฏู .\nุงุฑุงู ฺฏุฒุงุฑุด ูุงููุงุฑุ ุฑุจุนูุงุฑ ู ุณุงูุงูู ู ุนูุฏุงูุถุฑูุฑุช ุงุฒ ูุนุงูุช ูุง ู ุฏุณุช ุขูุฑุฏ ูุง ุจุฎุด ูุฑุจูุทูุ ุจู ููุธูุฑ ูุทูุน ุณุงุฎุชู ุขูุฑ ูุฑุจูุทู.\nุงุฌุฑุง ุณุงุฑ ูุธุงู ฺฉู ุงุฒ ุทุฑู ุขูุฑ ูุฑุจูุทู ูุทุงุจู ูพุงูุณ ุงุฏุงุฑู ุณูพุฑุฏู ูุดูุฏ.\nูุธุงู ููุงููฺฏ\nุชุงูู ุงุฑุชุจุงุท ู ููุงููฺฏ ุจุง ุจุฎุด ูุง ูุฑุจูุทู ุฌูุช ุงุฌุฑุง ุจูุชุฑ ุงููุฑ ูุญููู.\nJob Requirements\nุดุฑุงุท ุงุณุชุฎุฏุงู\nุชุงุจุนุช ุงูุบุงูุณุชุงู ุฑุง ุฏุงุดุชู ุจุงุดุฏ.\nุณู ู ุงุฒ (18) ุณุงู ฺฉูุชุฑ ู ุงุฒ (64) ุณุงู ุจุดุชุฑ ูุจุงุดุฏ.\nุณูู ุชุญุตู\nุฏุงุดุชู ุณูุฏ ุชุญุตู ูุณุงูุณ ุฏุฑ ฺฉ ุงุฒ ุฑุดุชูโูุง ุณุณุชู ูุนูููุงุช ุฌุบุฑุงูุง (GIS)ุ ุฑููุช ุณูุณูฺฏุ ุฌุบุฑุงููุ ุฌููุงุชฺฉ ู ฺฉุฏุณุชุฑุ ุฌูุงููุงุฑูุงุชฺฉุ ุฌูุฏุฒุ ุฌูููฺุ ุฒูู ุดูุงุณ ู ฺฉููพูุชุฑ ุณุงูุณ ุงุฒ ุฏุงุฎู ุง ุฎุงุฑุฌ ฺฉุดูุฑ ฺฉู ุจู ุชุงุฆุฏ ูุฒุงุฑุช ุชุญุตูุงุช ุนุงู ุฑุณุฏู ุจุงุดุฏ.\nุชุฌุฑุจู ฺฉุงุฑ\nูุงุฒ ูุฏุงุฑุฏ.\nููุงุฑุชูุง ูุงุฒู\nุชุณูุท ุจู ฺฉ ุงุฒ ุฒุจุงูโ ูุง ุฑุณู(ูพุดุชู ุง ุฏุฑ) ฺฉุดูุฑ.\nููุงุฑุช โูุง ฺฉููพูุชุฑ ุฏุฑ ุจุฑูุงูู โูุง ูุฑุชุจุท ุจู ูุธูู.\nSubmission Guideline\nุนูุงูููุฏุงู ูุงุฌุฏ ุดุฑุงุท ูุชูุงููุฏ ุจุตูุฑุช ุขููุงู ุจู ููฺฉ ุฐู (\nhttps://forms.gle/gh8gKdyXTkrDyuXK7\n)\nูุฑุงุฌุนู ูููุฏู ุงุณูุงุฏ ูุง ุฎูุด ุฑุง ุจุง ุถูุงู ุขู (ฺฉุงูพ ุชุฐฺฉุฑู ุชุงุจุนุชุ ุงุณูุงุฏ ุชุญุตูุ ูุฏุงุฑฺฉ ุชุฌุฑุจู ฺฉุงุฑ) ุซุจุช ููุฑู ุฏุฑุฎูุงุณุช ุขููุงู ููุงูุฏ.\nููุช: ุงุดุฎุงุต ูุงุฌุฏ ุดุฑุงุท ูุทุงุจู ุฑููููุฏ ููู ุงุณูุงุฏ ุฎูุด ุฑุง ุชุฑุชุจ ู ุซุจุช ููุฑู ุขููุงู ููุงูุฏ.\nุจุฑุง ูุนูููุงุช ุจุดุชุฑ ุจู ุดูุงุฑู:\n0202927048\nุฏุฑ ุชูุงุณ ุดูุฏ.\nFunctional Area\nGIS ( Geographic Information System)\nEngineering Geologist\nComputer Science\nCountries\nAfghanistan\nProvinces\nKabul\nApply Now\nPost Date\nDec 18, 2025\nClosing Date\nJan 27, 2026\nReference\n003\nNumber of Vacancies\n2\nSalary Range\nAs per company salary scale\nYears of Experience\nFresh\nProbation Period\nNot Specified\nContract Type\nPermanent\nContract Duration\n1 year\nContract Extensible\nYes\nMinimum Education\nBachelor's Degree\nGender\nMale\nRelated Jobs\nNETLINKS Plaza | Shahr-e-Naw,\nLane 3, Kabul, Afghanistan\nQuick Links\nAbout Us\nAdvertise with Us\nPrivacy Policy\nFor Companies\nPost a Job\nPost a Job\nPost a Job\nPost a Job\nPost RFP\nPost RFP\nPost RFP\nPost RFP\nPost Training\nPost Training\nPost Training\nPost Training\nFor Jobseekers\nBrowse Jobs\nBrowse Companies\nBuild Resume\nContact\ninfo@jobs.af\nContact Us\nยฉ 2012 - 2026 Jobs.af | All Rights Reserved\nPowered by:\nNETLINKS Ltd",
    "details": {
      "Post Date": "Dec 18, 2025",
      "Closing Date": "Jan 27, 2026",
      "Reference": "003",
      "Number Of Vacancies": "2",
      "Salary Range": "As per company salary scale",
      "Years Of Experience": "Fresh",
      "Probation Period": "Not Specified",
      "Contract Type": "Permanent",
      "Contract Duration": "1 year",
      "Contract Extensible": "Yes",
      "Minimum Education": "Bachelor's Degree",
      "https": "//forms.gle/gh8gKdyXTkrDyuXK7",
      "ููุช": "ุงุดุฎุงุต ูุงุฌุฏ ุดุฑุงุท ูุทุงุจู ุฑููููุฏ ููู ุงุณูุงุฏ ุฎูุด ุฑุง ุชุฑุชุจ ู ุซุจุช ููุฑู ุขููุงู ููุงูุฏ.",
      "Functional Area": "GIS ( Geographic Information System)",
      "Countries": "Afghanistan",
      "Provinces": "Kabul"
    },
    "scraped_at": "2026-01-21T05:00:22Z",
    "apply_emails": [],
    "apply_method": "unknown"
  },
  {
    "url": "https://jobs.af/jobs/adhw-mslky-kntrwl-kyfyt-malwmat-jghrafyayy-anwan-wzyfh",
    "title": "ุนุถู ูุณูฺฉ ฺฉูุชุฑูู ฺฉูุช ูุนูููุงุช ุฌุบุฑุงูุง",
    "company": null,
    "location": "Kabul",
    "closing_date": "2026-01-27",
    "closing_date_raw": "Jan 27, 2026",
    "apply_url": null,
    "description": "๐\nComing Soon The Jobs.af Freelancer Portal\nConnect with top clients and freelancers across Afghanistan all in one place!\nStay Tuned\nJobs\nProcurement Opportunities\nCompanies\nFreelancers\nServices\nProcurement Opportunities\nTrainings\nScholarships\nLogin\nRegister\nุนุถู ูุณูฺฉ ฺฉูุชุฑูู ฺฉูุช ูุนูููุงุช ุฌุบุฑุงูุง\nNational Statistics and Information Authority\nApply Now\nSee all jobs\nุนุถู ูุณูฺฉ ฺฉูุชุฑูู ฺฉูุช ูุนูููุงุช ุฌุบุฑุงูุง\nNational Statistics and Information Authority,\n                                        Kabul, Afghanistan\nApply Now\nBachelor's Degree\nKabul, Afghanistan\n(Kabul)\nFull Time\n4170\nAbout\n                                            National Statistics and Information Authority\nุงุฏุงุฑ ูู ุงุญุตุงุฆู ู ูุนูููุงุช\n\nุฏุฏฺฏุงู:\n\nุฏุงุดุชู ุณุณุชู ูุงุญุฏุ ูุนุงุฑุ ูพุงุณุฎฺฏูุ ูุงุจู ุงุนุชูุงุฏ ุฏุฑ ุณุทุญ ูู ู ุจู ุงููููุ ูพูุง ู ูพุงุฏุงุฑ ุงุญุตุงุฆู ู ูุนูููุงุช ุฏุฑ ฺฉุดูุฑ\n\nูุงููุฑุช:\n\nูุฏุฑุช ู ุงูฺฉุดุงู ุณุณุชู ุงุญุตุงุฆู ู ูุนูููุงุช ุจุฑ ุจูุงุฏ ูุงุฒููุฏ ูุง ฺฉุดูุฑ\n\nูุฏุฑุช ู ุงุฑุงู ูุนูููุงุช ุฏููุ ูุณุชูุฏุ ูุงุจู ุงุทููุงูุ ุจู ูููุนุ ุจุง ฺฉูุช ู ูุงุจู ุงุณุชูุงุฏู ุจุฑุง ุทุฑุญ ูพุงูุณ ูุงุ ุณุงุณุช ฺฏุฐุงุฑ ูุง ุุชุตูู ฺฏุฑ ูุงุ ูพูุงูฺฏุฐุงุฑ ูุงุ ุชุญููุงุชุ ุขฺฏุงู ุนุงููุ ุชุงูู ุดูุงูุช ู ุณุงุฑ ููุงุฑุฏ ุงุฒ ูุฑุฌุน ูุงุญุฏ\n\nุชุฃูู ุงุณุชููุงูุช ูุณูฺฉุ ุจฺฉุงุฑ ฺฏุฑ ุฑูุดูุง ุนููุ ูุนุงุฑ ู ุฑุนุงุช ุงุตูู ุจู ุงูููู ุงุญุตุงุฆู ูุง ุฑุณูุ ุชุฃูู ููุงููฺฏ ู ุฌููฺฏุฑ ุงุฒ ุชฺฉุฑุงุฑ ุนูู ุฏุฑ ุชูุงู ูุนุงูุช ูุง ู ุนุฑุถ ุฎุฏูุงุช ุงุญุตุงุฆู \n\nูุฏุฑุช ุณุณุชู ูุง ูุนูููุงุช ุจู ููุธูุฑ ุงุณุชูุงุฏู ููุซุฑ ุ ุจู ูููุน ู ููู ุฌุงูุจู ุงุฒ ุงุฑูุงู ุฌุงุฑูุ ุงุฑูุงู ุจุฒุฑฺฏ ู ูุนูููุงุช ุฌุบุฑุงูุง ุฏุฑ ุชูู ุงุญุตุงุฆู ูุง ุฑุณู ููฺูุงู ุชุฑูุฌุ ุชููุช ู ูพุงู ฺฏุฐุงุฑ ุงุญุตุงุฆู ูุง ุซุจุช.\n\nูุธุงู ู ุตูุงุญุช ูุง:\n\nุงุฌุงุฏุ ูุฏุฑุช ู ุงูฺฉุดุงู ุณุณุชู ูุงุญุฏ ุงุญุตุงุฆู ู ูุนูููุงุช ุฏุฑ ฺฉุดูุฑ\n\nุฌูุน ุขูุฑุ ุชูุญุฏุ ุชุญูู ู ูุดุฑ ูุนูููุงุช ุฏููุ ูุณุชูุฏุ ูุงุจู ุงุทููุงูุ ุจู ูููุน ู ุจุง ฺฉูุช ุงุญุตุงุฆู ุฏุฑ ุฑุงุจุทู ุจู ูููุณุ ุงููุฑ ุชุฌุงุฑุชุ ุตูุนุชุ ุฒุฑุงุนุชุ ูุงูุ ุงุฌุชูุงุนุ ุงูุชุตุงุฏุ ุตุญุ ูุญุท ู ูุถุน ูุนุงูุช ูุง ุนููู ูุฑุฏู\n\nุชุฃูู ููุงููฺฏุ ุฌููฺฏุฑ ุงุฒ ุชฺฉุฑุงุฑ ุนููุ ุงูุณุฌุงู ู ูุธุงุฑุช ุงุฒ ุชูุงู ูุนุงูุช ูุง ู ุนุฑุถ ุฎุฏูุงุช ุงุญุตุงุฆู ู ูุนูููุงุช ุฏุฑ ฺฉุดูุฑ\n\nูุฑุฌุน ูุงุญุฏ ูุดุฑ ูุนูููุงุช ู ุงุญุตุงุฆู ูุง ุฑุณู ุฏุฑ ฺฉุดูุฑ ู ุงุชุฎุงุฐ ุชุตูู ุฏุฑููุฑุฏ ุดู ุฌูุน ุขูุฑุ ุชูุญุฏุ ุชุญูู ู ฺฺฏููฺฏ ุฒูุงู ูุดุฑ ูุนูููุงุช ุงุญุตุงุฆู\n\nุงุฌุฑุง ุชูุงู ูุนุงูุช ูุง ุงุญุตุงุฆู ุจู ุดููู ุณุฑู ูุงุ ุณุฑ ุดูุงุฑ ูุงุ ุณูุฌุด ูุญุงุณุจุงุช ูู ู ุดุงุฎุต ููุ ุชุดุฎุต ู ุชุซุจุช ูุงุฒููุฏ ูุง ูุนูููุงุช ู ุงุญุตุงุฆู ุฏุฑ ฺฉุดูุฑ\n\nุชุซุจุช ู ุงุฑุงุฆู ุขุฎุฑู ุฑูู ูููุณ ฺฉู ฺฉุดูุฑ ุฏุฑ ูุฑ ุณุงู ุจุง ุณุชูุงุฏู ุงุฒ ุฑูุด ูุง ุนูู ุงุญุตุงุฆู\n\nููฺฉุงุฑ ุจุง ูุฒุงุฑุช ูุง ู ุงุฏุงุฑุงุช ุฏููุช ุฏุฑ ุฌูุน ุขูุฑุ ุชูุญุฏุ ุชุญูู ูุนูููุงุช ุงุญุตุงุฆู ู ูุนูููุงุช ุฌุบุฑุงูุง\n\nุชุฃูู ุงุณุชููุงูุช ูุณูฺฉุ ุงูฺฉุดุงู ู ุชุฌูุฒ ุชุตุงููุ ุชุนุงุฑูุ ุงุตููุ ุณุชูุฏุฑุฏ ูุง ู ุฑูุดูุง ุนูู ููุงุณุจ ุฌูุช ุงุณุชูุงุฏู ุฏุฑ ุชูุงู ูุนุงูุช ูุง ู ุนุฑุถ ุฎุฏูุงุช ุงุญุตุงุฆู ุฏุฑ ฺฉุดูุฑ\n\nุงุฌุงุฏุ ูุฏุฑุช ู ุงูฺฉุดุงู ุณุณุชู ูุนูููุงุช ุฌุบุฑุงูุง ูุงุญุฏ ุจู ููุธูุฑ ุฌููฺฏุฑ ุงุฒ ุชฺฉุฑุงุฑ ุนูู ู ูุฏุฑุช ูุคุซุฑ ูุนูููุงุช ุฌุบุฑุงูุง ุฏุฑ ฺฉุดูุฑ ู ูุณุงุนุฏ ุณุงุฎุชู ุฒููู ุฏุณุชุฑุณ ุขุณุงู ุจู ูุนูููุงุช ูุฐฺฉูุฑ ุจุฑุง ููู ุงุณุชูุงุฏู ฺฉููุฏฺฏุงู ุจู ุงุณุชุซูุง ูุนูููุงุช ูุญุฑู\n\nุชุญูู ู ุงุฑุชูุง ุธุฑูุช ุงุญุตุงุฆู ุฏุฑ ฺฉุดูุฑ ู ุชุฃูู ุฑูุงุจุท ฺฉุงุฑ ุจุง ุงุฏุงุฑุงุช ูุณูฺฉ ุจู ุงูููู ู ุงุณุชูุงุฏู ุงุฒ ุชุฌุงุฑุจ ูููู ุขููุง\n\nุงุฌุงุฏ ุณุณุชู ู ุฒุฑุจูุง ุฌูุช ุงุณุชูุงุฏู ู ุชุญูู ุงุฑูุงู ุจุฒุฑฺฏุ ุงูฺฉุดุงู ู ุฑูุชู ุจู ุณูุช ุงุญุตุงุฆู ูุง ุซุจุช ู ุณุฑูุงู ฺฏุฐุงุฑ ุจุดุชุฑ ุจุงูุง ุขู ุฏุฑ ุฏุฑุงุฒ ูุฏุช\nJob Summary\nุจุฑุฑุณ ฺฉูุช ูุนูููุงุช ุฌุบุฑุงูุง ุงุฒ ูุจู ุฏูุช ุชูุตูุ ุฏูุช ุฒูุงูุ ุณุงุฒฺฏุงุฑ ุณุงุฎุชุงุฑ ู ุฌุงูุนุช ุจู ููุธูุฑ ุงุฑุงุฆู ุงุฑูุงู ุจุง ฺฉูุช ูุนูููุงุช ุฌุบุฑุงูุง.\nDuties & Responsibilities\nูุธุงู ุงุณุงุณ\nุจุฑุฑุณ ฺฉูุช ูุนูููุงุช ุชูุตู ูุงู ูุง ุฌุบุฑุงูุง.\nุจุฑุฑุณ ฺฉุงูู ุจูุฏู ูุนูููุงุช ู ุซุจุช ุจุฎุด ูุง ูุงูุต ุฌูุช ุงุตูุงุญ ุขููุง.\nุฏุฑุฌ ุงูุชู ูุง ุจุฑุฑุณ ุฏุฑ ููุฑู ูุง ูุดุฎุต ุดุฏู ู ุชูู ฺฏุฒุงุฑุด ูุฑุจูุทู.\nููฺฉุงุฑ ุฏุฑ ุชุทุจู ฺฺฉ ูุณุช ูุง ฺฉูุชุฑูู ฺฉูุช ุดุงูู ุฏูุชุ ุณุงุฒฺฏุงุฑ ู ฺฉุงูู ุจูุฏู ูุนูููุงุช.\nููฺฉุงุฑ ุฏุฑ ุชูุธู ู ุจุฑูุฒ ูฺฏูุฏุงุดุชู ุฏุชุงุจุณ ูุงู ูุง ุจุฑุฑุณ ุดุฏู ุจุง ุฏุฑุฌ ูุถุนุช ู ฺฉูุช ุขููุง.\nุฑุนุงุช ุฏูู ุทุฑุฒุงูุนูู ูุง ู ูุนุงุฑ ูุง ฺฉูุชุฑูู ฺฉูุช ุฏุฑ ุงููุฑ ูุฑุจูุทู.\nููฺฉุงุฑ ุฏุฑ ููุงุณู ูุนูููุงุช ูุงู ูุง ุฌุบุฑุงูุง ุจุง ููุงุจุน ูุฑุฌุน ูุจูู ุดุฏู.\nูุธุงู ูุฏุฑุช\nุชูู ู ุชุฑุชุจ ูพูุงู ฺฉุงุฑ ูุงููุงุฑุ ุฑุจุนูุงุฑ ู ุณุงูุงูู ุฏุฑ ูุทุงุจูุช ุจุง ูพูุงู ุขูุฑุชุ ุฌูุช ุจุฏุณุช ุขูุฑุฏู ุงูุฏุงู ุชุนู ุดุฏู .\nุงุฑุงู ฺฏุฒุงุฑุด ูุงููุงุฑุ ุฑุจุนูุงุฑ ู ุณุงูุงูู ู ุนูุฏุงูุถุฑูุฑุช ุงุฒ ูุนุงูุช ูุง ู ุฏุณุช ุขูุฑุฏ ูุง ุจุฎุด ูุฑุจูุทูุ ุจู ููุธูุฑ ูุทูุน ุณุงุฎุชู ุขูุฑ ูุฑุจูุทู.\nุงุฌุฑุง ุณุงุฑ ูุธุงู ฺฉู ุงุฒ ุทุฑู ุขูุฑ ูุฑุจูุทู ูุทุงุจู ูพุงูุณ ุงุฏุงุฑู ุณูพุฑุฏู ูุดูุฏ.\nูุธุงู ููุงููฺฏ\nุชุงูู ุงุฑุชุจุงุท ู ููุงููฺฏ ุจุง ุจุฎุด ูุง ูุฑุจูุทู ุฌูุช ุงุฌุฑุง ุจูุชุฑ ุงููุฑ ูุญููู.\nJob Requirements\nุดุฑุงุท ุงุณุชุฎุฏุงู\nุชุงุจุนุช ุงูุบุงูุณุชุงู ุฑุง ุฏุงุดุชู ุจุงุดุฏ.\nุณู ู ุงุฒ (18) ุณุงู ฺฉูุชุฑ ู ุงุฒ (64) ุณุงู ุจุดุชุฑ ูุจุงุดุฏ.\nุณูู ุชุญุตู\nุฏุงุดุชู ุณูุฏ ุชุญุตู ูุณุงูุณ ุฏุฑ ฺฉ ุงุฒ ุฑุดุชูโูุง ุณุณุชู ูุนูููุงุช ุฌุบุฑุงูุง (GIS)ุ ุฑููุช ุณูุณูฺฏุ ุฌุบุฑุงููุ ุฌููุงุชฺฉ ู ฺฉุฏุณุชุฑุ ุฌูุงููุงุฑูุงุชฺฉุ ุฌูุฏุฒุ ุฌูููฺุ ุฒูู ุดูุงุณ ู ฺฉููพูุชุฑ ุณุงูุณ ุงุฒ ุฏุงุฎู ุง ุฎุงุฑุฌ ฺฉุดูุฑ ฺฉู ุจู ุชุงุฆุฏ ูุฒุงุฑุช ุชุญุตูุงุช ุนุงู ุฑุณุฏู ุจุงุดุฏ.\nุชุฌุฑุจู ฺฉุงุฑ\nูุงุฒ ูุฏุงุฑุฏ.\nููุงุฑุชูุง ูุงุฒู\nุชุณูุท ุจู ฺฉ ุงุฒ ุฒุจุงูโ ูุง ุฑุณู(ูพุดุชู ุง ุฏุฑ) ฺฉุดูุฑ.\nููุงุฑุช โูุง ฺฉููพูุชุฑ ุฏุฑ ุจุฑูุงูู โูุง ูุฑุชุจุท ุจู ูุธูู.\nSubmission Guideline\nุนูุงูููุฏุงู ูุงุฌุฏ ุดุฑุงุท ูุชูุงููุฏ ุจุตูุฑุช ุขููุงู ุจู ููฺฉ ุฐู (\nhttps://forms.gle/gh8gKdyXTkrDyuXK7\n)\nูุฑุงุฌุนู ูููุฏู ุงุณูุงุฏ ูุง ุฎูุด ุฑุง ุจุง ุถูุงู ุขู (ฺฉุงูพ ุชุฐฺฉุฑู ุชุงุจุนุชุ ุงุณูุงุฏ ุชุญุตูุ ูุฏุงุฑฺฉ ุชุฌุฑุจู ฺฉุงุฑ) ุซุจุช ููุฑู ุฏุฑุฎูุงุณุช ุขููุงู ููุงูุฏ.\nููุช: ุงุดุฎุงุต ูุงุฌุฏ ุดุฑุงุท ูุทุงุจู ุฑููููุฏ ููู ุงุณูุงุฏ ุฎูุด ุฑุง ุชุฑุชุจ ู ุซุจุช ููุฑู ุขููุงู ููุงูุฏ.\nุจุฑุง ูุนูููุงุช ุจุดุชุฑ ุจู ุดูุงุฑู:\n0202927048\nุฏุฑ ุชูุงุณ ุดูุฏ.\nFunctional Area\nGIS ( Geographic Information System)\nEngineering Geologist\nComputer Science\nCountries\nAfghanistan\nProvinces\nKabul\nApply Now\nPost Date\nDec 18, 2025\nClosing Date\nJan 27, 2026\nReference\n004\nNumber of Vacancies\n2\nSalary Range\nAs per company salary scale\nYears of Experience\nFresh\nProbation Period\nNot Specified\nContract Type\nPermanent\nContract Duration\n1 year\nContract Extensible\nYes\nMinimum Education\nBachelor's Degree\nGender\nMale\nRelated Jobs\nNETLINKS Plaza | Shahr-e-Naw,\nLane 3, Kabul, Afghanistan\nQuick Links\nAbout Us\nAdvertise with Us\nPrivacy Policy\nFor Companies\nPost a Job\nPost a Job\nPost a Job\nPost a Job\nPost RFP\nPost RFP\nPost RFP\nPost RFP\nPost Training\nPost Training\nPost Training\nPost Training\nFor Jobseekers\nBrowse Jobs\nBrowse Companies\nBuild Resume\nContact\ninfo@jobs.af\nContact Us\nยฉ 2012 - 2026 Jobs.af | All Rights Reserved\nPowered by:\nNETLINKS Ltd",
    "details": {
      "Post Date": "Dec 18, 2025",
      "Closing Date": "Jan 27, 2026",
      "Reference": "004",
      "Number Of Vacancies": "2",
      "Salary Range": "As per company salary scale",
      "Years Of Experience": "Fresh",
      "Probation Period": "Not Specified",
      "Contract Type": "Permanent",
      "Contract Duration": "1 year",
      "Contract Extensible": "Yes",
      "Minimum Education": "Bachelor's Degree",
      "https": "//forms.gle/gh8gKdyXTkrDyuXK7",
      "ููุช": "ุงุดุฎุงุต ูุงุฌุฏ ุดุฑุงุท ูุทุงุจู ุฑููููุฏ ููู ุงุณูุงุฏ ุฎูุด ุฑุง ุชุฑุชุจ ู ุซุจุช ููุฑู ุขููุงู ููุงูุฏ.",
      "Functional Area": "GIS ( Geographic Information System)",
      "Countries": "Afghanistan",
      "Provinces": "Kabul"
    },
    "scraped_at": "2026-01-21T05:00:22Z",
    "apply_emails": [],
    "apply_method": "unknown"
  },
  {
    "url": "https://jobs.af/jobs/adhw-mslky-myta-dyta",
    "title": "ุนุถู ูุณูฺฉ ูุชุง ุฏุชุง",
    "company": null,
    "location": "Kabul",
    "closing_date": "2026-01-27",
    "closing_date_raw": "Jan 27, 2026",
    "apply_url": null,
    "description": "๐\nComing Soon The Jobs.af Freelancer Portal\nConnect with top clients and freelancers across Afghanistan all in one place!\nStay Tuned\nJobs\nProcurement Opportunities\nCompanies\nFreelancers\nServices\nProcurement Opportunities\nTrainings\nScholarships\nLogin\nRegister\nุนุถู ูุณูฺฉ ูุชุง ุฏุชุง\nNational Statistics and Information Authority\nApply Now\nSee all jobs\nุนุถู ูุณูฺฉ ูุชุง ุฏุชุง\nNational Statistics and Information Authority,\n                                        Kabul, Afghanistan\nApply Now\nBachelor's Degree\nKabul, Afghanistan\n(Kabul)\nFull Time\n4105\nAbout\n                                            National Statistics and Information Authority\nุงุฏุงุฑ ูู ุงุญุตุงุฆู ู ูุนูููุงุช\n\nุฏุฏฺฏุงู:\n\nุฏุงุดุชู ุณุณุชู ูุงุญุฏุ ูุนุงุฑุ ูพุงุณุฎฺฏูุ ูุงุจู ุงุนุชูุงุฏ ุฏุฑ ุณุทุญ ูู ู ุจู ุงููููุ ูพูุง ู ูพุงุฏุงุฑ ุงุญุตุงุฆู ู ูุนูููุงุช ุฏุฑ ฺฉุดูุฑ\n\nูุงููุฑุช:\n\nูุฏุฑุช ู ุงูฺฉุดุงู ุณุณุชู ุงุญุตุงุฆู ู ูุนูููุงุช ุจุฑ ุจูุงุฏ ูุงุฒููุฏ ูุง ฺฉุดูุฑ\n\nูุฏุฑุช ู ุงุฑุงู ูุนูููุงุช ุฏููุ ูุณุชูุฏุ ูุงุจู ุงุทููุงูุ ุจู ูููุนุ ุจุง ฺฉูุช ู ูุงุจู ุงุณุชูุงุฏู ุจุฑุง ุทุฑุญ ูพุงูุณ ูุงุ ุณุงุณุช ฺฏุฐุงุฑ ูุง ุุชุตูู ฺฏุฑ ูุงุ ูพูุงูฺฏุฐุงุฑ ูุงุ ุชุญููุงุชุ ุขฺฏุงู ุนุงููุ ุชุงูู ุดูุงูุช ู ุณุงุฑ ููุงุฑุฏ ุงุฒ ูุฑุฌุน ูุงุญุฏ\n\nุชุฃูู ุงุณุชููุงูุช ูุณูฺฉุ ุจฺฉุงุฑ ฺฏุฑ ุฑูุดูุง ุนููุ ูุนุงุฑ ู ุฑุนุงุช ุงุตูู ุจู ุงูููู ุงุญุตุงุฆู ูุง ุฑุณูุ ุชุฃูู ููุงููฺฏ ู ุฌููฺฏุฑ ุงุฒ ุชฺฉุฑุงุฑ ุนูู ุฏุฑ ุชูุงู ูุนุงูุช ูุง ู ุนุฑุถ ุฎุฏูุงุช ุงุญุตุงุฆู \n\nูุฏุฑุช ุณุณุชู ูุง ูุนูููุงุช ุจู ููุธูุฑ ุงุณุชูุงุฏู ููุซุฑ ุ ุจู ูููุน ู ููู ุฌุงูุจู ุงุฒ ุงุฑูุงู ุฌุงุฑูุ ุงุฑูุงู ุจุฒุฑฺฏ ู ูุนูููุงุช ุฌุบุฑุงูุง ุฏุฑ ุชูู ุงุญุตุงุฆู ูุง ุฑุณู ููฺูุงู ุชุฑูุฌุ ุชููุช ู ูพุงู ฺฏุฐุงุฑ ุงุญุตุงุฆู ูุง ุซุจุช.\n\nูุธุงู ู ุตูุงุญุช ูุง:\n\nุงุฌุงุฏุ ูุฏุฑุช ู ุงูฺฉุดุงู ุณุณุชู ูุงุญุฏ ุงุญุตุงุฆู ู ูุนูููุงุช ุฏุฑ ฺฉุดูุฑ\n\nุฌูุน ุขูุฑุ ุชูุญุฏุ ุชุญูู ู ูุดุฑ ูุนูููุงุช ุฏููุ ูุณุชูุฏุ ูุงุจู ุงุทููุงูุ ุจู ูููุน ู ุจุง ฺฉูุช ุงุญุตุงุฆู ุฏุฑ ุฑุงุจุทู ุจู ูููุณุ ุงููุฑ ุชุฌุงุฑุชุ ุตูุนุชุ ุฒุฑุงุนุชุ ูุงูุ ุงุฌุชูุงุนุ ุงูุชุตุงุฏุ ุตุญุ ูุญุท ู ูุถุน ูุนุงูุช ูุง ุนููู ูุฑุฏู\n\nุชุฃูู ููุงููฺฏุ ุฌููฺฏุฑ ุงุฒ ุชฺฉุฑุงุฑ ุนููุ ุงูุณุฌุงู ู ูุธุงุฑุช ุงุฒ ุชูุงู ูุนุงูุช ูุง ู ุนุฑุถ ุฎุฏูุงุช ุงุญุตุงุฆู ู ูุนูููุงุช ุฏุฑ ฺฉุดูุฑ\n\nูุฑุฌุน ูุงุญุฏ ูุดุฑ ูุนูููุงุช ู ุงุญุตุงุฆู ูุง ุฑุณู ุฏุฑ ฺฉุดูุฑ ู ุงุชุฎุงุฐ ุชุตูู ุฏุฑููุฑุฏ ุดู ุฌูุน ุขูุฑุ ุชูุญุฏุ ุชุญูู ู ฺฺฏููฺฏ ุฒูุงู ูุดุฑ ูุนูููุงุช ุงุญุตุงุฆู\n\nุงุฌุฑุง ุชูุงู ูุนุงูุช ูุง ุงุญุตุงุฆู ุจู ุดููู ุณุฑู ูุงุ ุณุฑ ุดูุงุฑ ูุงุ ุณูุฌุด ูุญุงุณุจุงุช ูู ู ุดุงุฎุต ููุ ุชุดุฎุต ู ุชุซุจุช ูุงุฒููุฏ ูุง ูุนูููุงุช ู ุงุญุตุงุฆู ุฏุฑ ฺฉุดูุฑ\n\nุชุซุจุช ู ุงุฑุงุฆู ุขุฎุฑู ุฑูู ูููุณ ฺฉู ฺฉุดูุฑ ุฏุฑ ูุฑ ุณุงู ุจุง ุณุชูุงุฏู ุงุฒ ุฑูุด ูุง ุนูู ุงุญุตุงุฆู\n\nููฺฉุงุฑ ุจุง ูุฒุงุฑุช ูุง ู ุงุฏุงุฑุงุช ุฏููุช ุฏุฑ ุฌูุน ุขูุฑุ ุชูุญุฏุ ุชุญูู ูุนูููุงุช ุงุญุตุงุฆู ู ูุนูููุงุช ุฌุบุฑุงูุง\n\nุชุฃูู ุงุณุชููุงูุช ูุณูฺฉุ ุงูฺฉุดุงู ู ุชุฌูุฒ ุชุตุงููุ ุชุนุงุฑูุ ุงุตููุ ุณุชูุฏุฑุฏ ูุง ู ุฑูุดูุง ุนูู ููุงุณุจ ุฌูุช ุงุณุชูุงุฏู ุฏุฑ ุชูุงู ูุนุงูุช ูุง ู ุนุฑุถ ุฎุฏูุงุช ุงุญุตุงุฆู ุฏุฑ ฺฉุดูุฑ\n\nุงุฌุงุฏุ ูุฏุฑุช ู ุงูฺฉุดุงู ุณุณุชู ูุนูููุงุช ุฌุบุฑุงูุง ูุงุญุฏ ุจู ููุธูุฑ ุฌููฺฏุฑ ุงุฒ ุชฺฉุฑุงุฑ ุนูู ู ูุฏุฑุช ูุคุซุฑ ูุนูููุงุช ุฌุบุฑุงูุง ุฏุฑ ฺฉุดูุฑ ู ูุณุงุนุฏ ุณุงุฎุชู ุฒููู ุฏุณุชุฑุณ ุขุณุงู ุจู ูุนูููุงุช ูุฐฺฉูุฑ ุจุฑุง ููู ุงุณุชูุงุฏู ฺฉููุฏฺฏุงู ุจู ุงุณุชุซูุง ูุนูููุงุช ูุญุฑู\n\nุชุญูู ู ุงุฑุชูุง ุธุฑูุช ุงุญุตุงุฆู ุฏุฑ ฺฉุดูุฑ ู ุชุฃูู ุฑูุงุจุท ฺฉุงุฑ ุจุง ุงุฏุงุฑุงุช ูุณูฺฉ ุจู ุงูููู ู ุงุณุชูุงุฏู ุงุฒ ุชุฌุงุฑุจ ูููู ุขููุง\n\nุงุฌุงุฏ ุณุณุชู ู ุฒุฑุจูุง ุฌูุช ุงุณุชูุงุฏู ู ุชุญูู ุงุฑูุงู ุจุฒุฑฺฏุ ุงูฺฉุดุงู ู ุฑูุชู ุจู ุณูุช ุงุญุตุงุฆู ูุง ุซุจุช ู ุณุฑูุงู ฺฏุฐุงุฑ ุจุดุชุฑ ุจุงูุง ุขู ุฏุฑ ุฏุฑุงุฒ ูุฏุช\nJob Summary\nุชูู ู ุชุฌุฏุฏ ูุชุง ุฏุชุง ู ฺฏุฒุงุฑุด ูุง ูุนุฑู ู ูุดุฎุตุงุช ูุงู ูุง ุฌุบุฑุงูุง.\nDuties & Responsibilities\nูุธุงู ุงุณุงุณ\nุซุจุช ู ุชุฌุฏุฏ ูุชุง ุฏุชุงยูุฑุจูุท ุจู ูุงู ูุง ุฌุบุฑุงูุง ุฏุฑ ุณุณุชู ูุนูููุงุช ุฌุบุฑุงูุง.\nุงุทููุงู ุงุฒ ุฏูุชุ ฺฉูพุงุฑฺฺฏ ุณุงุฒ ูุชุง ุฏุชุง ูุงู ูุง ุฌุบุฑุงูุง.\nูุนุงุฑ ุณุงุฒ ูุชุง ุฏุชุง ูุงู ูุง ุฌุบุฑุงูุง.\nููฺฉุงุฑ ุจุง ุจุฎุด ูุฑุจูุทู ุจุฑุง ุชุทุจู ูุนุงุฑุงุช ูุชุง ุฏุชุง ูุงู ูุง ุฌุบุฑุงูุง.\nููฺฉุงุฑ ุฏุฑ ุชูยุฑุงูููุง ูุง ู ุฏุณุชูุฑ ุงูุนูู ูุง ูุชุง ุฏุชุง ุจุฑุง ฺฉุงุฑุจุฑุงู ู ุฐููุนุงู.\nููฺฉุงุฑ ุฏุฑ ุชู ุฑูุด ฺฉุฏ ฺฏุฐุงุฑ ุจุฑุง ูุงู ูุง ุฌุบุฑุงูุง.\nุชูู ู ุชุฑุชุจ ูุนุฑู ุฎูุงุตู ุจุฑุง ูุงู ูุง ุฌุบุฑุงูุง ุฌูุช ุชูุถุญ ูุดุฎุตุงุช ู ุงุณุชูุงุฏ ูุคุซุฑ ุขููุง.\nูุงุถุญ ุณุงุฎุชู ฺฉูุฏ ุงุตุทูุงุญุงุช ฺฉู ุฏุฑ ูุงู ูุง ุฌุบุฑุงูุง ุงุณุชูุงุฏู ูฺฏุฑุฏุฏ.\nูุดุฎุต ุณุงุฎุชู ูุถุนุช ุงูุชุดุงุฑ ุฏุชุง ูุง ุฌุบุฑุงูุง ูุธุฑ ุจู ุตูู ุจูุฏ ุฏุชุง ูุง ุฌุบุฑุงูุง.\nูุธุงู ูุฏุฑุช\nุชูู ู ุชุฑุชุจ ูพูุงู ฺฉุงุฑ ูุงููุงุฑุ ุฑุจุนูุงุฑ ู ุณุงูุงูู ุฏุฑ ูุทุงุจูุช ุจุง ูพูุงู ุขูุฑุชุ ุฌูุช ุจุฏุณุช ุขูุฑุฏู ุงูุฏุงู ุชุนู ุดุฏู .\nุงุฑุงู ฺฏุฒุงุฑุด ูุงููุงุฑุ ุฑุจุนูุงุฑ ู ุณุงูุงูู ู ุนูุฏุงูุถุฑูุฑุช ุงุฒ ูุนุงูุช ูุง ู ุฏุณุช ุขูุฑุฏ ูุง ุจุฎุด ูุฑุจูุทูุ ุจู ููุธูุฑ ูุทูุน ุณุงุฎุชู ุขูุฑ ูุฑุจูุทู.\nุงุฌุฑุง ุณุงุฑ ูุธุงู ฺฉู ุงุฒ ุทุฑู ุขูุฑ ูุฑุจูุทู ูุทุงุจู ูพุงูุณ ุงุฏุงุฑู ุณูพุฑุฏู ูุดูุฏ.\nูุธุงู ููุงููฺฏ\nุชุงูู ุงุฑุชุจุงุท ู ููุงููฺฏ ุจุง ุจุฎุด ูุง ูุฑุจูุทู ุฌูุช ุงุฌุฑุง ุจูุชุฑ ุงููุฑ ูุญููู.\nJob Requirements\nุดุฑุงุท ุงุณุชุฎุฏุงู\nุชุงุจุนุช ุงูุบุงูุณุชุงู ุฑุง ุฏุงุดุชู ุจุงุดุฏ.\nุณู ู ุงุฒ (18) ุณุงู ฺฉูุชุฑ ู ุงุฒ (64) ุณุงู ุจุดุชุฑ ูุจุงุดุฏ.\nุณูู ุชุญุตู\nุฏุงุดุชู ุณูุฏ ุชุญุตู ูุณุงูุณ ุฏุฑ ฺฉ ุงุฒ ุฑุดุชูโูุง ุณุณุชู ูุนูููุงุช ุฌุบุฑุงูุง (GIS)ุ ุฑููุช ุณูุณูฺฏุ ุฌุบุฑุงููุ ุฌููุงุชฺฉ ู ฺฉุฏุณุชุฑุ ุฌูุงููุงุฑูุงุชฺฉุ ุฌูุฏุฒุ ุฌูููฺุ ุฒูู ุดูุงุณ ู ฺฉููพูุชุฑ ุณุงูุณ ุงุฒ ุฏุงุฎู ุง ุฎุงุฑุฌ ฺฉุดูุฑ ฺฉู ุจู ุชุงุฆุฏ ูุฒุงุฑุช ุชุญุตูุงุช ุนุงู ุฑุณุฏู ุจุงุดุฏ.\nุชุฌุฑุจู ฺฉุงุฑ\nูุงุฒ ูุฏุงุฑุฏ.\nููุงุฑุชูุง ูุงุฒู\nุชุณูุท ุจู ฺฉ ุงุฒ ุฒุจุงูโ ูุง ุฑุณู(ูพุดุชู ุง ุฏุฑ) ฺฉุดูุฑ.\nููุงุฑุช โูุง ฺฉููพูุชุฑ ุฏุฑ ุจุฑูุงูู โูุง ูุฑุชุจุท ุจู ูุธูู.\nSubmission Guideline\nุนูุงูููุฏุงู ูุงุฌุฏ ุดุฑุงุท ูุชูุงููุฏ ุจุตูุฑุช ุขููุงู ุจู ููฺฉ ุฐู (\nhttps://forms.gle/gh8gKdyXTkrDyuXK7\n)\nูุฑุงุฌุนู ูููุฏู ุงุณูุงุฏ ูุง ุฎูุด ุฑุง ุจุง ุถูุงู ุขู (ฺฉุงูพ ุชุฐฺฉุฑู ุชุงุจุนุชุ ุงุณูุงุฏ ุชุญุตูุ ูุฏุงุฑฺฉ ุชุฌุฑุจู ฺฉุงุฑ) ุซุจุช ููุฑู ุฏุฑุฎูุงุณุช ุขููุงู ููุงูุฏ.\nููุช: ุงุดุฎุงุต ูุงุฌุฏ ุดุฑุงุท ูุทุงุจู ุฑููููุฏ ููู ุงุณูุงุฏ ุฎูุด ุฑุง ุชุฑุชุจ ู ุซุจุช ููุฑู ุขููุงู ููุงูุฏ.\nุจุฑุง ูุนูููุงุช ุจุดุชุฑ ุจู ุดูุงุฑู:\n0202927048\nุฏุฑ ุชูุงุณ ุดูุฏ.\nFunctional Area\nGIS ( Geographic Information System)\nEngineering Geologist\nComputer Science\nCountries\nAfghanistan\nProvinces\nKabul\nApply Now\nPost Date\nDec 18, 2025\nClosing Date\nJan 27, 2026\nReference\n005\nNumber of Vacancies\n1\nSalary Range\nAs per company salary scale\nYears of Experience\nFresh\nProbation Period\nNot Specified\nContract Type\nPermanent\nContract Duration\n1 year\nContract Extensible\nYes\nMinimum Education\nBachelor's Degree\nGender\nMale\nRelated Jobs\nNETLINKS Plaza | Shahr-e-Naw,\nLane 3, Kabul, Afghanistan\nQuick Links\nAbout Us\nAdvertise with Us\nPrivacy Policy\nFor Companies\nPost a Job\nPost a Job\nPost a Job\nPost a Job\nPost RFP\nPost RFP\nPost RFP\nPost RFP\nPost Training\nPost Training\nPost Training\nPost Training\nFor Jobseekers\nBrowse Jobs\nBrowse Companies\nBuild Resume\nContact\ninfo@jobs.af\nContact Us\nยฉ 2012 - 2026 Jobs.af | All Rights Reserved\nPowered by:\nNETLINKS Ltd",
    "details": {
      "Post Date": "Dec 18, 2025",
      "Closing Date": "Jan 27, 2026",
      "Reference": "005",
      "Number Of Vacancies": "1",
      "Salary Range": "As per company salary scale",
      "Years Of Experience": "Fresh",
      "Probation Period": "Not Specified",
      "Contract Type": "Permanent",
      "Contract Duration": "1 year",
      "Contract Extensible": "Yes",
      "Minimum Education": "Bachelor's Degree",
      "https": "//forms.gle/gh8gKdyXTkrDyuXK7",
      "ููุช": "ุงุดุฎุงุต ูุงุฌุฏ ุดุฑุงุท ูุทุงุจู ุฑููููุฏ ููู ุงุณูุงุฏ ุฎูุด ุฑุง ุชุฑุชุจ ู ุซุจุช ููุฑู ุขููุงู ููุงูุฏ.",
      "Functional Area": "GIS ( Geographic Information System)",
      "Countries": "Afghanistan",
      "Provinces": "Kabul"
    },
    "scraped_at": "2026-01-21T05:00:22Z",
    "apply_emails": [],
    "apply_method": "unknown"
  },
  {
    "url": "https://jobs.af/jobs/adhw-mslky-trh-w-ttbyq-palysy-hay-jghrafyayy",
    "title": "ุนุถู ูุณูฺฉ ุทุฑุญ ู ุชุทุจู ูพุงูุณ ูุง ุฌุบุฑุงูุง",
    "company": null,
    "location": "Kabul",
    "closing_date": "2026-01-27",
    "closing_date_raw": "Jan 27, 2026",
    "apply_url": null,
    "description": "๐\nComing Soon The Jobs.af Freelancer Portal\nConnect with top clients and freelancers across Afghanistan all in one place!\nStay Tuned\nJobs\nProcurement Opportunities\nCompanies\nFreelancers\nServices\nProcurement Opportunities\nTrainings\nScholarships\nLogin\nRegister\nุนุถู ูุณูฺฉ ุทุฑุญ ู ุชุทุจู ูพุงูุณ ูุง ุฌุบุฑุงูุง\nNational Statistics and Information Authority\nApply Now\nSee all jobs\nุนุถู ูุณูฺฉ ุทุฑุญ ู ุชุทุจู ูพุงูุณ ูุง ุฌุบุฑุงูุง\nNational Statistics and Information Authority,\n                                        Kabul, Afghanistan\nApply Now\nBachelor's Degree\nKabul, Afghanistan\n(Kabul)\nFull Time\n1995\nAbout\n                                            National Statistics and Information Authority\nุงุฏุงุฑ ูู ุงุญุตุงุฆู ู ูุนูููุงุช\n\nุฏุฏฺฏุงู:\n\nุฏุงุดุชู ุณุณุชู ูุงุญุฏุ ูุนุงุฑุ ูพุงุณุฎฺฏูุ ูุงุจู ุงุนุชูุงุฏ ุฏุฑ ุณุทุญ ูู ู ุจู ุงููููุ ูพูุง ู ูพุงุฏุงุฑ ุงุญุตุงุฆู ู ูุนูููุงุช ุฏุฑ ฺฉุดูุฑ\n\nูุงููุฑุช:\n\nูุฏุฑุช ู ุงูฺฉุดุงู ุณุณุชู ุงุญุตุงุฆู ู ูุนูููุงุช ุจุฑ ุจูุงุฏ ูุงุฒููุฏ ูุง ฺฉุดูุฑ\n\nูุฏุฑุช ู ุงุฑุงู ูุนูููุงุช ุฏููุ ูุณุชูุฏุ ูุงุจู ุงุทููุงูุ ุจู ูููุนุ ุจุง ฺฉูุช ู ูุงุจู ุงุณุชูุงุฏู ุจุฑุง ุทุฑุญ ูพุงูุณ ูุงุ ุณุงุณุช ฺฏุฐุงุฑ ูุง ุุชุตูู ฺฏุฑ ูุงุ ูพูุงูฺฏุฐุงุฑ ูุงุ ุชุญููุงุชุ ุขฺฏุงู ุนุงููุ ุชุงูู ุดูุงูุช ู ุณุงุฑ ููุงุฑุฏ ุงุฒ ูุฑุฌุน ูุงุญุฏ\n\nุชุฃูู ุงุณุชููุงูุช ูุณูฺฉุ ุจฺฉุงุฑ ฺฏุฑ ุฑูุดูุง ุนููุ ูุนุงุฑ ู ุฑุนุงุช ุงุตูู ุจู ุงูููู ุงุญุตุงุฆู ูุง ุฑุณูุ ุชุฃูู ููุงููฺฏ ู ุฌููฺฏุฑ ุงุฒ ุชฺฉุฑุงุฑ ุนูู ุฏุฑ ุชูุงู ูุนุงูุช ูุง ู ุนุฑุถ ุฎุฏูุงุช ุงุญุตุงุฆู \n\nูุฏุฑุช ุณุณุชู ูุง ูุนูููุงุช ุจู ููุธูุฑ ุงุณุชูุงุฏู ููุซุฑ ุ ุจู ูููุน ู ููู ุฌุงูุจู ุงุฒ ุงุฑูุงู ุฌุงุฑูุ ุงุฑูุงู ุจุฒุฑฺฏ ู ูุนูููุงุช ุฌุบุฑุงูุง ุฏุฑ ุชูู ุงุญุตุงุฆู ูุง ุฑุณู ููฺูุงู ุชุฑูุฌุ ุชููุช ู ูพุงู ฺฏุฐุงุฑ ุงุญุตุงุฆู ูุง ุซุจุช.\n\nูุธุงู ู ุตูุงุญุช ูุง:\n\nุงุฌุงุฏุ ูุฏุฑุช ู ุงูฺฉุดุงู ุณุณุชู ูุงุญุฏ ุงุญุตุงุฆู ู ูุนูููุงุช ุฏุฑ ฺฉุดูุฑ\n\nุฌูุน ุขูุฑุ ุชูุญุฏุ ุชุญูู ู ูุดุฑ ูุนูููุงุช ุฏููุ ูุณุชูุฏุ ูุงุจู ุงุทููุงูุ ุจู ูููุน ู ุจุง ฺฉูุช ุงุญุตุงุฆู ุฏุฑ ุฑุงุจุทู ุจู ูููุณุ ุงููุฑ ุชุฌุงุฑุชุ ุตูุนุชุ ุฒุฑุงุนุชุ ูุงูุ ุงุฌุชูุงุนุ ุงูุชุตุงุฏุ ุตุญุ ูุญุท ู ูุถุน ูุนุงูุช ูุง ุนููู ูุฑุฏู\n\nุชุฃูู ููุงููฺฏุ ุฌููฺฏุฑ ุงุฒ ุชฺฉุฑุงุฑ ุนููุ ุงูุณุฌุงู ู ูุธุงุฑุช ุงุฒ ุชูุงู ูุนุงูุช ูุง ู ุนุฑุถ ุฎุฏูุงุช ุงุญุตุงุฆู ู ูุนูููุงุช ุฏุฑ ฺฉุดูุฑ\n\nูุฑุฌุน ูุงุญุฏ ูุดุฑ ูุนูููุงุช ู ุงุญุตุงุฆู ูุง ุฑุณู ุฏุฑ ฺฉุดูุฑ ู ุงุชุฎุงุฐ ุชุตูู ุฏุฑููุฑุฏ ุดู ุฌูุน ุขูุฑุ ุชูุญุฏุ ุชุญูู ู ฺฺฏููฺฏ ุฒูุงู ูุดุฑ ูุนูููุงุช ุงุญุตุงุฆู\n\nุงุฌุฑุง ุชูุงู ูุนุงูุช ูุง ุงุญุตุงุฆู ุจู ุดููู ุณุฑู ูุงุ ุณุฑ ุดูุงุฑ ูุงุ ุณูุฌุด ูุญุงุณุจุงุช ูู ู ุดุงุฎุต ููุ ุชุดุฎุต ู ุชุซุจุช ูุงุฒููุฏ ูุง ูุนูููุงุช ู ุงุญุตุงุฆู ุฏุฑ ฺฉุดูุฑ\n\nุชุซุจุช ู ุงุฑุงุฆู ุขุฎุฑู ุฑูู ูููุณ ฺฉู ฺฉุดูุฑ ุฏุฑ ูุฑ ุณุงู ุจุง ุณุชูุงุฏู ุงุฒ ุฑูุด ูุง ุนูู ุงุญุตุงุฆู\n\nููฺฉุงุฑ ุจุง ูุฒุงุฑุช ูุง ู ุงุฏุงุฑุงุช ุฏููุช ุฏุฑ ุฌูุน ุขูุฑุ ุชูุญุฏุ ุชุญูู ูุนูููุงุช ุงุญุตุงุฆู ู ูุนูููุงุช ุฌุบุฑุงูุง\n\nุชุฃูู ุงุณุชููุงูุช ูุณูฺฉุ ุงูฺฉุดุงู ู ุชุฌูุฒ ุชุตุงููุ ุชุนุงุฑูุ ุงุตููุ ุณุชูุฏุฑุฏ ูุง ู ุฑูุดูุง ุนูู ููุงุณุจ ุฌูุช ุงุณุชูุงุฏู ุฏุฑ ุชูุงู ูุนุงูุช ูุง ู ุนุฑุถ ุฎุฏูุงุช ุงุญุตุงุฆู ุฏุฑ ฺฉุดูุฑ\n\nุงุฌุงุฏุ ูุฏุฑุช ู ุงูฺฉุดุงู ุณุณุชู ูุนูููุงุช ุฌุบุฑุงูุง ูุงุญุฏ ุจู ููุธูุฑ ุฌููฺฏุฑ ุงุฒ ุชฺฉุฑุงุฑ ุนูู ู ูุฏุฑุช ูุคุซุฑ ูุนูููุงุช ุฌุบุฑุงูุง ุฏุฑ ฺฉุดูุฑ ู ูุณุงุนุฏ ุณุงุฎุชู ุฒููู ุฏุณุชุฑุณ ุขุณุงู ุจู ูุนูููุงุช ูุฐฺฉูุฑ ุจุฑุง ููู ุงุณุชูุงุฏู ฺฉููุฏฺฏุงู ุจู ุงุณุชุซูุง ูุนูููุงุช ูุญุฑู\n\nุชุญูู ู ุงุฑุชูุง ุธุฑูุช ุงุญุตุงุฆู ุฏุฑ ฺฉุดูุฑ ู ุชุฃูู ุฑูุงุจุท ฺฉุงุฑ ุจุง ุงุฏุงุฑุงุช ูุณูฺฉ ุจู ุงูููู ู ุงุณุชูุงุฏู ุงุฒ ุชุฌุงุฑุจ ูููู ุขููุง\n\nุงุฌุงุฏ ุณุณุชู ู ุฒุฑุจูุง ุฌูุช ุงุณุชูุงุฏู ู ุชุญูู ุงุฑูุงู ุจุฒุฑฺฏุ ุงูฺฉุดุงู ู ุฑูุชู ุจู ุณูุช ุงุญุตุงุฆู ูุง ุซุจุช ู ุณุฑูุงู ฺฏุฐุงุฑ ุจุดุชุฑ ุจุงูุง ุขู ุฏุฑ ุฏุฑุงุฒ ูุฏุช\nJob Summary\nููฺฉุงุฑ ุฏุฑ ุชุณููุงุช ุทุฑุญ ุชุฎูฺฉ ู ุงูฺฉุดุงู ูพุงูุณ ูุง ูุนุงุฑ ูุง ู ุชุตุงูู ูุนูููุงุช ุฌุบุฑุงูุง.\nDuties & Responsibilities\nูุธุงู ุงุณุงุณ\nููฺฉุงุฑ ุฏุฑ ุทุฑุญ ู ุงูฺฉุดุงู ูพุงูุณ ูุงุ ูุนุงุฑูุง ู ุชุตุงูู ูุนูููุงุช ุฌุบุฑุงูุง.\nุชุทุจู ูพุงูุณ ูุง ูุนุงุฑ ุณุงุฒ ู ุตูู ุจูุฏ ูุนูููุงุช ุฌุบุฑุงูุง.\nุชุตูู ูุนูููุงุช ุฌุบุฑุงูุง ุจู ุงุณุงุณ ูพุงูุณ ูุง ู ูุนุงุฑ ูุง ูุถุน ุดุฏู ูุนูููุงุช ุฌุบุฑุงูุง.\nุชูู ูุงู ูุง ุฌุบุฑุงูุง ูุนุงุฑ ุทุจู ูพุงูุณ ุทุจูู ุจูุฏ ูุนูููุงุช ุฌุบุฑุงูุง ุฌูุช ุดุฑฺฉ ุณุงุฒ ุงุฒ ุทุฑู ุฌููพูุฑุชู(Geoportal).\nูุธุงู ูุฏุฑุช\nุชูู ู ุชุฑุชุจ ูพูุงู ฺฉุงุฑ ูุงููุงุฑุ ุฑุจุนูุงุฑ ู ุณุงูุงูู ุฏุฑ ูุทุงุจูุช ุจุง ูพูุงู ุขูุฑุชุ ุฌูุช ุจุฏุณุช ุขูุฑุฏู ุงูุฏุงู ุชุนู ุดุฏู .\nุงุฑุงู ฺฏุฒุงุฑุด ูุงููุงุฑุ ุฑุจุนูุงุฑ ู ุณุงูุงูู ู ุนูุฏุงูุถุฑูุฑุช ุงุฒ ูุนุงูุช ูุง ู ุฏุณุช ุขูุฑุฏ ูุง ุจุฎุด ูุฑุจูุทูุ ุจู ููุธูุฑ ูุทูุน ุณุงุฎุชู ุขูุฑ ูุฑุจูุทู.\nุงุฌุฑุง ุณุงุฑ ูุธุงู ฺฉู ุงุฒ ุทุฑู ุขูุฑ ูุฑุจูุทู ูุทุงุจู ูพุงูุณ ุงุฏุงุฑู ุณูพุฑุฏู ูุดูุฏ.\nูุธุงู ููุงููฺฏ\nููฺฉุงุฑ ุจุง ูุฒุงุฑุช ูุง ู ุงุฏุงุฑุงุช ุงูุงุฑุช ุฏุฑ ุชููุ ุชุฑุชุจ ู ุชุญูู ูุนูููุงุช ุฌุบุฑุงูุง.\nฺฉุฏฺฏุฐุงุฑ ูุงู ูุง ุงุณุงุณ ุฌุบุฑุงูุง ุทุจู ูุชูุฏ ุชูู ุดุฏู ุฏุฑ ููฺฉุงุฑ ู ููุงููฺฏ ุงุฏุงุฑุงุช ุฐุฑุจุท.\nุชุงูู ุงุฑุชุจุงุท ู ููุงููฺฏ ุจุง ุจุฎุด ูุง ูุฑุจูุทู ุฌูุช ุงุฌุฑุง ุจูุชุฑ ุงููุฑ ูุญููู.\nJob Requirements\nุดุฑุงุท ุงุณุชุฎุฏุงู\nุชุงุจุนุช ุงูุบุงูุณุชุงู ุฑุง ุฏุงุดุชู ุจุงุดุฏ.\nุณู ู ุงุฒ (18) ุณุงู ฺฉูุชุฑ ู ุงุฒ (64) ุณุงู ุจุดุชุฑ ูุจุงุดุฏ.\nุณูู ุชุญุตู\nุฏุงุดุชู ุณูุฏ ุชุญุตู ูุณุงูุณ ุฏุฑ ฺฉ ุงุฒ ุฑุดุชูโูุง ุณุณุชู ูุนูููุงุช ุฌุบุฑุงูุง (GIS)ุ ุฑููุช ุณูุณูฺฏุ ุฌุบุฑุงููุ ุฌููุงุชฺฉ ู ฺฉุฏุณุชุฑุ ุฌูุงููุงุฑูุงุชฺฉุ ุฌูุฏุฒุ ุฌูููฺุ ุฒูู ุดูุงุณ ู ฺฉููพูุชุฑ ุณุงูุณ ุงุฒ ุฏุงุฎู ุง ุฎุงุฑุฌ ฺฉุดูุฑ ฺฉู ุจู ุชุงุฆุฏ ูุฒุงุฑุช ุชุญุตูุงุช ุนุงู ุฑุณุฏู ุจุงุดุฏ.\nุชุฌุฑุจู ฺฉุงุฑ\nูุงุฒ ูุฏุงุฑุฏ.\nููุงุฑุชูุง ูุงุฒู\nุชุณูุท ุจู ฺฉ ุงุฒ ุฒุจุงูโ ูุง ุฑุณู(ูพุดุชู ุง ุฏุฑ) ฺฉุดูุฑ.\nููุงุฑุช โูุง ฺฉููพูุชุฑ ุฏุฑ ุจุฑูุงูู โูุง ูุฑุชุจุท ุจู ูุธูู.\nSubmission Guideline\nุนูุงูููุฏุงู ูุงุฌุฏ ุดุฑุงุท ูุชูุงููุฏ ุจุตูุฑุช ุขููุงู ุจู ููฺฉ ุฐู (\nhttps://forms.gle/gh8gKdyXTkrDyuXK7\n)\nูุฑุงุฌุนู ูููุฏู ุงุณูุงุฏ ูุง ุฎูุด ุฑุง ุจุง ุถูุงู ุขู (ฺฉุงูพ ุชุฐฺฉุฑู ุชุงุจุนุชุ ุงุณูุงุฏ ุชุญุตูุ ูุฏุงุฑฺฉ ุชุฌุฑุจู ฺฉุงุฑ) ุซุจุช ููุฑู ุฏุฑุฎูุงุณุช ุขููุงู ููุงูุฏ.\nููุช: ุงุดุฎุงุต ูุงุฌุฏ ุดุฑุงุท ูุทุงุจู ุฑููููุฏ ููู ุงุณูุงุฏ ุฎูุด ุฑุง ุชุฑุชุจ ู ุซุจุช ููุฑู ุขููุงู ููุงูุฏ.\nุจุฑุง ูุนูููุงุช ุจุดุชุฑ ุจู ุดูุงุฑู:\n0202927048\nุฏุฑ ุชูุงุณ ุดูุฏ.\nFunctional Area\nGIS ( Geographic Information System)\nEngineering Geologist\nComputer Science\nCountries\nAfghanistan\nProvinces\nKabul\nApply Now\nPost Date\nDec 18, 2025\nClosing Date\nJan 27, 2026\nReference\n002\nNumber of Vacancies\n1\nSalary Range\nAs per company salary scale\nYears of Experience\nFresh\nProbation Period\nNot Specified\nContract Type\nPermanent\nContract Duration\n1 year\nContract Extensible\nYes\nMinimum Education\nBachelor's Degree\nGender\nMale\nRelated Jobs\nNETLINKS Plaza | Shahr-e-Naw,\nLane 3, Kabul, Afghanistan\nQuick Links\nAbout Us\nAdvertise with Us\nPrivacy Policy\nFor Companies\nPost a Job\nPost a Job\nPost a Job\nPost a Job\nPost RFP\nPost RFP\nPost RFP\nPost RFP\nPost Training\nPost Training\nPost Training\nPost Training\nFor Jobseekers\nBrowse Jobs\nBrowse Companies\nBuild Resume\nContact\ninfo@jobs.af\nContact Us\nยฉ 2012 - 2026 Jobs.af | All Rights Reserved\nPowered by:\nNETLINKS Ltd",
    "details": {
      "Post Date": "Dec 18, 2025",
      "Closing Date": "Jan 27, 2026",
      "Reference": "002",
      "Number Of Vacancies": "1",
      "Salary Range": "As per company salary scale",
      "Years Of Experience": "Fresh",
      "Probation Period": "Not Specified",
      "Contract Type": "Permanent",
      "Contract Duration": "1 year",
      "Contract Extensible": "Yes",
      "Minimum Education": "Bachelor's Degree",
      "https": "//forms.gle/gh8gKdyXTkrDyuXK7",
      "ููุช": "ุงุดุฎุงุต ูุงุฌุฏ ุดุฑุงุท ูุทุงุจู ุฑููููุฏ ููู ุงุณูุงุฏ ุฎูุด ุฑุง ุชุฑุชุจ ู ุซุจุช ููุฑู ุขููุงู ููุงูุฏ.",
      "Functional Area": "GIS ( Geographic Information System)",
      "Countries": "Afghanistan",
      "Provinces": "Kabul"
    },
    "scraped_at": "2026-01-21T05:00:22Z",
    "apply_emails": [],
    "apply_method": "unknown"
  },
  {
    "url": "https://jobs.af/jobs/adhw-mslky-web-gis",
    "title": "ุนุถู ูุณูฺฉ Web GIS",
    "company": null,
    "location": "Kabul",
    "closing_date": "2026-01-27",
    "closing_date_raw": "Jan 27, 2026",
    "apply_url": null,
    "description": "๐\nComing Soon The Jobs.af Freelancer Portal\nConnect with top clients and freelancers across Afghanistan all in one place!\nStay Tuned\nJobs\nProcurement Opportunities\nCompanies\nFreelancers\nServices\nProcurement Opportunities\nTrainings\nScholarships\nLogin\nRegister\nุนุถู ูุณูฺฉ Web GIS\nNational Statistics and Information Authority\nApply Now\nSee all jobs\nุนุถู ูุณูฺฉ Web GIS\nNational Statistics and Information Authority,\n                                        Kabul, Afghanistan\nApply Now\nBachelor's Degree\nKabul, Afghanistan\n(Kabul)\nFull Time\n2663\nAbout\n                                            National Statistics and Information Authority\nุงุฏุงุฑ ูู ุงุญุตุงุฆู ู ูุนูููุงุช\n\nุฏุฏฺฏุงู:\n\nุฏุงุดุชู ุณุณุชู ูุงุญุฏุ ูุนุงุฑุ ูพุงุณุฎฺฏูุ ูุงุจู ุงุนุชูุงุฏ ุฏุฑ ุณุทุญ ูู ู ุจู ุงููููุ ูพูุง ู ูพุงุฏุงุฑ ุงุญุตุงุฆู ู ูุนูููุงุช ุฏุฑ ฺฉุดูุฑ\n\nูุงููุฑุช:\n\nูุฏุฑุช ู ุงูฺฉุดุงู ุณุณุชู ุงุญุตุงุฆู ู ูุนูููุงุช ุจุฑ ุจูุงุฏ ูุงุฒููุฏ ูุง ฺฉุดูุฑ\n\nูุฏุฑุช ู ุงุฑุงู ูุนูููุงุช ุฏููุ ูุณุชูุฏุ ูุงุจู ุงุทููุงูุ ุจู ูููุนุ ุจุง ฺฉูุช ู ูุงุจู ุงุณุชูุงุฏู ุจุฑุง ุทุฑุญ ูพุงูุณ ูุงุ ุณุงุณุช ฺฏุฐุงุฑ ูุง ุุชุตูู ฺฏุฑ ูุงุ ูพูุงูฺฏุฐุงุฑ ูุงุ ุชุญููุงุชุ ุขฺฏุงู ุนุงููุ ุชุงูู ุดูุงูุช ู ุณุงุฑ ููุงุฑุฏ ุงุฒ ูุฑุฌุน ูุงุญุฏ\n\nุชุฃูู ุงุณุชููุงูุช ูุณูฺฉุ ุจฺฉุงุฑ ฺฏุฑ ุฑูุดูุง ุนููุ ูุนุงุฑ ู ุฑุนุงุช ุงุตูู ุจู ุงูููู ุงุญุตุงุฆู ูุง ุฑุณูุ ุชุฃูู ููุงููฺฏ ู ุฌููฺฏุฑ ุงุฒ ุชฺฉุฑุงุฑ ุนูู ุฏุฑ ุชูุงู ูุนุงูุช ูุง ู ุนุฑุถ ุฎุฏูุงุช ุงุญุตุงุฆู \n\nูุฏุฑุช ุณุณุชู ูุง ูุนูููุงุช ุจู ููุธูุฑ ุงุณุชูุงุฏู ููุซุฑ ุ ุจู ูููุน ู ููู ุฌุงูุจู ุงุฒ ุงุฑูุงู ุฌุงุฑูุ ุงุฑูุงู ุจุฒุฑฺฏ ู ูุนูููุงุช ุฌุบุฑุงูุง ุฏุฑ ุชูู ุงุญุตุงุฆู ูุง ุฑุณู ููฺูุงู ุชุฑูุฌุ ุชููุช ู ูพุงู ฺฏุฐุงุฑ ุงุญุตุงุฆู ูุง ุซุจุช.\n\nูุธุงู ู ุตูุงุญุช ูุง:\n\nุงุฌุงุฏุ ูุฏุฑุช ู ุงูฺฉุดุงู ุณุณุชู ูุงุญุฏ ุงุญุตุงุฆู ู ูุนูููุงุช ุฏุฑ ฺฉุดูุฑ\n\nุฌูุน ุขูุฑุ ุชูุญุฏุ ุชุญูู ู ูุดุฑ ูุนูููุงุช ุฏููุ ูุณุชูุฏุ ูุงุจู ุงุทููุงูุ ุจู ูููุน ู ุจุง ฺฉูุช ุงุญุตุงุฆู ุฏุฑ ุฑุงุจุทู ุจู ูููุณุ ุงููุฑ ุชุฌุงุฑุชุ ุตูุนุชุ ุฒุฑุงุนุชุ ูุงูุ ุงุฌุชูุงุนุ ุงูุชุตุงุฏุ ุตุญุ ูุญุท ู ูุถุน ูุนุงูุช ูุง ุนููู ูุฑุฏู\n\nุชุฃูู ููุงููฺฏุ ุฌููฺฏุฑ ุงุฒ ุชฺฉุฑุงุฑ ุนููุ ุงูุณุฌุงู ู ูุธุงุฑุช ุงุฒ ุชูุงู ูุนุงูุช ูุง ู ุนุฑุถ ุฎุฏูุงุช ุงุญุตุงุฆู ู ูุนูููุงุช ุฏุฑ ฺฉุดูุฑ\n\nูุฑุฌุน ูุงุญุฏ ูุดุฑ ูุนูููุงุช ู ุงุญุตุงุฆู ูุง ุฑุณู ุฏุฑ ฺฉุดูุฑ ู ุงุชุฎุงุฐ ุชุตูู ุฏุฑููุฑุฏ ุดู ุฌูุน ุขูุฑุ ุชูุญุฏุ ุชุญูู ู ฺฺฏููฺฏ ุฒูุงู ูุดุฑ ูุนูููุงุช ุงุญุตุงุฆู\n\nุงุฌุฑุง ุชูุงู ูุนุงูุช ูุง ุงุญุตุงุฆู ุจู ุดููู ุณุฑู ูุงุ ุณุฑ ุดูุงุฑ ูุงุ ุณูุฌุด ูุญุงุณุจุงุช ูู ู ุดุงุฎุต ููุ ุชุดุฎุต ู ุชุซุจุช ูุงุฒููุฏ ูุง ูุนูููุงุช ู ุงุญุตุงุฆู ุฏุฑ ฺฉุดูุฑ\n\nุชุซุจุช ู ุงุฑุงุฆู ุขุฎุฑู ุฑูู ูููุณ ฺฉู ฺฉุดูุฑ ุฏุฑ ูุฑ ุณุงู ุจุง ุณุชูุงุฏู ุงุฒ ุฑูุด ูุง ุนูู ุงุญุตุงุฆู\n\nููฺฉุงุฑ ุจุง ูุฒุงุฑุช ูุง ู ุงุฏุงุฑุงุช ุฏููุช ุฏุฑ ุฌูุน ุขูุฑุ ุชูุญุฏุ ุชุญูู ูุนูููุงุช ุงุญุตุงุฆู ู ูุนูููุงุช ุฌุบุฑุงูุง\n\nุชุฃูู ุงุณุชููุงูุช ูุณูฺฉุ ุงูฺฉุดุงู ู ุชุฌูุฒ ุชุตุงููุ ุชุนุงุฑูุ ุงุตููุ ุณุชูุฏุฑุฏ ูุง ู ุฑูุดูุง ุนูู ููุงุณุจ ุฌูุช ุงุณุชูุงุฏู ุฏุฑ ุชูุงู ูุนุงูุช ูุง ู ุนุฑุถ ุฎุฏูุงุช ุงุญุตุงุฆู ุฏุฑ ฺฉุดูุฑ\n\nุงุฌุงุฏุ ูุฏุฑุช ู ุงูฺฉุดุงู ุณุณุชู ูุนูููุงุช ุฌุบุฑุงูุง ูุงุญุฏ ุจู ููุธูุฑ ุฌููฺฏุฑ ุงุฒ ุชฺฉุฑุงุฑ ุนูู ู ูุฏุฑุช ูุคุซุฑ ูุนูููุงุช ุฌุบุฑุงูุง ุฏุฑ ฺฉุดูุฑ ู ูุณุงุนุฏ ุณุงุฎุชู ุฒููู ุฏุณุชุฑุณ ุขุณุงู ุจู ูุนูููุงุช ูุฐฺฉูุฑ ุจุฑุง ููู ุงุณุชูุงุฏู ฺฉููุฏฺฏุงู ุจู ุงุณุชุซูุง ูุนูููุงุช ูุญุฑู\n\nุชุญูู ู ุงุฑุชูุง ุธุฑูุช ุงุญุตุงุฆู ุฏุฑ ฺฉุดูุฑ ู ุชุฃูู ุฑูุงุจุท ฺฉุงุฑ ุจุง ุงุฏุงุฑุงุช ูุณูฺฉ ุจู ุงูููู ู ุงุณุชูุงุฏู ุงุฒ ุชุฌุงุฑุจ ูููู ุขููุง\n\nุงุฌุงุฏ ุณุณุชู ู ุฒุฑุจูุง ุฌูุช ุงุณุชูุงุฏู ู ุชุญูู ุงุฑูุงู ุจุฒุฑฺฏุ ุงูฺฉุดุงู ู ุฑูุชู ุจู ุณูุช ุงุญุตุงุฆู ูุง ุซุจุช ู ุณุฑูุงู ฺฏุฐุงุฑ ุจุดุชุฑ ุจุงูุง ุขู ุฏุฑ ุฏุฑุงุฒ ูุฏุช\nJob Summary\nูุนุงู ูฺฏูุฏุงุดุชูุ ุญูุธุ ูุฑุงูุจุช ุฏุชุงุจุณ ู ุจุฑูุฒ ุฑุณุงู ุณุณุชู ุฌููพูุฑุชู.\nDuties & Responsibilities\nูุธุงู ุงุณุงุณ\nุญูุธ ู ูุฑุงูุจุช ุฏุชุงุจุณ ุฌุบุฑุงูุง ุงุฒ ุณุฑุงุช ูุฑูุณูุง ุจุง ุงุณุชูุงุฏู ุงุฒ ูุฑู ุงูุฒุงุฑูุง ุนุตุฑ ุถุฏ ูุฑูุณ.\nุฏุฒุงู ูููุฏู web Map ูุง ุฌุฏุฏ.\nุญูุธ ู ูฺฏูุฏุงุดุช ุณูุณูู ุชุฌุฏุฏ ูุงู ูุง ุฌุบุฑุงูุง ุงุณุงุณ.ุจุฑูุฒ ุฑุณุงู ุฏุชุงุจุณ Web Map ูุง ุชูู ุดุฏู.\nุงุฌุงุฏ ุฏุชุงุจุณ ูุงู ูุง ุงุณุงุณ ุฌุบุฑุงูุง ูุดุฑุดุฏู ุฏุฑ ุฌููพูุฑุชู.\nูุธุงู ูุฏุฑุช\nุชูู ู ุชุฑุชุจ ูพูุงู ฺฉุงุฑ ูุงููุงุฑุ ุฑุจุนูุงุฑ ู ุณุงูุงูู ุฏุฑ ูุทุงุจูุช ุจุง ูพูุงู ุขูุฑุชุ ุฌูุช ุจุฏุณุช ุขูุฑุฏู ุงูุฏุงู ุชุนู ุดุฏู .\nุงุฑุงู ฺฏุฒุงุฑุด ูุงููุงุฑุ ุฑุจุนูุงุฑ ู ุณุงูุงูู ู ุนูุฏุงูุถุฑูุฑุช ุงุฒ ูุนุงูุช ูุง ู ุฏุณุช ุขูุฑุฏ ูุง ุจุฎุด ูุฑุจูุทูุ ุจู ููุธูุฑ ูุทูุน ุณุงุฎุชู ุขูุฑ ูุฑุจูุทู.\nุงุฌุฑุง ุณุงุฑ ูุธุงู ฺฉู ุงุฒ ุทุฑู ุขูุฑ ูุฑุจูุทู ูุทุงุจู ูพุงูุณ ุงุฏุงุฑู ุณูพุฑุฏู ูุดูุฏ.\nูุธุงู ููุงููฺฏ\nุชุงูู ุงุฑุชุจุงุท ู ููุงููฺฏ ุจุง ุณุงุฑ ุจุฎุด ูุง ุฌูุช ุงุฌุฑุง ุจูุชุฑ ุงููุฑ ูุญููู.\nJob Requirements\nุดุฑุงุท ุงุณุชุฎุฏุงู\nุชุงุจุนุช ุงูุบุงูุณุชุงู ุฑุง ุฏุงุดุชู ุจุงุดุฏ.\nุณู ู ุงุฒ (18) ุณุงู ฺฉูุชุฑ ู ุงุฒ (64) ุณุงู ุจุดุชุฑ ูุจุงุดุฏ.\nุณูู ุชุญุตู\nุฏุงุดุชู ุณูุฏ ุชุญุตู ูุณุงูุณ ุฏุฑ ฺฉ ุงุฒ ุฑุดุชูโูุง ุณุณุชู ูุนูููุงุช ุฌุบุฑุงูุง (GIS)ุ ุฑููุช ุณูุณูฺฏุ ุฌุบุฑุงููุ ุฌููุงุชฺฉ ู ฺฉุฏุณุชุฑุ ุฌูุงููุงุฑูุงุชฺฉุ ุฌูุฏุฒุ ุฌูููฺุ ุฒูู ุดูุงุณ ู ฺฉููพูุชุฑ ุณุงูุณ ุงุฒ ุฏุงุฎู ุง ุฎุงุฑุฌ ฺฉุดูุฑ ฺฉู ุจู ุชุงุฆุฏ ูุฒุงุฑุช ุชุญุตูุงุช ุนุงู ุฑุณุฏู ุจุงุดุฏ.\nุชุฌุฑุจู ฺฉุงุฑ\nูุงุฒ ูุฏุงุฑุฏ.\nููุงุฑุชูุง ูุงุฒู\nุชุณูุท ุจู ฺฉ ุงุฒ ุฒุจุงูโ ูุง ุฑุณู(ูพุดุชู ุง ุฏุฑ) ฺฉุดูุฑ.\nููุงุฑุช โูุง ฺฉููพูุชุฑ ุฏุฑ ุจุฑูุงูู โูุง ูุฑุชุจุท ุจู ูุธูู.\nSubmission Guideline\nุนูุงูููุฏุงู ูุงุฌุฏ ุดุฑุงุท ูุชูุงููุฏ ุจุตูุฑุช ุขููุงู ุจู ููฺฉ ุฐู (\nhttps://forms.gle/gh8gKdyXTkrDyuXK7\n)\nูุฑุงุฌุนู ูููุฏู ุงุณูุงุฏ ูุง ุฎูุด ุฑุง ุจุง ุถูุงู ุขู (ฺฉุงูพ ุชุฐฺฉุฑู ุชุงุจุนุชุ ุงุณูุงุฏ ุชุญุตูุ ูุฏุงุฑฺฉ ุชุฌุฑุจู ฺฉุงุฑ) ุซุจุช ููุฑู ุฏุฑุฎูุงุณุช ุขููุงู ููุงูุฏ.\nููุช: ุงุดุฎุงุต ูุงุฌุฏ ุดุฑุงุท ูุทุงุจู ุฑููููุฏ ููู ุงุณูุงุฏ ุฎูุด ุฑุง ุชุฑุชุจ ู ุซุจุช ููุฑู ุขููุงู ููุงูุฏ.\nุจุฑุง ูุนูููุงุช ุจุดุชุฑ ุจู ุดูุงุฑู:\n0202927048\nุฏุฑ ุชูุงุณ ุดูุฏ.\nFunctional Area\nGIS ( Geographic Information System)\nEngineering Geologist\nComputer Science\nCountries\nAfghanistan\nProvinces\nKabul\nApply Now\nPost Date\nDec 18, 2025\nClosing Date\nJan 27, 2026\nReference\n001\nNumber of Vacancies\n1\nSalary Range\nAs per company salary scale\nYears of Experience\nFresh\nProbation Period\nNot Specified\nContract Type\nPermanent\nContract Duration\n1 year\nContract Extensible\nYes\nMinimum Education\nBachelor's Degree\nGender\nMale\nRelated Jobs\nNETLINKS Plaza | Shahr-e-Naw,\nLane 3, Kabul, Afghanistan\nQuick Links\nAbout Us\nAdvertise with Us\nPrivacy Policy\nFor Companies\nPost a Job\nPost a Job\nPost a Job\nPost a Job\nPost RFP\nPost RFP\nPost RFP\nPost RFP\nPost Training\nPost Training\nPost Training\nPost Training\nFor Jobseekers\nBrowse Jobs\nBrowse Companies\nBuild Resume\nContact\ninfo@jobs.af\nContact Us\nยฉ 2012 - 2026 Jobs.af | All Rights Reserved\nPowered by:\nNETLINKS Ltd",
    "details": {
      "Post Date": "Dec 18, 2025",
      "Closing Date": "Jan 27, 2026",
      "Reference": "001",
      "Number Of Vacancies": "1",
      "Salary Range": "As per company salary scale",
      "Years Of Experience": "Fresh",
      "Probation Period": "Not Specified",
      "Contract Type": "Permanent",
      "Contract Duration": "1 year",
      "Contract Extensible": "Yes",
      "Minimum Education": "Bachelor's Degree",
      "https": "//forms.gle/gh8gKdyXTkrDyuXK7",
      "ููุช": "ุงุดุฎุงุต ูุงุฌุฏ ุดุฑุงุท ูุทุงุจู ุฑููููุฏ ููู ุงุณูุงุฏ ุฎูุด ุฑุง ุชุฑุชุจ ู ุซุจุช ููุฑู ุขููุงู ููุงูุฏ.",
      "Functional Area": "GIS ( Geographic Information System)",
      "Countries": "Afghanistan",
      "Provinces": "Kabul"
    },
    "scraped_at": "2026-01-21T05:00:22Z",
    "apply_emails": [],
    "apply_method": "unknown"
  },
  {
    "url": "https://jobs.af/jobs/senior-android-application-developer-native-i2wws9bFY",
    "title": "Senior Android Application Developer (Native)",
    "company": null,
    "location": "Kabul",
    "closing_date": "2026-01-27",
    "closing_date_raw": "Jan 27, 2026",
    "apply_url": null,
    "description": "๐\nComing Soon The Jobs.af Freelancer Portal\nConnect with top clients and freelancers across Afghanistan all in one place!\nStay Tuned\nJobs\nProcurement Opportunities\nCompanies\nFreelancers\nServices\nProcurement Opportunities\nTrainings\nScholarships\nLogin\nRegister\nSenior Android Application Developer (Native)\nKabul Space Logistic & Technology Services\nApply Now\nSee all jobs\nSenior Android Application Developer (Native)\nKabul Space Logistic & Technology Services,\n                                        Kabul, Afghanistan\nApply Now\nBachelor's Degree\nKabul, Afghanistan\n(Kabul)\nFull Time\n877\nAbout\n                                            Kabul Space Logistic & Technology Services\nWelcome to KabulSpace\n, a premier\nsoftware development and IT solutions\ncompany headquartered in Kabul, Afghanistan. We specialize in creating tailored digital applications, offering end-to-end services from custom software design to system integration and consulting.\nOur expertise extends to enterprise networking and mission-critical network infrastructure, ensuring reliable support and scalability for businesses. With a skilled and passionate team, we deliver innovative, efficient, and customer-focused solutions that empower organizations, whether private enterprises or non-governmental entities, to thrive in a dynamic technological landscape. Letโs shape the future together!\nJob Summary\nAs a senior Android application developer (Java\nSE within Gradle) atยKabulspace, you will be responsible for designing, developing, and maintaining secure and complex mobile applications.\nYou will work closely with cross-functional teams to deliver high-quality software solutions that meet our client's needs and enhance user experience with a focus on real-time end-to-end encrypted communication.\nDuties & Responsibilities\nDeveloping and maintaining Enterprise Android applications using Java SE.\nKnowledge of real-time communication features and protocols.\nKnowledge of restful web API and Microservices.\nUtilize Git and GitHub for version control, code reviews, and collaborative development.\nAnalyze, debug, and test existing mobile applications, considering performance, processes, and productivity.\nParticipating in software testing processes such as unit testing, automated functional testing and integration testing to ensure app stability and performance.\nCollaborate with product managers, UI/UX designers, and other developers to define project requirements and specifications.\nWrite clean, scalable, and efficient code following best practices and coding standards.\nConduct code reviews, provide feedback, and mentor junior developers.\nProvide mentoring and training to junior developers and collaborate closely with the management team to provide status updates, challenges, and progress reports.\nWork under the supervision of the sub-directorate and provide regular tasks status update, challenges and reports to the management as per the service level agreement (SLA).\nWrite and maintain technical documentation, API guides, and user manuals.\nPerform any other duties related to the role assigned by the management.\nTraining and support for other team members.\nJob Requirements\nBachelorโs degree in Computer Science, Information System, or a related field.\n3+ years of professional experience in mobile application development.\nProficiency in Android Studio and Gradle structure.\nKnowledge of end-to-end encryption protocols.\nExperience with real-time communication protocols.\nExperience in integrating third-party libraries for real-time messaging\nFamiliarity with data encryption and data encryption protocols.\nTechnical experience with database systems such as mnesia, PostgreSQL, MariaDB, and SQLite.\nKnowledge of NoSQL databases for backend scaling.\nSolid understanding of RESTful APIs, JSON/XML data handling, and API integration.\nExperience with debugging tools, performance optimization, and memory profiling.\nPreferred Qualifications:\nKnowledge of containerization technologies such as Docker and Kubernetes.\nExperience implementing CI/CD pipelines for mobile application deployment.\nKnowledge of DevOps practices for mobile application deployment.\nSubmission Guideline\nApplicants are required to mention the Job Title and Vacancy # in the subject line of their email. Please attach your updated CV and a cover letter and send them to\nhr@kabulspace.af\n, with a copy (CC) to\nkabulspace2025@gmail.com\n. The application deadline is 10-Aug-2025, so ensure your submission is sent before this date.\nOnly shortlisted candidates will be contacted for an interview and a demo session. We look forward to receiving your applications\n.\nFunctional Area\nComputer Science\nCountries\nAfghanistan\nProvinces\nKabul\nSubmission Email\nhr@kabulspace.af\nkabulspace2025@gmail.com\nApply Now\nPost Date\nDec 27, 2025\nClosing Date\nJan 27, 2026\nReference\nKS-02\nNumber of Vacancies\n2\nSalary Range\nุ90000 - ุ110000 monthly\nYears of Experience\n3 years\nProbation Period\n3 month\nContract Type\nFixed-term\nContract Duration\n1 year\nContract Extensible\nYes\nMinimum Education\nBachelor's Degree\nGender\nMale\nRelated Jobs\nNETLINKS Plaza | Shahr-e-Naw,\nLane 3, Kabul, Afghanistan\nQuick Links\nAbout Us\nAdvertise with Us\nPrivacy Policy\nFor Companies\nPost a Job\nPost a Job\nPost a Job\nPost a Job\nPost RFP\nPost RFP\nPost RFP\nPost RFP\nPost Training\nPost Training\nPost Training\nPost Training\nFor Jobseekers\nBrowse Jobs\nBrowse Companies\nBuild Resume\nContact\ninfo@jobs.af\nContact Us\nยฉ 2012 - 2026 Jobs.af | All Rights Reserved\nPowered by:\nNETLINKS Ltd",
    "details": {
      "Post Date": "Dec 27, 2025",
      "Closing Date": "Jan 27, 2026",
      "Reference": "KS-02",
      "Number Of Vacancies": "2",
      "Salary Range": "ุ90000 - ุ110000 monthly",
      "Years Of Experience": "3 years",
      "Probation Period": "3 month",
      "Contract Type": "Fixed-term",
      "Contract Duration": "1 year",
      "Contract Extensible": "Yes",
      "Minimum Education": "Bachelor's Degree",
      "Functional Area": "Computer Science",
      "Countries": "Afghanistan",
      "Provinces": "Kabul"
    },
    "scraped_at": "2026-01-21T05:00:22Z",
    "apply_emails": [
      "hr@kabulspace.af",
      "kabulspace2025@gmail.com"
    ],
    "apply_method": "email"
  },
  {
    "url": "https://jobs.af/jobs/senior-ios-application-developer",
    "title": "Senior iOS Application Developer",
    "company": null,
    "location": "Kabul",
    "closing_date": "2026-01-27",
    "closing_date_raw": "Jan 27, 2026",
    "apply_url": null,
    "description": "๐\nComing Soon The Jobs.af Freelancer Portal\nConnect with top clients and freelancers across Afghanistan all in one place!\nStay Tuned\nJobs\nProcurement Opportunities\nCompanies\nFreelancers\nServices\nProcurement Opportunities\nTrainings\nScholarships\nLogin\nRegister\nSenior iOS Application Developer\nKabul Space Logistic & Technology Services\nApply Now\nSee all jobs\nSenior iOS Application Developer\nKabul Space Logistic & Technology Services,\n                                        Kabul, Afghanistan\nApply Now\nBachelor's Degree\nKabul, Afghanistan\n(Kabul)\nFull Time\n763\nAbout\n                                            Kabul Space Logistic & Technology Services\nWelcome to KabulSpace\n, a premier\nsoftware development and IT solutions\ncompany headquartered in Kabul, Afghanistan. We specialize in creating tailored digital applications, offering end-to-end services from custom software design to system integration and consulting.\nOur expertise extends to enterprise networking and mission-critical network infrastructure, ensuring reliable support and scalability for businesses. With a skilled and passionate team, we deliver innovative, efficient, and customer-focused solutions that empower organizations, whether private enterprises or non-governmental entities, to thrive in a dynamic technological landscape. Letโs shape the future together!\nJob Summary\nJob Summary:\nAs a senior iOS application developer at the Kabulspace, you will be responsible for designing, developing, and maintaining complex iOS applications. You will work closely with cross-functional teams to deliver high-quality software solutions that meet our clientsโ needs and enhance user experience.\nDuties & Responsibilities\nKey Responsibilities:\niOS App Development:\nDevelop and maintain iOS applications using Swift and/or Objective-C.\nEnsure seamless integration of UI/UX designs within the iOS ecosystem (UIKit, SwiftUI).\nReal-Time Communication:\nWork with real-time communication messaging protocols and libraries.\nIntegrate third-party libraries and services for real-time messaging.\nAPI & Data Handling:\nUnderstand and consume RESTful APIs; handle JSON/XML data.\nUtilize encryption protocols for secure message delivery.\nCode Analysis & Debugging:\nStudy, analyze, and understand complex software application code in Swift/Objective-C.\nDebug and optimize existing iOS applications, ensuring high performance and productivity.\nDatabase & Backend Integration:\nWork with relational databases such as PostgreSQL, MariaDB, or MySQL.\nHave basic familiarity with NoSQL (e.g., Firebase, MongoDB) for scalable backend solutions.\nUnderstand distributed key-value stores (e.g., Mnesia or relevant iOS-compatible alternatives).\nVersion Control & Collaboration:\nUtilize Git and GitHub for version control and collaboration.\nCollaborate with product managers, designers, and other developers to define project requirements and specifications.\nProvide feedback through code reviews and mentor junior developers.\nTesting & Quality Assurance:\nParticipate in software testing processes (unit testing, automated functional testing, integration testing).\nEnsure code quality and maintain best practices and coding standards.\nDocumentation & Reporting:\nWrite, revise, and maintain software technical documentation, operational documentation, and user guides.\nProvide regular task status updates, highlight challenges, and submit reports to management as per SLA.\nAdditional Responsibilities:\nPerform any other duties related to the role as assigned by management.\nTraining and support for junior developers.\nJob Requirements\nRequired Qualifications:\nEducation:\nBachelorโs degree in Computer Science, Information System, or a related field.\nExperience:\n5+ years of professional experience in mobile application development (iOS preferred).\nProven proficiency with iOS development in Swift and/or Objective-C.\nExperience with Xcode, Cocoa Touch frameworks, and iOS development best practices.\nTechnical Expertise:\nKnowledge of end-to-end encryption frameworks and protocols.\nExperience with real-time communication protocols.\nFamiliarity with integrating third-party libraries for real-time messaging.\nExperience with databases (PostgreSQL, MariaDB, MySQL) and distributed DBMS (Mnesia or similar).\nUnderstanding of NoSQL databases (e.g., Firebase, MongoDB) for scalable backend integration.\nProficiency in RESTful APIs and JSON/XML data handling.\nPreferred Qualifications (Pulse Points):\nContainerization & DevOps:\nKnowledge of Docker, Kubernetes, CI/CD pipelines, and DevOps practices.\nEncryption:\nFamiliarity with data encryption for secure communication and storage within iOS applications.\nSubmission Guideline\nApplicants are required to mention the Job Title and Vacancy # in the subject line of their email. Please attach your updated CV and a cover letter and send them to\nhr@kabulspace.af\n, with a copy (CC) to\nkabulspace2025@gmail.com\n. The application deadline is 10-Aug-2025, so ensure your submission is sent before this date.\nOnly shortlisted candidates will be contacted for an interview and a demo session. We look forward to receiving your applications\n.\nFunctional Area\nComputer Science\nCountries\nAfghanistan\nProvinces\nKabul\nSubmission Email\nhr@kabulspace.af\nkabulspace2025@gmail.com\nApply Now\nPost Date\nDec 27, 2025\nClosing Date\nJan 27, 2026\nReference\nKS-04\nNumber of Vacancies\n2\nSalary Range\nุ90000 - ุ110000 monthly\nYears of Experience\n3 - 5 years\nProbation Period\n3 month\nContract Type\nFixed-term\nContract Duration\n1 year\nContract Extensible\nYes\nMinimum Education\nBachelor's Degree\nGender\nMale\nRelated Jobs\nNETLINKS Plaza | Shahr-e-Naw,\nLane 3, Kabul, Afghanistan\nQuick Links\nAbout Us\nAdvertise with Us\nPrivacy Policy\nFor Companies\nPost a Job\nPost a Job\nPost a Job\nPost a Job\nPost RFP\nPost RFP\nPost RFP\nPost RFP\nPost Training\nPost Training\nPost Training\nPost Training\nFor Jobseekers\nBrowse Jobs\nBrowse Companies\nBuild Resume\nContact\ninfo@jobs.af\nContact Us\nยฉ 2012 - 2026 Jobs.af | All Rights Reserved\nPowered by:\nNETLINKS Ltd",
    "details": {
      "Post Date": "Dec 27, 2025",
      "Closing Date": "Jan 27, 2026",
      "Reference": "KS-04",
      "Number Of Vacancies": "2",
      "Salary Range": "ุ90000 - ุ110000 monthly",
      "Years Of Experience": "3 - 5 years",
      "Probation Period": "3 month",
      "Contract Type": "Fixed-term",
      "Contract Duration": "1 year",
      "Contract Extensible": "Yes",
      "Minimum Education": "Bachelor's Degree",
      "Functional Area": "Computer Science",
      "Countries": "Afghanistan",
      "Provinces": "Kabul"
    },
    "scraped_at": "2026-01-21T05:00:22Z",
    "apply_emails": [
      "hr@kabulspace.af",
      "kabulspace2025@gmail.com"
    ],
    "apply_method": "email"
  },
  {
    "url": "https://jobs.af/jobs/adhw-mslky-prwss-dyta-vpS2Aq1iQ",
    "title": "ุนุถู ูุณูฺฉ  ูพุฑูุณุณ ุฏุชุง",
    "company": null,
    "location": "Kabul",
    "closing_date": "2026-01-29",
    "closing_date_raw": "Jan 29, 2026",
    "apply_url": null,
    "description": "๐\nComing Soon The Jobs.af Freelancer Portal\nConnect with top clients and freelancers across Afghanistan all in one place!\nStay Tuned\nJobs\nProcurement Opportunities\nCompanies\nFreelancers\nServices\nProcurement Opportunities\nTrainings\nScholarships\nLogin\nRegister\nุนุถู ูุณูฺฉ  ูพุฑูุณุณ ุฏุชุง\nATRA\nApply Now\nSee all jobs\nุนุถู ูุณูฺฉ  ูพุฑูุณุณ ุฏุชุง\nATRA,\n                                        Kabul, Afghanistan\nApply Now\nBachelor's Degree\nKabul, Afghanistan\n(Kabul)\nFull Time\n1905\nAbout\n                                            ATRA\nุฏ ุงูุบุงูุณุชุงู ุฏ ูุฎุงุจุฑุงุชู ุฎุฏูุชููู ุฏ ุชูุธู ุงุฏุงุฑู (ุงูผุฑุง) ูพู ฒฐฐถ ููุงุฏู ฺฉุงู ูพู ููุงุฏ ฺฉ ุฏ ูุฎุงุจุฑุงุชู ุณฺฉุชูุฑ ุฏ ุชูุธู ุงู ูพุฑูุฎุชุง ููพุงุฑู ุฑุงููฺ ุชู ุดูู. ุฏุง ุงุฏุงุฑู ูฺู ฺฉูู ฺ ุฏ ูุฎุงุจุฑุงุชู ุงู ุงููผุฑููผู ุฎุฏูุชููู ุฒุฑุจูุงูู ุฏ ูุฏ ุงู ูพุฑูุฎุชุง ูพู ุจุฑุฎู ฺฉ ุฏ ุฎุตูุตู ุณฺฉุชูุฑ ููพุงุฑู ุฏ ูพุงูฺซูู ูพุงูฺ ุงู ููุงุณุจ ฺุงูพุฑุงู ุฑุงููฺุชู ฺฉฺู. ูพู ููุงุฏ ฺฉ ุฏ ฺู ููุฑุฑุงุชู ุงู ุชูุธูุงุชู ฺุงูพุฑุงู ุฑุงููฺุชู ฺฉููู ุงู ุชููุฐ ูู ูุงุฑ ูู ุชุจุนุถ ูพุฑุชู ูพู ุดูุงู ฺูู ุฏ ฺูุงฺฉูู ุฎุตูุตู ุณฺฉุชูุฑ ูุฎูุง ุญูุงู ุดูู ูุฎุงุจุฑุงุชู ุณฺฉุชูุฑ ุงู ุงฺููุฏู ุฎุฏูุชููู ุฑุงููฺุชู ฺฉููุ ุฏ ููุฑุฑุงุชู ูพูู ฺฉููุ ุฎุฏูุชููู ุชู ุณุฑุงุณุฑ ูุงุณุฑุณุ ุฏ ูุงุฑฺฉูผ ุชูุธูููุ ูพู ูุฎุงุจุฑุงุชู ูุงุฑฺฉููผ ฺฉ ุฏ ุณุงู ฺูผฺฉูุงู ุงู ูุธุงุฑุช ุฏ ุงูผุฑุง ุงุฏุงุฑ ููุฎ ุฏู. ุงูผุฑุง ุงุฏุงุฑู ูู ุงฺููุฏู ุงฺุฎููู ุฎุตูุตู ุณฺฉุชูุฑุ ุฏููุชู ุงุฏุงุฑู ุงู ุฏ ูุฎุงุจุฑุงุชู ุฎุฏูุชููู ูุดุชุฑฺฉูู ุณุฑู ู ฺุง ฺฉุงุฑ ฺฉููุ ฺู ุฏ ููุงุฏ ูพู ูุฎุงุจุฑุงุชู ุงู ุงููผุฑููผู ูุงุฑฺฉูผ ฺฉ ุณุงููู ุณุงูู ูพุฑูุฎุชฺซ ูฺฉฺู.\nุฏ ูุฎุงุจุฑุงุชู ุณฺฉุชูุฑ ุงู ุตูุนุช ูู 2002 ููุงุฏู ฺฉุงู ุฑุง ูพุฏุฎูุง ุฏ ููุงุฏ 34 ููุงุชููู ุงู ู ุดูุฑ ุฒุงุชู ููุณูุงูู ุชู ุฏ ุงููผุฑููผู ูพูฺฺ ูพู ูพุฑุงุฎุชุง ุณุฑู ฺซฺูุฏ ูุฏู ฺฉฺุฏู . ุงูผุฑุง ุงุฏุงุฑ ุฏ ููุงุฏ ูุฎุงุจุฑุงุชู ุจุงุฒุงุฑ ุฏ ฺู ูพุฑูุฎุชฺซ ุงู ุชูุธู ููพุงุฑู ุชู ูฺู ฺฉฺุ ฺ ุฏ ูฺูุงูู ฺฉูุฏู ูุฎุงุจุฑุงุชู ุดุฑฺฉุงูู ุณุฑู ููฺซุฑุชุง ุงู ุงฺฺฉ ูุง ูพุงูฺ ฺฉฺู ุชุฑฺู ูู ูฺูุงูู ุชุฌุฑุจู ฺุฎู ูพู ุงุณุชูุงุฏ ฺซูผูุฑ ูุงุฑ ฺุงุฑ ูพู ฺซูุชู ุงู ุฏ ููุงุฏ ูุงุฑฺฉูผ ุชู ูุฏู ูุฑฺฉฺู. ุธุฑูุช ุฌูฺููู ุฏ ูุฎุงุจุฑุงุชู ุตูุนุช ููพุงุฑู ู ุจู ููู ูผฺฉ ุฏ. ุฏ ุชู ูพู ฺฉุชู ุงูผุฑุง ุงุฏุงุฑ ุฏ ุงฺููุฏู ุณฺฉุชูุฑ ุงู ูุฎุงุจุฑุงุชู ุงู ุงููผุฑููผู ุดุฑฺฉุชููู ูพู ฺซฺูู ุฏ ุธุฑูุช ููฺููู ุชู ุจูุฏุฌู ฺุงูฺซฺ ุงู ุฏ ฺฉุงุฑ ุงฺฉูุณุณุชู ุฑุงููฺุชู ฺฉฺ ุฏุ ฺ ุฏุง ุจู ูพู ูุฎุงุจุฑุงุชู ุณฺฉุชูุฑ ฺฉ ุฏ ูพุงูฺซูู ุฌูุจ ุงู ูพุฑุฏููฺฉู ุชู ุฏ ูพุฑูุฎุชููู ูุฎุงุจุฑุงุชู ุฎุฏูุชููู ูฺุงูุฏ ฺฉููู ูุงูู ุดู. ููุฏุงุฑูฺซูุ ุงูผุฑุง ุงุฏุงุฑู ูู ููุฑู ุงฺููุฏู ุฎูุงู ูพู ฺุงูฺซฺ ุชูฺซู ฺฺูุฒู ุงู ุงฺฉุงฺูฺฉู ูุฑฺฉุฒููู ุณุฑู ูพู ฺซฺู ฺฉุงุฑ ฺฉููุ ุชุฑฺู ูพู ููุงุฏ ฺฉ ุฏ ูุฎุงุจุฑุงุชู ฺฉุงุฑู ฺูุงฺฉ ุชู ูพุงูฺุชุง ุงู ูุฏู ูุฑฺฉฺู ุงู ูพู ูุงุฑฺฉูผ ฺฉ ุฏ ุธุฑูุช ุฌูฺูู ุจุฑูุงูู ุชู ุฏ (ุชุฑููฺซ) ุงู ููุฑู ุฎุฏูุชููู ููพุงุฑู ูุงุฑู ุจุฑุงุจุฑู ฺฉฺู.\nJob Summary\nุนุถู ูุณูฺฉยูพุฑูุณุณ ุฏุชุง\nDuties & Responsibilities\nูุณุคูุช ูุง ูุธูู:\nุชุทุจู ูพูุงู ุฌูุช ูพุฑูุณุณ ูููุฏู ููููู ูุง ฺฉูุช ุฎุฏูุงุช ูุฎุงุจุฑุงุช ุงุฒ ููุงุงุช ฺฉุดูุฑ\nุชุทุจู ุทุฑุญ ู ูพูุงู ูุง ูุธุงุฑุช ู ุชูุชุด ุบุฑุถ ุชุซุจุช ู ุฏุฑุงูุช ููุงุฑุฏ ุชุฎุท ุงูพุฑุชุฑุงู ู ุนุฑุถู ฺฉููุฏฺฏุงู ุฎุฏูุงุช ููุจุงูุ ุฎุฏูุงุช ูุงุจุฑ ู DSL ุงุฒ ุดุฑุงุท ุฌูุงุฒ ู ุงุญฺฉุงู ูุงููู ุชูุธู ุฎุฏูุงุช ูุฎุงุจุฑุงุช\nุฏุฑุงูุช ูุงุฑุฒุงุจ ููุงุฑุฏ ุชุฎูู ุขูพุฑุชุฑุงู ุฎุฏูุงุช ุงูุชุฑูุช ูุทุงุจู ูุทุงุจู ุดุฑุงุท ูพุดุจู ุดุฏู ุฏุฑ ุฌูุงุฒ.\nุชุทุจู ู ูุฑุงูุจุช ุงุฒุชุตุงูู ุงุฏุงุฑู ู ุดุฑุงุท ุฌูุงุฒูุง ู ุฌูุงุฒูุงูู ูุง ูุฑุจูุท ุจู ุฎุฏูุงุช ูุฎุงุจุฑุงุช ูุทุงุจู ุจู ูพูุงู ุชู ูุฏุฑ ูุฑุจูุทู\nุชุซุจุช ุงุดุฎุงุต ูุชุฎูู ุงุฒุดุฑุงุท ุฌูุงุฒูุง ุง ุฌูุงุฒ ูุงูู ูุง ูุฑุจูุท.\nฺฺฏููฺฏ ุชุทุจู ุดุฑุงุท ุฌูุงุฒูุง ู ุฌูุงุฒูุงูู ูุง ุฎุฏูุงุช ุงูุชุฑูุช\nุชุทุจู ููุงููุ ุทุฑุฒุงูุนูู ูุง ู ูุฏุงุงุช ููุงูุงุช ุบุฑุถ ุจุงุฒุฏุฏ ู ููุงุญุธู ุงุณูุงุฏ ูุฑุจูุท ุจู ุขูพุฑูุชุฑุงู ู ุนุฑุถู ฺฉููุฏฺฏุงู ุฎุฏูุงุช ูุฎุงุจุฑุงุช ูุทุงุจู ุจู ูพูุงู\nุชุทุจู ูพูุงู ูุง ฺฉุงุฑ ูุดุฎุต ู ูุฏุงูู ุจู ุจุฎุด ูุฑุจูุทู\nุชุทุจูุ ุชุนูุจ ู ูพฺฏุฑ ููุถูุนุงุช ูุธูู ฺฉู ุจุง ุฏฺฏุฑ ููุงุฏูุง ุฏููุช ุงููุช ู ุนุฏูยูุถุง ุงุฑุชุจุงุท ูพุฏุง ูฺฉูุฏ ูุทุงุจู ุจู ูพูุงู ุชู ูุฏุฑ ูุฑุจูุทู\nุชุทุจู ูพูุงู ูุง ฺฉุงุฑ ุฑูุฒูุฑู\nฺฏุฒุงุฑุดุฏู ุฏููุ ููุธู ู ูุญุธู ุง ูุฑุชุจุท ุจู ูุธูู ุจู ููุงูุงุช ุฐุฑุท .\nุงูููุช ุฏุงุฏู ุจู ุชฺฉูู ู ุงูุฌุงู ูุธูู ูุญููู ุญุช ุฎุงุฑุฌ ุงุฒ ุณุงุนุงุช ู ุงุงู ุฑุณู\nุงุฌุฑุง ุณุงุฑ ุงููุฑ ฺฉู ุงุฒ ุทุฑู ูุณุฆูู ูุฑุจูุทู ุจุฑุงุด ุณูพุฑุฏู ูุดูุฏ .\nJob Requirements\nููุงุตูุงุช\nุชุญุตูุงุชุ ุชุฌุงุฑุจ ู ููุงุฑุช ูุง ูุงุฒู\n:\nุฏุฑุฌู ุชุญุตู\n:\nุฏุงุฑุง ุชุญุตูุงุช ุนุงู ุจู ุณูู ูุณุงูุณ ุฏุฑฺฉ ุงุฒ ุจุฎุด ูุง ุงูุฌูุฑ ุจุฑูุ ฺฉููพูุชุฑ ุณุงูุณ ู ูุฎุงุจุฑุงุช.\nุชุฌุงุฑุจ ูุงุฒูู\n:\nุฏุงุฑุง ุชุฌุฑุจู ุญุฏ ุงูู ุฏู ุณุงู ุฎุฏูุช ูุฑุชุจุท ู ุจุงููุนู ุฏุฑ ุจุฎุด ูุง ูุฎุงุจุฑุงุช ู ุชฺฉูุงููฺ ูุนูููุงุช.\nููุงุฑุช ูุง ุฏฺฏุฑ ( ฺฉูุฑุณ ูุง ฺฉูุชุงู ูุฏุชุ ุขููุฒุด ูุง ุฏุงุฎู ุฎุฏูุช ูุบุฑู\n(\nูุนูููุงุช ฺฉุงู ุฏุฑ ุจุงุฑู ูุงููู ุฎุฏูุงุช ูุฎุงุจุฑุงุชุ\nุชูุงูุง ฺฉุงู ุฏุฑ ฺฉุงุฑ ฺฏุฑููพ\nุฑุนุงุช ุฏุณูพูู ูุงู ู ุงุฏุงุฑ\nุฑุนุงุช ุณูุณูู ูุฑุงุชุจ\nุจุฑุฎูุฑุฏ ุฏูุณุชุงูู ุจุง ููฺฉุงุฑุงู\nุงุฑุชูุงุก ุธุฑูุช ุฎูุฏู\nูุณุฆููุช ูพุฐุฑ ู ุฌุฑุงุช ฺฉุงุฑู\nุจู ูพุฑูฺฏุฑุงู ูุง ฺฉููพูุชุฑ ูุฎุตูุตุง (MS Office) ู ุงูุชุฑูุช ุฏุณุชุฑุณ ุขุดูุง ฺฉุงูู ุฏุงุดุชู ุจุงุดุฏ.\nุฏุงุฑุง ุณูุงุจู ุฌุฑู ูุจุงุดุฏ\nุชุงุจุนุช ุงูุบุงูุณุชุงู ุฑุง ุฏุงุดุชู ู ุฏุฑ ฺฉุดูุฑ ููู ุจุงุดุฏ\nุจู ูุณุงู ูพุดุชู ู ุฏุฑู ุจู ุฎูุจ ุชฺฉูู ูููุฏู ู ุจู ูุณุงู ุงูฺฏูุณ ุขุดูุง ุฏุงุดุชู ุจุงุดุฏ.\nSubmission Guideline\nุฏ ูุญุชุฑูู ฺฉุงูุฏุฏุงูู ฺุฎู ููู ฺฉฺู ฺ ุชุฑ ฺู ุฏ ุงฺููุฏู ุจุณุช ููพุงุฑู ฺุงูฺซฺ ููุฑูู ฺฺฉู ุงู ูุงูุฏ ุจุฑูฺูุงูฺฉ ุชู ู ุฑุงูุงุณุชูู ุงู ููุฏุงุฑฺซู ฺฉููุง ุดู ฺ ุงุฏู ููุฑูู ุฏ ฺฉุงุฑฺฉูููฺฉู ุฏ ฺุงุฑู ยุฏ ุงุณุชุฎุฏุงู ุฏ ุขูุฑุช ฺุฎู ุชุฑูุงุณู ฺฉฺู .\nูพุชู : ุฏ ูุฎุงุจุฑุงุชู ุงู ูุนูููุงุชู ูผฺฉูุงููุฌ ูุฒุงุฑุช ฑธ ูพูฺุฒู ูุฏุงู ุฏุงุฑูุณู ููุฒู ุฏ ุงุณุชุฎุฏุงู ุขูุฑุช\nุจุฑฺูุงูฺฉ\njobs@atra.gov.af\nุฏ ุงฺฺฉู ุดูุฑู : 0202100763\nูููผ : ุฏ ูผููู ูุญุชุฑูู ฺฉุงูุฏุฏุงูู ฺุฎู ููู ฺฉฺู ฺ ฺฉู ฺุฑ ุณุชุงุณู ุชุญุตูุงุช ุงู ุง ูู ฺฉุงุฑู ุชุฌุฑุจู ุฏ ูพูุฑุชู ุจุณุช ุณุฑู ุณููู ูู ุฎูุฑู ูุทูุง ุฎูพู ุบูฺุชููฺฉ ูู ุฑุง ุงุณุชูุฆ .\nูพู ุฏุฑูฺุช\nSubmission Guidelines:\nAll applications ยForms ( CV & Cover Letters are notยconsidered )should be submitted via email to:\njobs@atra.gov.af\nPlease, clearly indicate on the subject line the title of the position. Applications received after the\nClosing date will not be considered.\nFunctional Area\nComputer Science\nTelecommunication\nElectrical Engineering, telecommunication\nCountries\nAfghanistan\nProvinces\nKabul\nSubmission Email\njobs@atra.gov.af\nAttachments\nApplication_Form ATRA.doc\nApply Now\nPost Date\nJan 14, 2026\nClosing Date\nJan 29, 2026\nReference\n002\nNumber of Vacancies\n1\nSalary Range\nAs per company salary scale\nYears of Experience\n2 years\nProbation Period\n3 month\nContract Type\nPermanent\nContract Duration\n1 year\nContract Extensible\nYes\nMinimum Education\nBachelor's Degree\nGender\nMale\nRelated Jobs\nNETLINKS Plaza | Shahr-e-Naw,\nLane 3, Kabul, Afghanistan\nQuick Links\nAbout Us\nAdvertise with Us\nPrivacy Policy\nFor Companies\nPost a Job\nPost a Job\nPost a Job\nPost a Job\nPost RFP\nPost RFP\nPost RFP\nPost RFP\nPost Training\nPost Training\nPost Training\nPost Training\nFor Jobseekers\nBrowse Jobs\nBrowse Companies\nBuild Resume\nContact\ninfo@jobs.af\nContact Us\nยฉ 2012 - 2026 Jobs.af | All Rights Reserved\nPowered by:\nNETLINKS Ltd",
    "details": {
      "Post Date": "Jan 14, 2026",
      "Closing Date": "Jan 29, 2026",
      "Reference": "002",
      "Number Of Vacancies": "1",
      "Salary Range": "As per company salary scale",
      "Years Of Experience": "2 years",
      "Probation Period": "3 month",
      "Contract Type": "Permanent",
      "Contract Duration": "1 year",
      "Contract Extensible": "Yes",
      "Minimum Education": "Bachelor's Degree",
      "ูพุชู": "ุฏ ูุฎุงุจุฑุงุชู ุงู ูุนูููุงุชู ูผฺฉูุงููุฌ ูุฒุงุฑุช ฑธ ูพูฺุฒู ูุฏุงู ุฏุงุฑูุณู ููุฒู ุฏ ุงุณุชุฎุฏุงู ุขูุฑุช",
      "ุฏ ุงฺฺฉู ุดูุฑู": "0202100763",
      "ูููผ": "ุฏ ูผููู ูุญุชุฑูู ฺฉุงูุฏุฏุงูู ฺุฎู ููู ฺฉฺู ฺ ฺฉู ฺุฑ ุณุชุงุณู ุชุญุตูุงุช ุงู ุง ูู ฺฉุงุฑู ุชุฌุฑุจู ุฏ ูพูุฑุชู ุจุณุช ุณุฑู ุณููู ูู ุฎูุฑู ูุทูุง ุฎูพู ุบูฺุชููฺฉ ูู ุฑุง ุงุณุชูุฆ .",
      "Functional Area": "Computer Science",
      "Countries": "Afghanistan",
      "Provinces": "Kabul"
    },
    "scraped_at": "2026-01-21T05:00:22Z",
    "apply_emails": [
      "jobs@atra.gov.af"
    ],
    "apply_method": "email"
  },
  {
    "url": "https://jobs.af/jobs/d-faybr-aw-antrnty-khdmtwnw-karmnd",
    "title": "ุฏ ูุงุจุฑ ุงู ุงูุชุฑูุชู ุฎุฏูุชููู ฺฉุงุฑููุฏ",
    "company": null,
    "location": "Kabul",
    "closing_date": "2026-01-29",
    "closing_date_raw": "Jan 29, 2026",
    "apply_url": null,
    "description": "๐\nComing Soon The Jobs.af Freelancer Portal\nConnect with top clients and freelancers across Afghanistan all in one place!\nStay Tuned\nJobs\nProcurement Opportunities\nCompanies\nFreelancers\nServices\nProcurement Opportunities\nTrainings\nScholarships\nLogin\nRegister\nุฏ ูุงุจุฑ ุงู ุงูุชุฑูุชู ุฎุฏูุชููู ฺฉุงุฑููุฏ\nATRA\nApply Now\nSee all jobs\nุฏ ูุงุจุฑ ุงู ุงูุชุฑูุชู ุฎุฏูุชููู ฺฉุงุฑููุฏ\nATRA,\n                                        Kabul, Afghanistan\nApply Now\nBachelor's Degree\nKabul, Afghanistan\n(Kabul)\nFull Time\n2665\nAbout\n                                            ATRA\nุฏ ุงูุบุงูุณุชุงู ุฏ ูุฎุงุจุฑุงุชู ุฎุฏูุชููู ุฏ ุชูุธู ุงุฏุงุฑู (ุงูผุฑุง) ูพู ฒฐฐถ ููุงุฏู ฺฉุงู ูพู ููุงุฏ ฺฉ ุฏ ูุฎุงุจุฑุงุชู ุณฺฉุชูุฑ ุฏ ุชูุธู ุงู ูพุฑูุฎุชุง ููพุงุฑู ุฑุงููฺ ุชู ุดูู. ุฏุง ุงุฏุงุฑู ูฺู ฺฉูู ฺ ุฏ ูุฎุงุจุฑุงุชู ุงู ุงููผุฑููผู ุฎุฏูุชููู ุฒุฑุจูุงูู ุฏ ูุฏ ุงู ูพุฑูุฎุชุง ูพู ุจุฑุฎู ฺฉ ุฏ ุฎุตูุตู ุณฺฉุชูุฑ ููพุงุฑู ุฏ ูพุงูฺซูู ูพุงูฺ ุงู ููุงุณุจ ฺุงูพุฑุงู ุฑุงููฺุชู ฺฉฺู. ูพู ููุงุฏ ฺฉ ุฏ ฺู ููุฑุฑุงุชู ุงู ุชูุธูุงุชู ฺุงูพุฑุงู ุฑุงููฺุชู ฺฉููู ุงู ุชููุฐ ูู ูุงุฑ ูู ุชุจุนุถ ูพุฑุชู ูพู ุดูุงู ฺูู ุฏ ฺูุงฺฉูู ุฎุตูุตู ุณฺฉุชูุฑ ูุฎูุง ุญูุงู ุดูู ูุฎุงุจุฑุงุชู ุณฺฉุชูุฑ ุงู ุงฺููุฏู ุฎุฏูุชููู ุฑุงููฺุชู ฺฉููุ ุฏ ููุฑุฑุงุชู ูพูู ฺฉููุ ุฎุฏูุชููู ุชู ุณุฑุงุณุฑ ูุงุณุฑุณุ ุฏ ูุงุฑฺฉูผ ุชูุธูููุ ูพู ูุฎุงุจุฑุงุชู ูุงุฑฺฉููผ ฺฉ ุฏ ุณุงู ฺูผฺฉูุงู ุงู ูุธุงุฑุช ุฏ ุงูผุฑุง ุงุฏุงุฑ ููุฎ ุฏู. ุงูผุฑุง ุงุฏุงุฑู ูู ุงฺููุฏู ุงฺุฎููู ุฎุตูุตู ุณฺฉุชูุฑุ ุฏููุชู ุงุฏุงุฑู ุงู ุฏ ูุฎุงุจุฑุงุชู ุฎุฏูุชููู ูุดุชุฑฺฉูู ุณุฑู ู ฺุง ฺฉุงุฑ ฺฉููุ ฺู ุฏ ููุงุฏ ูพู ูุฎุงุจุฑุงุชู ุงู ุงููผุฑููผู ูุงุฑฺฉูผ ฺฉ ุณุงููู ุณุงูู ูพุฑูุฎุชฺซ ูฺฉฺู.\nุฏ ูุฎุงุจุฑุงุชู ุณฺฉุชูุฑ ุงู ุตูุนุช ูู 2002 ููุงุฏู ฺฉุงู ุฑุง ูพุฏุฎูุง ุฏ ููุงุฏ 34 ููุงุชููู ุงู ู ุดูุฑ ุฒุงุชู ููุณูุงูู ุชู ุฏ ุงููผุฑููผู ูพูฺฺ ูพู ูพุฑุงุฎุชุง ุณุฑู ฺซฺูุฏ ูุฏู ฺฉฺุฏู . ุงูผุฑุง ุงุฏุงุฑ ุฏ ููุงุฏ ูุฎุงุจุฑุงุชู ุจุงุฒุงุฑ ุฏ ฺู ูพุฑูุฎุชฺซ ุงู ุชูุธู ููพุงุฑู ุชู ูฺู ฺฉฺุ ฺ ุฏ ูฺูุงูู ฺฉูุฏู ูุฎุงุจุฑุงุชู ุดุฑฺฉุงูู ุณุฑู ููฺซุฑุชุง ุงู ุงฺฺฉ ูุง ูพุงูฺ ฺฉฺู ุชุฑฺู ูู ูฺูุงูู ุชุฌุฑุจู ฺุฎู ูพู ุงุณุชูุงุฏ ฺซูผูุฑ ูุงุฑ ฺุงุฑ ูพู ฺซูุชู ุงู ุฏ ููุงุฏ ูุงุฑฺฉูผ ุชู ูุฏู ูุฑฺฉฺู. ุธุฑูุช ุฌูฺููู ุฏ ูุฎุงุจุฑุงุชู ุตูุนุช ููพุงุฑู ู ุจู ููู ูผฺฉ ุฏ. ุฏ ุชู ูพู ฺฉุชู ุงูผุฑุง ุงุฏุงุฑ ุฏ ุงฺููุฏู ุณฺฉุชูุฑ ุงู ูุฎุงุจุฑุงุชู ุงู ุงููผุฑููผู ุดุฑฺฉุชููู ูพู ฺซฺูู ุฏ ุธุฑูุช ููฺููู ุชู ุจูุฏุฌู ฺุงูฺซฺ ุงู ุฏ ฺฉุงุฑ ุงฺฉูุณุณุชู ุฑุงููฺุชู ฺฉฺ ุฏุ ฺ ุฏุง ุจู ูพู ูุฎุงุจุฑุงุชู ุณฺฉุชูุฑ ฺฉ ุฏ ูพุงูฺซูู ุฌูุจ ุงู ูพุฑุฏููฺฉู ุชู ุฏ ูพุฑูุฎุชููู ูุฎุงุจุฑุงุชู ุฎุฏูุชููู ูฺุงูุฏ ฺฉููู ูุงูู ุดู. ููุฏุงุฑูฺซูุ ุงูผุฑุง ุงุฏุงุฑู ูู ููุฑู ุงฺููุฏู ุฎูุงู ูพู ฺุงูฺซฺ ุชูฺซู ฺฺูุฒู ุงู ุงฺฉุงฺูฺฉู ูุฑฺฉุฒููู ุณุฑู ูพู ฺซฺู ฺฉุงุฑ ฺฉููุ ุชุฑฺู ูพู ููุงุฏ ฺฉ ุฏ ูุฎุงุจุฑุงุชู ฺฉุงุฑู ฺูุงฺฉ ุชู ูพุงูฺุชุง ุงู ูุฏู ูุฑฺฉฺู ุงู ูพู ูุงุฑฺฉูผ ฺฉ ุฏ ุธุฑูุช ุฌูฺูู ุจุฑูุงูู ุชู ุฏ (ุชุฑููฺซ) ุงู ููุฑู ุฎุฏูุชููู ููพุงุฑู ูุงุฑู ุจุฑุงุจุฑู ฺฉฺู.\nJob Summary\nุงุฌุฑุง ูพูุงู ูุง ุงุฌุฑุงู ูุฏุฑุช ูุฑุจูุทู ู ูุธุงุฑุช ุงุฒ ุฎุฏูุงุช ูุงุจุฑ ู ุงูุชุฑูุช\nDuties & Responsibilities\nูุณุคูุช ูุง ูุธูู:\nุงูุฌุงู ูพุฑูุณู ูุง ูุธุงุฑุช ุจุฑุง ฺฉูุชุฑูู ู ูุธุงุฑุช ุงุฒ ุงูฺฉุดุงู ุดุจฺฉู ูุง ูุงุจุฑ ููุฑ.\nุงุฑุฒุงุจ ฺฉู ฺฉุงุฑฺฉุฑุฏ ุดุจฺฉู ูุง ูุงุจุฑ/ุงูุชุฑูุช\nุงุดูุง ุจุง ุณุณุชู ูุง ฺูู ุจุงูุฏูุช ููุฌููุช ุดุฑฺฉุช ูุง ISP\nูุธุงุฑุช ุงุฒ ุดุจฺฉู ูุง ูุงุจุฑ ููุฑ ุฏุฑ ุฑูุดูุง ูพุงูุณ ู ุทุฑุฒุงูุนูู ูุฑุชุจุท ุจู ุดุจฺฉู ูุง ูุงุจุฑ ููุฑ\nุงูุฌุงู ุฏุงุฏู ุชุณุช ูุง ููุฌูุฏุช (Availability)ุ ฺฉูุช (Quality) ููพุงุฏุงุฑ ุดุจฺฉู ูุง ูุงุจุฑ/ุงูุชุฑูุช\nุฌูุน ุขูุฑุ ุชุญููุ ุชุฌุฒู ู ุงุฑุฒุงุจ ูุดุงูฺฏุฑ ูุง ฺฉูุฏ ฺฉุงุฑฺฉุฑุฏ (KPIs) ุดุจฺฉู ูุง ูุงุจุฑ/ุงูุชุฑูุช\nุงูุฌุงู ุณุงุฑ ฺฉุงุฑ ูุง ุฎุงุฑุฌ ุงุฒ ูุงุญู ูุธุงู ฺฉู ุงุฒ ุณู ุขูุฑ ูุณุชูู ุจู ุชู ูุฏุฑ ูุงูุชูุฑูฺฏ ุทู ุณูพุฑุฏู ู ุดูุฏ.\nุงุฑุงู ฺฏุฒุงุฑุด ูุง ุฏูู ุ ููุธู ู ุจู ูููุน ุจู ุขูุฑุช ุฌููฺฏุฑ ุงุฒ ูุนุงูุช ูุง ุบุฑ ูุฌุงุฒ ูุฎุงุจุฑุงุช.\nุงุฌุฑุง ุณุงุฑ ูุธุงู ฺฉู ุงุฒ ุทุฑู ูุณุฆูู ูุฑุจูุทู ุจุฑุงุด ุณูพุฑุฏู ูุดูุฏ .\nJob Requirements\nููุงุตูุงุช\nุชุญุตูุงุชุ ุชุฌุงุฑุจ ู ููุงุฑุช ูุง ูุงุฒู\n:\nุฏุฑุฌู ุชุญุตู\n:\nุณูุฏ ุชุญุตู ุญุฏ ุงูู ูุณุงูุณ ุฏุฑ ฺฉ ุงุฒ ุฑุดุชู ูุง ูุฎุงุจุฑุงุช ุ ุงูฺฉุชุฑููฺฉุณ ุ ุจุฑู ยูุง ฺฉููพูุชุฑ ุณุงูุณ\nุชุฌุงุฑุจ ูุงุฒูู\n:\nุจุง ุฏุงุดุชู ุญุฏ ุงูู ฒ ุณุงู ุชุฌุฑุจู ฺฉุงุฑ ุฏุฑุจุฎุด ูุฑุจูุทูุ\nููุงุฑุช ูุง ุฏฺฏุฑ ( ฺฉูุฑุณ ูุง ฺฉูุชุงู ูุฏุชุ ุขููุฒุด ูุง ุฏุงุฎู ุฎุฏูุช ูุบุฑู\n(\nุฏุงุฑุง ูุนูููุงุช ู ุชุฌุงุฑุจ ฺฉุงู ุฏุฑุจุฎุด ุดุจฺฉู ูุง ูุงุจุฑุ ISP ูุง ูุงููุช ุงุทูุงุนุงุช ู ุงูุชุฑูุช.\nูุงุจูุช ุงุณุชูุงุฏู ุงุฒ ุงุจุฒุงุฑ ูุง ูุฑุจูุทู ุจุฎุงุทุฑ ุชุดุฎุต ููุงูุตุ ุถุงุนุงุชุ ูุดฺฉูุงุช ู ูุงุฑุณุง ุฏุฑ ุดุจฺฉู ูุง ูุงุจุฑ ููุฑ\nูุชุนูุฏ ุจู ุญูุธ ุงุณุฑุงุฑ ู ูุญุฑูุช ูุนูููุงุช ุงุฏุงุฑู ุจุงุดุฏ.\nุฑุนุงุช ุฏุณูพูู ูุงู ู ุงุฏุงุฑ\nุฑุนุงุช ุณูุณูู ูุฑุงุชุจ\nุจุฑุฎูุฑุฏ ุฏูุณุชุงูู ุจุง ููฺฉุงุฑุงู\nุงุฑุชูุงุก ุธุฑูุช ุฎูุฏู\nุชูุงูุง ฺฉุงู ุฏุฑ ฺฉุงุฑ ฺฏุฑููพ\nุฏุงุฑุง ูุนูููุงุช ู ุชุฌุงุฑุจ ฺฏุณุชุฑุฏู ุฏุฑุจุฎุด ุงููุช ุงุทูุงุนุงุช ู ุงูุชุฑูุช.\nุฏุงุฑุง ุณูุงุจู ุฌุฑู ูุจุงุดุฏ\nุชุงุจุนุช ุงูุบุงูุณุชุงู ุฑุง ุฏุงุดุชู ู ุฏุฑ ฺฉุดูุฑ ููู ุจุงุดุฏ.\nุจู ูุณุงู ูุง ูพุดุชู ู ุฏุฑ ุจู ุฎูุจ ุชฺฉูู ูููุฏู ู ุจู ูุณุงู ุงูฺฏูุณ ุขุดูุง ุฏุงุดุชู ุจุงุดุฏ\nSubmission Guideline\nุฏ ูุญุชุฑูู ฺฉุงูุฏุฏุงูู ฺุฎู ููู ฺฉฺู ฺ ุชุฑ ฺู ุฏ ุงฺููุฏู ุจุณุช ููพุงุฑู ฺุงูฺซฺ ููุฑูู ฺฺฉู ุงู ูุงูุฏ ุจุฑูฺูุงูฺฉ ุชู ู ุฑุงูุงุณุชูู ุงู ููุฏุงุฑฺซู ฺฉููุง ุดู ฺ ุงุฏู ููุฑูู ุฏ ฺฉุงุฑฺฉูููฺฉู ุฏ ฺุงุฑู ยุฏ ุงุณุชุฎุฏุงู ุฏ ุขูุฑุช ฺุฎู ุชุฑูุงุณู ฺฉฺู .\nูพุชู : ุฏ ูุฎุงุจุฑุงุชู ุงู ูุนูููุงุชู ูผฺฉูุงููุฌ ูุฒุงุฑุช ฑธ ูพูฺุฒู ูุฏุงู ุฏุงุฑูุณู ููุฒู ุฏ ุงุณุชุฎุฏุงู ุขูุฑุช\nุจุฑฺูุงูฺฉ\njobs@atra.gov.af\nุฏ ุงฺฺฉู ุดูุฑู : 0202100763\nูููผ : ุฏ ูผููู ูุญุชุฑูู ฺฉุงูุฏุฏุงูู ฺุฎู ููู ฺฉฺู ฺ ฺฉู ฺุฑ ุณุชุงุณู ุชุญุตูุงุช ุงู ุง ูู ฺฉุงุฑู ุชุฌุฑุจู ุฏ ูพูุฑุชู ุจุณุช ุณุฑู ุณููู ูู ุฎูุฑู ูุทูุง ุฎูพู ุบูฺุชููฺฉ ูู ุฑุง ุงุณุชูุฆ .\nูพู ุฏุฑูฺุช\nSubmission Guidelines:\nAll applications ยForms ( CV & Cover Letters are notยconsidered )should be submitted via email to:\njobs@atra.gov.af\nPlease, clearly indicate on the subject line the title of the position. Applications received after the\nClosing date will not be considered.\nFunctional Area\nComputer Science\nTelecommunication\nElectrical Engineering, telecommunication\nCountries\nAfghanistan\nProvinces\nKabul\nSubmission Email\njobs@atra.gov.af\nAttachments\nApplication_Form ATRA.doc\nApply Now\nPost Date\nJan 14, 2026\nClosing Date\nJan 29, 2026\nReference\n003\nNumber of Vacancies\n1\nSalary Range\nAs per company salary scale\nYears of Experience\n2 years\nProbation Period\n3 month\nContract Type\nPermanent\nContract Duration\n1 year\nContract Extensible\nYes\nMinimum Education\nBachelor's Degree\nGender\nMale\nRelated Jobs\nNETLINKS Plaza | Shahr-e-Naw,\nLane 3, Kabul, Afghanistan\nQuick Links\nAbout Us\nAdvertise with Us\nPrivacy Policy\nFor Companies\nPost a Job\nPost a Job\nPost a Job\nPost a Job\nPost RFP\nPost RFP\nPost RFP\nPost RFP\nPost Training\nPost Training\nPost Training\nPost Training\nFor Jobseekers\nBrowse Jobs\nBrowse Companies\nBuild Resume\nContact\ninfo@jobs.af\nContact Us\nยฉ 2012 - 2026 Jobs.af | All Rights Reserved\nPowered by:\nNETLINKS Ltd",
    "details": {
      "Post Date": "Jan 14, 2026",
      "Closing Date": "Jan 29, 2026",
      "Reference": "003",
      "Number Of Vacancies": "1",
      "Salary Range": "As per company salary scale",
      "Years Of Experience": "2 years",
      "Probation Period": "3 month",
      "Contract Type": "Permanent",
      "Contract Duration": "1 year",
      "Contract Extensible": "Yes",
      "Minimum Education": "Bachelor's Degree",
      "ูพุชู": "ุฏ ูุฎุงุจุฑุงุชู ุงู ูุนูููุงุชู ูผฺฉูุงููุฌ ูุฒุงุฑุช ฑธ ูพูฺุฒู ูุฏุงู ุฏุงุฑูุณู ููุฒู ุฏ ุงุณุชุฎุฏุงู ุขูุฑุช",
      "ุฏ ุงฺฺฉู ุดูุฑู": "0202100763",
      "ูููผ": "ุฏ ูผููู ูุญุชุฑูู ฺฉุงูุฏุฏุงูู ฺุฎู ููู ฺฉฺู ฺ ฺฉู ฺุฑ ุณุชุงุณู ุชุญุตูุงุช ุงู ุง ูู ฺฉุงุฑู ุชุฌุฑุจู ุฏ ูพูุฑุชู ุจุณุช ุณุฑู ุณููู ูู ุฎูุฑู ูุทูุง ุฎูพู ุบูฺุชููฺฉ ูู ุฑุง ุงุณุชูุฆ .",
      "Functional Area": "Computer Science",
      "Countries": "Afghanistan",
      "Provinces": "Kabul"
    },
    "scraped_at": "2026-01-21T05:00:22Z",
    "apply_emails": [
      "jobs@atra.gov.af"
    ],
    "apply_method": "email"
  },
  {
    "url": "https://jobs.af/jobs/d-nn-brw-kastn-mslky-gh-y-cpNpVg7CL",
    "title": "ุฏ ูู ุจุฑูฺ ฺฉุงุณุชูฺซ ูุณูฺฉู ุบฺ",
    "company": null,
    "location": "Kabul",
    "closing_date": "2026-01-29",
    "closing_date_raw": "Jan 29, 2026",
    "apply_url": null,
    "description": "๐\nComing Soon The Jobs.af Freelancer Portal\nConnect with top clients and freelancers across Afghanistan all in one place!\nStay Tuned\nJobs\nProcurement Opportunities\nCompanies\nFreelancers\nServices\nProcurement Opportunities\nTrainings\nScholarships\nLogin\nRegister\nุฏ ูู ุจุฑูฺ ฺฉุงุณุชูฺซ ูุณูฺฉู ุบฺ\nATRA\nApply Now\nSee all jobs\nุฏ ูู ุจุฑูฺ ฺฉุงุณุชูฺซ ูุณูฺฉู ุบฺ\nATRA,\n                                        Kabul, Afghanistan\nApply Now\nBachelor's Degree\nKabul, Afghanistan\n(Kabul)\nFull Time\n704\nAbout\n                                            ATRA\nุฏ ุงูุบุงูุณุชุงู ุฏ ูุฎุงุจุฑุงุชู ุฎุฏูุชููู ุฏ ุชูุธู ุงุฏุงุฑู (ุงูผุฑุง) ูพู ฒฐฐถ ููุงุฏู ฺฉุงู ูพู ููุงุฏ ฺฉ ุฏ ูุฎุงุจุฑุงุชู ุณฺฉุชูุฑ ุฏ ุชูุธู ุงู ูพุฑูุฎุชุง ููพุงุฑู ุฑุงููฺ ุชู ุดูู. ุฏุง ุงุฏุงุฑู ูฺู ฺฉูู ฺ ุฏ ูุฎุงุจุฑุงุชู ุงู ุงููผุฑููผู ุฎุฏูุชููู ุฒุฑุจูุงูู ุฏ ูุฏ ุงู ูพุฑูุฎุชุง ูพู ุจุฑุฎู ฺฉ ุฏ ุฎุตูุตู ุณฺฉุชูุฑ ููพุงุฑู ุฏ ูพุงูฺซูู ูพุงูฺ ุงู ููุงุณุจ ฺุงูพุฑุงู ุฑุงููฺุชู ฺฉฺู. ูพู ููุงุฏ ฺฉ ุฏ ฺู ููุฑุฑุงุชู ุงู ุชูุธูุงุชู ฺุงูพุฑุงู ุฑุงููฺุชู ฺฉููู ุงู ุชููุฐ ูู ูุงุฑ ูู ุชุจุนุถ ูพุฑุชู ูพู ุดูุงู ฺูู ุฏ ฺูุงฺฉูู ุฎุตูุตู ุณฺฉุชูุฑ ูุฎูุง ุญูุงู ุดูู ูุฎุงุจุฑุงุชู ุณฺฉุชูุฑ ุงู ุงฺููุฏู ุฎุฏูุชููู ุฑุงููฺุชู ฺฉููุ ุฏ ููุฑุฑุงุชู ูพูู ฺฉููุ ุฎุฏูุชููู ุชู ุณุฑุงุณุฑ ูุงุณุฑุณุ ุฏ ูุงุฑฺฉูผ ุชูุธูููุ ูพู ูุฎุงุจุฑุงุชู ูุงุฑฺฉููผ ฺฉ ุฏ ุณุงู ฺูผฺฉูุงู ุงู ูุธุงุฑุช ุฏ ุงูผุฑุง ุงุฏุงุฑ ููุฎ ุฏู. ุงูผุฑุง ุงุฏุงุฑู ูู ุงฺููุฏู ุงฺุฎููู ุฎุตูุตู ุณฺฉุชูุฑุ ุฏููุชู ุงุฏุงุฑู ุงู ุฏ ูุฎุงุจุฑุงุชู ุฎุฏูุชููู ูุดุชุฑฺฉูู ุณุฑู ู ฺุง ฺฉุงุฑ ฺฉููุ ฺู ุฏ ููุงุฏ ูพู ูุฎุงุจุฑุงุชู ุงู ุงููผุฑููผู ูุงุฑฺฉูผ ฺฉ ุณุงููู ุณุงูู ูพุฑูุฎุชฺซ ูฺฉฺู.\nุฏ ูุฎุงุจุฑุงุชู ุณฺฉุชูุฑ ุงู ุตูุนุช ูู 2002 ููุงุฏู ฺฉุงู ุฑุง ูพุฏุฎูุง ุฏ ููุงุฏ 34 ููุงุชููู ุงู ู ุดูุฑ ุฒุงุชู ููุณูุงูู ุชู ุฏ ุงููผุฑููผู ูพูฺฺ ูพู ูพุฑุงุฎุชุง ุณุฑู ฺซฺูุฏ ูุฏู ฺฉฺุฏู . ุงูผุฑุง ุงุฏุงุฑ ุฏ ููุงุฏ ูุฎุงุจุฑุงุชู ุจุงุฒุงุฑ ุฏ ฺู ูพุฑูุฎุชฺซ ุงู ุชูุธู ููพุงุฑู ุชู ูฺู ฺฉฺุ ฺ ุฏ ูฺูุงูู ฺฉูุฏู ูุฎุงุจุฑุงุชู ุดุฑฺฉุงูู ุณุฑู ููฺซุฑุชุง ุงู ุงฺฺฉ ูุง ูพุงูฺ ฺฉฺู ุชุฑฺู ูู ูฺูุงูู ุชุฌุฑุจู ฺุฎู ูพู ุงุณุชูุงุฏ ฺซูผูุฑ ูุงุฑ ฺุงุฑ ูพู ฺซูุชู ุงู ุฏ ููุงุฏ ูุงุฑฺฉูผ ุชู ูุฏู ูุฑฺฉฺู. ุธุฑูุช ุฌูฺููู ุฏ ูุฎุงุจุฑุงุชู ุตูุนุช ููพุงุฑู ู ุจู ููู ูผฺฉ ุฏ. ุฏ ุชู ูพู ฺฉุชู ุงูผุฑุง ุงุฏุงุฑ ุฏ ุงฺููุฏู ุณฺฉุชูุฑ ุงู ูุฎุงุจุฑุงุชู ุงู ุงููผุฑููผู ุดุฑฺฉุชููู ูพู ฺซฺูู ุฏ ุธุฑูุช ููฺููู ุชู ุจูุฏุฌู ฺุงูฺซฺ ุงู ุฏ ฺฉุงุฑ ุงฺฉูุณุณุชู ุฑุงููฺุชู ฺฉฺ ุฏุ ฺ ุฏุง ุจู ูพู ูุฎุงุจุฑุงุชู ุณฺฉุชูุฑ ฺฉ ุฏ ูพุงูฺซูู ุฌูุจ ุงู ูพุฑุฏููฺฉู ุชู ุฏ ูพุฑูุฎุชููู ูุฎุงุจุฑุงุชู ุฎุฏูุชููู ูฺุงูุฏ ฺฉููู ูุงูู ุดู. ููุฏุงุฑูฺซูุ ุงูผุฑุง ุงุฏุงุฑู ูู ููุฑู ุงฺููุฏู ุฎูุงู ูพู ฺุงูฺซฺ ุชูฺซู ฺฺูุฒู ุงู ุงฺฉุงฺูฺฉู ูุฑฺฉุฒููู ุณุฑู ูพู ฺซฺู ฺฉุงุฑ ฺฉููุ ุชุฑฺู ูพู ููุงุฏ ฺฉ ุฏ ูุฎุงุจุฑุงุชู ฺฉุงุฑู ฺูุงฺฉ ุชู ูพุงูฺุชุง ุงู ูุฏู ูุฑฺฉฺู ุงู ูพู ูุงุฑฺฉูผ ฺฉ ุฏ ุธุฑูุช ุฌูฺูู ุจุฑูุงูู ุชู ุฏ (ุชุฑููฺซ) ุงู ููุฑู ุฎุฏูุชููู ููพุงุฑู ูุงุฑู ุจุฑุงุจุฑู ฺฉฺู.\nJob Summary\nุฏ ูู ุจุฑูฺ ฺฉุงุณุชูฺซ ูุณูฺฉู ุบฺ\nDuties & Responsibilities\nูุณุคูุช ูุง ูุธูู:\nุฑูููุงุ ุชูุถุญ ู ุตุฏูุฑ ุงุณูุงุฏ ู ุฑุงูพูุฑ ูุง ูุงุตูู ุงุฒ ุงุชุญุงุฏู ุจู ุงูููู ุชู ฺฉูููฺฉุดู (ITU)ุ ุฌูุนุช ูุฎุงุจุฑุงุช ุขุณุง ูพุงุณูฺฉ (APT)ุ ุงุชุญุงุฏู ุจุฑูุฏฺฉุงุณุชูฺฏ ุขุณุง (ABU)ุ ุดูุฑุง ุฑฺฏููุชุฑ ูุง ูุฎุงุจุฑุงุช ุฌููุจ ุขุณุง (SATRC) ู ุบุฑู ุณุงุฒูุงููุง ุจู ุงูููู ู ููุทูู ูุฎุงุจุฑุงุช ุจู ุจุฎุด ูุง ู ูุณููู ูุฑุจูุทู.\nุชุนู ู ุงูุชุฎุงุจ ุชุฎุตุตุงุช ูุฑฺฉููุณ ุฑุงุฏู ุจุฑุง ูุณุงู ู ุฏุณุชฺฏุงู ูุง ุจุณู ุจู ูุชุชูุงุถุงุงู ุงุนู ุงุฒ ููุณุณุงุช ุฏููุชุ ุบุฑ ุฏููุชุ ุณูุงุฑุชุฎุงูู ูุงุ ุดุฑฺฉุช ูุงุ ู ุงุดุฎุงุต ุงููุฑุงุฏ ุทุจู ููุฑุฑู ุจุณู ู ุฌุฏูู ุชุฎุตุตุงุช ูุฑฺฉููุณ ูู ู ุจู ุงูููู ฺฉูููฺฉุดู.\nููุงููฺฏ ุณุงุฎุชู ฺฉูู ูุฑฺฉููุณ ูุง ุฑุงุฏู ูุฌูุฒ ุงุฒ ุทุฑู ุงู ุงุฏุงุฑู ุฏุฑ ุณุทุญ ููุ ููุทูู ู ุจู ุงูููู ุทุจู (ITU-R).\nุซุจุชุ ุฑุงุฌุณุชุฑ ู ุงุทูุงุน ุฏู ูุฑฺฉููุณ ูุง ุชูุฒุน ุดุฏู ุจุง ุงุฏุงุฑู (MIFR) ู ุงุชุญุงุฏู ุจู ุงูููู ุชู ฺฉูููฺฉุดู (ITU).\nุชุญูู ู ููุณุฌู ุณุงุฒ ููุงุฑุฏ ุงุฎูุงู ูุฑฺฉููุณ ุฏุฑ ุดุจฺฉู ูุง ู ุฎุฏูุงุช ูู ุจุฑูุฏฺฉุงุณุชูฺฏ ฺฉู ุงุฒ ุงุฏุงุฑู ุงุชุฑุง ุฌูุงุฒูุงูู ุงุฎุฐ ฺฉุฑุฏู ุงูุฏ ูยุงุฑุณุงู ุขู ุจู ุฑุงุณุช ูุธุงุฑุช ูฺฉูุชุฑูู ู ูุฑุงุฌุน ุฐุฑุจุท.\nูุญุงุณุจู ู ุณูุฌุด ุงุฌุฑุช ูุฑฺฉููุณ ุฎุฏูุงุช ูู ุจุฑูุฏฺฉุงุณุชูฺฏ ู ุงุฌุฑุช ุญู ุงูุซุจุช ุงุณุชูุงุฏู ฺฉููุฏู ฺฏุงู ุฏุณุชฺฏุงู ูุง ู ูุณุงู ูุฑุจูุทู ูุทุงุจู ุจู ููุฑุฑุงุช ูุงูุฐู.\nุทุฑุฒ ุงุณุชูุงุฏู ูุคุซุฑ ู ูุทููุจ ุงุฒ ูุฑฺฉููุณ ูู ุจุฑูุฏฺฉุงุณุชูฺฏ ุจุง ุฏุฑ ูุธุฑ ุฏุงุดุช ุงุตู ุตุฑูู ุฌู ุงุฒ ุทู ูุฑฺฉููุณ ุฑุงุฏู ุจุญุซ ฺฉ ุงุฒ ููุงุจุน ูุญุฏูุฏ ุทุจุน ฺฉุดูุฑ.\nุงุชุฎุงุฐ ุชุฏุงุจุฑ ููุงู ุจู ููุธูุฑ ุฌููฺฏุฑ ุงุฒ ุณฺฉุชฺฏ ุฏุฑ ุงููุฑุ ู ูุฑุงูู ุขูุฑ ุชุณููุงุช ูุงุฒู ู ุงุฑุงู ูพุดููุงุฏุงุช ููุซุฑ ุจู ููุธูุฑ ุจูุจูุฏ ุฏุฑ ุงููุฑ ูุฑุจูุทู.\nุจุงุฒูฺฏุฑ ุฏูู ุณุงูุงูู ุจุฑ ุฌุฏูู ูู ุชุฎุตุตุงุช ูุฑฺฉููุณ ุงูุบุงูุณุชุงู ู ุงูพุฏุช ูฺฏูุฏุงุดุชู ุจุฎุด ูุง ูุฑุจูุทู ุขู ุจุง ุฏุฑ ูุธุฑุฏุงุดุช ูุนุงุฑูุง ู ุงุตูู ูู ู ุจู ุงูููู.\nูุฑุชุจ ุณุงุฒ ู ูฺฏูุฏุงุฑ ุงุณูุงุฏ ูุฑุจูุทู.\nุญูุธ ูุญุฑูุช ูุนูููุงุช ู ุงุณูุงุฏ ุงุฏุงุฑู\nุชุนูุจ ู ูพฺฏุฑ ุงููุฑ ููู ุจุง ุดุนุจุงุช ูุฑุจูุทู ู ุงุฏุงุฑุช ุฐุฑุจุท\nุงุฑุงู ูุนูููุงุช ู ุชูู ฺฏุฒุงุฑุด ูุง ูุฑุจูุทู ุฏุฑ ุตูุฑุช ุชูุงุถุง ุขูุฑ ูุงููู.\nุงูุฌุงู ุจูู ููุงุฑุฏ ฺฉู ุฏุฑ ูุญุฏูุฏู ฺฉุงุฑ ุงุฒ ุณู ูุณุฆูู ูุฑุจูุทู ุณูพุฑุฏู ูุดูุฏ.\nJob Requirements\nููุงุตูุงุช\nุชุญุตูุงุชุ ุชุฌุงุฑุจ ู ููุงุฑุช ูุง ูุงุฒู\n:\nุฏุฑุฌู ุชุญุตู\n:\nุฏุงุฑุง ุชุญุตูุงุช ุนุงู ุจู ุณูู ุญุฏุงูู ูุณุงูุณ ุฏุฑ ฺฉ ุงุฒ ุจุฎุด ูุง ุงูุฌูุฑ ูุฎุงุจุฑุงุชุ ุจุฑู ู ุงูฺฉุชุฑููฺฉุณ ู ฺฉููพูุชุฑ ุณุงูุณ ุจุงุดุฏ.\nุชุฌุงุฑุจ ูุงุฒูู\n:\nุฏุงุฑุง ุชุฌุฑุจู ุญุฏ ุงูู ุฏู ุณุงู ุฎุฏูุช ุจุงููุนู ุฏุฑ ุจุฎุด ูุฑฺฉููุณ ููุฌููุชุ ูุฑฺฉููุณ ูพูุงููฺฏ ุง ูุฑฺฉููุณ ุขูพุชูุงุฒุดู ุจุงุดุฏ.\n๏ปฟ\nููุงุฑุช ูุง ุฏฺฏุฑ ( ฺฉูุฑุณ ูุง ฺฉูุชุงู ูุฏุชุ ุขููุฒุด ูุง ุฏุงุฎู ุฎุฏูุช ูุบุฑู\n(\nุฏุงุฑุง ูุนูููุงุช ู ุชุฌุงุฑุจ ฺฏุณุชุฑุฏู ุฏุฑ ุงุจุนุงุฏ ูุฎุชูู ูุฑฺฉููุณุ ุจุงูุฏ ูุง ูุฎุชูู ูุฑฺฉููุณ ู ุฎุฏูุงุช ฺฉู ุจูุณูู ูุฑฺฉููุณ ุงุฑุงู ูุดูุฏุ ุจุงุดุฏ.\nุชูุงูุง ฺฉุงู ุฏุฑ ฺฉุงุฑ ฺฏุฑูู ุฏุงุดุชู ุจุงุดุฏ.\nุชุงุจุนุช ุงูุบุงูุณุชุงู ุฑุง ุฏุงุดุชู ู ุฏุฑ ุฏุงุฎู ฺฉุดูุฑ ููู ุจุงุดุฏ.\nุขุดูุง ุจุง ุณุงุฒูุงู ูุง ููุทูู ู ุจู ุงูููู ูุฎุงุจุฑุงุช ุฏุงุดุชู ุจุงุดุฏ.\nุฏุงุฑุง ุณูุงุจู ุฌุฑู ูุจุงุดุฏ.\nุจู ูพุฑูฺฏุฑุงู ูุง ฺฉููพูุชุฑ ูุฎุตูุตุง (MS Office) ู ุงูุชุฑูุช ุฏุณุชุฑุณ ู ุขุดูุง ฺฉุงูู ุฏุงุดุชู ุจุงุดุฏ.\nุจู ูุณุงู ูุง ูพฺุชู ู ุฏุฑู ุจู ุฎูุจ ุชฺฉูู ูููุฏู ู ุจู ูุณุงู ุงูฺฏูุณ ุขุดูุง ุฏุงุดุชู ุจุงุดุฏ.\nุณู ุงู ุงุฒ ฑธ ุณุงู ุจุงูุงุชุฑ ุจุงุดุฏ\nSubmission Guideline\nุฏ ูุญุชุฑูู ฺฉุงูุฏุฏุงูู ฺุฎู ููู ฺฉฺู ฺ ุชุฑ ฺู ุฏ ุงฺููุฏู ุจุณุช ููพุงุฑู ฺุงูฺซฺ ููุฑูู ฺฺฉู ุงู ูุงูุฏ ุจุฑูฺูุงูฺฉ ุชู ู ุฑุงูุงุณุชูู ุงู ููุฏุงุฑฺซู ฺฉููุง ุดู ฺ ุงุฏู ููุฑูู ุฏ ฺฉุงุฑฺฉูููฺฉู ุฏ ฺุงุฑู ยุฏ ุงุณุชุฎุฏุงู ุฏ ุขูุฑุช ฺุฎู ุชุฑูุงุณู ฺฉฺู .\nูพุชู : ุฏ ูุฎุงุจุฑุงุชู ุงู ูุนูููุงุชู ูผฺฉูุงููุฌ ูุฒุงุฑุช ฑธ ูพูฺุฒู ูุฏุงู ุฏุงุฑูุณู ููุฒู ุฏ ุงุณุชุฎุฏุงู ุขูุฑุช\nุจุฑฺูุงูฺฉ\njobs@atra.gov.af\nุฏ ุงฺฺฉู ุดูุฑู : 0202100763\nูููผ : ุฏ ูผููู ูุญุชุฑูู ฺฉุงูุฏุฏุงูู ฺุฎู ููู ฺฉฺู ฺ ฺฉู ฺุฑ ุณุชุงุณู ุชุญุตูุงุช ุงู ุง ูู ฺฉุงุฑู ุชุฌุฑุจู ุฏ ูพูุฑุชู ุจุณุช ุณุฑู ุณููู ูู ุฎูุฑู ูุทูุง ุฎูพู ุบูฺุชููฺฉ ูู ุฑุง ุงุณุชูุฆ .\nูพู ุฏุฑูฺุช\nSubmission Guidelines:\nAll applications ยForms ( CV & Cover Letters are notยconsidered )should be submitted via email to:\njobs@atra.gov.af\nPlease, clearly indicate on the subject line the title of the position. Applications received after the\nClosing date will not be considered.\nFunctional Area\nComputer Science\nTelecommunication\nElectrical Engineering, telecommunication\nCountries\nAfghanistan\nProvinces\nKabul\nSubmission Email\njobs@atra.gov.af\nAttachments\nApplication_Form ATRA.doc\nApply Now\nPost Date\nJan 14, 2026\nClosing Date\nJan 29, 2026\nReference\n001\nNumber of Vacancies\n1\nSalary Range\nAs per company salary scale\nYears of Experience\n2 years\nProbation Period\n3 month\nContract Type\nPermanent\nContract Duration\n1 year\nContract Extensible\nYes\nMinimum Education\nBachelor's Degree\nGender\nMale\nRelated Jobs\nNETLINKS Plaza | Shahr-e-Naw,\nLane 3, Kabul, Afghanistan\nQuick Links\nAbout Us\nAdvertise with Us\nPrivacy Policy\nFor Companies\nPost a Job\nPost a Job\nPost a Job\nPost a Job\nPost RFP\nPost RFP\nPost RFP\nPost RFP\nPost Training\nPost Training\nPost Training\nPost Training\nFor Jobseekers\nBrowse Jobs\nBrowse Companies\nBuild Resume\nContact\ninfo@jobs.af\nContact Us\nยฉ 2012 - 2026 Jobs.af | All Rights Reserved\nPowered by:\nNETLINKS Ltd",
    "details": {
      "Post Date": "Jan 14, 2026",
      "Closing Date": "Jan 29, 2026",
      "Reference": "001",
      "Number Of Vacancies": "1",
      "Salary Range": "As per company salary scale",
      "Years Of Experience": "2 years",
      "Probation Period": "3 month",
      "Contract Type": "Permanent",
      "Contract Duration": "1 year",
      "Contract Extensible": "Yes",
      "Minimum Education": "Bachelor's Degree",
      "ูพุชู": "ุฏ ูุฎุงุจุฑุงุชู ุงู ูุนูููุงุชู ูผฺฉูุงููุฌ ูุฒุงุฑุช ฑธ ูพูฺุฒู ูุฏุงู ุฏุงุฑูุณู ููุฒู ุฏ ุงุณุชุฎุฏุงู ุขูุฑุช",
      "ุฏ ุงฺฺฉู ุดูุฑู": "0202100763",
      "ูููผ": "ุฏ ูผููู ูุญุชุฑูู ฺฉุงูุฏุฏุงูู ฺุฎู ููู ฺฉฺู ฺ ฺฉู ฺุฑ ุณุชุงุณู ุชุญุตูุงุช ุงู ุง ูู ฺฉุงุฑู ุชุฌุฑุจู ุฏ ูพูุฑุชู ุจุณุช ุณุฑู ุณููู ูู ุฎูุฑู ูุทูุง ุฎูพู ุบูฺุชููฺฉ ูู ุฑุง ุงุณุชูุฆ .",
      "Functional Area": "Computer Science",
      "Countries": "Afghanistan",
      "Provinces": "Kabul"
    },
    "scraped_at": "2026-01-21T05:00:22Z",
    "apply_emails": [
      "jobs@atra.gov.af"
    ],
    "apply_method": "email"
  },
  {
    "url": "https://jobs.af/jobs/d-shbk-tkhnykr",
    "title": "ุฏ ุดุจฺฉ ุชุฎูฺฉุฑ",
    "company": null,
    "location": "Kabul",
    "closing_date": "2026-01-29",
    "closing_date_raw": "Jan 29, 2026",
    "apply_url": null,
    "description": "๐\nComing Soon The Jobs.af Freelancer Portal\nConnect with top clients and freelancers across Afghanistan all in one place!\nStay Tuned\nJobs\nProcurement Opportunities\nCompanies\nFreelancers\nServices\nProcurement Opportunities\nTrainings\nScholarships\nLogin\nRegister\nุฏ ุดุจฺฉ ุชุฎูฺฉุฑ\nATRA\nApply Now\nSee all jobs\nุฏ ุดุจฺฉ ุชุฎูฺฉุฑ\nATRA,\n                                        Kabul, Afghanistan\nApply Now\nBachelor's Degree\nKabul, Afghanistan\n(Kabul)\nFull Time\n1841\nAbout\n                                            ATRA\nุฏ ุงูุบุงูุณุชุงู ุฏ ูุฎุงุจุฑุงุชู ุฎุฏูุชููู ุฏ ุชูุธู ุงุฏุงุฑู (ุงูผุฑุง) ูพู ฒฐฐถ ููุงุฏู ฺฉุงู ูพู ููุงุฏ ฺฉ ุฏ ูุฎุงุจุฑุงุชู ุณฺฉุชูุฑ ุฏ ุชูุธู ุงู ูพุฑูุฎุชุง ููพุงุฑู ุฑุงููฺ ุชู ุดูู. ุฏุง ุงุฏุงุฑู ูฺู ฺฉูู ฺ ุฏ ูุฎุงุจุฑุงุชู ุงู ุงููผุฑููผู ุฎุฏูุชููู ุฒุฑุจูุงูู ุฏ ูุฏ ุงู ูพุฑูุฎุชุง ูพู ุจุฑุฎู ฺฉ ุฏ ุฎุตูุตู ุณฺฉุชูุฑ ููพุงุฑู ุฏ ูพุงูฺซูู ูพุงูฺ ุงู ููุงุณุจ ฺุงูพุฑุงู ุฑุงููฺุชู ฺฉฺู. ูพู ููุงุฏ ฺฉ ุฏ ฺู ููุฑุฑุงุชู ุงู ุชูุธูุงุชู ฺุงูพุฑุงู ุฑุงููฺุชู ฺฉููู ุงู ุชููุฐ ูู ูุงุฑ ูู ุชุจุนุถ ูพุฑุชู ูพู ุดูุงู ฺูู ุฏ ฺูุงฺฉูู ุฎุตูุตู ุณฺฉุชูุฑ ูุฎูุง ุญูุงู ุดูู ูุฎุงุจุฑุงุชู ุณฺฉุชูุฑ ุงู ุงฺููุฏู ุฎุฏูุชููู ุฑุงููฺุชู ฺฉููุ ุฏ ููุฑุฑุงุชู ูพูู ฺฉููุ ุฎุฏูุชููู ุชู ุณุฑุงุณุฑ ูุงุณุฑุณุ ุฏ ูุงุฑฺฉูผ ุชูุธูููุ ูพู ูุฎุงุจุฑุงุชู ูุงุฑฺฉููผ ฺฉ ุฏ ุณุงู ฺูผฺฉูุงู ุงู ูุธุงุฑุช ุฏ ุงูผุฑุง ุงุฏุงุฑ ููุฎ ุฏู. ุงูผุฑุง ุงุฏุงุฑู ูู ุงฺููุฏู ุงฺุฎููู ุฎุตูุตู ุณฺฉุชูุฑุ ุฏููุชู ุงุฏุงุฑู ุงู ุฏ ูุฎุงุจุฑุงุชู ุฎุฏูุชููู ูุดุชุฑฺฉูู ุณุฑู ู ฺุง ฺฉุงุฑ ฺฉููุ ฺู ุฏ ููุงุฏ ูพู ูุฎุงุจุฑุงุชู ุงู ุงููผุฑููผู ูุงุฑฺฉูผ ฺฉ ุณุงููู ุณุงูู ูพุฑูุฎุชฺซ ูฺฉฺู.\nุฏ ูุฎุงุจุฑุงุชู ุณฺฉุชูุฑ ุงู ุตูุนุช ูู 2002 ููุงุฏู ฺฉุงู ุฑุง ูพุฏุฎูุง ุฏ ููุงุฏ 34 ููุงุชููู ุงู ู ุดูุฑ ุฒุงุชู ููุณูุงูู ุชู ุฏ ุงููผุฑููผู ูพูฺฺ ูพู ูพุฑุงุฎุชุง ุณุฑู ฺซฺูุฏ ูุฏู ฺฉฺุฏู . ุงูผุฑุง ุงุฏุงุฑ ุฏ ููุงุฏ ูุฎุงุจุฑุงุชู ุจุงุฒุงุฑ ุฏ ฺู ูพุฑูุฎุชฺซ ุงู ุชูุธู ููพุงุฑู ุชู ูฺู ฺฉฺุ ฺ ุฏ ูฺูุงูู ฺฉูุฏู ูุฎุงุจุฑุงุชู ุดุฑฺฉุงูู ุณุฑู ููฺซุฑุชุง ุงู ุงฺฺฉ ูุง ูพุงูฺ ฺฉฺู ุชุฑฺู ูู ูฺูุงูู ุชุฌุฑุจู ฺุฎู ูพู ุงุณุชูุงุฏ ฺซูผูุฑ ูุงุฑ ฺุงุฑ ูพู ฺซูุชู ุงู ุฏ ููุงุฏ ูุงุฑฺฉูผ ุชู ูุฏู ูุฑฺฉฺู. ุธุฑูุช ุฌูฺููู ุฏ ูุฎุงุจุฑุงุชู ุตูุนุช ููพุงุฑู ู ุจู ููู ูผฺฉ ุฏ. ุฏ ุชู ูพู ฺฉุชู ุงูผุฑุง ุงุฏุงุฑ ุฏ ุงฺููุฏู ุณฺฉุชูุฑ ุงู ูุฎุงุจุฑุงุชู ุงู ุงููผุฑููผู ุดุฑฺฉุชููู ูพู ฺซฺูู ุฏ ุธุฑูุช ููฺููู ุชู ุจูุฏุฌู ฺุงูฺซฺ ุงู ุฏ ฺฉุงุฑ ุงฺฉูุณุณุชู ุฑุงููฺุชู ฺฉฺ ุฏุ ฺ ุฏุง ุจู ูพู ูุฎุงุจุฑุงุชู ุณฺฉุชูุฑ ฺฉ ุฏ ูพุงูฺซูู ุฌูุจ ุงู ูพุฑุฏููฺฉู ุชู ุฏ ูพุฑูุฎุชููู ูุฎุงุจุฑุงุชู ุฎุฏูุชููู ูฺุงูุฏ ฺฉููู ูุงูู ุดู. ููุฏุงุฑูฺซูุ ุงูผุฑุง ุงุฏุงุฑู ูู ููุฑู ุงฺููุฏู ุฎูุงู ูพู ฺุงูฺซฺ ุชูฺซู ฺฺูุฒู ุงู ุงฺฉุงฺูฺฉู ูุฑฺฉุฒููู ุณุฑู ูพู ฺซฺู ฺฉุงุฑ ฺฉููุ ุชุฑฺู ูพู ููุงุฏ ฺฉ ุฏ ูุฎุงุจุฑุงุชู ฺฉุงุฑู ฺูุงฺฉ ุชู ูพุงูฺุชุง ุงู ูุฏู ูุฑฺฉฺู ุงู ูพู ูุงุฑฺฉูผ ฺฉ ุฏ ุธุฑูุช ุฌูฺูู ุจุฑูุงูู ุชู ุฏ (ุชุฑููฺซ) ุงู ููุฑู ุฎุฏูุชููู ููพุงุฑู ูุงุฑู ุจุฑุงุจุฑู ฺฉฺู.\nJob Summary\nุฏ ุดุจฺฉ ุชุฎูฺฉุฑ\nDuties & Responsibilities\nูุณุคูุช ูุง ูุธูู:\nุฏูุฏ ุงู ูุณุคูุชููู (Duties and Responsibilities):\nโข ุฏ ุดุจฺฉ ุฏ ูุงุฑฺูุฑ (Network Hardware) ุงุฌุฒุงูู ุงู ฺฉุจูููู ูุตุจ ฺฉูู.\nโข ุฏ ุดุจฺฉ ุฏ ุณุงููผูุฑ (Network Software) ุชูุธู ุงู ฺฉุงููฺซูุฑ ฺฉูู.\nโข ุฏ ุดุจฺฉ ุฏ ุณุชููุฒู ุชุดุฎุต (Troubleshooting) ุงู ุญู ฺฉูู.\nโข ุฏ ุฏ ฺุงฺ ุชุฑูุงุณู ฺฉูู ฺ ุดุจฺฉู ูพู ุฎููุฏู ฺูู (Securely) ูุนุงูุช ฺฉูู.\nโข ุฏ NI (Network Infrastructure) ูผู ุฏ ููุฑู ุบฺู ุงู ูุฏุฑุช ุณุฑู ููฺฉุงุฑู ฺฉูู.\nโข ููฺฉุงุฑุงูู ุชู ุชุฎูฺฉู ููุงุชฺ (Technical Support) ุจุฑุงุจุฑูู.\nโข ุฏ ุงฺุชุง ูพุฑ ููุงู ุฏ ุดุจฺฉ ูพู ุฒุฑุจูุง (Network Infrastructure) ฺฉ ูุงุฒู ุงูพฺซุฑฺููู ุชุฑุณุฑู ฺฉูู.\nโข ุฏ ฺู ูุนุงูุช ูุฑููฺฉู ฺฉููพููผุฑู ุดุจฺฉูุ ุงฺฺฉู (Connections) ุงู ฺฉุจููฺซ ฺุฒุงู ุงู ูุตุจ ฺฉูู.\nโข ุฏ ุณุณูผู ุฏ ุฎุฑุงุจู (System Failures) ููพุงุฑู Troubleshooting ฺฉูู ุงู ุฏ ุดุจฺฉ ุฎูฺููู (Bottlenecks) ุชุดุฎุต ฺฉูู ุชุฑ ฺู ุฏ ุดุจฺฉ ุงูฺุฏููุงูู ููุซุฑุช ููู ุดู.\nโข ุฏ LAN ุฒุฑุจูุง ูุนุงูู ฺฉูู ุงู ฺฉูฺู ุง ููู ุณุชููุฒ/ุจฺซููู (Problems/Bugs) ุญู ฺฉูู.\nโข ุฏ ุณุงููผูุฑ ูผุณูผ ุงู ฺฉุงููฺซูุฑ ฺฉูู ุงู ุฏ ูุงุฑฺูุฑ ุงู ุฌุงูุจู ูุณุงูู (Peripheral Devices) ุณุงุชูู ุงู ุชุฑูู ฺฉูู.\nโข ุฏ ุดุจฺฉ ุฏ ูุนุงูุช ุงุฑุฒููู (Network Performance Evaluation) ฺฉูู ุงู ุฏ ฺูโูุงูู ูุงุฑ ฺุงุฑ ูููุฏู.\nโข ุฏ ุงุฏุงุฑ ุฏ ูุนูููุงุชู ุฏ ุณุงุชู ููพุงุฑู ููุธู ุฏ ฺุงูผุง ุจฺฉโุงูพููู (Data Backups) ุงุฎุณุชู.\nโข ููฺฉุงุฑุงูู ุชู ุฏ ฺฉููพููผุฑ ุงู ุดุจฺฉ ุฏ ฺฉุงุฑูู ูพู ุจุฑุฎู ฺฉ ุชุฎูฺฉู ูุงุฑฺููู ูุฑฺฉูู ุงู ุจุดูพฺ ูุดูุฑ ุงู ูุฏุงุงุช ูฺุงูุฏ ฺฉูู.\nโข ุฏ RTDMS ุฏ ุดุจฺฉ ุฏ ูุนุงุฑููู (Network Standards) ูู ูุฎ ุฏ ูผููู ุชุฌูุฒุงุชู ุงู ฺฉุจูููู ูุจู ุงู ูผฺซ ฺฉูู\nJob Requirements\nููุงุตูุงุช\nุชุญุตูุงุชุ ุชุฌุงุฑุจ ู ููุงุฑุช ูุง ูุงุฒู\n:\nุฏุฑุฌู ุชุญุตู\n:\nุญุฏุงูู ูุณุงูุณ ูพู ฺฉููพููผุฑ ุณุงูุณ ุงู ุง ูุฎุงุจุฑุงุช ูพู ุจุฑุฎู ฺฉ\nุชุฌุงุฑุจ ูุงุฒูู\n:\n๏ปฟ๏ปฟ\nุฏ ุดุจฺฉ ุฏ ุชุฎูฺฉุฑ\n(Network Technician)\nุง ูุฑุชู ุงฺููุฏ ุจุณุช ฺฉ ณ ฺฉุงูู ุซุงุจุชู ุงู ุนููู ฺฉุงุฑู ุชุฌุฑุจู ููุฑู .\nโข\nููู ุชุดุฎุตู\n(Diagnostic)\nุ ุฏ ุณุชููุฒู ุญู\n(Problem-Solving)\nุงู ุชุญููู\n(Analytical)\nููุงุฑุชููู\n.\nโข\nุฏ\nLAN/WAN\nุดุจฺฉูุ\nTCP/IP\nูพุฑูุชูฺฉููููู ุงู ุฏ ุดุจฺฉ ูผฺฉูุงููฺู ูพู ุจุฑุฎู ฺฉ ฺู ูพููู\n.\nโข\nูู ุนุงูู ุณุงููผูุฑููู ุงู ูุงุฑฺูุฑููู ุณุฑู ุนููู ุชุฌุฑุจู\n(Hands-on Experience).\nโข\nุฏ ุฏ ูฺุชุง ฺ ุฏ ฺฉุงุฑ ุฏ ุจุดูพฺููู ุงู ุฏ ุงูุงุฑูููู\n(Alarm)\nุฏ ฺูุงุจ ููพุงุฑู ูู ฺฉููพููผุฑ ุงู ุณูุงุฑูผ ููู ฺุฎู ุงุณุชูุงุฏู ูุดูุ ุฏูุชุฑู ุณุงููผูุฑููููพู ฺซฺูู.\nโข\nุฏ ุจูุงุจูู ุฎูฺฉู ุณุฑู ุฏ ฺซฺ ฺฉุงุฑ ฺฉููู ูฺุชุงุ ุชุฑ ฺู ฺฉุงุฑู ุฏูุฏ ุงู ูพุฑูฺ ุจุดูพฺ ุดู\n.\nโข\nุฏ ุฏูุชุฑู ุงฺุชุงูู ูู ูุฎ ุฏ ูุฑฺ ุงู ุดูพ ฺฉุงุฑ ฺฉููู ูฺุชุง\n.\nุฏ ูุธู ุดุฑุงุท:\nฑ โ ุฏ ุดุจฺฉ ุชุฎูฺฉุฑ ุจู ุฏ ุงฺููุฏู ุขูุฑุช ูพู ูุงุฑฺูููู ูพู ฒด ุณุงุนุชู ฺฉ ุญุฏุงูู ธ ุณุงุนุชู ฺฉุงุฑู ุดูุช ููุฑู ฺ ูพู ููุจุชูุงุฑ ุดฺฉู ุณุฑู ุจู ูุฑุชู ุชูุธู ฺฉฺู ุงูุจุชู ูพู ุนูููู ุฑุฎุตุชู ฺฉ ุจู ูู ธ ุณุงุนุชู ฺฉุงุฑู ุดูุช ููุฑู .\nููุฑ ููุงุฑุชููู :\nุฏ ฺฉุงูุฏุฏ ุณู ุจุงุฏ ุฏ ฑธ ฺฉุงูู ฺุฎู ููฺ ูู\nุฏ ููุช ุชุฐฺฉุฑู ููุฑู ุงู ูพู ููุงุฏ ฺฉ ูุดุช ูู\nุฏ ููฺฉุงุฑุงูู ุณุฑู ุฏูุณุชุงูู ุงฺฺฉู ููุฑู\nูพู ุชุฎูฺฉู ุจุฑุฎู ฺฉ ูพูุฑุชู ูุนูููุงุช ููุฑู .\nุฌุฑูู ุณุงุจูู ูููุฑู\nูพู ูพฺุชู ุ ุฏุฑู ุงู ุงูฺซูุณู ฺุจู ูพูุฑู ุชุณูุท ููุฑู\nSubmission Guideline\nุฏ ูุญุชุฑูู ฺฉุงูุฏุฏุงูู ฺุฎู ููู ฺฉฺู ฺ ุชุฑ ฺู ุฏ ุงฺููุฏู ุจุณุช ููพุงุฑู ฺุงูฺซฺ ููุฑูู ฺฺฉู ุงู ูุงูุฏ ุจุฑูฺูุงูฺฉ ุชู ู ุฑุงูุงุณุชูู ุงู ููุฏุงุฑฺซู ฺฉููุง ุดู ฺ ุงุฏู ููุฑูู ุฏ ฺฉุงุฑฺฉูููฺฉู ุฏ ฺุงุฑู ยุฏ ุงุณุชุฎุฏุงู ุฏ ุขูุฑุช ฺุฎู ุชุฑูุงุณู ฺฉฺู .\nูพุชู : ุฏ ูุฎุงุจุฑุงุชู ุงู ูุนูููุงุชู ูผฺฉูุงููุฌ ูุฒุงุฑุช ฑธ ูพูฺุฒู ูุฏุงู ุฏุงุฑูุณู ููุฒู ุฏ ุงุณุชุฎุฏุงู ุขูุฑุช\nุจุฑฺูุงูฺฉ\njobs@atra.gov.af\nุฏ ุงฺฺฉู ุดูุฑู : 0202100763\nูููผ : ุฏ ูผููู ูุญุชุฑูู ฺฉุงูุฏุฏุงูู ฺุฎู ููู ฺฉฺู ฺ ฺฉู ฺุฑ ุณุชุงุณู ุชุญุตูุงุช ุงู ุง ูู ฺฉุงุฑู ุชุฌุฑุจู ุฏ ูพูุฑุชู ุจุณุช ุณุฑู ุณููู ูู ุฎูุฑู ูุทูุง ุฎูพู ุบูฺุชููฺฉ ูู ุฑุง ุงุณุชูุฆ .\nูพู ุฏุฑูฺุช\nSubmission Guidelines:\nAll applications ยForms ( CV & Cover Letters are notยconsidered )should be submitted via email to:\njobs@atra.gov.af\nPlease, clearly indicate on the subject line the title of the position. Applications received after the\nClosing date will not be considered.\nFunctional Area\nComputer Science\nTelecommunication\nCountries\nAfghanistan\nProvinces\nKabul\nSubmission Email\njobs@atra.gov.af\nAttachments\nApplication_Form ATRA.doc\nApply Now\nPost Date\nJan 14, 2026\nClosing Date\nJan 29, 2026\nReference\n007\nNumber of Vacancies\n1\nSalary Range\nAs per company salary scale\nYears of Experience\n3 years\nProbation Period\n3 month\nContract Type\nPermanent\nContract Duration\n1 year\nContract Extensible\nYes\nMinimum Education\nBachelor's Degree\nGender\nMale\nRelated Jobs\nNETLINKS Plaza | Shahr-e-Naw,\nLane 3, Kabul, Afghanistan\nQuick Links\nAbout Us\nAdvertise with Us\nPrivacy Policy\nFor Companies\nPost a Job\nPost a Job\nPost a Job\nPost a Job\nPost RFP\nPost RFP\nPost RFP\nPost RFP\nPost Training\nPost Training\nPost Training\nPost Training\nFor Jobseekers\nBrowse Jobs\nBrowse Companies\nBuild Resume\nContact\ninfo@jobs.af\nContact Us\nยฉ 2012 - 2026 Jobs.af | All Rights Reserved\nPowered by:\nNETLINKS Ltd",
    "details": {
      "Post Date": "Jan 14, 2026",
      "Closing Date": "Jan 29, 2026",
      "Reference": "007",
      "Number Of Vacancies": "1",
      "Salary Range": "As per company salary scale",
      "Years Of Experience": "3 years",
      "Probation Period": "3 month",
      "Contract Type": "Permanent",
      "Contract Duration": "1 year",
      "Contract Extensible": "Yes",
      "Minimum Education": "Bachelor's Degree",
      "ูพุชู": "ุฏ ูุฎุงุจุฑุงุชู ุงู ูุนูููุงุชู ูผฺฉูุงููุฌ ูุฒุงุฑุช ฑธ ูพูฺุฒู ูุฏุงู ุฏุงุฑูุณู ููุฒู ุฏ ุงุณุชุฎุฏุงู ุขูุฑุช",
      "ุฏ ุงฺฺฉู ุดูุฑู": "0202100763",
      "ูููผ": "ุฏ ูผููู ูุญุชุฑูู ฺฉุงูุฏุฏุงูู ฺุฎู ููู ฺฉฺู ฺ ฺฉู ฺุฑ ุณุชุงุณู ุชุญุตูุงุช ุงู ุง ูู ฺฉุงุฑู ุชุฌุฑุจู ุฏ ูพูุฑุชู ุจุณุช ุณุฑู ุณููู ูู ุฎูุฑู ูุทูุง ุฎูพู ุบูฺุชููฺฉ ูู ุฑุง ุงุณุชูุฆ .",
      "Functional Area": "Computer Science",
      "Countries": "Afghanistan",
      "Provinces": "Kabul"
    },
    "scraped_at": "2026-01-21T05:00:22Z",
    "apply_emails": [
      "jobs@atra.gov.af"
    ],
    "apply_method": "email"
  },
  {
    "url": "https://jobs.af/jobs/d-spys-mnjmn-aamryt",
    "title": "ุฏ ุณูพุณ ููุฌูููผ ุขูุฑุช",
    "company": null,
    "location": "Kabul",
    "closing_date": "2026-01-29",
    "closing_date_raw": "Jan 29, 2026",
    "apply_url": null,
    "description": "๐\nComing Soon The Jobs.af Freelancer Portal\nConnect with top clients and freelancers across Afghanistan all in one place!\nStay Tuned\nJobs\nProcurement Opportunities\nCompanies\nFreelancers\nServices\nProcurement Opportunities\nTrainings\nScholarships\nLogin\nRegister\nุฏ ุณูพุณ ููุฌูููผ ุขูุฑุช\nATRA\nApply Now\nSee all jobs\nุฏ ุณูพุณ ููุฌูููผ ุขูุฑุช\nATRA,\n                                        Kabul, Afghanistan\nApply Now\nBachelor's Degree\nKabul, Afghanistan\n(Kabul)\nFull Time\n1459\nAbout\n                                            ATRA\nุฏ ุงูุบุงูุณุชุงู ุฏ ูุฎุงุจุฑุงุชู ุฎุฏูุชููู ุฏ ุชูุธู ุงุฏุงุฑู (ุงูผุฑุง) ูพู ฒฐฐถ ููุงุฏู ฺฉุงู ูพู ููุงุฏ ฺฉ ุฏ ูุฎุงุจุฑุงุชู ุณฺฉุชูุฑ ุฏ ุชูุธู ุงู ูพุฑูุฎุชุง ููพุงุฑู ุฑุงููฺ ุชู ุดูู. ุฏุง ุงุฏุงุฑู ูฺู ฺฉูู ฺ ุฏ ูุฎุงุจุฑุงุชู ุงู ุงููผุฑููผู ุฎุฏูุชููู ุฒุฑุจูุงูู ุฏ ูุฏ ุงู ูพุฑูุฎุชุง ูพู ุจุฑุฎู ฺฉ ุฏ ุฎุตูุตู ุณฺฉุชูุฑ ููพุงุฑู ุฏ ูพุงูฺซูู ูพุงูฺ ุงู ููุงุณุจ ฺุงูพุฑุงู ุฑุงููฺุชู ฺฉฺู. ูพู ููุงุฏ ฺฉ ุฏ ฺู ููุฑุฑุงุชู ุงู ุชูุธูุงุชู ฺุงูพุฑุงู ุฑุงููฺุชู ฺฉููู ุงู ุชููุฐ ูู ูุงุฑ ูู ุชุจุนุถ ูพุฑุชู ูพู ุดูุงู ฺูู ุฏ ฺูุงฺฉูู ุฎุตูุตู ุณฺฉุชูุฑ ูุฎูุง ุญูุงู ุดูู ูุฎุงุจุฑุงุชู ุณฺฉุชูุฑ ุงู ุงฺููุฏู ุฎุฏูุชููู ุฑุงููฺุชู ฺฉููุ ุฏ ููุฑุฑุงุชู ูพูู ฺฉููุ ุฎุฏูุชููู ุชู ุณุฑุงุณุฑ ูุงุณุฑุณุ ุฏ ูุงุฑฺฉูผ ุชูุธูููุ ูพู ูุฎุงุจุฑุงุชู ูุงุฑฺฉููผ ฺฉ ุฏ ุณุงู ฺูผฺฉูุงู ุงู ูุธุงุฑุช ุฏ ุงูผุฑุง ุงุฏุงุฑ ููุฎ ุฏู. ุงูผุฑุง ุงุฏุงุฑู ูู ุงฺููุฏู ุงฺุฎููู ุฎุตูุตู ุณฺฉุชูุฑุ ุฏููุชู ุงุฏุงุฑู ุงู ุฏ ูุฎุงุจุฑุงุชู ุฎุฏูุชููู ูุดุชุฑฺฉูู ุณุฑู ู ฺุง ฺฉุงุฑ ฺฉููุ ฺู ุฏ ููุงุฏ ูพู ูุฎุงุจุฑุงุชู ุงู ุงููผุฑููผู ูุงุฑฺฉูผ ฺฉ ุณุงููู ุณุงูู ูพุฑูุฎุชฺซ ูฺฉฺู.\nุฏ ูุฎุงุจุฑุงุชู ุณฺฉุชูุฑ ุงู ุตูุนุช ูู 2002 ููุงุฏู ฺฉุงู ุฑุง ูพุฏุฎูุง ุฏ ููุงุฏ 34 ููุงุชููู ุงู ู ุดูุฑ ุฒุงุชู ููุณูุงูู ุชู ุฏ ุงููผุฑููผู ูพูฺฺ ูพู ูพุฑุงุฎุชุง ุณุฑู ฺซฺูุฏ ูุฏู ฺฉฺุฏู . ุงูผุฑุง ุงุฏุงุฑ ุฏ ููุงุฏ ูุฎุงุจุฑุงุชู ุจุงุฒุงุฑ ุฏ ฺู ูพุฑูุฎุชฺซ ุงู ุชูุธู ููพุงุฑู ุชู ูฺู ฺฉฺุ ฺ ุฏ ูฺูุงูู ฺฉูุฏู ูุฎุงุจุฑุงุชู ุดุฑฺฉุงูู ุณุฑู ููฺซุฑุชุง ุงู ุงฺฺฉ ูุง ูพุงูฺ ฺฉฺู ุชุฑฺู ูู ูฺูุงูู ุชุฌุฑุจู ฺุฎู ูพู ุงุณุชูุงุฏ ฺซูผูุฑ ูุงุฑ ฺุงุฑ ูพู ฺซูุชู ุงู ุฏ ููุงุฏ ูุงุฑฺฉูผ ุชู ูุฏู ูุฑฺฉฺู. ุธุฑูุช ุฌูฺููู ุฏ ูุฎุงุจุฑุงุชู ุตูุนุช ููพุงุฑู ู ุจู ููู ูผฺฉ ุฏ. ุฏ ุชู ูพู ฺฉุชู ุงูผุฑุง ุงุฏุงุฑ ุฏ ุงฺููุฏู ุณฺฉุชูุฑ ุงู ูุฎุงุจุฑุงุชู ุงู ุงููผุฑููผู ุดุฑฺฉุชููู ูพู ฺซฺูู ุฏ ุธุฑูุช ููฺููู ุชู ุจูุฏุฌู ฺุงูฺซฺ ุงู ุฏ ฺฉุงุฑ ุงฺฉูุณุณุชู ุฑุงููฺุชู ฺฉฺ ุฏุ ฺ ุฏุง ุจู ูพู ูุฎุงุจุฑุงุชู ุณฺฉุชูุฑ ฺฉ ุฏ ูพุงูฺซูู ุฌูุจ ุงู ูพุฑุฏููฺฉู ุชู ุฏ ูพุฑูุฎุชููู ูุฎุงุจุฑุงุชู ุฎุฏูุชููู ูฺุงูุฏ ฺฉููู ูุงูู ุดู. ููุฏุงุฑูฺซูุ ุงูผุฑุง ุงุฏุงุฑู ูู ููุฑู ุงฺููุฏู ุฎูุงู ูพู ฺุงูฺซฺ ุชูฺซู ฺฺูุฒู ุงู ุงฺฉุงฺูฺฉู ูุฑฺฉุฒููู ุณุฑู ูพู ฺซฺู ฺฉุงุฑ ฺฉููุ ุชุฑฺู ูพู ููุงุฏ ฺฉ ุฏ ูุฎุงุจุฑุงุชู ฺฉุงุฑู ฺูุงฺฉ ุชู ูพุงูฺุชุง ุงู ูุฏู ูุฑฺฉฺู ุงู ูพู ูุงุฑฺฉูผ ฺฉ ุฏ ุธุฑูุช ุฌูฺูู ุจุฑูุงูู ุชู ุฏ (ุชุฑููฺซ) ุงู ููุฑู ุฎุฏูุชููู ููพุงุฑู ูุงุฑู ุจุฑุงุจุฑู ฺฉฺู.\nJob Summary\nุฏ ุณูพูฺูฺฉ ูุฏุงุฑ ุงู ูุฑฺฉููุณู ุฏ ููุบฺย(Satellite Orbit- Frequency Coordination) ุขูุฑ ุฏ ุฏ ูุณุคูุช ูุฑู ฺ ุฏ ููู ููุฑุฑุงุชู ยุงู ูฺูุงูู ููุฑุฑุงุชู (ITU Radio Regulations) ุณุฑู ุณู ุฏ ููุงุฏ ุฏ ุฏ ุณูผูุงูผ ุฏ ูุฏุงุฑ ุฏ ูููุนุช ยุงู ุฏ ุณูผูุงูผ ุฏ ยูุฑฺฉููุณููุฏ ุชุฎุตุตุ ุฏ ุงุฎูุงู (Interference) ฺุฎู ุฏ ูุฑฺฉููุณู ุฏ ุณุงุชูุ ูพูุงู ุฌูฺูู ุงู ุฏ ุณูผูุงูผููู ุฏ ูุฏุงุฑููู ุงู ูุฑฺฉููุณู ุฏ ููุบฺ (Orbit- Frequency Coordination) ุฏูุฏ ุชุฑุณุฑู ฺฉฺู.\nDuties & Responsibilities\nูุธููู ูุณุฆููุชููู :\nุฏ ูฺูุงูู ููุฑุฑุงุชู (ITU Radio Regulations) ุณุฑู ุณู ุฏ ุณูผูุงูผู ุดุจฺฉู ุฏ ูุงููฺซ (ุงุณูุงุฏู)\n(Advance Publication, Coordination and Notifications ) ฺูุชู ฺฉูู ุงู ุฏ ูุฎุงุจุฑุงุชู ูฺูุงู ุงุชุญุงุฏู ุชู ู ุงุณุชูู.\nุฏ ุณูผูุงูผููู ูพู ุจุฑุฎู ฺฉ ุฏ ููุบฺ ูพู ููุฎู ุฏ ุชุฎูฺฉู ูุทุงุจูุช ููพุงุฑู ุฏ\ntechnical compatibility (interference analysis, link budget calculations, coverage studies)\nูุทุงูุนุงุชู ุงู ูุญุงุณุจุงุชู ุณุฑู ฺฉูู.\nุฏ ููุฑู ููุงุฏููู/ ุงูพุฑูผุฑุงูู ุณุฑู ุฏ (orbit โ Frequency Coordination) ูพู ุฏูู ุงฺุฎุฒู ุงู ุฏุฑ ุงฺุฎุฒู ูุงุณุชู ฺฉ ฺซฺูู ฺฉูู.\nุฏ ูุถุฑู ุงุฎูุงู (Interference) ฺุฎู ุฏ ุงูุบุงูุณุชุงู ุฏ ุณูผูุงูผ ุฏ ูุฏุงุฑ ุฏ ูููุนุช ุณุงุชูู.\nุฏ BRIFIC ูุญุชูุงุช ูุทุงูุนู ฺฉูู ุงู ุฏ ูุฎุงุจุฑุงุชู ูฺูุงู ุงุชุญุงุฏ ุชู ุฏ ุงูุบุงูุณุชุงู ุฏ ฺูฺฉูู ูุฎุงุจุฑุงุชู (Terrestrial Telecommunication Services) ุงู ูุถุงูู ุฎุฏูุชููู (Space Telecommunication Services) ุชู ุฏ ุงุฎูุงู (Interference) ูพฺุฏู ูพู ุตูุฑุช ฺฉ ุฏ ูุฎุงุจุฑุงุชู ูฺูุงู ุงุชุญุงุฏ ุชู ุฎุจุฑ ูุฑฺฉูู ุงู ุฏ ูุบ ูุฎูู ฺฉูู.\nุฏ ุณูผูุงูผู ุฎุฏูุชููู ุฏ ููุบฺ ูพู ูพุฑูุณู ฺฉ ุฏ ุณู ุงู ูฺ ูู ููุงุฏููู ฺู ุฏ ุชุฑูุงุณู ฺฉุฏููฺฉู ุชุฎูฺฉู ุงุฏฺุชููู ุชุญูููู ุงู ูพู ุฎูพู ูุฎุช ุณุฑู ฺูุงุจ ูุฑฺฉูู.\nุฏ ุณูผูุงูผ ุฏ ูุฑฺฉููุณู ุงู ุฏ ุณูผูุงูผ ูุฏุงุฑูููยุงฺููุฏ ุฏ ุชุฎูฺฉู ููุฑุฑุงุชู ูพู ุฌูฺููู ฺฉ ุฏ ุงุฏุงุฑ ุณุฑู ููฺฉุงุฑู ฺฉูู.\nุฏ ุณูผูุงูผู ุดุจฺฉู ุฏ ููุบฺ (Satellite Networks Coordination)ุ ุฏ ูุฑฺฉููุณู ุฏ ุชูุฒุน( Frequency Assignment) ุงู ุฏ ุฌูุงุฒูฺฉููู ุฏ ุชูุฒุน ููพุงุฑู ุฏ ููู ุทุฑุฒุงูุนูู ุฌูฺูู.\nุฏ (Satellite Orbit - Frequency Coordination) ูพู ุจุฑุฎู ฺฉ ุฏ ูุฎุงุจุฑุงุชู ูฺูุงู ุงุชุญุงุฏู ุฏ ููุงู ูุดููู ุงู ููผู ูุฑุงุนุชูู.\nุฏ ITU-R ูุทุงูุนูู ฺูู(Study Groups)ุ ูฺูุงูู ุฑุงฺูู ฺฉููุฑุงูุณููู (WRCs) ุงู ุณูู ุฒู ุบููฺู ฺฉ ุฏ ููุงุฏ ุงุณุชุงุฒููู ฺฉูู.\nูพู ูฺูุงูู ุจุญุซููู ฺฉ ุฏ ููุงุฏ ุฏ ุชุฎูฺฉู ุฏุฑฺ ุฏ ููุงุชฺยูพู ููุฎู ุฏ ุชุฎูฺฉู (Input) ฺูุชู ฺฉูู.\nุฏ ุณูพูฺูฺฉ ุฌูุงุฒ ุบูฺุชููฺฉููู ุชุฎูฺฉู ุงู ูุงูููู ุงุฑุฒููู.\nุฏ ฺูฺฉูู ูุฑฺฉููุณู ฺุงูฺซู ุณุฑู ููุบฺู ฺฉูู ุชุฑฺู ุฏ ฺูฺฉูู ุงู ูุถุงู ุฎุฏูุงุชู ุชุฑููฺ ุฏ ูุฏุงุฎู ูุฎู ูููู ุดู.\nุฏ ุงฺุชุงูพุฑ ููุงู ุฏ ูุฑฺฉููุณู ุฏ ุทู ุฏ ููุฌูููผ ุฑุณ ูุฎูุง ุฏ ูุฑุณูพุงุฑู ฺฉุฏููฺฉู ูุนุงูุชููู ุงุฌุฑุง ฺฉูู.\nุฏ ุณูผูุงูผ ุขูุฑุช ูผูู ุชู ุฏุฏ ุขูุฑุช ุฏ ุฏูุฏู ุฏ ูุงุญ ูุทุงุจู ุฏ ูฺุชุง ููฺูู ุฏ ูุงุฒูู ุฑูุฒูุฒู ูพุฑูฺซุฑุงูููู ุจุฑุงุจุฑูู.\nุฏ ฺฉุงุฑู ูุญุฏูุฏ ูุทุงุจู ุฏ ูุงููู ุขูุฑ ูุฎูุง ุฏ ุจู ูุฑ ุณูพุงุฑู ุดู ุฏูุฏ ุณุฑุชู ุฑุณูู.\nJob Requirements\nููุงุตูุงุช\nุชุญุตูุงุชุ ุชุฌุงุฑุจ ุงู ูุงุฒู ููุงุฑุชููู\n:\nุฏุฑุฌู ุชุญุตู\n:\nูพู ูุฎุงุจุฑุงุชูุ ุจุฑฺูุงู ุงูุฌูุฑ ุง ฺฉููพููผุฑ ุณุงูุณ ฺฉ ูฺ ุชุฑ ูฺู ุฏ ูุณุงูุณ ุณูุฏ ููุฑู.\nุชุฌุงุฑุจ ูุงุฒูู:\n๏ปฟ\nูพู (Satellite Orbit โ Frequency Coordination) ูพู ุจุฑุฎู ยุง ูุฑุชู ุณุงุญู ฺฉ ูฺ ุชุฑ ูฺู (ด) ยฺฉุงูู ฺฉุงุฑู ุชุฌุฑุจู ููุฑู.\nุฏ ุณูผูุงูผ ุฏ ูุฑฺฉููุณู ุงู ุณูผูุงูผ ูุฏุงุฑููู ุฏ ูพฺูู ููุถูุนุงุชู ุฏ ุชุญูู ูฺุชุง ููุฑู.\nุฏ (Satellite Orbit โ Frequency Coordination) ูพู ุจุฑุฎู ฺฉ ุฏ ููู ุงู ูฺูุงูู ููุฑุฑุงุชู ุงู ูุนุงุฑููู ฺูุฑู ูพููู ููุฑู.\nููู ุชุญููู ุงู ุฏุณุชููุฒ ุฏ ุญู ฺฉููู ูฺุชุงู ููุฑู.\nุบูุฑู ุงฺฺฉ ุงู ุฏ ุฎูฺฉู ุณุฑู ุฏ ฺู ยฺููุฏ ููุงุฑุชููู ููุฑู.\nุฏ (Satellite Orbit โ Frequency Coordination) ุงฺููุฏู ุณุงููผูุฑููู ฺุฎู ุฏ ฺซูผ ุงุฎุณุชู ููุงุฑุช ููุฑู.\nูพู ฺซุฑููพู ฺฉุงุฑ ฺฉ ฺฉุงูู ุชูุงูุงู ููุฑู .\nุฏ ุงฺููุฏู ฺฉููพููผุฑู ูพุฑูฺซุฑุงููููุ ูพู ฺุงูฺซฺ ุชูฺซู (MS Office) ุจุดูพฺ ูพููู ุงู ููุงุฑุช ููุฑู.\nุฏ ุงูุบุงูุณุชุงู ุชุงุจุนุช ููุฑู ุงู ูพู ููุงุฏ ฺฉ ูุดุช ูู.\nุฏ ุฌุฑู ุณุงุจูู ููู ูุฑู.\nูพู ูพฺุชู ุงู ุฏุฑู ฺุจู ฺู ุฎุจุฑ ูฺฉฺู ุงู ุฏ ุงูฺซูุณู ฺุจ ุณุฑู ฺฉุงููู ุจูุฏุชุง ููุฑู.\nุฏ ุจุณู ูุฎุงุจุฑุงุชู ุฏ ูุฑฺฉููุณู ุฏ ูพฺูุฏู ููุงุฑุช ููุฑูุ ุงู ููุฏุงุฑูฺซู ุฏ ูุฌุงุฒ ุงู ุบุฑ ูุฌุงุฒ ูุฑฺฉููุณู ุชุฑ ููฺ ุชููพุฑ ูฺฉูู ุดู.\nูพู ูุฏุฑุช ุงู ุฑูุจุฑ ยุจุฑุฎู ฺฉ ฺฉุงูู ูฺุชุง ููุฑู.\nุฏ ูุงูู ุงู ุงุฏุงุฑู ุฏุณูพูู ูุฑุงุนุชูู.\nุฏ ูุฑุงุชุจู ุฏ ุณูุณู ูุฑุงุนุชููู ุชู ฺูู ูู.\nSubmission Guideline\nุฏ ูุญุชุฑูู ฺฉุงูุฏุฏุงูู ฺุฎู ููู ฺฉฺู ฺ ุชุฑ ฺู ุฏ ุงฺููุฏู ุจุณุช ููพุงุฑู ฺุงูฺซฺ ููุฑูู ฺฺฉู ุงู ูุงูุฏ ุจุฑูฺูุงูฺฉ ุชู ู ุฑุงูุงุณุชูู ุงู ููุฏุงุฑฺซู ฺฉููุง ุดู ฺ ุงุฏู ููุฑูู ุฏ ฺฉุงุฑฺฉูููฺฉู ุฏ ฺุงุฑู ยุฏ ุงุณุชุฎุฏุงู ุฏ ุขูุฑุช ฺุฎู ุชุฑูุงุณู ฺฉฺู .\nูพุชู : ุฏ ูุฎุงุจุฑุงุชู ุงู ูุนูููุงุชู ูผฺฉูุงููุฌ ูุฒุงุฑุช ฑธ ูพูฺุฒู ูุฏุงู ุฏุงุฑูุณู ููุฒู ุฏ ุงุณุชุฎุฏุงู ุขูุฑุช\nุจุฑฺูุงูฺฉ\njobs@atra.gov.af\nุฏ ุงฺฺฉู ุดูุฑู : 0202100763\nูููผ : ุฏ ูผููู ูุญุชุฑูู ฺฉุงูุฏุฏุงูู ฺุฎู ููู ฺฉฺู ฺ ฺฉู ฺุฑ ุณุชุงุณู ุชุญุตูุงุช ุงู ุง ูู ฺฉุงุฑู ุชุฌุฑุจู ุฏ ูพูุฑุชู ุจุณุช ุณุฑู ุณููู ูู ุฎูุฑู ูุทูุง ุฎูพู ุบูฺุชููฺฉ ูู ุฑุง ุงุณุชูุฆ .\nูพู ุฏุฑูฺุช\nSubmission Guidelines:\nAll applications ยForms ( CV & Cover Letters are notยconsidered )should be submitted via email to:\njobs@atra.gov.af\nPlease, clearly indicate on the subject line the title of the position. Applications received after the\nClosing date will not be considered.\nFunctional Area\nComputer Science\nCountries\nAfghanistan\nProvinces\nKabul\nSubmission Email\njobs@atra.gov.af\nAttachments\nApplication_Form ATRA.doc\nApply Now\nPost Date\nJan 14, 2026\nClosing Date\nJan 29, 2026\nReference\n005\nNumber of Vacancies\n1\nSalary Range\nAs per company salary scale\nYears of Experience\n4 years\nProbation Period\n3 month\nContract Type\nPermanent\nContract Duration\n1 year\nContract Extensible\nYes\nMinimum Education\nBachelor's Degree\nGender\nMale\nRelated Jobs\nNETLINKS Plaza | Shahr-e-Naw,\nLane 3, Kabul, Afghanistan\nQuick Links\nAbout Us\nAdvertise with Us\nPrivacy Policy\nFor Companies\nPost a Job\nPost a Job\nPost a Job\nPost a Job\nPost RFP\nPost RFP\nPost RFP\nPost RFP\nPost Training\nPost Training\nPost Training\nPost Training\nFor Jobseekers\nBrowse Jobs\nBrowse Companies\nBuild Resume\nContact\ninfo@jobs.af\nContact Us\nยฉ 2012 - 2026 Jobs.af | All Rights Reserved\nPowered by:\nNETLINKS Ltd",
    "details": {
      "Post Date": "Jan 14, 2026",
      "Closing Date": "Jan 29, 2026",
      "Reference": "005",
      "Number Of Vacancies": "1",
      "Salary Range": "As per company salary scale",
      "Years Of Experience": "4 years",
      "Probation Period": "3 month",
      "Contract Type": "Permanent",
      "Contract Duration": "1 year",
      "Contract Extensible": "Yes",
      "Minimum Education": "Bachelor's Degree",
      "ูพุชู": "ุฏ ูุฎุงุจุฑุงุชู ุงู ูุนูููุงุชู ูผฺฉูุงููุฌ ูุฒุงุฑุช ฑธ ูพูฺุฒู ูุฏุงู ุฏุงุฑูุณู ููุฒู ุฏ ุงุณุชุฎุฏุงู ุขูุฑุช",
      "ุฏ ุงฺฺฉู ุดูุฑู": "0202100763",
      "ูููผ": "ุฏ ูผููู ูุญุชุฑูู ฺฉุงูุฏุฏุงูู ฺุฎู ููู ฺฉฺู ฺ ฺฉู ฺุฑ ุณุชุงุณู ุชุญุตูุงุช ุงู ุง ูู ฺฉุงุฑู ุชุฌุฑุจู ุฏ ูพูุฑุชู ุจุณุช ุณุฑู ุณููู ูู ุฎูุฑู ูุทูุง ุฎูพู ุบูฺุชููฺฉ ูู ุฑุง ุงุณุชูุฆ .",
      "Functional Area": "Computer Science",
      "Countries": "Afghanistan",
      "Provinces": "Kabul"
    },
    "scraped_at": "2026-01-21T05:00:22Z",
    "apply_emails": [
      "jobs@atra.gov.af"
    ],
    "apply_method": "email"
  },
  {
    "url": "https://jobs.af/jobs/d-systm-arshd-a-myn",
    "title": "ุฏ ุณุณุชู ุงุฑุดุฏ ุงฺูู",
    "company": null,
    "location": "Kabul",
    "closing_date": "2026-01-29",
    "closing_date_raw": "Jan 29, 2026",
    "apply_url": null,
    "description": "๐\nComing Soon The Jobs.af Freelancer Portal\nConnect with top clients and freelancers across Afghanistan all in one place!\nStay Tuned\nJobs\nProcurement Opportunities\nCompanies\nFreelancers\nServices\nProcurement Opportunities\nTrainings\nScholarships\nLogin\nRegister\nุฏ ุณุณุชู ุงุฑุดุฏ ุงฺูู\nATRA\nApply Now\nSee all jobs\nุฏ ุณุณุชู ุงุฑุดุฏ ุงฺูู\nATRA,\n                                        Kabul, Afghanistan\nApply Now\nBachelor's Degree\nKabul, Afghanistan\n(Kabul)\nFull Time\n1291\nAbout\n                                            ATRA\nุฏ ุงูุบุงูุณุชุงู ุฏ ูุฎุงุจุฑุงุชู ุฎุฏูุชููู ุฏ ุชูุธู ุงุฏุงุฑู (ุงูผุฑุง) ูพู ฒฐฐถ ููุงุฏู ฺฉุงู ูพู ููุงุฏ ฺฉ ุฏ ูุฎุงุจุฑุงุชู ุณฺฉุชูุฑ ุฏ ุชูุธู ุงู ูพุฑูุฎุชุง ููพุงุฑู ุฑุงููฺ ุชู ุดูู. ุฏุง ุงุฏุงุฑู ูฺู ฺฉูู ฺ ุฏ ูุฎุงุจุฑุงุชู ุงู ุงููผุฑููผู ุฎุฏูุชููู ุฒุฑุจูุงูู ุฏ ูุฏ ุงู ูพุฑูุฎุชุง ูพู ุจุฑุฎู ฺฉ ุฏ ุฎุตูุตู ุณฺฉุชูุฑ ููพุงุฑู ุฏ ูพุงูฺซูู ูพุงูฺ ุงู ููุงุณุจ ฺุงูพุฑุงู ุฑุงููฺุชู ฺฉฺู. ูพู ููุงุฏ ฺฉ ุฏ ฺู ููุฑุฑุงุชู ุงู ุชูุธูุงุชู ฺุงูพุฑุงู ุฑุงููฺุชู ฺฉููู ุงู ุชููุฐ ูู ูุงุฑ ูู ุชุจุนุถ ูพุฑุชู ูพู ุดูุงู ฺูู ุฏ ฺูุงฺฉูู ุฎุตูุตู ุณฺฉุชูุฑ ูุฎูุง ุญูุงู ุดูู ูุฎุงุจุฑุงุชู ุณฺฉุชูุฑ ุงู ุงฺููุฏู ุฎุฏูุชููู ุฑุงููฺุชู ฺฉููุ ุฏ ููุฑุฑุงุชู ูพูู ฺฉููุ ุฎุฏูุชููู ุชู ุณุฑุงุณุฑ ูุงุณุฑุณุ ุฏ ูุงุฑฺฉูผ ุชูุธูููุ ูพู ูุฎุงุจุฑุงุชู ูุงุฑฺฉููผ ฺฉ ุฏ ุณุงู ฺูผฺฉูุงู ุงู ูุธุงุฑุช ุฏ ุงูผุฑุง ุงุฏุงุฑ ููุฎ ุฏู. ุงูผุฑุง ุงุฏุงุฑู ูู ุงฺููุฏู ุงฺุฎููู ุฎุตูุตู ุณฺฉุชูุฑุ ุฏููุชู ุงุฏุงุฑู ุงู ุฏ ูุฎุงุจุฑุงุชู ุฎุฏูุชููู ูุดุชุฑฺฉูู ุณุฑู ู ฺุง ฺฉุงุฑ ฺฉููุ ฺู ุฏ ููุงุฏ ูพู ูุฎุงุจุฑุงุชู ุงู ุงููผุฑููผู ูุงุฑฺฉูผ ฺฉ ุณุงููู ุณุงูู ูพุฑูุฎุชฺซ ูฺฉฺู.\nุฏ ูุฎุงุจุฑุงุชู ุณฺฉุชูุฑ ุงู ุตูุนุช ูู 2002 ููุงุฏู ฺฉุงู ุฑุง ูพุฏุฎูุง ุฏ ููุงุฏ 34 ููุงุชููู ุงู ู ุดูุฑ ุฒุงุชู ููุณูุงูู ุชู ุฏ ุงููผุฑููผู ูพูฺฺ ูพู ูพุฑุงุฎุชุง ุณุฑู ฺซฺูุฏ ูุฏู ฺฉฺุฏู . ุงูผุฑุง ุงุฏุงุฑ ุฏ ููุงุฏ ูุฎุงุจุฑุงุชู ุจุงุฒุงุฑ ุฏ ฺู ูพุฑูุฎุชฺซ ุงู ุชูุธู ููพุงุฑู ุชู ูฺู ฺฉฺุ ฺ ุฏ ูฺูุงูู ฺฉูุฏู ูุฎุงุจุฑุงุชู ุดุฑฺฉุงูู ุณุฑู ููฺซุฑุชุง ุงู ุงฺฺฉ ูุง ูพุงูฺ ฺฉฺู ุชุฑฺู ูู ูฺูุงูู ุชุฌุฑุจู ฺุฎู ูพู ุงุณุชูุงุฏ ฺซูผูุฑ ูุงุฑ ฺุงุฑ ูพู ฺซูุชู ุงู ุฏ ููุงุฏ ูุงุฑฺฉูผ ุชู ูุฏู ูุฑฺฉฺู. ุธุฑูุช ุฌูฺููู ุฏ ูุฎุงุจุฑุงุชู ุตูุนุช ููพุงุฑู ู ุจู ููู ูผฺฉ ุฏ. ุฏ ุชู ูพู ฺฉุชู ุงูผุฑุง ุงุฏุงุฑ ุฏ ุงฺููุฏู ุณฺฉุชูุฑ ุงู ูุฎุงุจุฑุงุชู ุงู ุงููผุฑููผู ุดุฑฺฉุชููู ูพู ฺซฺูู ุฏ ุธุฑูุช ููฺููู ุชู ุจูุฏุฌู ฺุงูฺซฺ ุงู ุฏ ฺฉุงุฑ ุงฺฉูุณุณุชู ุฑุงููฺุชู ฺฉฺ ุฏุ ฺ ุฏุง ุจู ูพู ูุฎุงุจุฑุงุชู ุณฺฉุชูุฑ ฺฉ ุฏ ูพุงูฺซูู ุฌูุจ ุงู ูพุฑุฏููฺฉู ุชู ุฏ ูพุฑูุฎุชููู ูุฎุงุจุฑุงุชู ุฎุฏูุชููู ูฺุงูุฏ ฺฉููู ูุงูู ุดู. ููุฏุงุฑูฺซูุ ุงูผุฑุง ุงุฏุงุฑู ูู ููุฑู ุงฺููุฏู ุฎูุงู ูพู ฺุงูฺซฺ ุชูฺซู ฺฺูุฒู ุงู ุงฺฉุงฺูฺฉู ูุฑฺฉุฒููู ุณุฑู ูพู ฺซฺู ฺฉุงุฑ ฺฉููุ ุชุฑฺู ูพู ููุงุฏ ฺฉ ุฏ ูุฎุงุจุฑุงุชู ฺฉุงุฑู ฺูุงฺฉ ุชู ูพุงูฺุชุง ุงู ูุฏู ูุฑฺฉฺู ุงู ูพู ูุงุฑฺฉูผ ฺฉ ุฏ ุธุฑูุช ุฌูฺูู ุจุฑูุงูู ุชู ุฏ (ุชุฑููฺซ) ุงู ููุฑู ุฎุฏูุชููู ููพุงุฑู ูุงุฑู ุจุฑุงุจุฑู ฺฉฺู.\nJob Summary\nุฏ ุณุณุชู ุงฺููุณูผุฑูผุฑ (System Administrator) ุฏ ATRA ุฏ RTDMS ูผู ู ููู ุบฺ ุฏ ฺ ุฏ ุณุณูผูููู ุฏ ูพุฑุงุฎุชุง (Development) ุงู ุณุงุชู (Maintenance) ููุงุชฺ ุจู ฺฉูู.\nุฏ ุณุณุชู ุงฺููุณูผุฑูผุฑ ูพู ุชูฺซูุ ูููุงูุฏ ุจู ุฏ ุณุณูผูููู ุงู ูุนูููุงุชู ูผฺฉูุงููุฌ ุฑุงุณุช ุฏ ุฑู ูผุงู ุฏ ุจุฑุฎ ูู ููุฑู ุบฺู ุณุฑู ูู ูฺุฏ ฺฉุงุฑ ฺฉููุ ุชุฑ ฺู ุฏ ุงฺููุฏู ุณุณูผูููู ุงุนุธูู ุงู ุบูุฑู ูุนุงูุช (Optimum Performance) ููู ุดู.\nDuties & Responsibilities\nูุงุญู ูุธุงู\nุฏูุฏ ุงู ูุณุคูุชููู:\nุฏ ุจูุงุจูู ูพุฑูฺู ุงู ุนููู ุงฺุชุงูู ููพุงุฑู ุฏ ุณุณุชู ุงฺููุณูผุฑุดู (Systems Administration)\nุงฺููุฏ ุญูโูุงุฑ ุทุฑุญู ุงู ุงูุฌูุฑู ฺฉูู\n.\nโข\nุฏ ูุนุงุฑููู ุงู ุฏ ูพุฑูฺ/ุนููู ุงฺุชุงูู ุณุฑู ุณู ุฏ ููู ุณุฑูุฑููู\n(Servers)\nูุตุจ ฺฉููุ ุฏ ููุฌูุฏู ุณุฑูุฑููู ุจุง ุฌูฺููุ ุงู ุฏ ูุงุฑฺูุฑุ\n(Peripherals)\nุ ุฎุฏูุงุชู\nุ ุชูุธูุงุชู\nุ\n(Directories)\nุงู\n(Storage)\nฺฉุงููฺซูุฑ ฺฉูู\n.\nโข\nุฏ ูุตุจ ุงู ฺฉุงููฺซูุฑุดู ฺฉฺููุงุฑ\n(Installation and Configuration Procedures)\nุฌูฺูู ุงู ุณุงุชู\n.\nโข\nูพู ุนููุงุชู ุงู ูพุฑุงุฎุชุงูู ุณุณูผูููู ฺฉ ุฏ ุงููุชู ูพฺููู\n(Security Patches)\nูุตุจ ุงู ุณุงุชููุ ฺ ูพฺฉ\nRed Hat Linux\nุ\nWindows 2012/2019\nุงู\nVMWare\nุดุงูู ุฏู ุฎู ูุญุฏูุฏ ูู ุฏู\n.\nโข\nุฏ ุณุณูผู ูุฑฺู ฺุงุฑ\n(Daily System Monitoring)\nุชุฑุณุฑู ฺฉููุ ุฏ ูผููู ูุงุฑฺูุฑุ\n(Server Resources)\nุ ุณุณูผูููู ุงู ูููู ุจูุฑููู\n(Integrity & Availability)\nุชุตุฏูููุ ุฏ ุณุณูผู ุงู ุงูพูฺฉุดู ูุงฺซููู\n(Logs)\nฺฉุชูุ ุงู ุฏ ููุงูโูุด ุดูู ฺฉุงุฑููู ูฺฉู\n(Backups)\nุฏ ุจุดูพฺุฏู ุชุงุฏ ฺฉูู\n.\nโข\nุฏ ุงููุช ููุธู ฺุงุฑ ุชุฑุณุฑู ฺฉูู ุชุฑ ฺู ูุฑ ฺูู ุงุญุชูุงูู ูููุฐ\n(Intrusions)\nุชุดุฎุต ุดู\n.\nโข\nุฏ ูุฑฺูู ุจฺฉโุงูพ ุนููุงุชู ุชุฑุณุฑู ฺฉููุ ุฏุง ฺุงฺ ุชุฑูุงุณู ฺฉูู ฺ ูผูู ุงฺู ูุงู ุณุณูผูููู ุงู ุฏ ุณุณูผู ฺุงูผุง ูพู ุจุฑุงูุชูุจ ุณุฑู ููุงุณุจ ูฺุง ุชู ุจฺฉโุงูพ ุดููุ ุฏ ุจุง ุฑุบูู ูผูพููู ุง ฺุณฺฉููู\n(Recovery Tapes/Disks)\nุฌูฺ ุดููุ ุงู ูฺุง ุฏ ุงฺุชุง ูพู ุตูุฑุช ฺฉ ุฑุณุงฺฉู ุงู ูู ุณุงูผ ฺุฎู ุจูุฑ\n(Off-site)\nูฺู ุดู ูู\n.\nโข\nุฏ ุงฺุชุง ุงู ุบูฺุชู ูู ูุฎ ุฏ ฺฉุงุฑูููฺฉู ุญุณุงุจููู\n(User Accounts)\nุฌูฺููุ ุจุฏููู ุงู ุญุฐู ฺฉูู\n.\nโข\nุฏ ูุงุฑฺูุฑ ุง ุณุงููผูุฑ ุฏ ุฎุฑุงุจู ุชุฑูู ุงู ุจุง ุฑุบููู\n(Repair & Recovery)\nุชุฑุณุฑู ฺฉููุ ุงู ูู ุงุบุฒููู ุงฺุฎููู ุณุฑู ููุบฺู ุงู ุงฺฺฉู ููู\n.\nโข\nูพู ููุธู ฺูู ุฏ ุนุงูู ุณุณูผู\n(OS)\nูพฺููู ุงู ุงูพฺซุฑฺููู ุชุทุจู ฺฉููุ ุงู ุงุฏุงุฑู ูุณุงู ุงู ููผููผูโฺซุงู\n(Administrative Tools & Utilities)\nุงูพฺซุฑฺ ฺฉููุ ุฏ ุงฺุชุง ูพู ุตูุฑุช ฺฉ ููู ุฎุฏูุงุช\n(Services)\nฺฉุงููฺซูุฑ ุงู ุฒุงุชูู\n.\nโข\nุฏ ูพุฑูฺ ุง ุนููู ุงฺุชุงูู ูู ูุฎ ุฏ ุฒุฑุจูุงู ุงูพูฺฉุดูููู ุง ุฏ ุดุชููู ุฏ ูุฏุฑุช\n(Asset Management)\nุงูพูฺฉุดูููู ููุงุชฺ ฺฉูููฺฉ ุณุณูผู ุณุงููผูุฑ ุงูพฺซุฑฺ ุงู ฺฉุงููฺซูุฑ ฺฉูู\n.\nโข\nุฏ ุงฺุชุง ูพุฑ ููุงู ุฏ ูุนุงูุช ุฏูุงูุฏุงุฑู ฺูโูุงู\n(Performance Tuning)\nุ ุฏ ูุงุฑฺูุฑ ุงูพฺซุฑฺููู ุงู ุฏ ุณุฑฺูู ุงุตูุงุญ\n(Resource Optimization)\nุชุฑุณุฑู ฺฉููุ ุฏ\nCPU\nุ ุญุงูุธ\n(Memory)\nุงู ฺุณฺฉ ุจุฑุฎ\n(Disk Partitions)\nฺฉุงููฺซูุฑ ฺฉูู\n.\nโข\nุฏ ฺูผุงุจุณ ุฏ ูุฏุฑุช ุณุณูผู\n(DBMS)\nูู ูุณุฎ ูุตุจ ุงู ูผุณูผ ฺฉูู\n.\nโข\nุฏ\nLinux\nูู ูุงุฑ ุฏ ูุงุดุชูู ููุงูโูุด ูู ูุฎ ุฏ ูพฺ ูุฏุฑุช\n(Patch Management)\nุชุฑุณุฑู ฺฉูู\n.\nโข\nูุฑู ุจูู ุฏูุฏู ฺ ุฏ\n(Line Manager)\nููโุฎูุง ูุฑุณูพุงุฑู ฺฉฺู\n.\nJob Requirements\nููุงุตูุงุช\nุชุญุตูุงุชุ ุชุฌุงุฑุจ ู ููุงุฑุช ูุง ูุงุฒู\n:\nุฏุฑุฌู ุชุญุตู\n:\nุญุฏุงูู ูุณุงูุณ ุฏ ยฺฉููพููผุฑ ุณุงูุณ ูพู ุจุฑุฎู ฺฉ ุฏ ุณุงููผูุฑ ุงูุฌูุฑู ฺุฎู ูุงุฑุบ ูู .\nุชุฌุงุฑุจ ูุงุฒูู:\n๏ปฟ\nด ฺฉูููยุฏ ุฏูุฏ ุณุฑู ูุฑุชุจุทู ยุซุงุจุชู ุงู ุนููู ฺฉุงุฑู ุชุฌุฑุจู ููุฑู .\nุฏ\nRed Hat\nุชุตุฏู ุดู ุณุณูผู ุงฺููุณูผุฑูผุฑ\n(Red Hat Certified System Administrator โ RHCSA)\nูุฑู ุบูุฑู ฺซฺผู ฺฉฺู\n.\nููุงุฑุชูููุ ูฺุชุงู ุงู ฺุงูฺซฺุชุงู (Skills, Qualifications, and Characteristics):\nูู\nVMware vCenter 7\nุง ุฏ ูุบ ูู ูุฑูุณุช ูุณุฎ ุงู/ุง\nOperations Manager\nุณุฑู ฺฉุงุฑู ุชุฌุฑุจู\n.\nโข\nุฏ\nRed Hat Enterprise Linux (RHEL) 7\nุ\nKerberos\nุ\nDELL EMC Unity\nุ\nSolarWinds\nุงู ุฏ ุณฺฉุฑูพูผูฺซ ฺุจู\n(Scripting Languages)\nูพู ุจุฑุฎู ฺฉ ูพุงูฺ ฺฉุงุฑู ูพููู\n.\nโข\nุฏ\nLinux\nุณุฑูุฑ ุฏ ุณุชููุฒู ุฏ ุชุดุฎุต ุงู ุญู ููู ููุงุฑุชููู\n(Linux Server Troubleshooting).\nโข\nูู\nJavaScript\nุงู\nPowerShell\nุณฺฉุฑูพูผูฺซ ฺุจู ุณุฑู ุนููู ุชุฌุฑุจู\n(Hands-on Experience).\nโข\nุฏ ฺูฺ\n(Latency)\nุงู ุฏ ูุนุงูุช\n(Performance)\nุฏ ุณุชููุฒู ุฏ ฺูโูุงูู ููพุงุฑู ุฏ ุญูโูุงุฑู ุฏ ฺุฒุงู ุชุฌุฑุจู\n.\nโข\nุฏ\nMultiprocessing\nุ\nThreading\nุ\nConcurrency\nุ\nDistributed Systems\nุ\nLoad Balancing\nุงู\nHigh Availability\nูพู ุจุฑุฎู ฺฉ ฺฉุงุฑู ูพููู\n.\nโข\nุฏ ุฎูพูููฺู ุงฺฺฉู\n(Interpersonal)\nููู ููุงุฑุชูููุ ฺ ูพฺฉ ุงุบุฒููู ููฺฉุงุฑูุ ฺุงูโูพููุงู\n(Self-awareness)\nุงู ุบูุฑู ูฺฉูู ุงู ุดูุงูู ุงฺฺฉ ุดุงูู ุฏู\n.\nโข\nุฏ ุชุญููู ุงู ููุธู ุทุฑู ูู ูุงุฑ ุฏ ูผููู ูพฺู\n(Incidents)\nุฏ ุงุบุฒูู ุญู ูฺุชุง\n.\nโข\nุฏ ููู ูุญุตููุงุชู ุงู ูผฺฉูุงููฺู ุฏ ุฒุฏู ฺฉฺ ูฺุชุง\n.\nโข\nุฏ ูุนุงุฑู ฺฉุงุฑู ฺฉฺููุงุฑู\n(Standard Operating Procedures โ SOPs)\nุงู ุฏ ูพุฑูฺ ุฏ ุงุณูุงุฏู\n(Project Documentation)\nุฏ ุฌูฺููู ูฺุชุง\n.\nโข\nุฏ ุจูุงุจูู ุณูุฏุงฺซุฑุฒู ุงฺุชุงูู ุงู ุชุฎูฺฉู ุณุชููุฒู ููพุงุฑู ุฏ ุญูโูุงุฑู ุฏ ฺฺู ูฺุชุงุ ฺ ูพฺฉ ุฏ ุจุฏูู ูุงุฑู ุงุฑุฒููู ุงู ุฏ ุณูพุงุฑฺุชูู ูฺุงูุฏ ฺฉูู ุดุงูู ุฏู\n.\nโข\nุนุงูู ูฺฉูู ุงู ุดูุงูู ุฏ ุงฺฺฉู ููุงุฑุชููู ููุฑู.\nุฏ ฺฉุงูุฏุฏ ุณู ุจุงุฏ ุฏ ฑธ ฺฉุงูู ฺุฎู ููฺ ูู\nุฏ ููุช ุชุฐฺฉุฑู ููุฑู ุงู ูพู ููุงุฏ ฺฉ ูุดุช ูู\nุฏ ููฺฉุงุฑุงูู ุณุฑู ุฏูุณุชุงูู ุงฺฺฉู ููุฑู\nูพู ุชุฎูฺฉู ุจุฑุฎู ฺฉ ูพูุฑุชู ูุนูููุงุช ููุฑู .\nุฌุฑูู ุณุงุจูู ูููุฑู\nูพู ูพฺุชู ุ ุฏุฑู ุงู ุงูฺซูุณู ฺุจู ูพูุฑู ุชุณูุท ููุฑู\nSubmission Guideline\nุฏ ูุญุชุฑูู ฺฉุงูุฏุฏุงูู ฺุฎู ููู ฺฉฺู ฺ ุชุฑ ฺู ุฏ ุงฺููุฏู ุจุณุช ููพุงุฑู ฺุงูฺซฺ ููุฑูู ฺฺฉู ุงู ูุงูุฏ ุจุฑูฺูุงูฺฉ ุชู ู ุฑุงูุงุณุชูู ุงู ููุฏุงุฑฺซู ฺฉููุง ุดู ฺ ุงุฏู ููุฑูู ุฏ ฺฉุงุฑฺฉูููฺฉู ุฏ ฺุงุฑู ยุฏ ุงุณุชุฎุฏุงู ุฏ ุขูุฑุช ฺุฎู ุชุฑูุงุณู ฺฉฺู .\nูพุชู : ุฏ ูุฎุงุจุฑุงุชู ุงู ูุนูููุงุชู ูผฺฉูุงููุฌ ูุฒุงุฑุช ฑธ ูพูฺุฒู ูุฏุงู ุฏุงุฑูุณู ููุฒู ุฏ ุงุณุชุฎุฏุงู ุขูุฑุช\nุจุฑฺูุงูฺฉ\njobs@atra.gov.af\nุฏ ุงฺฺฉู ุดูุฑู : 0202100763\nูููผ : ุฏ ูผููู ูุญุชุฑูู ฺฉุงูุฏุฏุงูู ฺุฎู ููู ฺฉฺู ฺ ฺฉู ฺุฑ ุณุชุงุณู ุชุญุตูุงุช ุงู ุง ูู ฺฉุงุฑู ุชุฌุฑุจู ุฏ ูพูุฑุชู ุจุณุช ุณุฑู ุณููู ูู ุฎูุฑู ูุทูุง ุฎูพู ุบูฺุชููฺฉ ูู ุฑุง ุงุณุชูุฆ .\nูพู ุฏุฑูฺุช\nSubmission Guidelines:\nAll applications ยForms ( CV & Cover Letters are notยconsidered )should be submitted via email to:\njobs@atra.gov.af\nPlease, clearly indicate on the subject line the title of the position. Applications received after the\nClosing date will not be considered.\nFunctional Area\nComputer Science\nCountries\nAfghanistan\nProvinces\nKabul\nSubmission Email\njobs@atra.gov.af\nAttachments\nApplication_Form ATRA.doc\nApply Now\nPost Date\nJan 14, 2026\nClosing Date\nJan 29, 2026\nReference\n008\nNumber of Vacancies\n1\nSalary Range\nAs per company salary scale\nYears of Experience\n4 years\nProbation Period\n3 month\nContract Type\nPermanent\nContract Duration\n1 year\nContract Extensible\nYes\nMinimum Education\nBachelor's Degree\nGender\nMale\nRelated Jobs\nNETLINKS Plaza | Shahr-e-Naw,\nLane 3, Kabul, Afghanistan\nQuick Links\nAbout Us\nAdvertise with Us\nPrivacy Policy\nFor Companies\nPost a Job\nPost a Job\nPost a Job\nPost a Job\nPost RFP\nPost RFP\nPost RFP\nPost RFP\nPost Training\nPost Training\nPost Training\nPost Training\nFor Jobseekers\nBrowse Jobs\nBrowse Companies\nBuild Resume\nContact\ninfo@jobs.af\nContact Us\nยฉ 2012 - 2026 Jobs.af | All Rights Reserved\nPowered by:\nNETLINKS Ltd",
    "details": {
      "Post Date": "Jan 14, 2026",
      "Closing Date": "Jan 29, 2026",
      "Reference": "008",
      "Number Of Vacancies": "1",
      "Salary Range": "As per company salary scale",
      "Years Of Experience": "4 years",
      "Probation Period": "3 month",
      "Contract Type": "Permanent",
      "Contract Duration": "1 year",
      "Contract Extensible": "Yes",
      "Minimum Education": "Bachelor's Degree",
      "ูพุชู": "ุฏ ูุฎุงุจุฑุงุชู ุงู ูุนูููุงุชู ูผฺฉูุงููุฌ ูุฒุงุฑุช ฑธ ูพูฺุฒู ูุฏุงู ุฏุงุฑูุณู ููุฒู ุฏ ุงุณุชุฎุฏุงู ุขูุฑุช",
      "ุฏ ุงฺฺฉู ุดูุฑู": "0202100763",
      "ูููผ": "ุฏ ูผููู ูุญุชุฑูู ฺฉุงูุฏุฏุงูู ฺุฎู ููู ฺฉฺู ฺ ฺฉู ฺุฑ ุณุชุงุณู ุชุญุตูุงุช ุงู ุง ูู ฺฉุงุฑู ุชุฌุฑุจู ุฏ ูพูุฑุชู ุจุณุช ุณุฑู ุณููู ูู ุฎูุฑู ูุทูุง ุฎูพู ุบูฺุชููฺฉ ูู ุฑุง ุงุณุชูุฆ .",
      "Functional Area": "Computer Science",
      "Countries": "Afghanistan",
      "Provinces": "Kabul"
    },
    "scraped_at": "2026-01-21T05:00:22Z",
    "apply_emails": [
      "jobs@atra.gov.af"
    ],
    "apply_method": "email"
  },
  {
    "url": "https://jobs.af/jobs/karshnas-thbt-w-mdyryt-amlak-dr-wb-sayt-aaryazmyn",
    "title": "ฺฉุงุฑุดูุงุณ ุซุจุช ู ูุฏุฑุช ุงููุงฺฉ ุฏุฑ ูุจโุณุงุช ุขุฑุงุฒูู",
    "company": null,
    "location": "Kabul",
    "closing_date": "2026-01-31",
    "closing_date_raw": "Jan 31, 2026",
    "apply_url": null,
    "description": "๐\nComing Soon The Jobs.af Freelancer Portal\nConnect with top clients and freelancers across Afghanistan all in one place!\nStay Tuned\nJobs\nProcurement Opportunities\nCompanies\nFreelancers\nServices\nProcurement Opportunities\nTrainings\nScholarships\nLogin\nRegister\nฺฉุงุฑุดูุงุณ ุซุจุช ู ูุฏุฑุช ุงููุงฺฉ ุฏุฑ ูุจโุณุงุช ุขุฑุงุฒูู\nMarketplace\nApply Now\nSee all jobs\nฺฉุงุฑุดูุงุณ ุซุจุช ู ูุฏุฑุช ุงููุงฺฉ ุฏุฑ ูุจโุณุงุช ุขุฑุงุฒูู\nMarketplace,\n                                        Multi Location\nApply Now\nSecondary School\nMulti Location\n(Kabul, Nangarhar, Balkh, Herat)\nFull Time\n5018\n163\nAbout\n                                            Marketplace\nุฏุฑุจุงุฑู ุขุฑุงุฒูู (Aryazamin) www. AryaZamin.com\nุขุฑุงุฒููุ ูพู ูุงู ูุดุชุฑ ู ุฑูููุง ูุนุงููุงุช ุงููุงฺฉ ุฏุฑ ุฏุงุฎู ุงูุบุงูุณุชุงู ู ุงูุบุงูโูุง ุชูุงู ุฌูุงู ุงุณุช.\nุขุฑุงุฒูู ฺฉ ูพูุชูุฑู ูุฏุฑู ู ุขููุงู ุฏุฑ ุงูุบุงูุณุชุงู ุงุณุช ฺฉู ุจุง ูุฏู\nุณุงุฏูโุณุงุฒ ุฌุณุชุฌูุ ุฎุฑุฏุ ูุฑูุด ู ฺฉุฑุงูู ุงููุงฺฉ\nุฑุงูโุงูุฏุงุฒ ุดุฏู ุงุณุช. ุงู ูุจโุณุงุช ุจู ฺฉุงุฑุจุฑุงู ุงูฺฉุงู ูโุฏูุฏ ุจุฏูู ูุงุฒ ุจู ุฌุณุชุฌู ุญุถูุฑ ุฏุฑ ุฏูุงุชุฑ ูุนุงููุงุช ุงููุงฺฉ ุง ุฑูุชู ุงุฒ ฺฉูฺู ุจู ฺฉูฺูุ ููฺฉ ููุฑุฏ ูุธุฑ ุฎูุฏ ุฑุง ุชููุง ุจุง ฺูุฏ ฺฉูฺฉ ุฌุณุชุฌู ู ุงูุชุฎุงุจ ฺฉููุฏ.\nูุฏู ุงุตู ุขุฑุงุฒูู ุงุฌุงุฏ ฺฉ ุชุญูู ูุซุจุช ุฏุฑ ุจุงุฒุงุฑ ุงููุงฺฉ ุงูุบุงูุณุชุงู ุงุณุช. ูุง ูโุฎูุงูู ุจุง ูุฑุงูู ฺฉุฑุฏู ุจุณุชุฑ ฺฉุงููุงู ุขููุงูุ ุฏุณุชุฑุณ ุณุฑุนุ ุขุณุงู ู ููุฑุงู ุจุง ูุนูููุงุช ุฏูู ููฺฉ ุฑุง ุจุฑุง ููู ูุฑุงูู ฺฉูู. ุขุฑุงุฒูู ููโุชููุง ุจุฑุง ุงูุฑุงุฏ ุณุงฺฉู ุงูุบุงูุณุชุงู ุทุฑุงุญ ุดุฏูุ ุจูฺฉู ุฎุฏูุงุช ุฎูุฏ ุฑุง ุจู ุงูุบุงูโูุง ููู ุฎุงุฑุฌ ูุฒ ุงุฑุงุฆู ูโุฏูุฏุ ฺฉุณุงู ฺฉู ูุตุฏ ุจุงุฒฺฏุดุช ุฏุงุฑูุฏ ู ูโุฎูุงููุฏ ูพุด ุงุฒ ุณูุฑุ ููฺฉ ุฏูุฎูุงู ุฎูุฏ ุฑุง ุงูุชุฎุงุจ ู ุจุฑูุงููโุฑุฒ ฺฉููุฏ. ููฺูู ุจุฑุง ุงูุบุงูโูุง ฺฉู ุจู ูุนุงููุงุช ุชุฌุงุฑ ุงููุงฺฉ ุนูุงููโููุฏูุฏุ ุฒูููู ุฏุณุชุฑุณ ุขุณุงู ุจู ูุนูููุงุช ูุงุฒู ุฑุง ูุฑุงูู ูโุณุงุฒุฏ.\nุงุฑุฒุดโูุง ูุชูุงุฒ ุขุฑุงุฒูู:\nุดูุงูุช:\nุชููุง ุฑูููุงูุง ุฏุงุฑุง ุฌูุงุฒ ุฑุณู ุงุฌุงุฒูู ูุณุช ฺฉุฑุฏู ุงููุงฺฉ ุฑุง ุฏุงุฑูุฏ. ูููู ูุณุชโูุง ูพุณ ุงุฒ ุจุฑุฑุณ ููุชุดุฑ ูโุดููุฏ ู ฺฉุงุฑุจุฑุงู ูโุชูุงููุฏ ุงุทูุงุนุงุช ูุงุฏุฑุณุช ุฑุง ฺฏุฒุงุฑุด ุฏููุฏ.\nุณูููุช:\nุชูุงู ูุฑุขูุฏูุง ุขููุงู ุงุณุช ุชุง ฺฉุงุฑุจุฑุงู ุจุชูุงููุฏ ุจู ุฑุงุญุช ููฺฉ ููุฑุฏ ูุธุฑุดุงู ุฑุง ูพุฏุง ุง ุซุจุช ฺฉููุฏ.\nูุดุชุฑโูุญูุฑ:\nุฑุถุงุช ฺฉุงุฑุจุฑุงู ุงูููุช ูุงุณุช. ูพุดุชุจุงู ุงุฒ ุทุฑู ูุงุชุณุงูพุ ุงูู ู ูพุงู ุฏุฑ ูุณโุจูฺฉ ููุดู ุฏุฑ ุฏุณุชุฑุณ ุงุณุช.\nููุขูุฑ:\nูุง ูููุงุฑู ููุงูุฑโูุง ุฌุฏุฏ ุฑุง ุจุฑุง ุจูุจูุฏ ุชุฌุฑุจู ฺฉุงุฑุจุฑุงู ุจู ูพูุชูุฑู ุงุถุงูู ูโฺฉูู.\nุจุฏูู ูพุฑุฏุงุฎุช ุขููุงู:\nุฎุฑุฏ ู ูุฑูุด ูุณุชููุงู ูุงู ูุดุชุฑ ู ุฑูููุง ูุนุงููุงุช ุงูุฌุงู ูโุดูุฏ. ุขุฑุงุฒูู ุตุฑูุงู ุฏุฑ ูุณูุช ุงุนูุงู ู ูุณุช ฺฉุฑุฏู ุงููุงฺฉ ุณูููุช ุงุฌุงุฏ ฺฉุฑุฏู ุชุง ูุดุชุฑุงู ุจุชูุงููุฏ ุงููุงฺฉ ููุฑุฏ ูุธุฑ ุฎูุฏ ุฑุง ุจูโุขุณุงู ุฌุณุชุฌู ฺฉููุฏ.\nJob Summary\nูููุนุช ฺฉุงุฑ ุงุฒ ุฎุงูู ุฏุฑ ููุงุงุช:\nฺฉุงุจู\nูุฑุงุช\nููฺฏุฑูุงุฑ\nูุฒุงุฑุดุฑู\nุชุนุฏุงุฏ ูพุณุช ูุง: 4\nฺฉุงุฑุดูุงุณ ุซุจุช ุงููุงฺฉ ูุณุฆูู ุฌุณุชุฌู ุงููุงฺฉ ูุฑูุด ู ฺฉุฑุง ุงุฒ ุทุฑู ุดุจฺฉูโูุง ุงุฌุชูุงุน ุฏุฑ ฺฉุงุจูุ ูุฒุงุฑุดุฑูุ ููฺฏุฑูุงุฑ ู ุณุงุฑ ููุงุงุช ููุฌูุงุฑ ูโุจุงุดุฏ. ุงู ูุฑุฏ ูฺฉูู ุงุณุช ุจุฑุง ุฑูููุงูุง ูุนุงููุงุช ููฺฉ ุญุณุงุจ ุงุฌุงุฏ ฺฉุฑุฏู ู ูุนูููุงุช ฺฉุงูู ุขูโูุง ุฑุง ุฏุฑ ูุจโุณุงุช ุขุฑุงุฒูู ุซุจุช ููุงุฏ.\nูุธุงู ูุดุฎุต:\nุฌุณุชุฌู ุงููุงฺฉ ูุฑูุด ู ฺฉุฑุง ุงุฒ ุตูุญุงุช ุงุฌุชูุงุน\nุณุงุฎุช ุญุณุงุจ ุจุฑุง ุฑูููุงูุง ู ุชฺฉูู ุชูุงู ูุนูููุงุช ูุงุฒู\nุซุจุช ุนฺฉุณโูุงุ ููุชุ ูููุนุชุ ุชูุถุญุงุช ู ูุนูููุงุช ุชูุงุณ ูุฑ ููฺฉ\nุซุจุช ููฺฉ ุฑู ููุดู\nุชูุงุณ ูุงุชุณุงูพ ุจุง ุฑูููุงูุงุ ูุนุฑู ุขุฑุงุฒูู ู ุงุฑุณุงู ูุฏููุง ุขููุฒุด\nุขููุฒุด ุดููู ูุฏุฑุช ุตูุญู ู ูุณุช ุงููุงฺฉ ุจุฑุง ุฑูููุง\nุฑุนุงุช ุณุฑุนุช ู ุฏูุช ุฏุฑ ุซุจุช ุงููุงฺฉ ุทุจู ุงุณุชุงูุฏุงุฑุฏ ุขุฑุงุฒูู\nูฺฉุชู ููู:\nโ ุจุฑุง ุงูุฌุงู ุงู ูุธูู ุฏุงุดุชู ฺฉููพูุชุฑ ู ุงูุชุฑูุช ุจุง ุณุฑุนุช ููุงุณุจ ฺฉุงููุงู ุถุฑูุฑ ุงุณุช ุชุง ุซุจุช ุงููุงฺฉ ุจุง ุณุฑุนุช ู ฺฉูุช ุจุงูุง ุงูุฌุงู ุดูุฏ.\nุชุนุฑู ุฑูููุง ูุนุงู:\nโ ูุฑ ุฑูููุง ฺฉู ุฏุฑ ุทูู ููุงู ูุงู ุญุฏุงูู ฒ ููฺฉ ุฑุง ุฏุฑ ุณุงุช ุขุฑุงุฒูู ุซุจุช ฺฉูุฏุ ุฏุฑ ููุงู ูุงู ุฑูููุง ูุนุงู ุญุณุงุจ ูโุดูุฏ.\nุฏุฑู ูุธูู ุฎุงูู ูุง ุชุฑุฌุญ ุฏุงุฏู ูุดููุฏ.\nุงุฒ ูุฑ ููุงุช ฺฉู ูุณุชุฏ ูุชูุงูุฏ ุจู ุงู ูุธูู ุฏุฑุฎูุงุณุช ุจุฏูุฏ ฺูู ุฏุฑ ูุฑููุงุช ฺฉู ุจุงุดุฏ ุงฺฏุฑ ุดุฑุงุท ุขูุฑุง ุฏุงุดุชู ุจุงุดุฏ ูุชูุงูุฏ ุงุณุชุฎุฏุงู ุดูุฏ.\nูุง ฺฏุฑฺู ฺูุฏ ููุงุช ูุดุฎุต ุฑุง ูุงู ฺฏุฑูุชู ูู ฺฉุงุฑููุฏ ูุง ูุง ุชูุงู ููุงุงุช ุฑุง ูพูุดุด ูุฏููุฏ ู ูุชูุงูุฏ ุงุฒ ูุฑููุงุช ุจุงุดุฏ.\nููุนุช ฺฉุงุฑ:\nฺฉุงุฑ ุงุฒ ุฎุงูู ุงูุฌุงู ูโุดูุฏ (ุจุง ููุจุงู ุง ฺฉููพูุชุฑ ู ุงูุชุฑูุช)\nุณุณุชู ูพุฑุฏุงุฎุช ุดุงูู\nูุนุงุด ุซุงุจุช + ูุฒุฏ ุซุงุจุช ุซุจุช ุฑูููุง + ฺฉูุดู ุฑูููุงูุง ูุนุงู\nูโุจุงุดุฏ.\nDuties & Responsibilities\nุดุฑุงุท ูุงุฒู:\n* ุขุดูุง ุจุง ฺฉููพูุชุฑุ ุดุจฺฉูโูุง ุงุฌุชูุงุน ู ุงูุชุฑูุช\n* ุณุฑุนุช ุฎูุจ ุฏุฑ ุชุงูพ ู ูุงุฑุฏ ฺฉุฑุฏู ูุนูููุงุช (Data Entry)\n* ุขุดูุง ุงุจุชุฏุง ุจุง ููุดู ู ุขุฏุฑุณโูุง ุดูุฑ ูุง\n* ุฏุงุดุชู ุชุฌุฑุจู ุฏุฑ ุจุงุฒุงุฑุงุจ ู ูุฑูุด ฺฉ ุงูุชุงุฒ ูุซุจุช ุงุณุช ฺูู ูุชูุงูุฏ ุงู ูุธูู ุจู ูุธูู ูุฑูุดุงุช ุชุจุฏู ุดูุฏ.\nุชุฌุฑุจู ู ุชุญุตูุงุช ุนุงู ุฌุฒ ุงุฒ ุถุฑูุฑุงุช ููุจุงุดุฏ ุชุง ุฌุงฺฉู ูุธูู ุฑุง ูพุด ุจุฑุฏู ุจุชูุงูุฏ.\nุงฺฏุฑ ุชุนููุงุช ุชุงู ูุฒ ุชุง ุตูู ฑฒ ูุณุช ูุชูุงูุฏ ุฏุฑุฎูุงุณุช ุจุฏูุฏ.\nุจู ูุงุฑุบู ฺฉููพูุชุฑุณุงูุณ ู ูุงุฑฺฉุชูฺฏ ุชุฑุฌุญ ุฏุงุฏู ูุดูุฏ\nJob Requirements\nุฌุณุชุฌู ุงููุงฺฉ ูุฑูุด ุง ฺฉุฑุง ุจุตูุฑุช ุขููุงู ุฏุฑ ฺฉุงุจู ุ ูุฒุงุฑุดุฑู ูุฑุงุช ู ููุงุงุช ููุฌูุงุฑ\nุงุฌุงุฏ ุญุณุงุจ ุจุฑุง ุฑูููุงูุง ู ุซุจุช ูุดุฎุตุงุช ุขูโูุง ุฏุฑ ูุจโุณุงุช\nุซุจุช ุงููุงฺฉ ููุฑุงู ุจุง ุนฺฉุณโูุงุ ููุชุ ูููุนุชุ ุชูุถุญุงุช ู ุฌุฒุฆุงุช ุชูุงุณ ุฏุฑ ุณุณุชูู ู ููุดู\nSubmission Guideline\nุฑุงูููุง ุงุฑุณุงู ูุนูููุงุช ุจุฑุง ุฏุฑุฎูุงุณุช ฺฉุงุฑ\nุดูุง ูโุชูุงูุฏ ูุนูููุงุช ฺฉุงูู ุฎูุฏ ุฑุงุ ุดุงูู ุชุญุตูุงุชุ ุชุฌุฑุจุงุช ฺฉุงุฑ ู ููุงุฑุชโูุงุ ุงุฒ ูุฑ ุทุฑููโุง ฺฉู ุจุฑุงุชุงู ุขุณุงูโุชุฑ ุงุณุชุ ุจุฑุง ูุง ุงุฑุณุงู ฺฉูุฏ. ุฏุฑ ุตูุฑุช ุฏุงุดุชู ุฑุฒููู ุง ยซุณโูยปุ ูุทูุงู ุขู ุฑุง ูุฒ ุจูุฑุณุชุฏ ุชุง ุจุฑุฑุณ ุฏููโุชุฑ ุตูุฑุช ฺฏุฑุฏ.\nุจุฑุง ุงุฑุณุงู ูุนูููุงุชุ ูโุชูุงูุฏ ุงุฒ ฺฉ ุงุฒ ุฑุงูโูุง ุชูุงุณ ุฒุฑ ุงุณุชูุงุฏู ููุงุฏ:\n๐\nุตูุญู ูุณโุจูฺฉ:\nhttps://www.facebook.com/profile.php?id=61581846081977&mibextid=ZbWKwL\n๐ผ\nุตูุญู ููฺฉุฏู:\nhttps://www.linkedin.com/company/%D8%A2%D8%B1%DB%8C%D8%A7-%D8%B2%D9%85%DB%8C%D9%86/\n๐ง\nุงูู:\ninfo.aryazamin@gmail.com\n๐ฑ\nุดูุงุฑู ูุงุชุณุงูพ:\nWhatsApp Number:\n+1 840 265 6048\n๐\nูุจโุณุงุช:\nwww.aryazamin.com\nุชู ุขุฑุงุฒูู ูพุณ ุงุฒ ุฏุฑุงูุช ูุนูููุงุช ุดูุง ุจุง ุดูุง ุฏุฑ ุชูุงุณ ุฎูุงูุฏ ุดุฏ ุชุง ูุฑุงุญู ุจุนุฏ ุฑุง ููุงููฺฏ ููุงุฏ.\nFunctional Area\nSales/Marketing\nMedia\nComputer Science\nData Entry\nTeaching\nCountries\nAfghanistan\nProvinces\nKabul\nNangarhar\nBalkh\nHerat\nApply Now\nPost Date\nOct 21, 2025\nClosing Date\nJan 31, 2026\nReference\nAZ105\nNumber of Vacancies\n4\nSalary Range\nุ14000 - ุ21000 monthly\nYears of Experience\nFresh\nProbation Period\nNot Specified\nContract Type\nPermanent\nContract Duration\nNot specified\nContract Extensible\nYes\nMinimum Education\nSecondary School\nGender\nFemale\nRelated Jobs\nNETLINKS Plaza | Shahr-e-Naw,\nLane 3, Kabul, Afghanistan\nQuick Links\nAbout Us\nAdvertise with Us\nPrivacy Policy\nFor Companies\nPost a Job\nPost a Job\nPost a Job\nPost a Job\nPost RFP\nPost RFP\nPost RFP\nPost RFP\nPost Training\nPost Training\nPost Training\nPost Training\nFor Jobseekers\nBrowse Jobs\nBrowse Companies\nBuild Resume\nContact\ninfo@jobs.af\nContact Us\nยฉ 2012 - 2026 Jobs.af | All Rights Reserved\nPowered by:\nNETLINKS Ltd",
    "details": {
      "Post Date": "Oct 21, 2025",
      "Closing Date": "Jan 31, 2026",
      "Reference": "AZ105",
      "Number Of Vacancies": "4",
      "Salary Range": "ุ14000 - ุ21000 monthly",
      "Years Of Experience": "Fresh",
      "Probation Period": "Not Specified",
      "Contract Type": "Permanent",
      "Contract Duration": "Not specified",
      "Contract Extensible": "Yes",
      "Minimum Education": "Secondary School",
      "ุชุนุฏุงุฏ ูพุณุช ูุง": "4",
      "https": "//www.facebook.com/profile.php?id=61581846081977&mibextid=ZbWKwL",
      "Functional Area": "Sales/Marketing",
      "Countries": "Afghanistan",
      "Provinces": "Kabul"
    },
    "scraped_at": "2026-01-21T05:00:22Z",
    "apply_emails": [
      "info.aryazamin@gmail.com"
    ],
    "apply_method": "email"
  },
  {
    "url": "https://jobs.af/jobs/marketing-and-sale-executive",
    "title": "Marketing & Sale Executive",
    "company": null,
    "location": "Kabul",
    "closing_date": "2026-01-31",
    "closing_date_raw": "Jan 31, 2026",
    "apply_url": null,
    "description": "๐\nComing Soon The Jobs.af Freelancer Portal\nConnect with top clients and freelancers across Afghanistan all in one place!\nStay Tuned\nJobs\nProcurement Opportunities\nCompanies\nFreelancers\nServices\nProcurement Opportunities\nTrainings\nScholarships\nLogin\nRegister\nMarketing & Sale Executive\nBehtar LTD (Behtar Group)\nApply Now\nSee all jobs\nMarketing & Sale Executive\nBehtar LTD (Behtar Group),\n                                        Kabul, Afghanistan\nApply Now\nBachelor's Degree\nKabul, Afghanistan\n(Kabul)\nFull Time\n422\nAbout\n                                            Behtar LTD (Behtar Group)\nBehtar is a group of companies that has been at the forefront of the telecommunications, mobile money, and e-commerce sectors for 20 years. The company was founded with the vision of connecting people and businesses, and facilitating commerce in an increasingly connected world. Through the years, Behtar has grown to become a leading provider of telecommunications, mobile money, and e-commerce services in Afghanistan, with a strong reputation for innovation and customer service. Started as a small telecom service provider and quickly recognized the potential for growth and expansion in the financial services sector. we worked hard to provide innovative and cutting-edge solutions that could improve the lives of our customers. We were the first to offer high-speed internet and mobile banking services in our country, and as a result, we rapidly grew our customer base. With the passage of time, we continued to adapt and evolve to meet the changing needs of our customers, always looking for ways to push the boundaries of what was possible.\nToday, the Behtar group of companies is a well-established and respected player in both the telecom and financial services sectors, known for our commitment to excellence and our ability to deliver results. We are excited to continue growing and serving our customers for many years to come.\nJob Summary\nThe Digital Marketing Executive โ IT & Technology is responsible for planning, executing, and optimizing digital marketing initiatives to promote IT products, services, platforms, and technology solutions. The role requires hands-on expertise in digital advertising, performance marketing, content distribution, SEO, and analytics to enhance brand visibility, drive lead generation, and support customer acquisition objectives.\nDuties & Responsibilities\n1.\tDigital Campaign Management\nโข\tPlan, execute, and manage integrated digital marketing campaigns for IT products, services, and platforms.\nโข\tPromote websites, applications, digital platforms, and technology solutions across multiple digital channels.\nโข\tContinuously optimize campaigns to maximize traffic, engagement, and conversion performance.\n2.\tPerformance Marketing & Analytics\nโข\tManage paid advertising campaigns across Google Ads, social media platforms, and other digital channels.\nโข\tMonitor and analyze key performance indicators (KPIs), including traffic, click-through rates (CTR), conversion rates, and return on investment (ROI).\nโข\tPrepare regular performance reports and provide data-driven optimization recommendations.\n3.\tContent & Social Media Marketing\nโข\tCoordinate the creation, scheduling, and distribution of digital content, including social media posts, banners, videos, blogs, and promotional materials.\nโข\tManage and grow the organizationโs presence across relevant social media platforms.\nโข\tCommunicate IT use cases, features, and benefits through effective digital storytelling and campaigns.\n4.\tSEO & Website Promotion\nโข\tSupport search engine optimization (SEO) activities, including keyword research, on-page optimization, and content alignment.\nโข\tImprove website visibility, organic traffic, and search engine rankings.\nโข\tCoordinate with technical and content teams to ensure SEO best practices are implemented.\n5.\tEmail Marketing & Lead Generation\nโข\tPlan and execute email marketing campaigns and lead nurturing workflows.\nโข\tGenerate, track, and qualify leads for IT products and technology services.\nโข\tMaintain lead databases, campaign tracking, and performance dashboards.\n6.\tCoordination & Communication\nโข\tCoordinate closely with IT, product development, design, and sales teams.\nโข\tAlign digital marketing strategies with business objectives and product roadmaps.\nโข\tSupport product launches, feature releases, and promotional campaigns.\nJob Requirements\nโข\tBachelorโs degree in Marketing, Information Technology, Business Administration, or a related field.\nโข\tProven experience in digital marketing, preferably within IT, technology, or digital platforms.\nโข\tHands-on experience with Google Ads, social media advertising platforms, and analytics tools.\nโข\tStrong understanding of SEO, SEM, digital marketing funnels, and conversion optimization.\nโข\tExcellent analytical, reporting, and communication skills.\nKey Performance Indicators (KPIs)\nโข\tGrowth in website traffic and user engagement.\nโข\tLead generation volume and conversion rates.\nโข\tCampaign ROI and cost-efficiency.\nโข\tBrand visibility, reach, and online presence growth.\nSubmission Guideline\nInterested national candidates are kindly requested to submit their application (Cover letter & updated CV) no later than 31 Jan 2026 to the below email:\nkbl.hr@behtar.com.af\nNote that the applicant must be based in Kabul.\nFunctional Area\nMarketing\nInformation Technology\nBusiness Administration\nCountries\nAfghanistan\nProvinces\nKabul\nSubmission Email\nkbl.hr@behtar.com.af\nApply Now\nPost Date\nJan 18, 2026\nClosing Date\nJan 31, 2026\nReference\n016\nNumber of Vacancies\n2\nSalary Range\nAs per company salary scale\nYears of Experience\n1 - 3 years\nProbation Period\n3 month\nContract Type\nPermanent\nContract Duration\n1 year\nContract Extensible\nYes\nMinimum Education\nBachelor's Degree\nGender\nMale\nRelated Jobs\nNETLINKS Plaza | Shahr-e-Naw,\nLane 3, Kabul, Afghanistan\nQuick Links\nAbout Us\nAdvertise with Us\nPrivacy Policy\nFor Companies\nPost a Job\nPost a Job\nPost a Job\nPost a Job\nPost RFP\nPost RFP\nPost RFP\nPost RFP\nPost Training\nPost Training\nPost Training\nPost Training\nFor Jobseekers\nBrowse Jobs\nBrowse Companies\nBuild Resume\nContact\ninfo@jobs.af\nContact Us\nยฉ 2012 - 2026 Jobs.af | All Rights Reserved\nPowered by:\nNETLINKS Ltd",
    "details": {
      "Post Date": "Jan 18, 2026",
      "Closing Date": "Jan 31, 2026",
      "Reference": "016",
      "Number Of Vacancies": "2",
      "Salary Range": "As per company salary scale",
      "Years Of Experience": "1 - 3 years",
      "Probation Period": "3 month",
      "Contract Type": "Permanent",
      "Contract Duration": "1 year",
      "Contract Extensible": "Yes",
      "Minimum Education": "Bachelor's Degree",
      "Functional Area": "Marketing",
      "Countries": "Afghanistan",
      "Provinces": "Kabul"
    },
    "scraped_at": "2026-01-21T05:00:22Z",
    "apply_emails": [
      "kbl.hr@behtar.com.af"
    ],
    "apply_method": "email"
  },
  {
    "url": "https://jobs.af/jobs/software-developer-intern-full-stack-mobile",
    "title": "Software Developer Intern (Full Stack/Mobile)",
    "company": null,
    "location": "Kabul",
    "closing_date": "2026-01-31",
    "closing_date_raw": "Jan 31, 2026",
    "apply_url": null,
    "description": "๐\nComing Soon The Jobs.af Freelancer Portal\nConnect with top clients and freelancers across Afghanistan all in one place!\nStay Tuned\nJobs\nProcurement Opportunities\nCompanies\nFreelancers\nServices\nProcurement Opportunities\nTrainings\nScholarships\nLogin\nRegister\nSoftware Developer Intern (Full Stack/Mobile)\nQuick Prime\nApply Now\nSee all jobs\nSoftware Developer Intern (Full Stack/Mobile)\nQuick Prime ,\n                                        Kabul, Afghanistan\nApply Now\nBachelor's Degree\nKabul, Afghanistan\n(Kabul)\nFull Time\n2762\nAbout\n                                            Quick Prime\nQuick Prime Logistics is a trusted service provider in Afghanistan, delivering reliable logistics solutions for businesses and individuals. Alongside our core logistics services, we offer complete technology solutionsโincluding web development, mobile app development, and custom softwareโto help organizations modernize operations, improve efficiency, and grow with confidence. From planning and design to development, deployment, and support, Quick Prime combines practical industry experience with modern technology to deliver secure, scalable, and user-friendly systems.\nJob Summary\nQuick Prime Logistics is hiring\nIntern Developers\nto join our team in\nAfghanistan\n. This internship is designed for students, recent graduates, and self-learners who want practical, real-project experience with guidance from experienced developers.\nNo previous professional experience is required.\nIf you have foundational knowledge and a strong willingness to learn, you are encouraged to apply.\nAs an Intern Developer, you will contribute to real software products and internal tools. You may work in one or more areas such as web development, mobile development, or general software engineering, depending on your interests and team needs.\nDuties & Responsibilities\nContribute to building and improving software features under mentorship\nWrite clean, readable, and maintainable code\nAssist with debugging, testing, and performance improvements\nParticipate in code reviews and learn development best practices\nWork with the team to understand requirements and deliver tasks on time\nMaintain documentation for features, fixes, and technical notes\nCollaborate with designers, developers, and product stakeholders\nJob Requirements\nSkills and Qualifications (Preferred)\nProgramming & Computer Science\nUnderstanding of programming concepts such as OOP, data structures, and algorithms\nStrong problem-solving and logical thinking\nFamiliarity with software development lifecycle and coding standards\nWeb Development (if applying for web/full-stack track)\nHTML, CSS, JavaScript\nFamiliarity with modern front-end development practices (component-based UI, responsive design)\nExperience or exposure to frameworks such as React\nUnderstanding of back-end development concepts (APIs, authentication, server-side logic)\nExposure to Node.js, Django, Laravel, or similar frameworks\nMobile Development (if applying for mobile track)\nUnderstanding of mobile app development workflows\nExposure to Flutter, React Native, or native Android/iOS development\nFamiliarity with app navigation, UI layouts, and integrating APIs\nDatabases & Data Handling\nUnderstanding of relational databases and querying\nExperience or exposure to SQL, MySQL, or PostgreSQL\nFamiliarity with data modeling concepts and validation\nTools & Professional Practices\nVersion control using Git and GitHub\nFamiliarity with issue tracking and task management tools (Jira, Trello, GitHub Issues, etc.)\nAbility to read documentation and learn new technologies independently\nClear communication, teamwork, and time management\nQuality & Delivery\nUnderstanding of testing concepts (unit testing, integration testing)\nAttention to detail and ability to follow requirements\nInterest in writing secure, reliable, and scalable code\nNote\nIf you donโt meet every preferred skill listed above, we still encourage you to apply. We value motivation, learning ability, and a strong work ethic.\nWhat You Will Gain\nHands-on experience with real projects and professional workflows\nMentorship and technical growth through reviews and collaboration\nStronger portfolio and CV through practical contributions\nExperience working in a team environment with modern tools and processes\nSubmission Guideline\nInterested applicants are requested to send their CV to\nsafaryar.technologies@gmail.com\nand include\njawad.safaryar@gmail.com\nin CC.\nPlease mention the position you are applying for in the email subject line.\nFunctional Area\nIT - Software\nTechnical\nInformation Management\nsoftware development\nWeb Development\nWeb Application Development\nsoftware development\nDatabase Development\nProgramming\nCountries\nAfghanistan\nProvinces\nKabul\nSubmission Email\nsafaryar.technologies@gmail.com\nApply Now\nPost Date\nDec 31, 2025\nClosing Date\nJan 31, 2026\nReference\nQP-ST\nNumber of Vacancies\n3\nSalary Range\nAs per company salary scale\nYears of Experience\nFresh\nProbation Period\n3 month\nContract Type\nInternship\nContract Duration\n3 month\nContract Extensible\nMaybe\nMinimum Education\nBachelor's Degree\nGender\nAny\nRelated Jobs\nNETLINKS Plaza | Shahr-e-Naw,\nLane 3, Kabul, Afghanistan\nQuick Links\nAbout Us\nAdvertise with Us\nPrivacy Policy\nFor Companies\nPost a Job\nPost a Job\nPost a Job\nPost a Job\nPost RFP\nPost RFP\nPost RFP\nPost RFP\nPost Training\nPost Training\nPost Training\nPost Training\nFor Jobseekers\nBrowse Jobs\nBrowse Companies\nBuild Resume\nContact\ninfo@jobs.af\nContact Us\nยฉ 2012 - 2026 Jobs.af | All Rights Reserved\nPowered by:\nNETLINKS Ltd",
    "details": {
      "Post Date": "Dec 31, 2025",
      "Closing Date": "Jan 31, 2026",
      "Reference": "QP-ST",
      "Number Of Vacancies": "3",
      "Salary Range": "As per company salary scale",
      "Years Of Experience": "Fresh",
      "Probation Period": "3 month",
      "Contract Type": "Internship",
      "Contract Duration": "3 month",
      "Contract Extensible": "Maybe",
      "Minimum Education": "Bachelor's Degree",
      "Functional Area": "IT - Software",
      "Countries": "Afghanistan",
      "Provinces": "Kabul"
    },
    "scraped_at": "2026-01-21T05:00:22Z",
    "apply_emails": [
      "safaryar.technologies@gmail.com",
      "jawad.safaryar@gmail.com"
    ],
    "apply_method": "email"
  },
  {
    "url": "https://jobs.af/jobs/software-development-assistant-react-developer",
    "title": "Software Development Assistant (React Developer)",
    "company": null,
    "location": "Kabul",
    "closing_date": "2026-02-03",
    "closing_date_raw": "Feb 03, 2026",
    "apply_url": null,
    "description": "๐\nComing Soon The Jobs.af Freelancer Portal\nConnect with top clients and freelancers across Afghanistan all in one place!\nStay Tuned\nJobs\nProcurement Opportunities\nCompanies\nFreelancers\nServices\nProcurement Opportunities\nTrainings\nScholarships\nLogin\nRegister\nSoftware Development Assistant (React Developer)\nPARSA Technologies\nApply Now\nSee all jobs\nSoftware Development Assistant (React Developer)\nPARSA Technologies,\n                                        Kabul, Afghanistan\nApply Now\nBachelor's Degree\nKabul, Afghanistan\n(Kabul)\nFull Time\n214\nAbout\n                                            PARSA Technologies\nFor almost a decade, PARSA relentless innovation, quality of products, responsible management, and dedication made it the partner of choice for many of the Afghanโs most trusted brands.\nPARSA in the local Afghanistan Market is one of the trusted partners in domains of web application development, mobile application development, value-added services, HR MIS, Finance Management System, SMS Platform, and e-commerce. We are glad to demonstrate through our work that we have the capabilities, people, processes, technology, and the desire to be the strategic technology partner of choice for many Afghan entities, including government departments, the private sector, and non-government organizations (NGOs).\nPARSAโs primary objective is to develop an environment of fairness, honesty, integrity, and courtesy towards our clients, employees, vendors, and society at large. We areยcommitted to our customers & partners and have a passion for technology.\nJob Summary\nThe Software Development Assistant will work under the overall guidance of the ChiefยExecutive Officer and under the direct supervision of the Software Development Team Head.\nDuties & Responsibilities\nHe/she will work in close collaboration with the Software Development Department andยwill fulfill the following duties and responsibilities:\nDesigning and Development of web and mobile applications.\nConducting feasibility studies for software projects.\nCompleting tasks such as coding, testing, and debugging.\nWriting advanced programming code.\nManaging project timelines and tasks.\nWork in close partnership with operation, business, and management departments\nV. Competencies and Critical Success Factors\nFunctional Competencies\nKnowledge Management and Learning\nShares knowledge and experience;\nActively works towards continuing personal learning and development andยapplies newly acquired skills.\nDevelopment and Operational Effectiveness.\nProficiency with React\nProficiency in HTML, CSS, Bootstrap, Javascript + ES6, Sass, Tailwind CSS\nExcellent understanding of React-redux, Webpack, REST API\nGood knowledge of version control system like git\nGood knowledge of UI and UX and Proficiency with Figma\nAbility to perform a broad range of parallel specialized activities\nExcellent analytical and problem-solving skills.\nExcellent organization and time management skills.\nExcellent written and verbal communication skills.\nDemonstrated ability to lead others.\nLeadership and Self-Management\nFocuses on result for the client and responds positively to feedback;\nAbility to team work.\nConsistently approaches work with energy and a positive, constructive attitude; Demonstrates openness to change and ability to manage complexity.\nAbility to handle daily tasks mainly in the field.\nAbility to establish good working relations with a range of stakeholders.\nAbility to coach, mentor, and develop people skills.\nAbility to focus on results\nConsistently approaches work with energy in a positive and constructive attitude.\nJob Requirements\nBachelor's in Computer Science, Software Engineering, or equivalent subject\nAt least 3+ years of experience in the above-mentioned field\nSubmission Guideline\nInterested individual submits their Personal CV indicating all past experience from similarยjob, as well as the contact details (email and telephone number) of the Candidate to: hr@parsa.technology\nNote:\napplicants are instructed to\nwrite the position title in the subject line\nof their email when submitting their application.\nFunctional Area\nComputer Science\nSoftware engineering\nCountries\nAfghanistan\nProvinces\nKabul\nSubmission Email\nhr@parsa.technology\nApply Now\nPost Date\nJan 20, 2026\nClosing Date\nFeb 03, 2026\nReference\nPT#000265\nNumber of Vacancies\n1\nSalary Range\nSalary is negotiable\nYears of Experience\n3 years\nProbation Period\n3 month\nContract Type\nPermanent\nContract Duration\n1 year\nContract Extensible\nYes\nMinimum Education\nBachelor's Degree\nGender\nMale\nRelated Jobs\nNETLINKS Plaza | Shahr-e-Naw,\nLane 3, Kabul, Afghanistan\nQuick Links\nAbout Us\nAdvertise with Us\nPrivacy Policy\nFor Companies\nPost a Job\nPost a Job\nPost a Job\nPost a Job\nPost RFP\nPost RFP\nPost RFP\nPost RFP\nPost Training\nPost Training\nPost Training\nPost Training\nFor Jobseekers\nBrowse Jobs\nBrowse Companies\nBuild Resume\nContact\ninfo@jobs.af\nContact Us\nยฉ 2012 - 2026 Jobs.af | All Rights Reserved\nPowered by:\nNETLINKS Ltd",
    "details": {
      "Post Date": "Jan 20, 2026",
      "Closing Date": "Feb 03, 2026",
      "Reference": "PT#000265",
      "Number Of Vacancies": "1",
      "Salary Range": "Salary is negotiable",
      "Years Of Experience": "3 years",
      "Probation Period": "3 month",
      "Contract Type": "Permanent",
      "Contract Duration": "1 year",
      "Contract Extensible": "Yes",
      "Minimum Education": "Bachelor's Degree",
      "Functional Area": "Computer Science",
      "Countries": "Afghanistan",
      "Provinces": "Kabul"
    },
    "scraped_at": "2026-01-21T05:00:22Z",
    "apply_emails": [
      "hr@parsa.technology"
    ],
    "apply_method": "email"
  },
  {
    "url": "https://jobs.af/jobs/backend-developer-php-node-js",
    "title": "Backend Developer (PHP / Node.js)",
    "company": null,
    "location": "Kabul",
    "closing_date": "2026-02-04",
    "closing_date_raw": "Feb 04, 2026",
    "apply_url": null,
    "description": "๐\nComing Soon The Jobs.af Freelancer Portal\nConnect with top clients and freelancers across Afghanistan all in one place!\nStay Tuned\nJobs\nProcurement Opportunities\nCompanies\nFreelancers\nServices\nProcurement Opportunities\nTrainings\nScholarships\nLogin\nRegister\nBackend Developer (PHP / Node.js)\nTecTors Technology and Software Hous Co\nApply Now\nSee all jobs\nBackend Developer (PHP / Node.js)\nTecTors Technology and Software Hous Co,\n                                        Kabul, Afghanistan\nApply Now\nBachelor's Degree\nKabul, Afghanistan\n(Kabul)\nFull Time\n3376\n80\nAbout\n                                            TecTors Technology and Software Hous Co\nTecTors Technology and Software House\nis a professional technology company based in Kabul, Afghanistan, providing complete digital and software solutions for businesses.\nOur services include:\nDevelopment of business databases and commercial websites\nDomain registration and web hosting\ncPanel training and setup\nCreation of official business emails\nUI/UX design and digital branding\nAt TecTors, we empower businesses to grow through modern, secure, and reliable technology solutions.\nJob Summary\nTecTors Technology and Software House is looking for a skilled and motivated\nBackend Developer (PHP / Node.js)\nto join our growing technology team.\nThe ideal candidate will be responsible for developing, maintaining, and optimizing backend systems, building APIs, and integrating databases for modern web applications.\nThis is a\nlong-term\nposition based in\nKabul\n, offering the opportunity to work on innovative digital solutions for businesses.\nDuties & Responsibilities\nDevelop, test, and maintain backend applications using\nPHP (Laravel)\nor\nNode.js (Express.js / Nest.js)\nBuild and integrate APIs with frontend and third-party systems\nDesign and optimize databases for business applications\nEnsure code quality, security, and performance\nCollaborate closely with UI/UX designers and frontend developers\nTroubleshoot and resolve backend issues\nJob Requirements\nProven experience in\nPHP (Laravel)\nor\nNode.js\ndevelopment\nFamiliarity with\nMySQL\n,\nMongoDB\n, or other databases\nKnowledge of\nRESTful API\ndesign and integration\nUnderstanding of frontend-backend collaboration\nProblem-solving skills and attention to detail\nMinimum 1โ2 years of professional experience\nStrong communication skills in English\nSubmission Guideline\nInterested candidates should submit their CV and portfolio to\ninfo@tectors.com\nwith the subject line:\nBackend Developer โ TecTors\n.\nApplications will be reviewed on a rolling basis. Only shortlisted candidates will be contacted.\nFor any questions regarding the position, contact via WhatsApp: +93 70 449 5743 (11:00 โ 15:00 Kabul time)\nFunctional Area\nInformation Technology\nIT - Software\nWeb Developer\nSoftware Development and Data Management\nCountries\nAfghanistan\nProvinces\nKabul\nApply Now\nPost Date\nNov 04, 2025\nClosing Date\nFeb 04, 2026\nReference\nTT-BE-01\nNumber of Vacancies\n1\nSalary Range\nSalary is negotiable\nYears of Experience\n1 - 3 years\nProbation Period\n1 month\nContract Type\nLong-term\nContract Duration\nNot specified\nContract Extensible\nYes\nMinimum Education\nBachelor's Degree\nGender\nMale\nRelated Jobs\nNETLINKS Plaza | Shahr-e-Naw,\nLane 3, Kabul, Afghanistan\nQuick Links\nAbout Us\nAdvertise with Us\nPrivacy Policy\nFor Companies\nPost a Job\nPost a Job\nPost a Job\nPost a Job\nPost RFP\nPost RFP\nPost RFP\nPost RFP\nPost Training\nPost Training\nPost Training\nPost Training\nFor Jobseekers\nBrowse Jobs\nBrowse Companies\nBuild Resume\nContact\ninfo@jobs.af\nContact Us\nยฉ 2012 - 2026 Jobs.af | All Rights Reserved\nPowered by:\nNETLINKS Ltd",
    "details": {
      "Post Date": "Nov 04, 2025",
      "Closing Date": "Feb 04, 2026",
      "Reference": "TT-BE-01",
      "Number Of Vacancies": "1",
      "Salary Range": "Salary is negotiable",
      "Years Of Experience": "1 - 3 years",
      "Probation Period": "1 month",
      "Contract Type": "Long-term",
      "Contract Duration": "Not specified",
      "Contract Extensible": "Yes",
      "Minimum Education": "Bachelor's Degree",
      "For any questions regarding the position, contact via WhatsApp": "+93 70 449 5743 (11:00 โ 15:00 Kabul time)",
      "Functional Area": "Information Technology",
      "Countries": "Afghanistan",
      "Provinces": "Kabul"
    },
    "scraped_at": "2026-01-21T05:00:22Z",
    "apply_emails": [
      "info@tectors.com"
    ],
    "apply_method": "email"
  },
  {
    "url": "https://jobs.af/jobs/senior-software-development-officer-6-Du94VTa",
    "title": "Senior Software Development Officer",
    "company": null,
    "location": "Kabul",
    "closing_date": "2026-02-04",
    "closing_date_raw": "Feb 04, 2026",
    "apply_url": null,
    "description": "๐\nComing Soon The Jobs.af Freelancer Portal\nConnect with top clients and freelancers across Afghanistan all in one place!\nStay Tuned\nJobs\nProcurement Opportunities\nCompanies\nFreelancers\nServices\nProcurement Opportunities\nTrainings\nScholarships\nLogin\nRegister\nSenior Software Development Officer\nPARSA Technologies\nApply Now\nSee all jobs\nSenior Software Development Officer\nPARSA Technologies,\n                                        Kabul, Afghanistan\nApply Now\nBachelor's Degree\nKabul, Afghanistan\n(Kabul)\nFull Time\n398\nAbout\n                                            PARSA Technologies\nFor almost a decade, PARSA relentless innovation, quality of products, responsible management and dedication made it the partner of choice for many of the Afghanโs most trusted brands.\nPARSA in the local Afghanistan Market is one of the trusted partners in domains of web application development, mobile application development, value added services, HR MIS, Finance Management System, SMS Platform and e-commerce. We are glad to demonstrate through our work, that we have the capabilities, people, processes, technology and the desire to be the strategic technology partner of choice for many Afghan entitles, including government departments, private sector and no-government organizations (NGOs).\nPARSAโs primary objective is to develop an environment of fairness, honesty, integrity and courtesy towards our clients, employees, vendors and society at large. We are committed to our customers & partners and have a passion for technology.\nJob Summary\nSenior Software Development Officer\nwill work under the overall guidance of the Chief Executive Officer and under direct supervision of the Software Development Manager.\nDuties & Responsibilities\nDUTIES AND RESPONSIBILITIES:\nHe/she will work in close collaboration with the Software Development Department and will fulfill the following duties and responsibilities:\nDesigning and Development of new software projects, websites, and mobile applications.\nConducting feasibility studies for software projects.\nAssigning tasks to junior developers such as coding, testing, and debugging.\nWriting advanced programming code.\nManaging project timelines and tasks.\nWork in close partnership with operation, business, IT and management departments\nFunctional Competencies\nKnowledge Management and Learning\nShares knowledge and experience;\nActively works towards continuing personal learning and development and applies newly acquired skills.\nDevelopment and Operational Effectiveness\n.\nProficiency with React JS library\nProficiency in Spring Boot, Spring MVC, Hibernate or one of programming languages\nGood knowledge of version control system like git\nGood knowledge of databases like MySQL, PostgreSQL, MangoDB\nAbility to perform a broad range of parallel specialized activities\nExcellent analytical and problem-solving skills.\nExcellent organization and time management skills.\nExcellent written and verbal communication skills.\nDemonstrated ability to lead others.\nLeadership and Self-Management\nFocuses on result for the client and responds positively to feedback;\nAbility to team work.\nConsistently approaches work with energy and a positive, constructive attitude;\nDemonstrates openness to change and ability to manage complexity.\nAbility to handle daily tasks mainly in the field.\nAbility to establish good working relations with a range of stakeholders.\nAbility to coach, mentor, and develop people skills.\nAbility to focus on results\nConsistently approaches work with energy in a positive and constructive attitude.\nJob Requirements\nRecruitment Qualifications:\nBachelors in Computer Science, Software Engineering or equivalent subject\nAt least 3 years of experience in above mentioned field.\nSubmission Guideline\nInterested individual submit their\nPersonal CV\nindicating all past experience from similar job, as well as the contact details (email and telephone number) of the Candidate to\nhr@parsatechnologies.com\nPlease ensure that applicants are instructed to\nwrite the position title in the subject line\nof their email when submitting their application.\nFunctional Area\nsoftware development\nCountries\nAfghanistan\nProvinces\nKabul\nSubmission Email\nhr@parsatechnologies.com\nApply Now\nPost Date\nJan 19, 2026\nClosing Date\nFeb 04, 2026\nReference\nPT#000256\nNumber of Vacancies\n1\nSalary Range\nAs per company salary scale\nYears of Experience\n3 years\nProbation Period\n3 month\nContract Type\nPermanent\nContract Duration\n1 year\nContract Extensible\nYes\nMinimum Education\nBachelor's Degree\nGender\nAny\nRelated Jobs\nNETLINKS Plaza | Shahr-e-Naw,\nLane 3, Kabul, Afghanistan\nQuick Links\nAbout Us\nAdvertise with Us\nPrivacy Policy\nFor Companies\nPost a Job\nPost a Job\nPost a Job\nPost a Job\nPost RFP\nPost RFP\nPost RFP\nPost RFP\nPost Training\nPost Training\nPost Training\nPost Training\nFor Jobseekers\nBrowse Jobs\nBrowse Companies\nBuild Resume\nContact\ninfo@jobs.af\nContact Us\nยฉ 2012 - 2026 Jobs.af | All Rights Reserved\nPowered by:\nNETLINKS Ltd",
    "details": {
      "Post Date": "Jan 19, 2026",
      "Closing Date": "Feb 04, 2026",
      "Reference": "PT#000256",
      "Number Of Vacancies": "1",
      "Salary Range": "As per company salary scale",
      "Years Of Experience": "3 years",
      "Probation Period": "3 month",
      "Contract Type": "Permanent",
      "Contract Duration": "1 year",
      "Contract Extensible": "Yes",
      "Minimum Education": "Bachelor's Degree",
      "Functional Area": "software development",
      "Countries": "Afghanistan",
      "Provinces": "Kabul"
    },
    "scraped_at": "2026-01-21T05:00:22Z",
    "apply_emails": [
      "hr@parsatechnologies.com"
    ],
    "apply_method": "email"
  },
  {
    "url": "https://jobs.af/jobs/ui-ux-designer-m0U7LzCtL",
    "title": "UI/UX Designer",
    "company": null,
    "location": "Kabul",
    "closing_date": "2026-02-04",
    "closing_date_raw": "Feb 04, 2026",
    "apply_url": null,
    "description": "๐\nComing Soon The Jobs.af Freelancer Portal\nConnect with top clients and freelancers across Afghanistan all in one place!\nStay Tuned\nJobs\nProcurement Opportunities\nCompanies\nFreelancers\nServices\nProcurement Opportunities\nTrainings\nScholarships\nLogin\nRegister\nUI/UX Designer\nTecTors Technology and Software Hous Co\nApply Now\nSee all jobs\nUI/UX Designer\nTecTors Technology and Software Hous Co,\n                                        Kabul, Afghanistan\nApply Now\nBachelor's Degree\nKabul, Afghanistan\n(Kabul)\nFull Time\n1658\n19\nAbout\n                                            TecTors Technology and Software Hous Co\nTecTors Technology and Software House\nis a Kabul-based technology company specializing in creating\ninnovative digital solutions\nfor businesses.\nOur services include:\nDeveloping commercial websites\nCreating and managing business databases\nDomain registration and web hosting\nSetting up official company emails\nTraining on cPanel and server management\nAt TecTors, we focus on\ndelivering high-quality, user-friendly, and transformative solutions\nto help our clients grow their digital presence.\nJob Summary\nTecTors Technology and Software House is seeking a\ncreative UI/UX & Graphic Designer\nto join our team in Kabul.\nThe ideal candidate will design\nuser-friendly interfaces, engaging visuals, and compelling graphics\nfor websites and applications.\nThis is a\nlong-term position\noffering opportunities to work on\ninnovative digital projects\nand grow professionally in a dynamic technology environment.\nDuties & Responsibilities\nDesign and optimize\nuser interfaces (UI) and user experiences (UX)\nfor web applications, commercial websites, and database management systems.\nCreate\nwireframes, prototypes, mockups, and interactive designs\nfor digital products.\nCollaborate with\nBackend and Frontend developers\nto ensure seamless integration of design and functionality.\nConduct\nuser research, usability testing, and feedback analysis\nto improve design decisions.\nDevelop\nresponsive, accessible, and visually appealing interfaces\nacross devices.\nEnsure consistency with\ndesign systems, brand guidelines, and UI standards\n.\nStay updated on\nlatest UI/UX trends, tools, and best practices\n, especially for web and database applications.\nAssist in designing\ndashboards, forms, and data visualization components\nfor internal and client systems.\nOptimize\nuser workflows and navigation\nfor efficiency and clarity.\nJob Requirements\nBachelorโs degree in\nGraphic Design, UI/UX Design, Multimedia, Computer Science, or related field\n.\nMinimum\n1โ3 years of professional experience\nin UI/UX design for web applications, commercial websites, or database systems.\nStrong portfolio demonstrating\nUI/UX projects, interactive designs, and visual graphics\n.\nProficiency in\ndesign tools\n: Figma, Adobe XD, Sketch, Photoshop, Illustrator.\nExperience with\nwireframing, prototyping, mockups, and user flows\n.\nUnderstanding of\nuser-centered design principles, usability, and accessibility standards\n.\nAbility to\ncollaborate with developers\nand translate requirements into functional design.\nKnowledge of\nresponsive design\nand cross-browser/device compatibility.\nStrong\nvisual design, typography, and color theory\nskills.\nExcellent\ncommunication, problem-solving, and creative thinking\nskills.\nSubmission Guideline\nInterested candidates should submit their\nCV and portfolio\nto\ninfo@tectors.com\nFor any questions regarding this position, candidates can also contact us via\nWhatsApp\n: +93 70 449 5743 (11:00 โ 15:00 Kabul time).\nwith the subject line:\nUI/UX & Graphic Designer โ TecTors\nApplications will be\nreviewed on a rolling basis\n, and only\nshortlisted candidates will be contacted\n.\nNote:\nPortfolio should include\nUI/UX projects, website designs, and graphic design work\nto demonstrate relevant skills.\nFunctional Area\nIT - Software\nComputer Science\nGraphic Designer\nGraphics\nPhotography\nWeb Designing\nWeb Development\nCountries\nAfghanistan\nProvinces\nKabul\nApply Now\nPost Date\nNov 04, 2025\nClosing Date\nFeb 04, 2026\nReference\nTT-UI-02\nNumber of Vacancies\n1\nSalary Range\nSalary is negotiable\nYears of Experience\n1 - 3 years\nProbation Period\n1 month\nContract Type\nLong-term\nContract Duration\nNot specified\nContract Extensible\nYes\nMinimum Education\nBachelor's Degree\nGender\nMale\nRelated Jobs\nNETLINKS Plaza | Shahr-e-Naw,\nLane 3, Kabul, Afghanistan\nQuick Links\nAbout Us\nAdvertise with Us\nPrivacy Policy\nFor Companies\nPost a Job\nPost a Job\nPost a Job\nPost a Job\nPost RFP\nPost RFP\nPost RFP\nPost RFP\nPost Training\nPost Training\nPost Training\nPost Training\nFor Jobseekers\nBrowse Jobs\nBrowse Companies\nBuild Resume\nContact\ninfo@jobs.af\nContact Us\nยฉ 2012 - 2026 Jobs.af | All Rights Reserved\nPowered by:\nNETLINKS Ltd",
    "details": {
      "Post Date": "Nov 04, 2025",
      "Closing Date": "Feb 04, 2026",
      "Reference": "TT-UI-02",
      "Number Of Vacancies": "1",
      "Salary Range": "Salary is negotiable",
      "Years Of Experience": "1 - 3 years",
      "Probation Period": "1 month",
      "Contract Type": "Long-term",
      "Contract Duration": "Not specified",
      "Contract Extensible": "Yes",
      "Minimum Education": "Bachelor's Degree",
      "Functional Area": "IT - Software",
      "Countries": "Afghanistan",
      "Provinces": "Kabul"
    },
    "scraped_at": "2026-01-21T05:00:22Z",
    "apply_emails": [
      "info@tectors.com"
    ],
    "apply_method": "email"
  },
  {
    "url": "https://jobs.af/jobs/it-and-designing-2GqAIcpZT",
    "title": "IT & Designing",
    "company": null,
    "location": "Kabul",
    "closing_date": "2026-02-07",
    "closing_date_raw": "Feb 07, 2026",
    "apply_url": null,
    "description": "๐\nComing Soon The Jobs.af Freelancer Portal\nConnect with top clients and freelancers across Afghanistan all in one place!\nStay Tuned\nJobs\nProcurement Opportunities\nCompanies\nFreelancers\nServices\nProcurement Opportunities\nTrainings\nScholarships\nLogin\nRegister\nIT & Designing\nInam Bahar Dairy and Beverages Production Company\nApply Now\nSee all jobs\nIT & Designing\nInam Bahar Dairy and Beverages Production Company ,\n                                        Kabul, Afghanistan\nApply Now\nBachelor's Degree\nKabul, Afghanistan\n(Kabul)\nFull Time\n1145\nAbout\n                                            Inam Bahar Dairy and Beverages Production Company\nWe take pride in ourselves on using only the best quality ingredients in our products. Our team of professional employees and food nutritionists ensure that only the best products are delivered to your table. All Inam bahar products are produced in accordance with the internationally recognized HACCP and ISO 9001 standards.\nInam Bahar Dairy and Beverages Production Company is one of the leading manufacturers and distributors of dairy products, long life UHT milk,ยjuicesย&ยCream.\nJob Summary\nWe are seeking a versatile and skilled professional to fill the dual role of Designer and IT Technician. This unique position combines creative design expertise with technical IT support to ensure seamless operations across both creative and technical domains. The ideal candidate will be responsible for creating visually appealing designs while also maintaining and troubleshooting IT systems to support the organizationโs goals.\nDuties & Responsibilities\nDevelop creative designs for digital and print media, including graphics, layouts, logos, and marketing materials.\nCollaborate with teams to conceptualize and execute design projects that align with brand guidelines.\nUse design software (e.g., Adobe Creative Suite, Canva, Figma) to produce high-quality visuals\nDevelop creative designs for digital and print media, including graphics, layouts, logos, and marketing materials.\nCollaborate with teams to conceptualize and execute design projects that align with brand guidelines.\nUse design software (e.g., Adobe Creative Suite, Canva, Figma) to produce high-quality visuals\nProvide technical support for hardware, software, and network systems.\nTroubleshoot and resolve IT issues, including system errors, network connectivity, and software malfunctions.\nInstall, configure, and maintain computer systems, servers, and other IT equipment.\nMonitor and maintain IT infrastructure to ensure optimal performance and security.\nAssist in the implementation of IT policies, procedures, and best practices.\nSet up and manage user accounts, permissions, and access controls.\nConduct regular system updates, backups, and data recovery processes.\nProvide training and support to staff on IT systems and tools\nJob Requirements\nProven experience in graphic design, multimedia design, or a related field.\nProficiency in design software such as Adobe Creative Suite (Photoshop, Illustrator, InDesign), Canva, or Figma.\nStrong portfolio showcasing creative design work.\nSolid understanding of IT systems, including hardware, software, and networking.\nExperience in troubleshooting and resolving technical issues.\nKnowledge of operating systems (Windows, macOS, Linux) and office productivity tools (Microsoft Office, Google Workspace).\nFamiliarity with cybersecurity principles and best practices.\nExcellent problem-solving skills and attention to detail.\nStrong communication and interpersonal skills to collaborate with diverse teams.\nAbility to manage time effectively and prioritize tasks in a fast-paced environment.\nA degree or certification in Graphic Design, IT, Computer Science, or a related field is preferred.\nSubmission Guideline\nInterested candidates are requested to submit their CVs and a two-page cover letter to\nAzizi@inambahar.com\n, clearly mentioning in the subject line the VA number for which they have applied. Alternatively, applications could be dropped at our office at Inam Bahar Dairy & Beverages Production Company, Pul-e-Charkhi Industrial Park, Kabul, Afghanistan.\nFunctional Area\nIT - Hardware\nIT - Software\nGraphic Designer\nCountries\nAfghanistan\nProvinces\nKabul\nSubmission Email\nAzizi@inambahar.com\nApply Now\nPost Date\nJan 07, 2026\nClosing Date\nFeb 07, 2026\nReference\n005\nNumber of Vacancies\n1\nSalary Range\nAs per company salary scale\nYears of Experience\n2 years\nProbation Period\n3 month\nContract Type\nPermanent\nContract Duration\n1 year\nContract Extensible\nYes\nMinimum Education\nBachelor's Degree\nGender\nMale\nRelated Jobs\nNETLINKS Plaza | Shahr-e-Naw,\nLane 3, Kabul, Afghanistan\nQuick Links\nAbout Us\nAdvertise with Us\nPrivacy Policy\nFor Companies\nPost a Job\nPost a Job\nPost a Job\nPost a Job\nPost RFP\nPost RFP\nPost RFP\nPost RFP\nPost Training\nPost Training\nPost Training\nPost Training\nFor Jobseekers\nBrowse Jobs\nBrowse Companies\nBuild Resume\nContact\ninfo@jobs.af\nContact Us\nยฉ 2012 - 2026 Jobs.af | All Rights Reserved\nPowered by:\nNETLINKS Ltd",
    "details": {
      "Post Date": "Jan 07, 2026",
      "Closing Date": "Feb 07, 2026",
      "Reference": "005",
      "Number Of Vacancies": "1",
      "Salary Range": "As per company salary scale",
      "Years Of Experience": "2 years",
      "Probation Period": "3 month",
      "Contract Type": "Permanent",
      "Contract Duration": "1 year",
      "Contract Extensible": "Yes",
      "Minimum Education": "Bachelor's Degree",
      "Functional Area": "IT - Hardware",
      "Countries": "Afghanistan",
      "Provinces": "Kabul"
    },
    "scraped_at": "2026-01-21T05:00:22Z",
    "apply_emails": [
      "azizi@inambahar.com"
    ],
    "apply_method": "email"
  },
  {
    "url": "https://jobs.af/jobs/sourcing-and-quotation-specialist",
    "title": "Sourcing & Quotation Specialist",
    "company": null,
    "location": "Kabul",
    "closing_date": "2026-02-11",
    "closing_date_raw": "Feb 11, 2026",
    "apply_url": null,
    "description": "๐\nComing Soon The Jobs.af Freelancer Portal\nConnect with top clients and freelancers across Afghanistan all in one place!\nStay Tuned\nJobs\nProcurement Opportunities\nCompanies\nFreelancers\nServices\nProcurement Opportunities\nTrainings\nScholarships\nLogin\nRegister\nSourcing & Quotation Specialist\nVASTGLOBE LOGISTICS LLC\nApply Now\nSee all jobs\nSourcing & Quotation Specialist\nVASTGLOBE LOGISTICS LLC,\n                                        Multi Location\nApply Now\nBachelor's Degree\nMulti Location\n(Kabul, Kapisa, Parwan, Wardak, Logar, Nangarhar, Laghman, Panjshir, Baghlan, Bamyan, Ghazni, Paktika, Paktya, Khost, Konar, Nooristan, Badakhshan, Takhar, Kunduz, Samangan, Balkh, Sar-e-Pul, Ghor, Daykundi, Urozgan, Zabul, Kandahar, Jawzjan, Faryab, Helmand, Badghis, Herat, Farah, Nimroz, North Zone, East Zone, West Zone, South Zone)\nFull Time\n2506\n153\nAbout\n                                            VASTGLOBE LOGISTICS LLC\nVastGlobe Logistics is a procurement-driven logistics company that specializes in finding, sourcing, and delivering a wide range of equipment, technology, and facility solutions large organizational customers worldwide. We work with trusted manufacturers and distributors, manage complex requirements, and coordinate delivery from suppliers to final destinations with a strong focus on documentation, quality, and on-time performance.\nJob Summary\nWe are looking for a\nhighly disciplined, detail-obsessed International Sourcing & Quotation Specialist\nto work\nnight shifts (not a 9โ5 job)\n.\nYour main job:\nFind opportunities\nFind the right items online\nCall and email vendors to get pricing and terms\nPrepare and submit professional quotations\nYou will be talking to different vendors every day, so you must be\nfluent in English\n(not โmedium Englishโ), a\nstrong critical thinker\n, and have a\nsolid IT background\n.\nDuties & Responsibilities\nMarket & Opportunity Research\nSearch online for new tenders/RFQs and product opportunities based on internal guidance.\nRead and understand basic technical descriptions, item specs, and scope documents.\nShortlist relevant opportunities and share them with management.\nVendor Sourcing & Communication\nFind manufacturers and authorized distributors online for required items.\nContact vendors by\nemail and phone\nduring your shift to:\nRequest quotes\nClarify specifications\nConfirm stock, lead time, and shipping options.\nFollow up consistently until you receive complete quotations.\nQuotation & Pricing Preparation\nCollect all vendor price offers and organize them in Excel/Sheets.\nCompare prices, lead times, and technical compliance.\nBuild clean, professional quotations using company templates.\nDouble-check all numbers, SKUs, quantities, and terms before submission.\nCoordination & Documentation\nKeep accurate records of all vendor communications and quotes.\nUpdate internal trackers and CRM tools with status, prices, and follow-ups.\nWork closely with management to finalize margins and submission prices.\nMake sure deadlines are never missed and everything is submitted on time.\nProfessionalism & Discipline\nBe\npunctual\n: login on time, attend calls on time, and meet every deadline.\nBe\nresponsive\n: reply quickly on email, WhatsApp, or internal tools during your shift.\nKeep a professional tone in all communication with vendors.\nJob Requirements\nMust-Have\nFluent English\nโ very good spoken and written English; able to speak clearly and confidently on the phone with international vendors.\nStrong IT Background\nโ comfortable with:\nOnline research, advanced Google search\nExcel/Google Sheets (formulas, filtering, sorting)\nEmail tools, cloud storage, and basic CRMs\nReading basic technical specs for IT, equipment, and machinery\nCritical Thinking Skills\nCan read a requirement and quickly understand what exactly is needed.\nCan tell if a quote is incomplete or risky and ask the right follow-up questions.\nNight-Shift Availability\nReady to work\nnight hours\n(not a typical 9โ5), aligned with client/vendor time zones.\nAttention to Detail\nVery careful with numbers, quantities, SKUs, and dates.\nDouble-checks work before sending anything out.\nDiscipline & Work Ethic\nHighly dedicated, reliable, and consistent.\nCan work independently without constant supervision.\nCommunication Skills\nComfortable making frequent phone calls to vendors.\nClear and polite communication style (no slang, no unprofessional language).\nNice-to-Have (Plus Points)\nPrevious experience in:\nProcurement, sourcing, or supply chain\nGovernment / B2B tenders and RFQs\nExperience using:\nOnline tender portals\nProject management tools (Notion, ClickUp, Trello, etc.)\nKnowledge of IT hardware, industrial equipment, or logistics.\nSubmission Guideline\nSubmit online in jobs.af, please make sure your cv is in pdf.\nFunctional Area\nSales/Marketing\nInformation Technology\nCountries\nAfghanistan\nProvinces\nKabul\nKapisa\nParwan\nWardak\nLogar\nNangarhar\nLaghman\nPanjshir\nBaghlan\nBamyan\nGhazni\nPaktika\nPaktya\nKhost\nKonar\nNooristan\nBadakhshan\nTakhar\nKunduz\nSamangan\nBalkh\nSar-e-Pul\nGhor\nDaykundi\nUrozgan\nZabul\nKandahar\nJawzjan\nFaryab\nHelmand\nBadghis\nHerat\nFarah\nNimroz\nNorth Zone\nEast Zone\nWest Zone\nSouth Zone\nApply Now\nPost Date\nDec 11, 2025\nClosing Date\nFeb 11, 2026\nReference\n12122025\nNumber of Vacancies\n3\nSalary Range\nAs per company salary scale\nYears of Experience\n1 year\nProbation Period\nNot Specified\nContract Type\nLong-term\nContract Duration\nNot specified\nContract Extensible\nNo\nMinimum Education\nBachelor's Degree\nGender\nAny\nRelated Jobs\nNETLINKS Plaza | Shahr-e-Naw,\nLane 3, Kabul, Afghanistan\nQuick Links\nAbout Us\nAdvertise with Us\nPrivacy Policy\nFor Companies\nPost a Job\nPost a Job\nPost a Job\nPost a Job\nPost RFP\nPost RFP\nPost RFP\nPost RFP\nPost Training\nPost Training\nPost Training\nPost Training\nFor Jobseekers\nBrowse Jobs\nBrowse Companies\nBuild Resume\nContact\ninfo@jobs.af\nContact Us\nยฉ 2012 - 2026 Jobs.af | All Rights Reserved\nPowered by:\nNETLINKS Ltd",
    "details": {
      "Post Date": "Dec 11, 2025",
      "Closing Date": "Feb 11, 2026",
      "Reference": "12122025",
      "Number Of Vacancies": "3",
      "Salary Range": "As per company salary scale",
      "Years Of Experience": "1 year",
      "Probation Period": "Not Specified",
      "Contract Type": "Long-term",
      "Contract Duration": "Not specified",
      "Contract Extensible": "No",
      "Minimum Education": "Bachelor's Degree",
      "Functional Area": "Sales/Marketing",
      "Countries": "Afghanistan",
      "Provinces": "Kabul"
    },
    "scraped_at": "2026-01-21T05:00:22Z",
    "apply_emails": [],
    "apply_method": "unknown"
  },
  {
    "url": "https://jobs.af/jobs/operation-manager-mRC71Yj8-",
    "title": "Operation Specialist",
    "company": null,
    "location": "Kabul",
    "closing_date": "2026-02-14",
    "closing_date_raw": "Feb 14, 2026",
    "apply_url": null,
    "description": "๐\nComing Soon The Jobs.af Freelancer Portal\nConnect with top clients and freelancers across Afghanistan all in one place!\nStay Tuned\nJobs\nProcurement Opportunities\nCompanies\nFreelancers\nServices\nProcurement Opportunities\nTrainings\nScholarships\nLogin\nRegister\nOperation Specialist\nCOMSIS SOLUTIONS LLC\nApply Now\nSee all jobs\nOperation Specialist\nCOMSIS SOLUTIONS LLC,\n                                        Multi Location\nApply Now\nBachelor's Degree\nMulti Location\n(Kabul, Kapisa, Parwan, Wardak, Logar, Nangarhar, Laghman, Panjshir, Baghlan, Bamyan, Ghazni, Paktika, Paktya, Khost, Konar, Nooristan, Badakhshan, Takhar, Kunduz, Samangan, Balkh, Sar-e-Pul, Ghor, Daykundi, Urozgan, Zabul, Kandahar, Jawzjan, Faryab, Helmand, Badghis, Herat, Farah, Nimroz, North Zone, East Zone, West Zone, South Zone)\nFull Time\n3917\n232\nAbout\n                                            COMSIS SOLUTIONS LLC\nAbout Us\nCOMSIS Solutions is a U.S.-based company located in Alexandria, Virginia. Since 2014, we have been providing advanced technology, cybersecurity, artificial intelligence, and logistics solutions. We work closely with U.S. Government agencies and ensure all our projects comply fully with FAR/DFARS regulations.\nOur focus is on quality, compliance, on-time delivery, and transparency. COMSIS offers a professional and collaborative work environment that values integrity, teamwork, and growth. We provide excellent opportunities for learning, career development, and innovation.\nJob Summary\nWe are seeking a highly organized and proactive Operation Manager to oversee and coordinate the daily operations of the company. The ideal candidate will ensure efficiency across all departments, maintain smooth workflows, and support the companyโs strategic goals.\nThis role requires strong leadership, decision-making, and communication skills. The Operation Specialist will work closely with department head (Operations & Finance Manager) to identify challenges, implement solutions, and improve overall performance.The position is remote, with occasional coordination with the U.S. office and field teams.\nDuties & Responsibilities\nOversee and manage the companyโs day-to-day operational activities.\nCoordinate between different departments to ensure smooth workflow and communication.\nDevelop and implement operational policies and procedures to improve efficiency.\nSupervise project progress and ensure tasks are completed on time and within scope.\nSupport procurement, logistics, and administrative functions when required.\nPrepare regular reports on performance, risks, and improvement areas.\nEnsure compliance with internal company standards and U.S. Government requirements.\nCollaborate with management to align operations with the companyโs strategic objectives.\nLead, motivate, and support team members to achieve individual and collective goals.\nJob Requirements\nBachelorโs degree in IT or Business Administration, Management, or a related field.\nMinimum 3โ5 years of experience in operations, management, or customer support.\nStrong leadership, communication, and organizational skills.\nExcellent command of the English language (both written and spoken).\nProven ability to manage teams and multiple projects simultaneously.\nHigh problem-solving ability and attention to detail.\nProficiency in Microsoft Office and familiarity with business productivity tools.\nStrong sense of responsibility, punctuality, and commitment to quality.\nAbility to work independently with minimal supervision\nSubmission Guideline\nFunctional Area\nData Management, IT, Administration, GIS, Warehouse, Network\nAdministration, leadership, legal, procurement and financial\nCountries\nAfghanistan\nProvinces\nKabul\nKapisa\nParwan\nWardak\nLogar\nNangarhar\nLaghman\nPanjshir\nBaghlan\nBamyan\nGhazni\nPaktika\nPaktya\nKhost\nKonar\nNooristan\nBadakhshan\nTakhar\nKunduz\nSamangan\nBalkh\nSar-e-Pul\nGhor\nDaykundi\nUrozgan\nZabul\nKandahar\nJawzjan\nFaryab\nHelmand\nBadghis\nHerat\nFarah\nNimroz\nNorth Zone\nEast Zone\nWest Zone\nSouth Zone\nApply Now\nPost Date\nNov 14, 2025\nClosing Date\nFeb 14, 2026\nReference\n06374519\nNumber of Vacancies\n1\nSalary Range\nAs per company salary scale\nYears of Experience\n3 years\nProbation Period\nNot Specified\nContract Type\nPermanent\nContract Duration\nNot specified\nContract Extensible\nNo\nMinimum Education\nBachelor's Degree\nGender\nAny\nRelated Jobs\nNETLINKS Plaza | Shahr-e-Naw,\nLane 3, Kabul, Afghanistan\nQuick Links\nAbout Us\nAdvertise with Us\nPrivacy Policy\nFor Companies\nPost a Job\nPost a Job\nPost a Job\nPost a Job\nPost RFP\nPost RFP\nPost RFP\nPost RFP\nPost Training\nPost Training\nPost Training\nPost Training\nFor Jobseekers\nBrowse Jobs\nBrowse Companies\nBuild Resume\nContact\ninfo@jobs.af\nContact Us\nยฉ 2012 - 2026 Jobs.af | All Rights Reserved\nPowered by:\nNETLINKS Ltd",
    "details": {
      "Post Date": "Nov 14, 2025",
      "Closing Date": "Feb 14, 2026",
      "Reference": "06374519",
      "Number Of Vacancies": "1",
      "Salary Range": "As per company salary scale",
      "Years Of Experience": "3 years",
      "Probation Period": "Not Specified",
      "Contract Type": "Permanent",
      "Contract Duration": "Not specified",
      "Contract Extensible": "No",
      "Minimum Education": "Bachelor's Degree",
      "Functional Area": "Data Management, IT, Administration, GIS, Warehouse, Network",
      "Countries": "Afghanistan",
      "Provinces": "Kabul"
    },
    "scraped_at": "2026-01-21T05:00:22Z",
    "apply_emails": [],
    "apply_method": "unknown"
  },
  {
    "url": "https://jobs.af/jobs/system-administrator-8kwvk2qFY",
    "title": "System Administrator",
    "company": null,
    "location": "Kabul",
    "closing_date": "2026-02-19",
    "closing_date_raw": "Feb 19, 2026",
    "apply_url": null,
    "description": "๐\nComing Soon The Jobs.af Freelancer Portal\nConnect with top clients and freelancers across Afghanistan all in one place!\nStay Tuned\nJobs\nProcurement Opportunities\nCompanies\nFreelancers\nServices\nProcurement Opportunities\nTrainings\nScholarships\nLogin\nRegister\nSystem Administrator\nAurum Afghanistan Financial Company\nApply Now\nSee all jobs\nSystem Administrator\nAurum Afghanistan Financial Company,\n                                        Kabul, Afghanistan\nApply Now\nBachelor's Degree\nKabul, Afghanistan\n(Kabul)\nFull Time\n730\nAbout\n                                            Aurum Afghanistan Financial Company\nAurum Afghanistan Financial Company is a full-fledged electronic money institution regulated by the central bank of Afghanistan operating under the license No. EMI101006. In addition to our regulatory license, we are also equipped with license No. 78895 from the Ministry of industry and commerce of Afghanistan. We possess advanced technology infrastructure which enables our clients to access financial services through their mobile phones securely, quickly and conveniently. Our services are available to everyone, particularly individuals who may not have access to traditional banking services. We offer significant opportunities for improving the efficiency of digital financial services by expanding access and lowering transaction costs. We provide a customized electronic payment solution. Aurum Afghanistan facilitates digital financial transactions, which includes services such as mobile wallet to mobile wallet, bank 02 to mobile wallet, mobile wallet to bank, electricity and other utilities bill payments, merchantโs payments, AfPay card services, payments through PoS machines and other prospective electronic payments services. AurumPay is a leading electronic money platform in Afghanistan, operating under the supervision of the Central Bank of Afghanistan. We empower individuals, merchants, and corporations with secure, convenient, and innovative financial solutions. Join our mission to bring digital payments to every corner of Afghanistan!\nJob Summary\nJob Summary\nAurumPay EMI is seeking an experienced\nSystem Administrator\nto manage, configure, and maintain our IT infrastructure. The ideal candidate will be responsible for Oracle servers, network security using Sophos firewalls, backup management, and data center setup and operations.\nDuties & Responsibilities\nKey Responsibilities\nConfigure, install, and maintain\nOracle servers and Oracle databases\nManage, configure, and monitor\nSophos Firewalls\nPerform regular\nbackups\nof:\nServers\nOracle databases\nFirewalls\nEnsure backup integrity, restoration testing, and disaster recovery readiness\nPlan, set up, and manage\ndata center infrastructure\nMonitor system performance, security, and availability\nTroubleshoot system, network, and database-related issues\nMaintain system documentation and operational procedures\nEnsure compliance with security and operational best practices\nJob Requirements\nRequired Skills & Experience\nProven experience as a\nSystem Administrator\nStrong hands-on experience with\nOracle Servers and Oracle Databases\nExperience configuring and managing\nSophos Firewalls\nSolid knowledge of\nbackup and recovery strategies\nExperience with\ndata center setup and operations\nUnderstanding of network security, system monitoring, and disaster recovery\nStrong problem-solving and documentation skills\nPreferred Qualifications\nCertifications related to Oracle, Linux/Windows Server\nExperience in financial services or EMI environments\nKnowledge of compliance and security standards\nSubmission Guideline\nInterested male and female candidates are encouraged to submit their CV to:\n๐ง\njobs@aurumaf.com\n.\n๐ Subject line:\nSystem Administrator โ AurumPay\nOnly shortlisted candidates will be contacted.\nFunctional Area\nSystem Integration\nSystem admin\ndatabase administration\nData Management, IT, Administration, GIS, Warehouse, Network\nCountries\nAfghanistan\nProvinces\nKabul\nSubmission Email\njobs@aurumaf.com\nApply Now\nPost Date\nJan 19, 2026\nClosing Date\nFeb 19, 2026\nReference\nAurum 057\nNumber of Vacancies\n1\nSalary Range\nAs per company salary scale\nYears of Experience\n3 years\nProbation Period\n3 month\nContract Type\nPermanent\nContract Duration\nNot specified\nContract Extensible\nYes\nMinimum Education\nBachelor's Degree\nGender\nAny\nRelated Jobs\nNETLINKS Plaza | Shahr-e-Naw,\nLane 3, Kabul, Afghanistan\nQuick Links\nAbout Us\nAdvertise with Us\nPrivacy Policy\nFor Companies\nPost a Job\nPost a Job\nPost a Job\nPost a Job\nPost RFP\nPost RFP\nPost RFP\nPost RFP\nPost Training\nPost Training\nPost Training\nPost Training\nFor Jobseekers\nBrowse Jobs\nBrowse Companies\nBuild Resume\nContact\ninfo@jobs.af\nContact Us\nยฉ 2012 - 2026 Jobs.af | All Rights Reserved\nPowered by:\nNETLINKS Ltd",
    "details": {
      "Post Date": "Jan 19, 2026",
      "Closing Date": "Feb 19, 2026",
      "Reference": "Aurum 057",
      "Number Of Vacancies": "1",
      "Salary Range": "As per company salary scale",
      "Years Of Experience": "3 years",
      "Probation Period": "3 month",
      "Contract Type": "Permanent",
      "Contract Duration": "Not specified",
      "Contract Extensible": "Yes",
      "Minimum Education": "Bachelor's Degree",
      "Functional Area": "System Integration",
      "Countries": "Afghanistan",
      "Provinces": "Kabul"
    },
    "scraped_at": "2026-01-21T05:00:22Z",
    "apply_emails": [
      "jobs@aurumaf.com"
    ],
    "apply_method": "email"
  },
  {
    "url": "https://jobs.af/jobs/information-comm-technology-associate-gs6-fixed-term-kandahar-19484-and-herat-19391",
    "title": "Information Comm. Technology Associate, GS6, Fixed Term, Kandahar (#19484) & Herat (#19391)",
    "company": null,
    "location": "Herat",
    "closing_date": "2026-02-22",
    "closing_date_raw": "Feb 22, 2026",
    "apply_url": null,
    "description": "๐\nComing Soon The Jobs.af Freelancer Portal\nConnect with top clients and freelancers across Afghanistan all in one place!\nStay Tuned\nJobs\nProcurement Opportunities\nCompanies\nFreelancers\nServices\nProcurement Opportunities\nTrainings\nScholarships\nLogin\nRegister\nInformation Comm. Technology Associate, GS6, Fixed Term, Kandahar (#19484) & Herat (#19391)\nUNICEF Afghanistan\nApply Now\nSee all jobs\nInformation Comm. Technology Associate, GS6, Fixed Term, Kandahar (#19484) & Herat (#19391)\nUNICEF Afghanistan,\n                                        Multi Location\nApply Now\nSecondary School\nMulti Location\n(Herat, Kandahar)\nFull Time\n2815\nAbout\n                                            UNICEF Afghanistan\nUNICEF works in some of the worldโs toughest places, to reach the worldโs most disadvantaged children. To save their lives. To defend their rights. To help them fulfill their potential.\n\nAcross 190 countries and territories, we work for every child, everywhere, every day, to build a better world for everyone.\n\nAnd we never give up.\nFor every child, Passion!\nJob Summary\nHow can you make a difference?\nPurpose for the job\n:ยICT/T4D Associates will assist programme teams in the identification, assessment and integration of ICT and digital innovation into UNICEF programming; strengthening internal capacity to support T4D related initiatives; identifying and engaging with key partners; building and maintaining business relationships; applying reusable and replicable technical buildings blocks; and maximizing the potential for the scale-up and sustainability of technology and digital innovation for UNICEF programming.\nDuties & Responsibilities\nSummary of Key function, accountabilities and related duties/tasks\n๏ปฟ\nGeneral ICT/T4D Office Support:\nT4D Portfolio Coordination\nMinimal ICT Administration\nIf you would like to know more about this position, please review the complete Job Description here:\nJD/TOR- ICT Associate G-6\nJob Requirements\nTo qualify as an advocate for every child you will haveโฆ\nMinimum requirements:\nEducation:\nCompletion of Secondary education is required, supplemented with formal training in Computer Science, Information Systems, Telecommunications, Engineering.\nWork Experience:\nA minimum of six years of practical work experience in information technology, requiring systematic methods of troubleshooting and problem solving is required.\nA bachelorโs degree from a recognized academic institution in a relevant field may replace three years of related work experience. A masterโs degree may replace an additional two years.\nITIL Foundation Certificate or equivalent customer support certification is an asset.\nExperience in providing assistance to users with IT products and services, and use of applications and diagnostic tools is required.\nPractical experience in providing technical and business Customer Support and Services is required.\nPractical experience and working knowledge of various computer platforms and applications are required.\nLanguage Requirements:\nFluency in English is required. Knowledge of another official UN language (Arabic, Chinese, French, Russian or Spanish) or a local language is an asset.\nDesirables:\nRelevant experience at country level, particularly in development, fragile settings and humanitarian contexts.\nSubmission Guideline\nRemarks:\nAs per Article 101, paragraph 3, of the Charter of the United Nations, the paramount consideration in the employment of the staff is the necessity of securing the highest standards of efficiency, competence, and integrity.\nUNICEF is committed to fostering an inclusive, representative, and welcoming workforce. For this position, eligible and suitable\nFemale\ncandidates\nare encouraged to apply.\nVacancy announcement is open to internal and external candidates. Priority will be given to staff in abolished posts and internal staff members.\nGovernment employees who are considered for employment with UNICEF are normally requiredยto resign from their government positions before taking up an assignment with UNICEF. UNICEF reserves the right to withdraw an offer of appointment, without compensation, if a visa or medical clearance is not obtained, or necessary inoculation requirements are not met, within a reasonable period for any reason.\nUNICEF does not charge a processing fee at any stage of its recruitment, selection, and hiring processes (i.e., application stage, interview stage, validation stage, or appointment and training). UNICEF will not ask for applicantsโ bank account information.\nHumanitarian action is a cross-cutting priority within UNICEFโs Strategic Plan. UNICEF is committed to stay and deliver in humanitarian contexts. Therefore, all staff, at all levels across all functional areas, can be called upon to be deployed to support humanitarian response, contributing to both strengthening resilience of communities and capacity of national authorities.\nAll UNICEF positions are advertised, and only shortlisted candidates will be contacted and advance to the next stage of the selection process. An internal candidate performing at the level of the post in the relevant functional area, or an internal/external candidate in the corresponding Talent Group, may be selected, if suitable for the post, without assessment of other candidates.\nCandidates who have applied previously do not need to reapply.\nAdditional information about working for UNICEF can be found\nhere\n.\nApplicants are requested to apply through the provided link;\nVacancies | UNICEF Careers\nApplications received via JOBS.AF online portal will not be given consideration.\nFunctional Area\nit\nIT - Hardware\nIT - Software\nCountries\nAfghanistan\nProvinces\nHerat\nKandahar\nApply Now\nPost Date\nJan 18, 2026\nClosing Date\nFeb 22, 2026\nReference\n589363\nNumber of Vacancies\n2\nSalary Range\nAs per company salary scale\nYears of Experience\n6 years\nProbation Period\nNot Specified\nContract Type\nFixed-term\nContract Duration\nNot specified\nContract Extensible\nYes\nMinimum Education\nSecondary School\nGender\nAny\nRelated Jobs\nNETLINKS Plaza | Shahr-e-Naw,\nLane 3, Kabul, Afghanistan\nQuick Links\nAbout Us\nAdvertise with Us\nPrivacy Policy\nFor Companies\nPost a Job\nPost a Job\nPost a Job\nPost a Job\nPost RFP\nPost RFP\nPost RFP\nPost RFP\nPost Training\nPost Training\nPost Training\nPost Training\nFor Jobseekers\nBrowse Jobs\nBrowse Companies\nBuild Resume\nContact\ninfo@jobs.af\nContact Us\nยฉ 2012 - 2026 Jobs.af | All Rights Reserved\nPowered by:\nNETLINKS Ltd",
    "details": {
      "Post Date": "Jan 18, 2026",
      "Closing Date": "Feb 22, 2026",
      "Reference": "589363",
      "Number Of Vacancies": "2",
      "Salary Range": "As per company salary scale",
      "Years Of Experience": "6 years",
      "Probation Period": "Not Specified",
      "Contract Type": "Fixed-term",
      "Contract Duration": "Not specified",
      "Contract Extensible": "Yes",
      "Minimum Education": "Secondary School",
      "Functional Area": "it",
      "Countries": "Afghanistan",
      "Provinces": "Herat"
    },
    "scraped_at": "2026-01-21T05:00:22Z",
    "apply_emails": [],
    "apply_method": "unknown"
  },
  {
    "url": "https://jobs.af/jobs/senior-full-stack-developer-permanent-position",
    "title": "Senior Full-Stack Developer (Permanent Position)",
    "company": null,
    "location": "Kabul",
    "closing_date": "2026-02-25",
    "closing_date_raw": "Feb 25, 2026",
    "apply_url": null,
    "description": "๐\nComing Soon The Jobs.af Freelancer Portal\nConnect with top clients and freelancers across Afghanistan all in one place!\nStay Tuned\nJobs\nProcurement Opportunities\nCompanies\nFreelancers\nServices\nProcurement Opportunities\nTrainings\nScholarships\nLogin\nRegister\nSenior Full-Stack Developer (Permanent Position)\nPeshtaz Academy\nApply Now\nSee all jobs\nSenior Full-Stack Developer (Permanent Position)\nPeshtaz Academy,\n                                        Multi Location\nApply Now\nBachelor's Degree\nMulti Location\n(Kabul, Kapisa, Parwan, Wardak, Logar, Nangarhar, Laghman, Panjshir, Baghlan, Bamyan, Ghazni, Paktika, Paktya, Khost, Konar, Nooristan, Badakhshan, Takhar, Kunduz, Samangan, Balkh, Sar-e-Pul, Ghor, Daykundi, Urozgan, Zabul, Kandahar, Jawzjan, Faryab, Helmand, Badghis, Herat, Farah, Nimroz, North Zone, East Zone, West Zone, South Zone)\nFull Time\n2499\nAbout\n                                            Peshtaz Academy\nLinkshops is a fast-growing multi-vendor marketplace platform delivering modern solutions across\ne-commerce, delivery, and on-demand services\n. Our products include high-performance\nAndroid, iOS, and web applications\n, built to scale and serve thousands of users. We are expanding our technical team and are looking for a\nhighly skilled Full-Stack Developer\nwho is passionate about building reliable, scalable, and user-focused digital products.\nJob Summary\nWe are seeking a\nProfessional Full-Stack Developer\nto join our core development team on a\npermanent basis\n. You will play a critical role in designing, developing, maintaining, and optimizing our Linkshops applications across web and mobile platforms. This role is ideal for someone who thrives in a fast-paced environment and takes ownership of products from concept to deployment.\nDuties & Responsibilities\nKey Responsibilities\nDesign, develop, and maintain\nscalable full-stack applications\nfor web and mobile\nWork with\nReact and Flutter\nto build modern, high-performance user interfaces\nDevelop and maintain backend services using\nLaravel\nManage databases using\nMySQL\nand\nFirebase\nIntegrate\nRESTful APIs\n, third-party services, and internal systems\nImplement and maintain\npayment gateway integrations\nWork with\nGoogle Maps APIs\nfor location-based services\nBuild, test, and deploy applications for\nAndroid and iOS\nEnsure application security, performance optimization, and code quality\nCollaborate closely with product managers, designers, and QA teams\nParticipate in architecture decisions and technical planning\nJob Requirements\nRequired Skills & Qualifications\nProven experience as a\nFull-Stack Developer\nStrong expertise in:\nReact\nFlutter\nLaravel\nFirebase\nMySQL\nExperience with\nAndroid and iOS app development\nSolid knowledge of\nGoogle APIs\n, especially\nGoogle Maps\nHands-on experience integrating\npayment gateways\nStrong understanding of\nAPIs, authentication, and data security\nClean coding practices and experience with version control (Git)\nAbility to work independently and as part of a team\nStrong problem-solving and communication skills\nNice to Have\nExperience with large-scale marketplace or delivery platforms\nDevOps or cloud deployment experience\nPerformance optimization and scalability experience\nPrior work on multi-vendor or fintech applications\nWhat We Offer\nPermanent, long-term position\nCompetitive salary based on experience\nOpportunity to work on a\nlarge, real-world production platform\nFlexible working environment (remote/hybrid)\nProfessional growth and leadership opportunities\nA collaborative, innovative, and respectful team culture\nWhy Join Linkshops?\nAt Linkshops, you wonโt just write code โ youโll help shape a platform used by real businesses and customers every day. If you are a motivated, skilled developer looking for\nstability, impact, and long-term growth\n, we would love to hear from you.\nSubmission Guideline\nInterested candidates are encouraged to submit their applications\nas soon as possible\n. Applications will be reviewed on a rolling basis until the position is filled. Early submission is highly recommended.\ninfo@golinkshops.com\ninfo@peshtazacademy.com\n+93788124805\n+19799432798\nFunctional Area\nIT - Hardware\nIT - Software\nProgramme\nSoftware engineering\nsoftware development\nWeb Designing\nWeb Development\nDatabase Development\nsoftware analysis\nsoftware development\nProgramming\nWebsite Designing\nWeb Developer\nWeb Designer\nCountries\nAfghanistan\nProvinces\nKabul\nKapisa\nParwan\nWardak\nLogar\nNangarhar\nLaghman\nPanjshir\nBaghlan\nBamyan\nGhazni\nPaktika\nPaktya\nKhost\nKonar\nNooristan\nBadakhshan\nTakhar\nKunduz\nSamangan\nBalkh\nSar-e-Pul\nGhor\nDaykundi\nUrozgan\nZabul\nKandahar\nJawzjan\nFaryab\nHelmand\nBadghis\nHerat\nFarah\nNimroz\nNorth Zone\nEast Zone\nWest Zone\nSouth Zone\nApply Now\nPost Date\nDec 25, 2025\nClosing Date\nFeb 25, 2026\nReference\nLinksGRP2026\nNumber of Vacancies\n4\nSalary Range\nSalary is negotiable\nYears of Experience\n2 - 5 years\nProbation Period\nNot Specified\nContract Type\nPermanent\nContract Duration\nNot specified\nContract Extensible\nYes\nMinimum Education\nBachelor's Degree\nGender\nAny\nRelated Jobs\nNETLINKS Plaza | Shahr-e-Naw,\nLane 3, Kabul, Afghanistan\nQuick Links\nAbout Us\nAdvertise with Us\nPrivacy Policy\nFor Companies\nPost a Job\nPost a Job\nPost a Job\nPost a Job\nPost RFP\nPost RFP\nPost RFP\nPost RFP\nPost Training\nPost Training\nPost Training\nPost Training\nFor Jobseekers\nBrowse Jobs\nBrowse Companies\nBuild Resume\nContact\ninfo@jobs.af\nContact Us\nยฉ 2012 - 2026 Jobs.af | All Rights Reserved\nPowered by:\nNETLINKS Ltd",
    "details": {
      "Post Date": "Dec 25, 2025",
      "Closing Date": "Feb 25, 2026",
      "Reference": "LinksGRP2026",
      "Number Of Vacancies": "4",
      "Salary Range": "Salary is negotiable",
      "Years Of Experience": "2 - 5 years",
      "Probation Period": "Not Specified",
      "Contract Type": "Permanent",
      "Contract Duration": "Not specified",
      "Contract Extensible": "Yes",
      "Minimum Education": "Bachelor's Degree",
      "Functional Area": "IT - Hardware",
      "Countries": "Afghanistan",
      "Provinces": "Kabul"
    },
    "scraped_at": "2026-01-21T05:00:22Z",
    "apply_emails": [
      "info@golinkshops.com",
      "info@peshtazacademy.com"
    ],
    "apply_method": "email"
  },
  {
    "url": "https://jobs.af/jobs/procurement-and-operations-specialist-remote-suEhktHso",
    "title": "Procurement & Operations Specialist (Remote)",
    "company": null,
    "location": "Kabul",
    "closing_date": "2026-03-06",
    "closing_date_raw": "Mar 06, 2026",
    "apply_url": null,
    "description": "๐\nComing Soon The Jobs.af Freelancer Portal\nConnect with top clients and freelancers across Afghanistan all in one place!\nStay Tuned\nJobs\nProcurement Opportunities\nCompanies\nFreelancers\nServices\nProcurement Opportunities\nTrainings\nScholarships\nLogin\nRegister\nProcurement & Operations Specialist (Remote)\nCOMSIS SOLUTIONS LLC\nApply Now\nSee all jobs\nProcurement & Operations Specialist (Remote)\nCOMSIS SOLUTIONS LLC,\n                                        Multi Location\nApply Now\nBachelor's Degree\nMulti Location\n(Kabul, Kapisa, Parwan, Wardak, Logar, Nangarhar, Laghman, Panjshir, Baghlan, Bamyan, Ghazni, Paktika, Paktya, Khost, Konar, Nooristan, Badakhshan, Takhar, Kunduz, Samangan, Balkh, Sar-e-Pul, Ghor, Daykundi, Urozgan, Zabul, Kandahar, Jawzjan, Faryab, Helmand, Badghis, Herat, Farah, Nimroz, North Zone, East Zone, West Zone, South Zone)\nFull Time\n5855\n360\nAbout\n                                            COMSIS SOLUTIONS LLC\nAbout Us\nCOMSIS Solutions is a U.S.-based company located in Alexandria, Virginia. Since 2014, we have been providing advanced technology, cybersecurity, artificial intelligence, and logistics solutions. We work with U.S. Government agencies and deliver all our projects in full compliance with FAR/DFARS regulations. Our focus is on quality, compliance, on-time delivery, and transparency. COMSIS offers a professional and collaborative work environment with strong opportunities for growth and learning.\nJob Summary\nWe are seeking a highly motivated and independent Procurement & Operations Specialist to manage th e end-to-end procurement process for cur company. This role involves sourcing, negotiating, purchasing. vendor management, and resolving issues as they arise. You will work remotely and independently, often on-demand, to support different contracts and global supply chain need.\nDuties & Responsibilities\nHandle the complete procurement lifecycle from sourcing to purchasing.\nNegotiate pricing, terms, and lead times with vendors and supplier.\nRequest and collect quotations from vendors via phone and email.\nPlace purchase orders and track deliveries.\nPrepare and manage invoices, documentation, and compliance paperwork.\nResolve issues with vendors, logistics, or product availability.\nEnsure timely procurement based on project deadlines.\nPerform multitasking and versatile duties to support operations as needed.\nCommunicate directly with the management team regarding procurement status.\nMaintain organized records of purchases, contracts, and supplier communications.\nJob Requirements\nProven experience in procurement, purchasing, or vendor management.\nStrong communication skills, both written and verbal.\nAbility to negotiate effectively and close deals.\nMust be highly independent, proactive, and able to work without supervision.\nFlexible availability (not fixed to standard 9-5 hours).\nReliable laptop/computer and stable high-speed internet connection.\nStrong attention to detail and organizational skills.\nFast learner with a problem-solving mindset.\nComfortable with remote work and taking full responsibility for tasks.\nFluent in English.\nKnowledge and skills in IT to work with digital systems and toolsz\nSubmission Guideline\nFunctional Area\nIT - Software\nCountries\nAfghanistan\nProvinces\nKabul\nKapisa\nParwan\nWardak\nLogar\nNangarhar\nLaghman\nPanjshir\nBaghlan\nBamyan\nGhazni\nPaktika\nPaktya\nKhost\nKonar\nNooristan\nBadakhshan\nTakhar\nKunduz\nSamangan\nBalkh\nSar-e-Pul\nGhor\nDaykundi\nUrozgan\nZabul\nKandahar\nJawzjan\nFaryab\nHelmand\nBadghis\nHerat\nFarah\nNimroz\nNorth Zone\nEast Zone\nWest Zone\nSouth Zone\nApply Now\nPost Date\nNov 06, 2025\nClosing Date\nMar 06, 2026\nReference\n06564380\nNumber of Vacancies\n3\nSalary Range\nAs per company salary scale\nYears of Experience\n1 year\nProbation Period\nNot Specified\nContract Type\nPermanent\nContract Duration\nNot specified\nContract Extensible\nNo\nMinimum Education\nBachelor's Degree\nGender\nAny\nRelated Jobs\nNETLINKS Plaza | Shahr-e-Naw,\nLane 3, Kabul, Afghanistan\nQuick Links\nAbout Us\nAdvertise with Us\nPrivacy Policy\nFor Companies\nPost a Job\nPost a Job\nPost a Job\nPost a Job\nPost RFP\nPost RFP\nPost RFP\nPost RFP\nPost Training\nPost Training\nPost Training\nPost Training\nFor Jobseekers\nBrowse Jobs\nBrowse Companies\nBuild Resume\nContact\ninfo@jobs.af\nContact Us\nยฉ 2012 - 2026 Jobs.af | All Rights Reserved\nPowered by:\nNETLINKS Ltd",
    "details": {
      "Post Date": "Nov 06, 2025",
      "Closing Date": "Mar 06, 2026",
      "Reference": "06564380",
      "Number Of Vacancies": "3",
      "Salary Range": "As per company salary scale",
      "Years Of Experience": "1 year",
      "Probation Period": "Not Specified",
      "Contract Type": "Permanent",
      "Contract Duration": "Not specified",
      "Contract Extensible": "No",
      "Minimum Education": "Bachelor's Degree",
      "Functional Area": "IT - Software",
      "Countries": "Afghanistan",
      "Provinces": "Kabul"
    },
    "scraped_at": "2026-01-21T05:00:22Z",
    "apply_emails": [],
    "apply_method": "unknown"
  },
  {
    "url": "https://jobs.af/jobs/database-developer-J03M_67b9",
    "title": "Database Developer",
    "company": null,
    "location": "Kabul",
    "closing_date": "2026-06-30",
    "closing_date_raw": "Jun 30, 2026",
    "apply_url": null,
    "description": "๐\nComing Soon The Jobs.af Freelancer Portal\nConnect with top clients and freelancers across Afghanistan all in one place!\nStay Tuned\nJobs\nProcurement Opportunities\nCompanies\nFreelancers\nServices\nProcurement Opportunities\nTrainings\nScholarships\nLogin\nRegister\nDatabase Developer\nHushmand Shahar Information Technology Service Company\nApply Now\nSee all jobs\nDatabase Developer\nHushmand Shahar Information Technology Service Company,\n                                        Kabul, Afghanistan\nApply Now\nBachelor's Degree\nKabul, Afghanistan\n(Kabul)\nFull Time\n9700\nAbout\n                                            Hushmand Shahar Information Technology Service Company\nHushmand Shahar Information Technology Service Company is a trusted provider of\nIT solutions, software development, and digital transformation services\nin Afghanistan. Our mission is to empower businesses with innovative technology solutions that enhance efficiency, security, and scalability.\nWith a team of experienced professionals, we specialize in\ncustom software development, enterprise solutions, cloud computing, and IT infrastructure services\n. We are committed to delivering cutting-edge solutions that help organizations stay competitive in the digital world.\nOur Services\nSoftware Development:\nCustom web and mobile applications using Laravel, React, Next.js, and more.\nEnterprise IT Solutions:\nERP, MIS, CRM, and custom business software.\nIT Consultancy:\nDigital strategy, system integration, and cybersecurity.\nCloud Solutions:\nAWS, DigitalOcean, Laravel Forge, and cloud-based deployments.\nE-Commerce Development:\nScalable online store solutions with secure payment gateways.\nWhy Choose Us?\nExpert Team:\nSkilled professionals with expertise in software engineering and IT solutions.\nQuality & Security:\nIndustry-standard practices ensuring high-performance and secure applications.\nClient-Focused Approach:\nTailored solutions that align with business needs.\nReliable Support:\nOngoing maintenance and technical support for seamless operations.\nOur Vision\nTo be a leading technology service provider in Afghanistan, driving digital innovation and business growth.\nOur Mission\nTo develop reliable, scalable, and high-performance technology solutions that help businesses streamline their operations and achieve success.\nJob Summary\nWe are seeking a\nhighly skilled Laravel Developer\nto join our dynamic team at\nHushmand Shahar Information Technology Service Company\n. The ideal candidate will have strong expertise in\nLaravel, PHP, and modern web development technologies\nand will be responsible for designing, developing, and maintaining robust, scalable, and high-performance web applications.\nThis role requires a deep understanding of\nMVC architecture, database management, and front-end technologies\n. As a Laravel Developer, you will collaborate with cross-functional teams to\nbuild secure applications, integrate APIs, optimize performance\n, and troubleshoot technical challenges.\nDuties & Responsibilities\nDevelop, maintain, and enhance web applications using\nLaravel and PHP\n.\nDesign and implement efficient\ndatabase architectures\nusing MySQL, PostgreSQL, or other relational databases.\nWrite clean, well-documented, and scalable\nRESTful APIs\nand integrate third-party services.\nOptimize application\nperformance, security, and scalability\n.\nImplement authentication and authorization mechanisms such as\nJWT, OAuth, or Laravel Sanctum\n.\nWork with front-end developers to integrate\nVue.js, React, or Alpine.js\ninto Laravel applications.\nTroubleshoot, debug, and resolve software defects and application errors.\nUtilize\nGit version control\nand follow best practices in software development workflows.\nImplement\nautomated testing (PHPUnit, Pest) and CI/CD pipelines\nfor seamless deployment.\nMaintain clear\ntechnical documentation\nand follow agile development methodologies.\nJob Requirements\nProven experience (2+ years) as a Laravel Developer\nor in a similar role.\nProficiency in\nPHP, Laravel, MySQL, and object-oriented programming (OOP)\n.\nStrong knowledge of\nMVC architecture\nand best coding practices.\nExperience in\nfront-end technologies\n(HTML5, CSS3, JavaScript, Vue.js, React, or Alpine.js).\nFamiliarity with\nLaravel Blade templating\nand Livewire (preferred but not mandatory).\nHands-on experience with\nRESTful API development and third-party API integration\n.\nUnderstanding of\nsecurity best practices\n, including data encryption and secure authentication.\nExperience with\nqueues, cron jobs, and background task processing in Laravel\n.\nKnowledge of\nGit, GitHub, Bitbucket, or GitLab for version control\n.\nStrong debugging and troubleshooting skills.\nFamiliarity with\nAgile development methodologies (Scrum, Kanban)\n.\nExcellent problem-solving skills and ability to work independently or within a team.\nPreferred Qualifications:\nExperience with\nFilamentPHP, Inertia.js, or Laravel Nova\n.\nFamiliarity with\nDocker, Kubernetes, or cloud deployment (AWS, DigitalOcean, Laravel Forge)\n.\nHands-on experience with\nNoSQL databases (MongoDB, Firebase, etc.)\n.\nSubmission Guideline\nVacancy Number:\nPlease mention the vacancy number in the\nemail subject line\n.\nCV & Previous Projects:\nApplicants must attach their\nCV\nand a list with links of\nprevious projects\nthey have worked on.\nEmail Submission:\nSend your application to\nhr@hushmandshahar.com\nbefore the deadline.\nFunctional Area\nIT - Software\nSofware developer and data base development\nSoftware developer\nCountries\nAfghanistan\nProvinces\nKabul\nSubmission Email\nhr@hushmandshahar.com\nApply Now\nPost Date\nFeb 17, 2025\nClosing Date\nJun 30, 2026\nReference\n#dev-01\nNumber of Vacancies\n5\nSalary Range\nAs per company salary scale\nYears of Experience\n5 years\nProbation Period\n1 week\nContract Type\nPermanent\nContract Duration\n1 year\nContract Extensible\nYes\nMinimum Education\nBachelor's Degree\nGender\nAny\nRelated Jobs\nNETLINKS Plaza | Shahr-e-Naw,\nLane 3, Kabul, Afghanistan\nQuick Links\nAbout Us\nAdvertise with Us\nPrivacy Policy\nFor Companies\nPost a Job\nPost a Job\nPost a Job\nPost a Job\nPost RFP\nPost RFP\nPost RFP\nPost RFP\nPost Training\nPost Training\nPost Training\nPost Training\nFor Jobseekers\nBrowse Jobs\nBrowse Companies\nBuild Resume\nContact\ninfo@jobs.af\nContact Us\nยฉ 2012 - 2026 Jobs.af | All Rights Reserved\nPowered by:\nNETLINKS Ltd",
    "details": {
      "Post Date": "Feb 17, 2025",
      "Closing Date": "Jun 30, 2026",
      "Reference": "#dev-01",
      "Number Of Vacancies": "5",
      "Salary Range": "As per company salary scale",
      "Years Of Experience": "5 years",
      "Probation Period": "1 week",
      "Contract Type": "Permanent",
      "Contract Duration": "1 year",
      "Contract Extensible": "Yes",
      "Minimum Education": "Bachelor's Degree",
      "Functional Area": "IT - Software",
      "Countries": "Afghanistan",
      "Provinces": "Kabul"
    },
    "scraped_at": "2026-01-21T05:00:22Z",
    "apply_emails": [
      "hr@hushmandshahar.com"
    ],
    "apply_method": "email"
  },
  {
    "url": "https://jobs.af/jobs/customer-service-agent-english-translator",
    "title": "Customer Service Agent - English Translator.",
    "company": null,
    "location": "Kabul",
    "closing_date": "2026-12-17",
    "closing_date_raw": "Dec 17, 2026",
    "apply_url": null,
    "description": "๐\nComing Soon The Jobs.af Freelancer Portal\nConnect with top clients and freelancers across Afghanistan all in one place!\nStay Tuned\nJobs\nProcurement Opportunities\nCompanies\nFreelancers\nServices\nProcurement Opportunities\nTrainings\nScholarships\nLogin\nRegister\nCustomer Service Agent - English Translator.\nSpeenkai\nApply Now\nSee all jobs\nCustomer Service Agent - English Translator.\nSpeenkai,\n                                        Kabul, Afghanistan\nApply Now\nHigh School\nKabul, Afghanistan\n(Kabul)\nFull Time\n5797\nAbout\n                                            Speenkai\nSpeenkai is Afghanistan's first and leading BPO (Business Process Outsourcing) service company, specializing in providing comprehensive administrative and technical support to Afghan-owned companies abroad. Our mission is to empower Afghan entrepreneurs and businesses operating internationally by offering high-quality, reliable support services from our base in Afghanistan. With a team of skilled professionals, we help Afghan companies streamline their operations, enhance efficiency, and achieve success.\nJob Summary\nNight-Shift Job\nAre you a motivated, detail-oriented professional fluent in English, and ready to grow in a dynamic environment? Speenkai, Afghanistan's first BPO service company, and\nBay Master Appliance Services LLC\nare looking to hire experienced individuals to join our\nfull-time night shift team\nas\nDispatchers/Customer Service Representatives\n.\nIn this role, you will take inbound calls, set appointments for customers, and dispatch technicians efficiently. The ideal candidate will take charge of daily operations, including planning, scheduling, and managing the tech force.\nPLEASE DO NOT APPLY IF YOU ARE NOT FLUENT IN ENGLISH\nto save yourself time.\nIf you have strong communication skills, thrive under pressure, and are passionate about delivering exceptional support, we want to hear from you!\nDuties & Responsibilities\nDuties & Responsibilities\n1.ยยReceive incoming calls from clients and setup service appointments.\n2.ยยReceive incoming calls from technicians throughout the shift.\n3.ยยKeep track of daily schedule and job status throughout work schedule.\n4.ยยRespond to open email requests and inquiries via email\n5.ยยAbility to enter tickets into the CRM\nJob Requirements\nJob Requirements\nยทยยยยยยยยFluent in English and must possess excellent verbal and written skills.\nโขยยยยยยยยMotivated self-starter\nโขยยยยยยยยOffice work experience\nโขยยยยยยยยAbility to multitask in fast paced environment is crucial.\nโขยยยยยยยยCapable of typing 45+ words per minute necessary\nโขยยยยยยยยCustomer Service skills and Conflict Resolution skills.\nโขยยยยยยยยTelemarketing experience is a plus\nโขยยยยยยยยMicrosoft Office Products\nSubmission Guideline\nThis link will redirect you to an online assessment. There a video question at the end. If you don not answer, you application will not be accepted.\nThe assessment is around 50 minutes long. Find a quiet place and stable internet. Answers from Ai and cheating cold be identified and will ruin your chances to be considered.\nClick on the link below, enter your email, and the assessment will be sent to your email to start.\nGood Luck.\nhttps://app.testtrick.com/public-invitation/e885f319cea28b209c18006ed8106143-56e8c05f9ca1d33d4a0c544fc4c87568\nFunctional Area\nSales/Marketing\nManagement\nAdministrative\nTranslation\nCommunication\nOperation\nData Collection\nData Entry\nOPERATIONS\nCountries\nAfghanistan\nProvinces\nKabul\nApply Now\nPost Date\nDec 17, 2025\nClosing Date\nDec 17, 2026\nReference\n1014\nNumber of Vacancies\n15\nSalary Range\nAs per company salary scale\nYears of Experience\n2 years\nProbation Period\nNot Specified\nContract Type\nPermanent\nContract Duration\nNot specified\nContract Extensible\nYes\nMinimum Education\nHigh School\nGender\nMale\nRelated Jobs\nNETLINKS Plaza | Shahr-e-Naw,\nLane 3, Kabul, Afghanistan\nQuick Links\nAbout Us\nAdvertise with Us\nPrivacy Policy\nFor Companies\nPost a Job\nPost a Job\nPost a Job\nPost a Job\nPost RFP\nPost RFP\nPost RFP\nPost RFP\nPost Training\nPost Training\nPost Training\nPost Training\nFor Jobseekers\nBrowse Jobs\nBrowse Companies\nBuild Resume\nContact\ninfo@jobs.af\nContact Us\nยฉ 2012 - 2026 Jobs.af | All Rights Reserved\nPowered by:\nNETLINKS Ltd",
    "details": {
      "Post Date": "Dec 17, 2025",
      "Closing Date": "Dec 17, 2026",
      "Reference": "1014",
      "Number Of Vacancies": "15",
      "Salary Range": "As per company salary scale",
      "Years Of Experience": "2 years",
      "Probation Period": "Not Specified",
      "Contract Type": "Permanent",
      "Contract Duration": "Not specified",
      "Contract Extensible": "Yes",
      "Minimum Education": "High School",
      "https": "//app.testtrick.com/public-invitation/e885f319cea28b209c18006ed8106143-56e8c05f9ca1d33d4a0c544fc4c87568",
      "Functional Area": "Sales/Marketing",
      "Countries": "Afghanistan",
      "Provinces": "Kabul"
    },
    "scraped_at": "2026-01-21T05:00:22Z",
    "apply_emails": [],
    "apply_method": "unknown"
  },
  {
    "url": "https://jobs.af/jobs/undefined",
    "title": null,
    "company": null,
    "location": null,
    "closing_date": null,
    "closing_date_raw": null,
    "apply_url": null,
    "description": "๐\nComing Soon The Jobs.af Freelancer Portal\nConnect with top clients and freelancers across Afghanistan all in one place!\nStay Tuned\nJobs\nProcurement Opportunities\nCompanies\nFreelancers\nServices\nProcurement Opportunities\nTrainings\nScholarships\nLogin\nRegister\n404\nPage Not found\nThis page does not exist or removed we\nsuggest you back home.\nBack Home",
    "details": {},
    "scraped_at": "2026-01-21T05:00:22Z",
    "apply_emails": [],
    "apply_method": "unknown"
  }
]