{
  "generated_at": "2026-01-21T09:34:09.604153",
  "today": "2026-01-21",
  "total_jobs": 36,
  "new_count": 1,
  "expiring_today_count": 2,
  "expiring_soon_count": 3,
  "new_jobs": [
    {
      "url": "https://jobs.af/jobs/software-development-assistant-react-developer",
      "title": "Software Development Assistant (React Developer)",
      "company": null,
      "location": "Kabul",
      "closing_date": "2026-02-03",
      "closing_date_raw": "Feb 03, 2026",
      "apply_url": null,
      "description": "ğŸš€\nComing Soon The Jobs.af Freelancer Portal\nConnect with top clients and freelancers across Afghanistan all in one place!\nStay Tuned\nJobs\nProcurement Opportunities\nCompanies\nFreelancers\nServices\nProcurement Opportunities\nTrainings\nScholarships\nLogin\nRegister\nSoftware Development Assistant (React Developer)\nPARSA Technologies\nApply Now\nSee all jobs\nSoftware Development Assistant (React Developer)\nPARSA Technologies,\n                                        Kabul, Afghanistan\nApply Now\nBachelor's Degree\nKabul, Afghanistan\n(Kabul)\nFull Time\n214\nAbout\n                                            PARSA Technologies\nFor almost a decade, PARSA relentless innovation, quality of products, responsible management, and dedication made it the partner of choice for many of the Afghanâ€™s most trusted brands.\nPARSA in the local Afghanistan Market is one of the trusted partners in domains of web application development, mobile application development, value-added services, HR MIS, Finance Management System, SMS Platform, and e-commerce. We are glad to demonstrate through our work that we have the capabilities, people, processes, technology, and the desire to be the strategic technology partner of choice for many Afghan entities, including government departments, the private sector, and non-government organizations (NGOs).\nPARSAâ€™s primary objective is to develop an environment of fairness, honesty, integrity, and courtesy towards our clients, employees, vendors, and society at large. We areÂ committed to our customers & partners and have a passion for technology.\nJob Summary\nThe Software Development Assistant will work under the overall guidance of the ChiefÂ Executive Officer and under the direct supervision of the Software Development Team Head.\nDuties & Responsibilities\nHe/she will work in close collaboration with the Software Development Department andÂ will fulfill the following duties and responsibilities:\nDesigning and Development of web and mobile applications.\nConducting feasibility studies for software projects.\nCompleting tasks such as coding, testing, and debugging.\nWriting advanced programming code.\nManaging project timelines and tasks.\nWork in close partnership with operation, business, and management departments\nV. Competencies and Critical Success Factors\nFunctional Competencies\nKnowledge Management and Learning\nShares knowledge and experience;\nActively works towards continuing personal learning and development andÂ applies newly acquired skills.\nDevelopment and Operational Effectiveness.\nProficiency with React\nProficiency in HTML, CSS, Bootstrap, Javascript + ES6, Sass, Tailwind CSS\nExcellent understanding of React-redux, Webpack, REST API\nGood knowledge of version control system like git\nGood knowledge of UI and UX and Proficiency with Figma\nAbility to perform a broad range of parallel specialized activities\nExcellent analytical and problem-solving skills.\nExcellent organization and time management skills.\nExcellent written and verbal communication skills.\nDemonstrated ability to lead others.\nLeadership and Self-Management\nFocuses on result for the client and responds positively to feedback;\nAbility to team work.\nConsistently approaches work with energy and a positive, constructive attitude; Demonstrates openness to change and ability to manage complexity.\nAbility to handle daily tasks mainly in the field.\nAbility to establish good working relations with a range of stakeholders.\nAbility to coach, mentor, and develop people skills.\nAbility to focus on results\nConsistently approaches work with energy in a positive and constructive attitude.\nJob Requirements\nBachelor's in Computer Science, Software Engineering, or equivalent subject\nAt least 3+ years of experience in the above-mentioned field\nSubmission Guideline\nInterested individual submits their Personal CV indicating all past experience from similarÂ job, as well as the contact details (email and telephone number) of the Candidate to: hr@parsa.technology\nNote:\napplicants are instructed to\nwrite the position title in the subject line\nof their email when submitting their application.\nFunctional Area\nComputer Science\nSoftware engineering\nCountries\nAfghanistan\nProvinces\nKabul\nSubmission Email\nhr@parsa.technology\nApply Now\nPost Date\nJan 20, 2026\nClosing Date\nFeb 03, 2026\nReference\nPT#000265\nNumber of Vacancies\n1\nSalary Range\nSalary is negotiable\nYears of Experience\n3 years\nProbation Period\n3 month\nContract Type\nPermanent\nContract Duration\n1 year\nContract Extensible\nYes\nMinimum Education\nBachelor's Degree\nGender\nMale\nRelated Jobs\nNETLINKS Plaza | Shahr-e-Naw,\nLane 3, Kabul, Afghanistan\nQuick Links\nAbout Us\nAdvertise with Us\nPrivacy Policy\nFor Companies\nPost a Job\nPost a Job\nPost a Job\nPost a Job\nPost RFP\nPost RFP\nPost RFP\nPost RFP\nPost Training\nPost Training\nPost Training\nPost Training\nFor Jobseekers\nBrowse Jobs\nBrowse Companies\nBuild Resume\nContact\ninfo@jobs.af\nContact Us\nÂ© 2012 - 2026 Jobs.af | All Rights Reserved\nPowered by:\nNETLINKS Ltd",
      "details": {
        "Post Date": "Jan 20, 2026",
        "Closing Date": "Feb 03, 2026",
        "Reference": "PT#000265",
        "Number Of Vacancies": "1",
        "Salary Range": "Salary is negotiable",
        "Years Of Experience": "3 years",
        "Probation Period": "3 month",
        "Contract Type": "Permanent",
        "Contract Duration": "1 year",
        "Contract Extensible": "Yes",
        "Minimum Education": "Bachelor's Degree",
        "Functional Area": "Computer Science",
        "Countries": "Afghanistan",
        "Provinces": "Kabul"
      },
      "scraped_at": "2026-01-21T05:00:22Z",
      "apply_emails": [
        "hr@parsa.technology"
      ],
      "apply_method": "email"
    }
  ],
  "expiring_today": [
    {
      "url": "https://jobs.af/jobs/full-stack-developer-4M5yN57sq",
      "title": "Full Stack Developer",
      "company": null,
      "location": "Kabul",
      "closing_date": "2026-01-21",
      "closing_date_raw": "Jan 21, 2026",
      "apply_url": null,
      "description": "ğŸš€\nComing Soon The Jobs.af Freelancer Portal\nConnect with top clients and freelancers across Afghanistan all in one place!\nStay Tuned\nJobs\nProcurement Opportunities\nCompanies\nFreelancers\nServices\nProcurement Opportunities\nTrainings\nScholarships\nLogin\nRegister\nFull Stack Developer\nBaheer Group (BG)\nApply Now\nSee all jobs\nFull Stack Developer\nBaheer Group (BG),\n                                        Kabul, Afghanistan\nApply Now\nBachelor's Degree\nKabul, Afghanistan\n(Kabul)\nFull Time\n1712\nAbout\n                                            Baheer Group (BG)\nBaheer Group (BG) is a prominent manufacturer and provider of high-quality papers and paper products, offering premium solutions in Papers, Packaging, Printing, Mines & Energy, and supplying state-of-the-art Printing Machineries. Our commitment to excellence is reflected in our diversified portfolio, which caters to both domestic and international markets. Backed by an extensive Group of Companies, BG consistently surpasses industry standards, specializing in customized products tailored to meet the unique needs of our clients.\nJob Summary\nWe are seeking an experienced Full stack developer to join our team. This role is suited for a developer who has worked on production systems, understands modern development workflows, and can contribute effectively to both backend and frontend development in a professional environment.\nThe ideal candidate is comfortable working with established systems, writing high-quality code, and collaborating with other engineers to deliver reliable and scalable software solutions.\nDuties & Responsibilities\nDesign, develop, and maintain web applications using Laravel on the backend and React (TypeScript, React Query) on the frontend\nBuild and maintain clean, scalable, and maintainable backend services and APIs\nDevelop user-facing features using modern frontend practices\nCollaborate with cross-functional teams to translate business requirements into technical solutions\nReview code, provide constructive feedback, and help maintain high engineering standards\nOptimize application performance, database queries, and system reliability\nWork with Git and GitHub in a collaborative, team-based workflow\nUse Docker for development, testing, and deployment environments\nParticipate in system improvements, refactoring, and technical decision-making\nContribute to documentation and technical knowledge sharing\nJob Requirements\nStrong professional experience with Laravel (PHP) in production environments\nSolid experience with React.js, TypeScript and modern JavaScript development\nStrong knowledge of HTML, CSS, and JavaScript\nExperience designing and consuming RESTful APIs\nGood understanding of relational databases (MySQL, PostgreSQL, or similar)\nProficiency with Git and GitHub (branching strategies, pull requests, code reviews)\nPractical experience using Docker in real projects\nAbility to write clean, readable, and well-structured code\nExperience working in a collaborative, professional software team\nStrong problem-solving skills and attention to detail\nSubmission Guideline\nBaheer Group is an excellent place to grow your career. Don't hesitate to apply. the vacant position.\nPlease note only short-listed candidates will be contacted for an interview.\nMeanwhile: send a copy of your application to the below email while applying\nvp@baheer.af\nFunctional Area\nComputer Science\nCountries\nAfghanistan\nProvinces\nKabul\nSubmission Email\nvp@baheer.af\nApply Now\nPost Date\nDec 21, 2025\nClosing Date\nJan 21, 2026\nReference\nBG25-054\nNumber of Vacancies\n1\nSalary Range\nSalary is negotiable\nYears of Experience\n3 - 4 years\nProbation Period\n3 month\nContract Type\nPermanent\nContract Duration\n1 year\nContract Extensible\nYes\nMinimum Education\nBachelor's Degree\nGender\nMale\nRelated Jobs\nNETLINKS Plaza | Shahr-e-Naw,\nLane 3, Kabul, Afghanistan\nQuick Links\nAbout Us\nAdvertise with Us\nPrivacy Policy\nFor Companies\nPost a Job\nPost a Job\nPost a Job\nPost a Job\nPost RFP\nPost RFP\nPost RFP\nPost RFP\nPost Training\nPost Training\nPost Training\nPost Training\nFor Jobseekers\nBrowse Jobs\nBrowse Companies\nBuild Resume\nContact\ninfo@jobs.af\nContact Us\nÂ© 2012 - 2026 Jobs.af | All Rights Reserved\nPowered by:\nNETLINKS Ltd",
      "details": {
        "Post Date": "Dec 21, 2025",
        "Closing Date": "Jan 21, 2026",
        "Reference": "BG25-054",
        "Number Of Vacancies": "1",
        "Salary Range": "Salary is negotiable",
        "Years Of Experience": "3 - 4 years",
        "Probation Period": "3 month",
        "Contract Type": "Permanent",
        "Contract Duration": "1 year",
        "Contract Extensible": "Yes",
        "Minimum Education": "Bachelor's Degree",
        "Meanwhile": "send a copy of your application to the below email while applying",
        "Functional Area": "Computer Science",
        "Countries": "Afghanistan",
        "Provinces": "Kabul"
      },
      "scraped_at": "2026-01-21T05:00:22Z",
      "apply_emails": [
        "vp@baheer.af"
      ],
      "apply_method": "email"
    },
    {
      "url": "https://jobs.af/jobs/mdyr-ahsaeyh-w-dytabys-jwaz-ha-ryast-tjarty",
      "title": "Ù…Ø¯ÛŒØ±ÛŒØª Ø§Ø­ØµØ§Ø¦ÛŒÙ‡ Ùˆ Ø¯ÛŒØªØ§Ø¨ÛŒØ³ Ø¬ÙˆØ§Ø² Ù‡Ø§ØŒ Ø±ÛŒØ§Ø³Øª ØªØ¬Ø§Ø±ØªÛŒ",
      "company": null,
      "location": "Kabul",
      "closing_date": "2026-01-21",
      "closing_date_raw": "Jan 21, 2026",
      "apply_url": null,
      "description": "ğŸš€\nComing Soon The Jobs.af Freelancer Portal\nConnect with top clients and freelancers across Afghanistan all in one place!\nStay Tuned\nJobs\nProcurement Opportunities\nCompanies\nFreelancers\nServices\nProcurement Opportunities\nTrainings\nScholarships\nLogin\nRegister\nÙ…Ø¯ÛŒØ±ÛŒØª Ø§Ø­ØµØ§Ø¦ÛŒÙ‡ Ùˆ Ø¯ÛŒØªØ§Ø¨ÛŒØ³ Ø¬ÙˆØ§Ø² Ù‡Ø§ØŒ Ø±ÛŒØ§Ø³Øª ØªØ¬Ø§Ø±ØªÛŒ\nAfghanistan Oil and Gas Sate-Owned Corporation (AOGC) Ø´Ø±Ú©Øª Ø§Ù…Ø§Ø±ØªÛŒ Ù†ÙØª Ùˆ Ú¯Ø§Ø² Ø§ÙØºØ§Ù†Ø³ØªØ§Ù†\nApply Now\nSee all jobs\nÙ…Ø¯ÛŒØ±ÛŒØª Ø§Ø­ØµØ§Ø¦ÛŒÙ‡ Ùˆ Ø¯ÛŒØªØ§Ø¨ÛŒØ³ Ø¬ÙˆØ§Ø² Ù‡Ø§ØŒ Ø±ÛŒØ§Ø³Øª ØªØ¬Ø§Ø±ØªÛŒ\nAfghanistan Oil and Gas Sate-Owned Corporation (AOGC) Ø´Ø±Ú©Øª Ø§Ù…Ø§Ø±ØªÛŒ Ù†ÙØª Ùˆ Ú¯Ø§Ø² Ø§ÙØºØ§Ù†Ø³ØªØ§Ù†,\n                                        Kabul, Afghanistan\nApply Now\nBachelor's Degree\nKabul, Afghanistan\n(Kabul)\nFull Time\n919\n68\nAbout\n                                            Afghanistan Oil and Gas Sate-Owned Corporation (AOGC) Ø´Ø±Ú©Øª Ø§Ù…Ø§Ø±ØªÛŒ Ù†ÙØª Ùˆ Ú¯Ø§Ø² Ø§ÙØºØ§Ù†Ø³ØªØ§Ù†\nØ¯ Ø§ÙØºØ§Ù†Ø³ØªØ§Ù† Ù†ÙØª Ø§Ùˆ Ú«Ø§Ø² Ø§Ù…Ø§Ø±ØªÛŒ Ø´Ø±Ú©Øª Ù„Ù†Ú‰Ù‡ Ù¾ÙŠÚ˜Ù†Ø¯Ù†Ù‡ :\nØ¯ Ø§ÙØºØ§Ù†Ø³ØªØ§Ù† Ù†ÙØª Ø§Ùˆ Ú«Ø§Ø² Ø§Ù…Ø§Ø±ØªÛŒ Ø´Ø±Ú©Øª Ø¯ Ù„ÙˆÙ…Ú“ÙŠ ÚÙ„ Ù„Ù¾Ø§Ø±Ù‡ Ù¾Ù‡ Û±Û³Û³Û° Ù„Ù…Ø±ÛŒØ² Ú©Ø§Ù„ Ú©Û Ø¯ Ø¯ÙˆÙ„ØªÛŒ Ø§Ù†Ø­ØµØ§Ø±Ø§ØªÙˆ ØªØ± Ø¹Ù†ÙˆØ§Ù† Ù„Ø§Ù†Ø¯Û Ø¯ Ù†ÙØªÙˆ Ø¯ Ø³Ú©ØªÙˆØ± Ø§Ú“ÙˆÙ†Ø¯Ù‡ Ú©Ú“Ù†Ùˆ Ø¯ Ù…Ø¯ÛŒØ±ÛŒØª Ø§Ùˆ Ú…Ø§Ø±Ù†Û Ù¾Ù‡ Ù…ÙˆØ®Ù‡ ØªØ§Ø³ÛŒØ³ Ø´Ùˆ. Ø¯ ÛŒØ§Ø¯ Ø´Ø±Ú©Øª Ø­Ù‚ÙˆÙ‚ÙŠ Ø´Ø®ØµÛŒØª Ø¯ Ú©Ù„ÙˆÙ†Ùˆ Ù¾Ù‡ Ø§ÙˆÚ–Ø¯Ùˆ Ú©Û Ø¯ ÙˆØ®Øª Ø¯ ØºÙˆÚšØªÙ†Ùˆ Ù¾Ù‡ Ù¾Ø§Ù… Ú©Û Ù†ÛŒÙˆÙ„Ùˆ Ø³Ø±Ù‡ Ú…Ùˆ ÚÙ„Û Ø¨Ø¯Ù„ÙˆÙ† Ú©Ú“ÛŒ Ú†Û Ø¨Ù„Ø§ Ø¢Ø®Ø±Ù‡ Ù¾Ù‡ Û±Û³Û¹Û¸ Ù„Ù…Ø±ÛŒØ² Ú©Ø§Ù„ Ú©Û Ø¯ ÛŒØ§Ø¯ Ø´Ø±Ú©Øª Ø­Ù‚ÙˆÙ‚ÙŠ Ø´Ø®ØµÛŒØª Ù„Ù‡ ØªØµØ¯ÛŒ Ú…Ø®Ù‡ Ø´Ø±Ú©Øª ØªÙ‡ Ø¨Ø¯Ù„ÙˆÙ† ÙˆÙ…ÙˆÙ†Ø¯. Ø¯ Ø§ÙØºØ§Ù†Ø³ØªØ§Ù† Ù†ÙØª Ø§Ùˆ Ú«Ø§Ø² Ø¯ÙˆÙ„ØªÛŒ Ø´Ø±Ú©Øª Ø¯ ØªÛŒÙ„Ùˆ Ø§Ùˆ Ú«Ø§Ø²Ùˆ Ø¯ Ù¾ÛŒØ±ØŒ Ù¾Ù„ÙˆØ±ØŒ Ø°Ø®ÛŒØ±Ù‡ Ú©ÙˆÙ„Ùˆ Ø§Ùˆ Ø¯ ØªÛŒÙ„Ùˆ Ø§Ùˆ Ú«Ø§Ø²Ùˆ Ø¯ Ú©Ù…ÛŒØªØŒ Ú©ÛŒÙÛŒØªØŒ Ø§Ùˆ Ù‚ÛŒÙ…Øª Ø¯ Ú…Ø§Ø±Ù†Û Ø§Ùˆ Ø®ØµÙˆØµÙŠ Ø³Ú©ØªÙˆØ± ØªÙ‡ Ø¯ Ø®Ø¯Ù…ØªÙˆÙ†Ùˆ Ø¯ ÙˆÚ“Ø§Ù†Ø¯Û Ú©ÙˆÙ„Ùˆ Ù¾Ù‡ Ø¨Ø±Ø®Ù‡ Ú©Û Ú©Ú“Ù†Û ØªØ±Ø³Ø±Ù‡ Ú©ÙˆÙŠ.\nJob Summary\nØ·Ø±Ø­ Ùˆ Ø§Ù†Ú©Ø´Ø§Ù Ø¯ÛŒØªØ§Ø¨ÛŒØ³ Ø¬Ø§Ù…Ø¹ Ø§Ø² Ø¬ÙˆØ§Ø² Ù‡Ø§ Ø¨Ø± Ø§Ø³Ø§Ø³ Ù†ÛŒØ§Ø²Ù…Ù†Ø¯ÛŒ Ø´Ø±Ú©Øª Ùˆ Ø§ØªØ®Ø§Ø° Ø§Ù‚Ø¯Ø§Ù…Ø§Øª Ù„Ø§Ø²Ù… Ø¯Ø± Ø²Ù…ÛŒÙ†Ù‡ Ùˆ Ø­ÙØ¸ Ùˆ Ù†Ú¯Ù‡Ø¯Ø§Ø´Øª Ø¢Ù†.\nDuties & Responsibilities\nÂ·Â ØªØ±ØªÛŒØ¨ Ù¾Ù„Ø§Ù† Ú©Ø§Ø±ÛŒ Ù…Ø§Ù‡ÙˆØ§Ø±ØŒ Ø±Ø¨Ø¹ÙˆØ§Ø± Ùˆ Ø³Ø§Ù„Ø§Ù†Ù‡ Ø¯Ø± Ù…Ø·Ø§Ø¨Ù‚Øª Ø¨Ø§ Ù¾Ù„Ø§Ù† Ø¢Ù…Ø±ÛŒØª Ù…Ø±Ø¨ÙˆØ·Ù‡ Ø¬Ù‡Øª Ø±Ø³ÛŒØ¯Ù† Ø¨Ù‡ Ø§Ù‡Ø¯Ø§Ù ØªØ¹ÛŒÛŒÙ† Ø´Ø¯Ù‡ Ø§Ø¯Ø§Ø±Ù‡\nÂ·Â Ø¨Ø±Ø±Ø³ÛŒ Ùˆ ØªØ­Ù„ÛŒÙ„ Ù†ÛŒØ§Ø² Ù‡Ø§ÛŒ Ø§Ø·Ù„Ø§Ø¹Ø§ØªÛŒ Ù…Ø±ØªØ¨Ø· Ø¨Ø§ Ø¬ÙˆØ§Ø²Ø¯Ù‡ÛŒ\nÂ·Â Ø·Ø±Ø­ Ùˆ Ø§Ù†Ú©Ø´Ø§Ù Ø¯ÛŒØªØ§Ø¨ÛŒØ³ Ø§Ú©Ø³Ù„ Ø¬ÙˆØ§Ø² Ù‡Ø§ Ù…Ø·Ø§Ø¨Ù‚ Ø¨Ø§ Ù†ÛŒØ§Ø²Ù…Ù†Ø¯ÛŒ Ù‡Ø§ÛŒ Ø´Ø±Ú©Øª Ø¯ÙˆÙ„ØªÛŒ Ù†ÙØª Ùˆ Ú¯Ø§Ø² Ø§ÙØºØ§Ù†Ø³ØªØ§Ù†\nÂ·Â Ø§Ø±Ø²ÛŒØ§Ø¨ÛŒ Ú©ÛŒÙÛŒØª Ùˆ ØµØ­Øª Ø¯Ø§Ø¯Ù‡ Ù‡Ø§ÛŒ Ù…ÙˆØ¬ÙˆØ¯ Ø¯Ø± Ø¯ÛŒØªØ§Ø¨ÛŒØ³ Ùˆ Ú©Ø³Ø¨ Ø§Ø·Ù…ÛŒÙ†Ø§Ù† Ø§Ø² Ø¯Ø± Ø¯Ø³ØªØ±Ø³ Ø¨ÙˆØ¯Ù† Ø¢Ù† Ø¯Ø± Ù…ÙˆØ§Ù‚Ø¹ Ù†ÛŒØ§Ø²\nÂ·Â Ø§Ø±Ø§Ø¦Ù‡ Ø¢Ù…Ø§Ø± Ùˆ Ø§Ø·Ù„Ø§Ø¹Ø§Øª Ù…Ø±ØªØ¨Ø· Ø¨Ù‡ Ø¬ÙˆØ§Ø² Ù‡Ø§ Ø¨Ø±Ø§ÛŒ Ù…Ø¯ÛŒØ±Ø§Ù† Ùˆ Ø¢Ù…Ø±ÛŒÙ† Ù…Ø§ÙÙˆÙ‚\nÂ·Â Ø¨Ø±Ø±Ø³ÛŒ Ùˆ Ø§Ø¬Ø±Ø§ÛŒ Ø§Ù‚Ø¯Ø§Ù…Ø§Øª Ù„Ø§Ø²Ù… Ø¨Ø±Ø§ÛŒ Ø¨Ù‡Ø¨ÙˆØ¯ Ú©ÛŒÙÛŒØª Ùˆ Ø¹Ù…Ù„Ú©Ø±Ø¯ Ø¯ÛŒØªØ§Ø¨ÛŒØ³\nÂ·Â Ø§ØªØ®Ø§Ø° Ø§Ù‚Ø¯Ø§Ù…Ø§Øª Ù„Ø§Ø²Ù… Ø¯Ø± Ø¬Ù‡Øª Ø­ÙØ¸ Ùˆ Ù†Ú¯Ù‡Ø¯Ø§Ø±ÛŒ (Ø¨Ú© Ø¢Ù¾ Ú¯ÛŒØ±ÛŒ) Ø§Ø² Ø¯ÛŒØªØ§Ø¨ÛŒØ³ Ø¬ÙˆØ§Ø² Ù‡Ø§\nÂ·Â ØªØ§Ù…ÛŒÙ† Ø±ÙˆØ§Ø¨Ø· Ú©Ø§Ø±ÛŒ Ø¨Ø§ Ù†Ù…Ø§ÛŒÙ†Ø¯Ú¯ÛŒ Ù‡Ø§ÛŒ Ù…Ø±Ø¨ÙˆØ· Ø¬Ù‡Øª Ø¨Ø±ÙˆØ² Ø±Ø³Ø§Ù†ÛŒ Ø¯ÛŒØªØ§Ø¨ÛŒØ³\nÂ·Â Ø¢Ù…ÙˆØ²Ø´ Ùˆ Ø§Ø±ØªÙ‚Ø§Ø¡ Ø¯Ø§Ù†Ø´ Ú©Ø§Ø±Ú©Ù†Ø§Ù† Ø¯Ø± Ø²Ù…ÛŒÙ†Ù‡ Ø§Ø³ØªÙØ§Ø¯Ù‡ Ø§Ø² Ø¯ÛŒØªØ§Ø¨ÛŒØ³ Ø¬ÙˆØ§Ø² Ù‡Ø§\nÂ·Â Ø§Ø±Ø²ÛŒØ§Ø¨ÛŒ Ø®Ø·Ø±Ø§Øª Ùˆ Ø§Ø¬Ø±Ø§ÛŒ Ø§Ù‚Ø¯Ø§Ù…Ø§Øª Ù„Ø§Ø²Ù… Ø¨Ø±Ø§ÛŒ Ø­ÙØ§Ø¸Øª Ø§Ø² Ø¯Ø§Ø¯Ù‡ Ù‡Ø§ Ùˆ Ø§Ø±Ø§Ø¦Ù‡ Ù¾ÛŒØ´Ù†Ù‡Ø§Ø¯Ø§Øª Ø³Ø§Ø²Ù†Ø¯Ù‡ Ø¯Ø± Ø²Ù…ÛŒÙ†Ù‡ Ø¨Ù‡Ø¨ÙˆØ¯ Ø¯ÛŒØªØ§Ø¨ÛŒØ³\nÂ·Â Ù¾ÛŒØ´Ù†Ù‡Ø§Ø¯ Ùˆ Ø§Ø¬Ø±Ø§ÛŒ ØªØºÛŒÛŒØ±Ø§Øª Ùˆ Ø¨Ù‡Ø¨ÙˆØ¯ Ù‡Ø§ÛŒ Ù„Ø§Ø²Ù… Ø¯Ø± Ø¯ÛŒØªØ§Ø¨ÛŒØ³ Ø¬ÙˆØ§Ø²Ø¯Ù‡ÛŒ ØªØ§Ù†Ú© Ù‡Ø§ÛŒ ØªÛŒÙ„\nÂ·Â ØªØ±ØªÛŒØ¨ Ù…Ú©Ø§ØªÛŒØ¨ØŒ Ù¾ÛŒØ´Ù†Ù‡Ø§Ø¯Ø§ØªØŒ Ø§Ø³ØªØ¹Ù„Ø§Ù…ÛŒÙ‡ Ù‡Ø§ Ùˆ Ø³Ø§ÛŒØ± Ø§Ø³Ù†Ø§Ø¯ Ù…Ø¯ÛŒØ±ÛŒØª Ø¬Ù‡Øª ØªØ³Ø±ÛŒØ¹ Ø±ÙˆÙ†Ø¯ Ø§Ø¬Ø±Ø§Ø¢Øª Ú©Ø§Ø±ÛŒ\nÂ·Â ØªØ±ØªÛŒØ¨ Ùˆ Ø§Ø±Ø§Ø¦Ù‡ Ú¯Ø²Ø§Ø±Ø´Ø§Øª Ù…Ø§Ù‡ÙˆØ§Ø±ØŒ Ø±Ø¨Ø¹ÙˆØ§Ø±ØŒ Ø³Ø§Ù„Ø§Ù†Ù‡ Ø§Ø² ÙØ¹Ø§Ù„ÛŒØª Ù‡Ø§ Ùˆ Ø¯Ø³Øª Ø¢ÙˆØ±Ø¯ Ù‡Ø§ Ø¨Ù‡ Ù…Ø¯ÛŒØ± Ù…Ø±Ø¨ÙˆØ·Ù‡\nÂ·Â Ø§Ø¬Ø±Ø§ÛŒ Ø³Ø§ÛŒØ± ÙˆØ¸Ø§ÛŒÙ Ú©Ù‡ ØªÙˆØ³Ø· Ø¢Ù…Ø± Ù…Ø±Ø¨ÙˆØ·Ù‡ Ù…Ø·Ø§Ø¨Ù‚ Ù‚ÙˆØ§Ù†ÛŒÙ†ØŒ Ù…Ù‚Ø±Ø±Ø§Øª Ùˆ Ø§Ù‡Ø¯Ø§Ù Ø´Ø±Ú©Øª Ø¨Ù‡ ÙˆÛŒ Ø³Ù¾Ø±Ø¯Ù‡ Ù…ÛŒ Ø´ÙˆØ¯\nJob Requirements\nÂ·Â Ø¯Ø§Ø´ØªÙ† Ø³Ù†Ø¯ ØªØ­ØµÛŒÙ„ÛŒ Ø­Ø¯ Ø§Ù‚Ù„ Ù„ÛŒØ³Ø§Ù†Ø³ Ø¯Ø± Ø±Ø´ØªÙ‡ Ù‡Ø§ÛŒ Ø§Ø­ØµØ§Ø¦ÛŒÙ‡ØŒ ØªÚ©Ù†Ø§Ù„ÙˆÚ˜ÛŒ Ù…Ø¹Ù„ÙˆÙ…Ø§ØªÛŒØŒ Ú©Ù…Ù¾ÛŒÙˆØªØ± Ø³Ø§ÛŒÙ†Ø³ Ùˆ ÛŒØ§ Ø³Ø§ÛŒØ± Ø±Ø´ØªÙ‡ Ù‡Ø§ÛŒ Ù…Ø±ØªØ¨Ø· Ø¨Ù‡ ÙˆØ¸ÛŒÙÙ‡\nÂ·Â Ø¯Ø§Ø´ØªÙ† Ø­Ø¯ Ø§Ù‚Ù„ 1 Ø³Ø§Ù„ ØªØ¬Ø±Ø¨Ù‡ Ú©Ø§Ø±ÛŒ Ù…Ø±ØªØ¨Ø· Ø¨Ù‡ ÙˆØ¸ÛŒÙÙ‡ - Ø­Ø§ÛŒØ² Ø³Ù†Ø¯ ØªØ­ØµÛŒÙ„ÛŒ Ù…Ø§Ø³ØªØ± Ùˆ Ø¯ÙˆÚ©ØªÙˆØ±Ø§ Ø§Ø² Ø§ÛŒÙ† Ø­Ú©Ù… Ù…Ø³ØªØ«Ù†ÛŒ Ù…ÛŒ Ø¨Ø§Ø´Ø¯\nÂ·Â Ø¯Ø§Ø´ØªÙ† Ù‚ÙˆÙ‡ Ø§ÙÙ‡Ø§Ù… Ùˆ ØªÙÙ‡ÛŒÙ… Ù…Ø¯ÛŒØ±ÛŒØª Ú©Ø§Ø±ÛŒ\nÂ·Â ØªÙˆØ§Ù†Ø§ÛŒÛŒ Ø§ÛŒØ¬Ø§Ø¯ Ø§Ø¨ØªÚ©Ø§Ø± Ùˆ Ø®Ù„Ø§Ù‚ÛŒØª Ø¯Ø± Ø±ÙˆØ´ Ù‡Ø§ÛŒ Ú©Ø§Ø±ÛŒ\nÂ·Â Ø§Ù†Ø¹Ø·Ø§Ù Ù¾Ø°ÛŒØ±ÛŒ Ú©Ø§Ø±ÛŒ Ùˆ Ø§ÙˆÙ„ÙˆÛŒØª Ø¨Ù†Ø¯ÛŒ Ú©Ø§Ø± Ù‡Ø§ Ø¯Ø± Ø´Ø±Ø§ÛŒØ· Ø¯Ø´ÙˆØ§Ø±\nÂ·Â Ø³Ø±Ø¹Øª Ú©Ø§Ø± Ø¯Ø± Ú¯Ø²Ø§Ø±Ø´ Ú¯ÛŒØ±ÛŒ Ùˆ Ú¯Ø²Ø§Ø±Ø´ Ø¯Ù‡ÛŒ\nÂ·Â ØªØ³Ù„Ø· Ø¨Ù‡ ÛŒÚ©ÛŒ Ø§Ø² Ø²Ø¨Ø§Ù†Ù‡Ø§ÛŒ Ù‡Ø§ÛŒ Ø±Ø³Ù…ÛŒ(Ø¯Ø±ÛŒ ÛŒØ§ Ù¾Ø´ØªÙˆ) Ùˆ Ø¢Ø´Ù†Ø§ÛŒÛŒ( ØªØ­Ø±ÛŒØ± Ùˆ ØªÚ©Ù„Ù…) Ø¨Ø§ Ø²Ø¨Ø§Ù† Ø§Ù†Ú¯Ù„ÛŒØ³ÛŒ\nÂ·Â Ø¢Ø´Ù†Ø§ÛŒÛŒ Ø¨Ø§ Ø¨Ø±Ù†Ø§Ù…Ù‡Ø§ÛŒ Ú©Ù…Ù¾ÛŒÙˆØªØ± Ù…Ø±ØªØ¨Ø· Ø¨Ù‡ ÙˆØ¸ÛŒÙÙ‡\nÂ·Â ØªÙˆØ§Ù†Ø§ÛŒÛŒ Ú©Ø§Ø± Ø¨Ø´Ú©Ù„ ÙØ±Ø¯ÛŒ Ùˆ Ø¬Ù…Ø¹ÛŒ\nSubmission Guideline\nØ±Ù‡Ù†Ù…Ø§ÛŒÛŒ Ø«Ø¨Øª Ù†Ø§Ù… Ù…ØªÙ‚Ø§Ø¶ÛŒØ§Ù†:\nÙ…ØªÙ‚Ø§Ø¶ÛŒØ§Ù† Ù…Ø­ØªØ±Ù… Ø¨Ø±Ø§ÛŒ Ø«Ø¨Øª Ù†Ø§Ù… Ø±ÙˆÛŒ Ú¯Ø²ÛŒÙ†Ù‡ apply now Ú©Ù„ÛŒÚ© Ù†Ù…ÙˆØ¯Ù‡ Ù…Ø¹Ù„ÙˆÙ…Ø§Øª Ø®ÙˆÛŒØ´ Ø±Ø§ Ø§Ø±Ø³Ø§Ù„ Ø¨Ø¯Ø§Ø±Ù†Ø¯.\nØ¯Ø±Ø¬Ø±ÛŒØ§Ù† Ø«Ø¨Øª Ù†Ø§Ù… Ù…ÙˆØ§Ø±Ø¯ Ø°ÛŒÙ„ Ø±Ø§ Ø¯Ø± Ù†Ø¸Ø± Ø¯Ø§Ø´ØªÙ‡ Ø¨Ø§Ø´Ù†Ø¯:\nï¼‘. ØªÙ…Ø§Ù… Ù…Ø¹Ù„ÙˆÙ…Ø§Øª Ø®ÙˆÛŒØ´ Ø±Ø§ Ø¯Ù‚ÛŒÙ‚ Ø¨Ø±ÙˆÛŒØª Ø§Ø³Ù†Ø§Ø¯ Ø¯Ø±Ø¬ Ù†Ù…Ø§ÛŒÙ†Ø¯ Ø¯Ø± ØµÙˆØ±Øª Ù†Ø§Ø¯Ø±Ø³Øª Ø¨ÙˆØ¯Ù† Ù…Ø¹Ù„ÙˆÙ…Ø§Øª Ø¯Ø±Ø¬ Ø´Ø¯Ù‡ Ù…ØªÙ‚Ø§Ø¶ÛŒ Ø§Ø² Ù¾Ø±ÙˆØ³Ù‡\nØ­Ø°Ù Ù…ÛŒÚ¯Ø±Ø¯Ø¯.\n2. ÛŒÚ© ÙØ±Ø¯ ØµØ±Ù ÛŒÚ©Ø¨Ø§Ø± Ø«Ø¨Øª Ù†Ø§Ù… Ú©Ø±Ø¯Ù‡ Ù…ÛŒØªÙˆØ§Ù†Ø¯.\n3. Ø¯Ø± Ù‚Ø³Ù…Øª Ø¯Ø±Ø¬ Ø¹Ù†ÙˆØ§Ù† Ø¨Ø³Øª Ùˆ Ú©ÙˆØ¯ Ø¨Ø³Øª Ø¯Ù‚Øª Ù„Ø§Ø²Ù… Ù†Ù…Ø§Ø¦ÛŒØ¯.\nØ¢Ø¯Ø±Ø³: Ø±ÛŒØ§Ø³Øª Ø¹Ù…ÙˆÙ…ÛŒ Ø´Ø±Ú©Øª Ø§Ù…Ø§Ø±ØªÛŒ Ù†ÙØª Ùˆ Ú¯Ø§Ø² Ø§ÙØºØ§Ù†Ø³ØªØ§Ù† ÙˆØ§Ù‚Ø¹ Ú©ÙˆØªÙ„ Ø®ÛŒØ±Ø®Ø§Ù†Ù‡ Ø¬ÙˆØ§Ø± Ù†Ø§Ø­ÛŒÙ‡ Ù‡ÙØ¯Ù‡Ù…ØŒ Ú©Ø§Ø¨Ù„- Ø§ÙØºØ§Ù†Ø³ØªØ§Ù† Ø¯Ø±ØµÙˆØ±Øª Ø¶Ø±ÙˆØ±Øª Ø¨Ù‡ Ø´Ù…Ø§Ø±Ù‡ Ø°ÛŒÙ„ ØªÙ…Ø§Ø³ Ú¯Ø±ÙØªÙ‡ Ù…ÛŒØªÙˆØ§Ù†ÛŒØ¯:Â Û°Û·Û´Û·Û·Û·Û·ÛµÛ·Û°\nÙ†ÙˆØª: ØªÙ†Ù‡Ø§ Ø¨Ø±Ø§ÛŒ Ú©Ø§Ù†Ø¯ÛŒØ¯Ø§Ù†ÛŒ ØªÙ…Ø§Ø³ Ú¯Ø±ÙØªÙ‡ Ù…ÛŒØ´ÙˆØ¯ Ú©Ù‡ Ø¯Ø± Ø¨Ø³Øª Ù…ØªØ°Ú©Ø±Ù‡ Ø´Ø§Ø±Øª Ù„Ø³Øª Ú¯Ø±Ø¯Ù†Ø¯.\nØ§Ù…ØªØ­Ø§Ù† Ø¨Ø³Øª Ù…ØªØ°Ú©Ø±Ù‡ Ø¯ÙØªØ± Ù…Ø±Ú©Ø²ÛŒ Ø±ÛŒØ§Ø³Øª Ø¹Ù…ÙˆÙ…ÛŒ Ø´Ø±Ú©Øª Ø§Ù…Ø§Ø±ØªÛŒ Ù†ÙØª Ùˆ Ú¯Ø§Ø² Ø§ÙØºØ§Ù†Ø³ØªØ§Ù† Ø§Ø®Ø° Ù…ÛŒÚ¯Ø±Ø¯Ø¯.\nFunctional Area\nStatistics\nInformation Technology\nComputer Science\nCountries\nAfghanistan\nProvinces\nKabul\nApply Now\nPost Date\nJan 07, 2026\nClosing Date\nJan 21, 2026\nReference\n0181-1403\nNumber of Vacancies\n1\nSalary Range\nAs per company salary scale\nYears of Experience\n1 year\nProbation Period\n3 month\nContract Type\nPermanent\nContract Duration\nNot specified\nContract Extensible\nYes\nMinimum Education\nBachelor's Degree\nGender\nMale\nRelated Jobs\nNETLINKS Plaza | Shahr-e-Naw,\nLane 3, Kabul, Afghanistan\nQuick Links\nAbout Us\nAdvertise with Us\nPrivacy Policy\nFor Companies\nPost a Job\nPost a Job\nPost a Job\nPost a Job\nPost RFP\nPost RFP\nPost RFP\nPost RFP\nPost Training\nPost Training\nPost Training\nPost Training\nFor Jobseekers\nBrowse Jobs\nBrowse Companies\nBuild Resume\nContact\ninfo@jobs.af\nContact Us\nÂ© 2012 - 2026 Jobs.af | All Rights Reserved\nPowered by:\nNETLINKS Ltd",
      "details": {
        "Post Date": "Jan 07, 2026",
        "Closing Date": "Jan 21, 2026",
        "Reference": "0181-1403",
        "Number Of Vacancies": "1",
        "Salary Range": "As per company salary scale",
        "Years Of Experience": "1 year",
        "Probation Period": "3 month",
        "Contract Type": "Permanent",
        "Contract Duration": "Not specified",
        "Contract Extensible": "Yes",
        "Minimum Education": "Bachelor's Degree",
        "Ø¢Ø¯Ø±Ø³": "Ø±ÛŒØ§Ø³Øª Ø¹Ù…ÙˆÙ…ÛŒ Ø´Ø±Ú©Øª Ø§Ù…Ø§Ø±ØªÛŒ Ù†ÙØª Ùˆ Ú¯Ø§Ø² Ø§ÙØºØ§Ù†Ø³ØªØ§Ù† ÙˆØ§Ù‚Ø¹ Ú©ÙˆØªÙ„ Ø®ÛŒØ±Ø®Ø§Ù†Ù‡ Ø¬ÙˆØ§Ø± Ù†Ø§Ø­ÛŒÙ‡ Ù‡ÙØ¯Ù‡Ù…ØŒ Ú©Ø§Ø¨Ù„- Ø§ÙØºØ§Ù†Ø³ØªØ§Ù† Ø¯Ø±ØµÙˆØ±Øª Ø¶Ø±ÙˆØ±Øª Ø¨Ù‡ Ø´Ù…Ø§Ø±Ù‡ Ø°ÛŒÙ„ ØªÙ…Ø§Ø³ Ú¯Ø±ÙØªÙ‡ Ù…ÛŒØªÙˆØ§Ù†ÛŒØ¯:Â Û°Û·Û´Û·Û·Û·Û·ÛµÛ·Û°",
        "Ù†ÙˆØª": "ØªÙ†Ù‡Ø§ Ø¨Ø±Ø§ÛŒ Ú©Ø§Ù†Ø¯ÛŒØ¯Ø§Ù†ÛŒ ØªÙ…Ø§Ø³ Ú¯Ø±ÙØªÙ‡ Ù…ÛŒØ´ÙˆØ¯ Ú©Ù‡ Ø¯Ø± Ø¨Ø³Øª Ù…ØªØ°Ú©Ø±Ù‡ Ø´Ø§Ø±Øª Ù„Ø³Øª Ú¯Ø±Ø¯Ù†Ø¯.",
        "Functional Area": "Statistics",
        "Countries": "Afghanistan",
        "Provinces": "Kabul"
      },
      "scraped_at": "2026-01-21T05:00:22Z",
      "apply_emails": [],
      "apply_method": "unknown"
    }
  ],
  "expiring_soon": [
    {
      "url": "https://jobs.af/jobs/ran-back-office-engineer-huawei-otzPc0NUs",
      "title": "RAN Back Office Engineer ( Huawei)",
      "company": null,
      "location": "Kabul",
      "closing_date": "2026-01-22",
      "closing_date_raw": "Jan 22, 2026",
      "apply_url": null,
      "description": "ğŸš€\nComing Soon The Jobs.af Freelancer Portal\nConnect with top clients and freelancers across Afghanistan all in one place!\nStay Tuned\nJobs\nProcurement Opportunities\nCompanies\nFreelancers\nServices\nProcurement Opportunities\nTrainings\nScholarships\nLogin\nRegister\nRAN Back Office Engineer ( Huawei)\nI Engineering Group\nApply Now\nSee all jobs\nRAN Back Office Engineer ( Huawei)\nI Engineering Group,\n                                        Kabul, Afghanistan\nApply Now\nBachelor's Degree\nKabul, Afghanistan\n(Kabul)\nFull Time\n1362\nAbout\n                                            I Engineering Group\nieng Group provides EPC and O&M infrastructure services with a focus on the telecom and power industries. The Group's subsidiaries Eki.Struct (tower) and GreenPole (power), along with its affiliated asset management company CREI complement the functions provided by ieng.\nEstablished in 2007, the Group is a leading provider of telecom infrastructure and managed services in Africa and Emerging Markets.\nWe have grown rapidly since our inception in 2007 and are now operational in 19 countries: Afghanistan, Algeria, Cameroon, Central African Republic, Chad, DR Congo, Ethiopia, Ghana, Guinea, Kenya, KSA, Lebanon, Liberia, Myanmar, Nigeria, Pakistan, Philippines, South Sudan and Uganda.\nToday, we maintain over 31,200+ sites for Africaâ€™s largest MNOs and all TowerCos.\nOur vision\nTo become the leading Engineering Procurement and Construction (EPC) and Operation and Maintenance (O&M) contractor in global emerging markets.\nï»¿Our Mission\nWe provide EPC and O&M services to the telecom, renewable energy and construction industries in global emerging markets, seamlessly integrating our core competencies with our customersâ€™ businesses, so they benefit from competitive and comprehensive solutions.\nJob Summary\nieng Afghanistan is seeking highly skilled Huawei experts for RAN to join our team. The ideal candidate must have extensive experience with Huawei networks and equipment. This role involves leading network swap, network planning, optimization, troubleshooting, and maintenance efforts to ensure the highest performance and reliability of network.\nAttractive package will be offered\nDuties & Responsibilities\nÂ·Â Â Â Â Â Â Â Provide Analysis and monitoring Network performance by Checking Key Quality Indicators (KQI's)\nÂ·Â Â Â Â Â Â Â Monitor and demarcating service degradation (Voice and Data) by checking performance of the network nodes\nÂ·Â Â Â Â Â Â Â Knowledge of performance counters of RAN and Core KPIâ€™s to make sure that all necessary counters are activated for daily, weekly, monthly and critical outages.\nÂ·Â Â Â Â Â Â Â Using Big Data analytics to provide trend analysis for KQI/KPI and provide suggestions and solution on performance improvement\nÂ·Â Â Â Â Â Â Â Customer proactive support using signaling call flows and big data analytics to improve Customer experience.\nÂ·Â Â Â Â Â Â Â Investigate and analyze individual User complaints for \" CS and PS\" services, international link's (link utilization, call performance)\nÂ·Â Â Â Â Â Â Â Mapping between KPI's & KQI's that's related to worst cell/Site/Node analysis to assist relevant team in improving network performance.\nÂ·Â Â Â Â Â Â Â Detect value added cases by analyzing which KPI affect services.\nÂ·Â Â Â Â Â Â Â Reviewing and making guidelines for network performance and people management.\nÂ·Â Â Â Â Â Â Â Managing day-to-day Network KPIs and performed required analysis to improve the service delivery\nÂ·Â Â Â Â Â Â Â Review of various reports (Site outage report, KPI reports, Daily CR report, Pending Outage Reports).\nÂ·Â Â Â Â Â Â Â Checking and reviewing of the KPIs and SLA of the TTâ€™s created by Monitoring team.\nÂ·Â Â Â Â Â Â Â Technical review of the work orders change request which are impacting the NOC monitoring.\nÂ·Â Â Â Â Â Â Â Providing post incident report and Root cause analysis for Major and Critical Incidents and User complaints.\nÂ·Â Â Â Â Â Â Â Expert knowledge of U2020, BSC, RNC, 2G, 3G, LTE/5G technologies and Huawei RAN solutions.\nÂ·Â Â Â Â Â Â Empower local RAN team to do complex task and train them daily, weekly and monthly basis.\nÂ·Â Â Â Â Â Â Â Proven experience in leading large-scale RAN projects and optimization initiatives.\nÂ·Â Â Â Â Â Â Network deployment and implementation to oversee installation and configuration of RAN components and ensure equipment is step according design and standards.\nÂ·Â Â Â Â Capacity Management to assess network traffic and make sure that each interface has enough capacity to handle peak hours traffic.\nÂ·Â Â Â Â Trouble shooting and Problem Resolution to analyze problem, degradation and other RAN KPIs.\nÂ·Â Â Â Â Â Use available or third partiesâ€™ or specialized software tools for network analysis and trouble shooting.\nÂ·Â Â Â Â Technology Upgrades and Updates, Ability to migrate from vendor to Vendor and advance wireless technology.\nOH&S/QMS Role and Responsibilities:\nReports any hazards or risks in addition to Accidents/Incident to QHSE department.\nBe aware of and complies to i engineeringâ€™s IMS Policy.\nAbides by i engineeringâ€™s Local Legal and Client Requirements.\nAttends and engages in IMS Awareness Sessions.\nEnsures that all IMS procedures are regularly followed and raises the issue when they are not\nJob Requirements\nÂ·Â Â Â Â Â Â Â Minimum 5 years of experience.\nÂ·Â Â Â Â Â Â Â BSc. in /Electrical/IT, Telecom Engineering/Computer Engineering\nÂ·Â Â Â Â Â Â Â Excellent presentation skills.\nÂ·Â Â Â Â Â Â Â Must have strong telecom skills and knowledge of common programs such as Microsoft Office.\nÂ·Â Â Â Â Â Â Â Ability to work under pressure.\nï»¿ï»¿ï»¿ï»¿\nÂ·Â Â Â Â Â Â Â Strong analytical skills with the ability to interpret complex data and make data-driven decisions.\nÂ·Â Â Â Â Â Â Â Excellent communication, presentation, and client-facing abilities.\nSubmission Guideline\nPlease ensure to write the position title and vacancy number in the subject line of your email, and send your CV along with a cover letter. Only shortlisted candidates will be notified.\nFunctional Area\nElectrical Engineering\nCommunication\nInformation Technology\nComputer Science\nTelecome Engineering\nTelecommunication\nCountries\nAfghanistan\nProvinces\nKabul\nSubmission Email\nfanosha@ieng-group.com\nApply Now\nPost Date\nJan 08, 2026\nClosing Date\nJan 22, 2026\nReference\nIeng-RAN-BO-001\nNumber of Vacancies\n1\nSalary Range\nAs per company salary scale\nYears of Experience\n4 - 5 years\nProbation Period\nNot Specified\nContract Type\nLong-term\nContract Duration\nNot specified\nContract Extensible\nYes\nMinimum Education\nBachelor's Degree\nGender\nMale\nRelated Jobs\nNETLINKS Plaza | Shahr-e-Naw,\nLane 3, Kabul, Afghanistan\nQuick Links\nAbout Us\nAdvertise with Us\nPrivacy Policy\nFor Companies\nPost a Job\nPost a Job\nPost a Job\nPost a Job\nPost RFP\nPost RFP\nPost RFP\nPost RFP\nPost Training\nPost Training\nPost Training\nPost Training\nFor Jobseekers\nBrowse Jobs\nBrowse Companies\nBuild Resume\nContact\ninfo@jobs.af\nContact Us\nÂ© 2012 - 2026 Jobs.af | All Rights Reserved\nPowered by:\nNETLINKS Ltd",
      "details": {
        "Post Date": "Jan 08, 2026",
        "Closing Date": "Jan 22, 2026",
        "Reference": "Ieng-RAN-BO-001",
        "Number Of Vacancies": "1",
        "Salary Range": "As per company salary scale",
        "Years Of Experience": "4 - 5 years",
        "Probation Period": "Not Specified",
        "Contract Type": "Long-term",
        "Contract Duration": "Not specified",
        "Contract Extensible": "Yes",
        "Minimum Education": "Bachelor's Degree",
        "Functional Area": "Electrical Engineering",
        "Countries": "Afghanistan",
        "Provinces": "Kabul"
      },
      "scraped_at": "2026-01-21T05:00:22Z",
      "apply_emails": [
        "fanosha@ieng-group.com"
      ],
      "apply_method": "email"
    },
    {
      "url": "https://jobs.af/jobs/aafysr-arshd-shbkh-shft-shb",
      "title": "Ø¢ÙÛŒØ³Ø± Ø§Ø±Ø´Ø¯ Ø´Ø¨Ú©Ù‡ Ø´ÙØª Ø´Ø¨",
      "company": null,
      "location": "Kabul",
      "closing_date": "2026-01-24",
      "closing_date_raw": "Jan 24, 2026",
      "apply_url": null,
      "description": "ğŸš€\nComing Soon The Jobs.af Freelancer Portal\nConnect with top clients and freelancers across Afghanistan all in one place!\nStay Tuned\nJobs\nProcurement Opportunities\nCompanies\nFreelancers\nServices\nProcurement Opportunities\nTrainings\nScholarships\nLogin\nRegister\nØ¢ÙÛŒØ³Ø± Ø§Ø±Ø´Ø¯ Ø´Ø¨Ú©Ù‡ Ø´ÙØª Ø´Ø¨\nDa Afghanistan Bank\nApply Now\nSee all jobs\nØ¢ÙÛŒØ³Ø± Ø§Ø±Ø´Ø¯ Ø´Ø¨Ú©Ù‡ Ø´ÙØª Ø´Ø¨\nDa Afghanistan Bank,\n                                        Kabul, Afghanistan\nApply Now\nBachelor's Degree\nKabul, Afghanistan\n(Kabul)\nFull Time\n4158\n210\nAbout\n                                            Da Afghanistan Bank\nØ¯ Ø§ÙØºØ§Ù†Ø³ØªØ§Ù† Ø¨Ø§Ù†Ú© Ù‚Ø±Ø§Ø± ØªØµÙˆÛŒØ¨ Ø´Ù…Ø§Ø±Ù‡ 152 Ù…ÙˆØ±Ø® 3/2/1318 Ù…Ø¬Ù„Ø³ ÙˆØ²Ø±Ø§ØŒ ØªØµÙˆÛŒØ¨ Ø´Ù…Ø§Ø±Ù‡ 11 Ù…ÙˆØ±Ø® 19/6/1318 Ø´ÙˆØ±Ø§ÛŒ Ù…Ù„ÛŒØŒ ØªØµÙˆÛŒØ¨ ØªØ§Ø±ÛŒØ®ÛŒ 12/6/1318 Ù…Ø¬Ù„Ø³ Ø§Ø¹ÛŒØ§Ù† Ùˆ Ù…Ù†Ø¸ÙˆØ±ÛŒ 5280/1317 ØªØ§Ø±ÛŒØ®ÛŒ 17/11/1318 Ø­Ø¶ÙˆØ± Ø´Ø§Ù‡Ø§Ù†Ù‡ Ø¨Ù‡ Ø³Ø±Ù…Ø§ÛŒÙ‡ Ø§Ø¨ØªØ¯Ø§Ø¦ÛŒ Ù…Ø¨Ù„Øº ÛŒÚ©ØµØ¯ Ùˆ Ø¨ÛŒØ³Øª Ù…Ù„ÛŒÙˆÙ† Ø§ÙØºØ§Ù†ÛŒ Ø¯Ø± Ù¾Ø§ÛŒØªØ®Øª Ú©Ø´ÙˆØ± Ø´Ù‡Ø± Ú©Ø§Ø¨Ù„ Ø§ÙØªØªØ§Ø­ Ø´Ø¯ Ú©Ù‡ Ø¯Ø± Ø¯Ø§Ø®Ù„ Ùˆ Ø®Ø§Ø±Ø¬ Ú©Ø´ÙˆØ± Ø¨Ø§ Ø§Ø®ØªÛŒØ§Ø±Ø§Øª Ùˆ ÙˆØ¸Ø§ÛŒÙ Ù„Ø§Ø²Ù… Ù…ÛŒØªÙˆØ§Ù†Ø³Øª Ù†Ù…Ø§ÛŒÙ†Ø¯Ú¯ÛŒ Ùˆ ÙØ±ÙˆØ¹ Ø®ÙˆØ¯ Ø±Ø§ ØªØ£Ø³ÛŒØ³ Ùˆ Ø¨Ø§Ù†Ú©Ù‡Ø§ÛŒ Ø³Ú©ØªÙˆØ±ÛŒ Ø±Ø§ ØªØ¹ÛŒÛŒÙ† Ù†Ù…Ø§ÛŒØ¯. Ù†Ø¸Ø§Ù… Ø¨Ø§Ù†Ú©Ø¯Ø§Ø±ÛŒ Ø§ÙØºØ§Ù†Ø³ØªØ§Ù† Ø¨Ø§ ØªØ£Ø³ÛŒØ³ Ø¨Ø§Ù†Ú© Ù…Ù„ÛŒ Ø§ÙØºØ§Ù† Ø¯Ø± Ø³Ø§Ù„ 1312 Ù‡Ø¬Ø±ÛŒ Ø´Ù…Ø³ÛŒ Ù¾Ø§ Ø¨Ù‡ Ø¹Ø±ØµÙ‡ ÙˆØ¬ÙˆØ¯ Ú¯Ø°Ø§Ø´Øª Ùˆ Ù‚Ø¨Ù„ Ø§Ø² ØªØ£Ø³ÛŒØ³ Ø¯ Ø§ÙØºØ§Ù†Ø³ØªØ§Ù† Ø¨Ø§Ù†Ú©ØŒ Ø§Ù…ÙˆØ± Ø¨Ø§Ù†Ú©Ø¯Ø§Ø±ÛŒ Ø¯ÙˆÙ„ØªÛŒ Ø±Ø§ Ø§ÛŒÙ† Ø¨Ø§Ù†Ú© Ø¨Ù‡ Ù¾ÛŒØ´ Ù…ÛŒØ¨Ø±Ø¯. Ø¨Ø¹Ø¯ Ø§Ø² ØªØ£Ø³ÛŒØ³ Ø¯ Ø§ÙØºØ§Ù†Ø³ØªØ§Ù† Ø¨Ø§Ù†Ú© ÙˆØ¸Ø§ÛŒÙ Ø¨Ø§Ù†Ú©Ø¯Ø§Ø±ÛŒ Ø¯ÙˆÙ„ØªÛŒ Ø¨Ù‡ Ø´Ù…ÙˆÙ„ Ú†Ø§Ù¾ Ùˆ Ù†Ø´Ø± Ù¾ÙˆÙ„ Ø§ÙØºØ§Ù†ÛŒ Ø¨Ù‡ Ø§ÛŒÙ† Ø¨Ø§Ù†Ú© Ù…Ù†ØªÙ‚Ù„ Ú¯Ø±Ø¯ÛŒØ¯. Ø¯ Ø§ÙØºØ§Ù†Ø³ØªØ§Ù† Ø¨Ø§Ù†Ú© Ø¨Ø­ÛŒØ« Ø¨Ø§Ù†Ú©Ø¯Ø§Ø± Ø¯ÙˆÙ„Øª Ùˆ Ø¨Ø§Ù†Ú© ØªØ¬Ø§Ø±ØªÛŒ ØªÙˆØ§Ù†Ø³Øª ØªØ­ÙˆÙ„Ø§Øª Ùˆ Ø§Ù†Ú©Ø´Ø§ÙØ§Øª Ú†Ø´Ù…Ú¯ÛŒØ± Ùˆ Ø¨Ø²Ø±Ú¯ÛŒ Ø±Ø§ Ù‡Ù… Ø¯Ø± Ø±Ø§Ø¨Ø·Ù‡ Ø¨Ù‡ Ú†Ø§Ù¾ Ùˆ Ù†Ø´Ø± Ù¾ÙˆÙ„ Ø§ÙØºØ§Ù†ÛŒ Ø¨Ù‡ ÙˆØ¬ÙˆØ¯ Ø¢ÙˆØ±Ø¯ Ùˆ Ù‡Ù… Ø¯Ø± Ø³Ù…Øª Ùˆ Ø³ÙˆÛŒ Ù†Ø¸Ø§Ù… Ø¨Ø§Ù†Ú©ÛŒ Ø¨Ù‡ Ø¯Ø³ØªØ§ÙˆØ±Ø¯ Ù‡Ø§ÛŒ Ù†Ø§Ø¦Ù„ Ú¯Ø±Ø¯Ø¯. ÙØ¹Ø§Ù„ÛŒØª Ø¯ Ø§ÙØºØ§Ù†Ø³ØªØ§Ù† Ø¨Ø§Ù†Ú© Ø±Ø§ Ù…ÛŒ ØªÙˆØ§Ù† Ø¨Ù‡ Ø¯Ùˆ Ù…Ø±Ø­Ù„Ù‡ ØªÙ‚Ø³ÛŒÙ… Ø¨Ù†Ø¯ÛŒ Ú©Ø±Ø¯: Ø¯Ø± Ù…Ø±Ø­Ù„Ù‡ Ø§ÙˆÙ„ Ú©Ù‡ Ø§Ø² Ø³Ø§Ù„ 1318 Ø§Ù„ÛŒ Ø³Ø§Ù„ 1380 Ø±Ø§ Ø§Ø­ØªÙˆØ§ Ù…ÛŒ Ù†Ù…Ø§ÛŒØ¯Ø› Ø¯ Ø§ÙØºØ§Ù†Ø³ØªØ§Ù† Ø¨Ø§Ù†Ú© Ø¯Ø± Ù‚Ø³Ù…Øª Ú†Ø§Ù¾ØŒ Ø¶Ø±Ø¨ Ùˆ Ù†Ø´Ø± Ù¾ÙˆÙ„ Ø§ÙØºØ§Ù†ÛŒ Ù…Ø·Ø§Ø¨Ù‚ Ø¨Ù‡ ØªÙ‚Ø§Ø¶Ø§ÛŒ Ø¨Ø§Ø²Ø§Ø±ØŒ Ø­ÙØ¸ Ø§Ø±Ø²Ø´ Ù¾ÙˆÙ„ Ùˆ Ø§Ù…ÙˆØ± Ø¨Ø§Ù†Ú©Ø¯Ø§Ø±ÛŒ Ø¯ÙˆÙ„ØªÛŒ Ù…ØµØ±ÙˆÙ Ø¨ÙˆØ¯ Ú©Ù‡ Ø¯Ø± Ù¾Ù‡Ù„ÙˆÛŒ Ø§ÛŒÙ† ÙˆØ¸Ø§ÛŒÙØŒ Ø§Ù…ÙˆØ± ØªØ¬Ø§Ø±ØªÛŒ Ø±Ø§ Ù†ÛŒØ² Ø·Ø¨Ù‚ ÙØ¹Ø§Ù„ÛŒØª Ù‡Ø§ÛŒ Ø³Ø§ÛŒØ± Ø¨Ø§Ù†Ú©Ù‡Ø§ÛŒ ØªØ¬Ø§Ø±ÛŒ Ø§ÙØºØ§Ù†Ø³ØªØ§Ù† Ø§Ù†Ø¬Ø§Ù… Ù…ÛŒØ¯Ø§Ø¯ Ú©Ù‡ Ù…ÛŒ ØªÙˆØ§Ù† Ø§Ø² Ø§ÙØªØªØ§Ø­ Ø­Ø³Ø§Ø¨Ø§Øª Ù¾Ø³ Ø§Ù†Ø¯Ø§Ø²ØŒ Ø¬Ø§Ø±ÛŒØŒ Ù…ÛŒØ¹Ø§Ø¯ÛŒØŒ Ø§Ø¬Ø±Ø§ÛŒ Ù‚Ø±ÙˆØ¶ Ø¨Ù‡ Ù…Ù†Ø¸ÙˆØ± ØªÙ‚ÙˆÛŒÙ‡ Ø³Ø±Ù…Ø§ÛŒÙ‡ Ú¯Ø°Ø§Ø±ÛŒ Ù‡Ø§ Ùˆ Ø§Ø¬Ø±Ø§ÛŒ Ø³Ø§ÛŒØ± Ù‚Ø±ÙˆØ¶ Ø¯Ø± Ø¨Ø®Ø´ Ù‡Ø§ÛŒ ØªØ¬Ø§Ø±ÛŒ ÛŒØ§Ø¯ Ø¢ÙˆØ±ÛŒ Ú©Ø±Ø¯. Ù…Ø±Ø­Ù„Ù‡ Ø¯ÙˆÙ… Ø§Ø² Ø³Ø§Ù„ 1381 Ø¢ØºØ§Ø² Ù…ÛŒ Ø´ÙˆØ¯. Ø¨Ø¹Ø¯ Ø§Ø² ØªØµÙˆÛŒØ¨ Ù‚Ø§Ù†ÙˆÙ† Ø§Ø³Ø§Ø³ÛŒ Ø§ÙØºØ§Ù†Ø³ØªØ§Ù†ØŒ Ø¨Ø§Ù†Ú© Ù…Ø±Ú©Ø²ÛŒ Ø¨Ø± Ø§Ø³Ø§Ø³ Ù…Ø§Ø¯Ù‡ Ø¯ÙˆØ§Ø²Ø¯Ù‡Ù… Ø§ÛŒÙ† Ù‚Ø§Ù†ÙˆÙ†ØŒ Ù…Ù†Ø­ÛŒØ« ÛŒÚ© Ø¨Ø§Ù†Ú© Ù…Ø³ØªÙ‚Ù„ ØªØ³Ø¬ÛŒÙ„ Ú¯Ø±Ø¯ÛŒØ¯ Ùˆ Ø¨Ø§ ØµÙ„Ø§Ø­ÛŒØª Ù‡Ø§ÛŒÛŒ Ú©Ù‡ Ø¨Ù‡ Ø¢Ù† ØªÙÙˆÛŒØ¶ Ø´Ø¯ Ø¨Ù‡ Ø¯Ø³ØªØ§ÙˆØ±Ø¯ Ù‡Ø§ÛŒ Ù‚Ø§Ø¨Ù„ ØªÙˆØ¬Ù‡ÛŒ Ø¯Ø± Ø¹Ø±ØµÙ‡ Ù‡Ø§ÛŒ Ú¯ÙˆÙ†Ø§Ú¯ÙˆÙ† Ø¯Ø³Øª ÛŒØ§ÙØª. Ø¯ Ø§ÙØºØ§Ù†Ø³ØªØ§Ù† Ø¨Ø§Ù†Ú© Ø¨Ø± Ø§Ø³Ø§Ø³ Ù‚ÙˆØ§Ù†ÛŒÙ† Ø¬Ø¯ÛŒØ¯ Ø¨Ø§Ù†Ú©ÛŒ Ùˆ Ù…Ø§Ù„ÛŒ ØªÙ…Ø§Ù… Ø§Ù…ÙˆØ± ØªØ¬Ø§Ø±ØªÛŒ Ø±Ø§ Ø¨Ù‡ Ø¨Ø§Ù†Ú©Ù‡Ø§ÛŒ Ø¯ÙˆÙ„ØªÛŒ Ùˆ Ø®ØµÙˆØµÛŒ ÙˆØ§Ú¯Ø°Ø§Ø± Ù†Ù…ÙˆØ¯ Ùˆ Ù…Ø³ÙˆÙˆÙ„ÛŒØª Ø§Ø¹Ø·Ø§ÛŒ Ø¬ÙˆØ§Ø² ÙØ¹Ø§Ù„ÛŒØª Ùˆ Ù†Ø¸Ø§Ø±Øª Ø§Ø² Ù…Ø¤Ø³Ø³Ø§Øª Ø¨Ø§Ù†Ú©ÛŒ Ùˆ Ù…Ø§Ù„ÛŒ Ø±Ø§ Ø¨Ø¹Ù‡Ø¯Ù‡ Ú¯Ø±ÙØª. Ø¨Ø± Ø§Ø³Ø§Ø³ Ù‚Ø§Ù†ÙˆÙ† Ø¯ Ø§ÙØºØ§Ù†Ø³ØªØ§Ù† Ø¨Ø§Ù†Ú©ØŒ Ø«Ø¨Ø§Øª Ù‚ÛŒÙ… Ù‡Ø¯Ù Ø§ÙˆÙ„ÛŒÙ‡ Ùˆ Ø§Ø³Ø§Ø³ÛŒ Ø¯ Ø§ÙØºØ§Ù†Ø³ØªØ§Ù† Ø¨Ø§Ù†Ú© Ù…ÛŒ Ø¨Ø§Ø´Ø¯ Ùˆ Ø¨Ù‡ Ø§ÛŒÙ† Ù…Ù†Ø¸ÙˆØ± Ø·Ø±Ø­ØŒ ØªØ·Ø¨ÛŒÙ‚ Ùˆ Ø§ØªØ®Ø§Ø° Ø³ÛŒØ§Ø³Øª Ù‡Ø§ÛŒ Ù¾ÙˆÙ„ÛŒØŒ Ø³ÛŒØ§Ø³Øª Ø§Ø±Ø² Ùˆ ØªØ±ØªÛŒØ¨Ø§Øª Ø§Ø³Ø¹Ø§Ø±ØŒ Ú†Ø§Ù¾ Ø¨Ø§Ù†Ú©Ù†ÙˆØª Ùˆ Ø¶Ø±Ø¨ Ù…Ø³Ú©ÙˆÚ©Ø§Øª Ø§Ø² ÙˆØ¸Ø§ÛŒÙ Ø¨Ø§Ù†Ú© Ù…Ø±Ú©Ø²ÛŒ ØªØ¹ÛŒÛŒÙ† Ú¯Ø±Ø¯ÛŒØ¯ Ú©Ù‡ Ø¯Ø± Ú©Ù†Ø§Ø± Ø¢Ù† Ø·Ø¨Ù‚ Ù‚Ø§Ù†ÙˆÙ† Ø¨Ù‡ Ø­ÛŒØ« Ø¨Ø§Ù†Ú©Ø¯Ø§Ø± Ùˆ Ù†Ù…Ø§ÛŒÙ†Ø¯Ù‡ Ù…Ø§Ù„ÛŒ Ø¯ÙˆÙ„ØªØŒ Ù†Ù‡Ø§Ø¯ ØµØ¯ÙˆØ± Ùˆ Ø«Ø¨Øª Ø¬ÙˆØ§Ø² ÙØ¹Ø§Ù„ÛŒØª Ø¨Ø§Ù†Ú©Ù‡Ø§ØŒ ØµØ±Ø§ÙØ§Ù† Ùˆ Ø¹Ø±Ø¶Ù‡ Ú©Ù†Ù†Ø¯Ú¯Ø§Ù† Ø®Ø¯Ù…Ø§Øª Ù¾ÙˆÙ„ÛŒ Ùˆ Ø§Ø³Ù†Ø§Ø¯ Ø¨Ù‡Ø§Ø¯Ø§Ø± Ùˆ Ø³ÛŒØ³ØªÙ… Ù¾Ø±Ø¯Ø§Ø®Øª Ù…ØµÙˆÙ† Ùˆ Ø³Ø§Ù„Ù… Ù†ÛŒØ² ÙØ¹Ø§Ù„ÛŒØª Ù…ÛŒ Ù†Ù…Ø§ÛŒØ¯.\nJob Summary\nØ¹Ù†ÙˆØ§Ù† ÙˆØ¸ÛŒÙÙ‡\n: Ø¢ÙÛŒØ³Ø± Ø§Ø±Ø´Ø¯ Ø´Ø¨Ú©Ù‡ Ø´ÙØª Ø´Ø¨\nØ¢Ù…Ø±ÛŒØª\n:\nØ¢Ù…Ø±ÛŒØª Ø¹Ù…ÙˆÙ…ÛŒ ØªÚ©Ù†Ø§Ù„ÙˆÚ˜ÛŒ Ù…Ø¹Ù„ÙˆÙ…Ø§ØªÛŒ\nÚ¯Ø±ÛŒØ¯\n: Ù‡ÙØªÙ… (\nÛ·\n)\nØªØ¹Ø¯Ø§Ø¯ Ø¨Ø³Øª\n: ÛŒÚ© (\nÛ±\n)\nØªØ§Ø±ÛŒØ® Ø¢ØºØ§Ø²\n: Û±Û´Û°Û´/Û±Û°/Û²Û°\nØªØ§Ø±ÛŒØ® Ø®ØªÙ…\n: Û±Û´Û°Û´/Û±Û±/Û°Û´\nÙ†ÙˆØ¹ Ø§Ø¹Ù„Ø§Ù†\n:\nØ¯Ø§Ø®Ù„ÛŒ Ùˆ Ø®Ø§Ø±Ø¬ÛŒ\nÙ†ÙˆØ¹ Ø§Ø³ØªØ®Ø¯Ø§Ù…\n:\nØ¯Ø§Ø¦Ù…ÛŒ\nDuties & Responsibilities\nÙˆØ¸Ø§ÛŒÙ Ùˆ Ù…Ø³Ø¦ÙˆÙ„ÛŒØª Ù‡\nØ§\nÂ·Â Â Â Â Ú©Ø§Ù†ÙÛŒÚ¯ÙˆØ±ÛŒØ´Ù† Ø³ÛŒØ³Ú©Ùˆ Ø³ÙˆÛŒÚ† Ù‡Ø§ØŒ Ø³ÛŒØ³Ú©ÙˆØ±ÙˆØªØ±Ù‡Ø§ØŒ ÙØ§ÛŒØ±ÙˆØ§Ù„ Ù‡Ø§ÛŒ ASA Ùˆ Cyber roamØŒ Sophos Ùˆ Update operating server systemÂ Ùˆ Ø³Ø§ÛŒØ± Ø§Ø¬Ø²Ø§ÛŒ Ù…Ø±Ø¨ÙˆØ· Ø¨Ù‡ Ø´Ø¨Ú©Ù‡ Ø¯Ø± Ø¨Ø§Ù†Ú© Ù…Ø±Ú©Ø²ØŒ Ø´Ù‡Ø±ÛŒ Ú…Ø§Ù†Ú¯Ù‡ Ù‡Ø§ Ùˆ Ø²ÙˆÙ† Ù‡Ø§ÛŒ Ù‡ÙØª Ú¯Ø§Ù†Ù‡ Ø¯ Ø§ÙØºØ§Ù†Ø³ØªØ§Ù† Ø¨Ø§Ù†Ú©\nÂ·Â Â Â Â Â Ø­Ù„ Ùˆ Ø±Ø³ÛŒØ¯Ú¯ÛŒ Ø¨Ù‡ Ù…Ø´Ú©Ù„Ø§Øª ØªØ®Ù†ÛŒÚ©ÛŒ Ø¨Ø®Ø´ Ø´Ø¨Ú©Ù‡ Ùˆ Ø§Ù†ØªØ±Ù†Øª Ø¯ÙØ§ØªØ± Ù…Ø±Ú©Ø²ÛŒØŒ Ø²ÙˆÙ† Ù‡Ø§ Ùˆ Ù†Ù…Ø§ÛŒÙ†Ø¯Ú¯ÛŒ Ù‡Ø§ÛŒ ÙˆÙ„Ø§ÛŒØªÛŒ Ú©Ù‡ Ø§Ø² Ø·Ø±Ù Ø´Ø¨ ÙØ¹Ø§Ù„ÛŒØª Ø¯Ø§Ø±Ù†Ø¯\nÂ·Â Â Â Â Â ØªØ±ØªÛŒØ¨ Ùˆ ØªÙ†Ø¸ÛŒÙ… Ú©Ø§Ø± Ù‡Ø§ÛŒ ØªØ®Ù†ÛŒÚ©ÛŒ Ùˆ Ù…Ø³Ù„Ú©ÛŒ Ø³ÛŒØ³ØªÙ… Ù…Ø¯ÛŒØ±ÛŒØª Ø´Ø¨Ú©ÙˆØ¨ Ø¯ Ø§ÙØºØ§Ù†Ø³ØªØ§Ù† Ø¨Ø§Ù†Ú© Ùˆ Ø¨Ø±Ù‚Ø±Ø§Ø± Ø³Ø§Ø®ØªÙ† Ø§Ø±ØªØ¨Ø§Ø· Ø¨Ø§ Ú©Ù…Ù¾Ù†ÛŒ Ù‡Ø§ÛŒ Ø®Ø¯Ù…Ø§ØªÛŒ Ø´Ø¨Ú©ÙˆÛŒ Ùˆ Ø§Ù†ØªØ±Ù†ØªÛŒ ØºØ±Ø¶ Ù…Ø³Ø§Ø¦Ù„ ØªØ®Ù†ÛŒÚ©ÛŒ Ùˆ Ø­Ù„ Ù…Ø´Ú©Ù„Ø§Øª Ø§Ø² Ø·Ø±Ù Ø´Ø¨\nÂ·Â Â Â Â Ø§Ù†Ø³ØªØ§Ù„ÛŒØ´Ù† Ùˆ Ú©Ø§Ù†ÙÛŒÚ¯ÙˆØ±ÛŒØ´Ù† Ø³ÛŒØ³ØªÙ… ØªÛŒÙ„ÛŒÙÙˆÙ† Ù‡Ø§ÛŒ Ø¯Ø§Ø®Ù„ÛŒ AVAYA Ø¨Ø±Ø§ÛŒ Ù…Ø±Ú©Ø² Ùˆ Ù†Ù…Ø§ÛŒÙ†Ø¯Ú¯ÛŒ Ù‡Ø§\nÂ·Â Â Â Â Ø¨Ø± Ù‚Ø±Ø§Ø± Ù†Ú¯Ù‡Ø¯Ø§Ø´ØªÙ† Ø®Ø¯Ù…Ø§Øª Ø¨Ù‡ØªØ± Ø§Ù†ØªØ±Ù†ØªÛŒØŒ Ø´Ø¨Ú©Ù‡ØŒ Ù‡Ù…Ø§Ù‡Ù†Ú¯ Ùˆ Ù‡Ù…Ú©Ø§Ø±ÛŒ Ø¨Ø§ Ù…Ø¯ÛŒØ± Ù…Ø³ØªÙ‚ÛŒÙ…\nÂ·Â Â Â Â ØªØ³Ù„ÛŒÙ… Ú¯ÛŒØ±ÛŒ Ùˆ ØªØ³Ù„ÛŒÙ… Ø¯Ù‡ÛŒ Ø§Ù…ÙˆØ± Ù…Ø±Ø¨ÙˆØ· Ø¨Ù‡ Ø´ÙØª Ø¨Ø§ Ø­ÙØ¸ Ù…Ø³Ø¤Ù„ÛŒØª Ú©Ø§Ø±ÛŒ Ø¯Ø± Ù‡Ù…Ø¢Ù‡Ù†Ú¯ÛŒ Ø¨Ø§ Ù…Ø¯ÛŒØ± Ù…Ø³ØªÙ‚ÛŒÙ…\nÂ·Â Â Â Â ØªØ­Ø±ÛŒØ± Ù…Ú©Ø§ØªÛŒØ¨ØŒ Ù¾ÛŒØ´Ù†Ù‡Ø§Ø¯Ø§ØªØŒ Ø§Ø³ØªØ¹Ù„Ø§Ù… Ù‡Ø§ Ùˆ Ø³Ø§ÛŒØ± Ù…Ø±Ø§Ø³Ù„Ø§Øª Ø§Ø¯Ø§Ø±ÛŒ Ùˆ Ø·ÛŒ Ù…Ø±Ø§Ø­Ù„ Ø¢Ù† Ø¯Ø± ÙˆÙ‚Øª Ù…Ø¹ÛŒÙ† Ø·Ø¨Ù‚ Ù‡Ø¯Ø§ÛŒØª Ù…Ø¯ÛŒØ± Ù…Ø³ØªÙ‚ÛŒÙ… ÙˆØ¢Ù…Ø± Ø°ÛŒØµÙ„Ø§Ø­\nÂ·Â Â Â Â ØªÙ†Ø¸ÛŒÙ… Ùˆ Ø­ÙØ¸ Ù…Ú©Ø§ØªÛŒØ¨ØŒ Ù¾ÛŒØ´Ù†Ù‡Ø§Ø¯Ø§ØªØŒ Ø§Ø³ØªØ¹Ù„Ø§Ù… Ù‡Ø§ Ùˆ Ø³Ø§ÛŒØ± Ù…Ø±Ø§Ø³Ù„Ø§Øª Ø§Ø¯Ø§Ø±ÛŒ Ø¯Ø± Ø¯ÙˆØ³ÛŒÙ‡ Ù‡Ø§ Ùˆ Ú©Ø§Ø±ØªÙ† Ù‡Ø§ Ø·ÙˆØ± Ø¯Ù‚ÛŒÙ‚ Ùˆ Ù…Ù†Ø¸Ù… Ø¨Ù‡ Ø´Ú©Ù„ Ù‡Ø§Ø±Ø¯ Ùˆ Ø³Ø§ÙØª Ú©Ø§Ù¾ÛŒ\nÂ·Â Â Â Â Ø¬Ù…Ø¹ Ø¢ÙˆØ±ÛŒØŒ ØªÙˆØ­ÛŒØ¯ Ùˆ ØªØ±ØªÛŒØ¨ Ú¯Ø²Ø§Ø±Ø´ Ù‡Ø§ÛŒ Ù‡ÙØªÙ‡ ÙˆØ§Ø±ØŒ Ù…Ø§Ù‡ÙˆØ§Ø±ØŒ Ø±Ø¨Ø¹ÙˆØ§Ø±ØŒ Ø³Ø§Ù„Ø§Ù†Ù‡ Ùˆ Ø¹Ù†Ø¯Ø§Ù„Ø¶Ø±ÙˆØ±Øª Ø§Ø² Ù¾ÛŒØ´Ø±ÙØª ÙØ¹Ø§Ù„ÛŒØªÙ‡Ø§ Ùˆ Ø¯Ø³Øª Ø¢ÙˆØ±Ø¯ Ù‡Ø§ÛŒ Ù…Ø¯ÛŒØ±ÛŒØª Ù…Ø±Ø¨ÙˆØ·\nÂ·Â Â Â Â ØªØ±ØªÛŒØ¨ Ù¾Ù„Ø§Ù† Ù‡Ø§ÛŒ Ú©Ø§Ø±ÛŒ Ùˆ Ø§Ø±Ø§ÛŒÛ€ Ú¯Ø²Ø§Ø±Ø´ Ú©Ø§Ø±ÛŒ Ø¨Ù‡ Ù…Ø¯ÛŒØ± Ù…Ø³ØªÙ‚ÛŒÙ… Ùˆ Ø¢Ù…Ø± Ø°ÛŒØµÙ„Ø§Ø­\nÂ·Â Â Â Ø§Ù†Ø¬Ø§Ù… Ø³Ø§ÛŒØ± ÙˆØ¸Ø§ÛŒÙ Ùˆ Ù…Ø³Ø¦ÙˆÙ„ÛŒØª Ù‡Ø§ÛŒ Ú©Ù‡ Ø¨ØªØ£Ø³ÛŒ Ø§Ø² Ø·Ø±Ø²Ø§Ù„Ø¹Ù…Ù„ Ù‡Ø§ØŒ Ø¯Ø³ØªÙˆØ±Ø§Ù„Ø¹Ù…Ù„ Ùˆ Ù‡Ø¯Ø§ÛŒØ§Øª Ù…Ù‚Ø§Ù… Ù…Ø§ÙÙˆÙ‚ Ø·Ø¨Ù‚ Ù„Ø§ÛŒØ­Ù‡ Ùˆ Ù…Ù‚Ø±Ø±Ø§Øª Ø§Ø±Ø¬Ø§Ø¹ Ù…ÛŒÚ¯Ø±Ø¯Ø¯\nJob Requirements\nØ¯Ø±Ø¬Ù‡ ØªØ­ØµÛŒÙ„ÛŒ\nÂ·Â Â Â Â Â Â Â Ù„ÛŒØ³Ø§Ù†Ø³ Ø¯Ø± Ø¨Ø®Ø´ Ú©Ù…Ù¾ÛŒÙˆØªØ± Ø³Ø§ÛŒÙ†Ø³ØŒ ØªÚ©Ù†Ø§Ù„ÙˆÚ˜ÛŒ Ù…Ø¹Ù„ÙˆÙ…Ø§ØªÛŒ\nØªØ¬Ø±Ø¨Ù‡\nÂ·\nØ¯Ùˆ (2) Ø³Ø§Ù„ ØªØ¬Ø±Ø¨Û€ Ú©Ø§Ø±ÛŒ Ù…Ø±ØªØ¨Ø· Ø¨Ù‡ ÙˆØ¸ÛŒÙÙ‡\nÙ…Ù‡Ø§Ø±Øª Ù‡Ø§ Ùˆ ØªÙˆØ§Ù†Ø§Ø¦ÛŒ Ù‡Ø§\nÂ·Â Â Â Â Â Â Ø¨Ù„Ø¯ÛŒØª Ø¨Ù‡ Ø²Ø¨Ø§Ù† Ù‡Ø§ÛŒ Ø±Ø³Ù…ÛŒ Ú©Ø´ÙˆØ± Ùˆ Ø§Ù†Ú¯Ù„ÛŒØ³ÛŒ\nÂ·Â Â Â Â Â Â Ø¯Ø§Ø´ØªÙ† Ù…Ù‡Ø§Ø±Øª Ù‡Ø§ÛŒ Ù…Ø¯ÛŒØ±ÛŒØªÛŒ\nÂ·Â Â Â Â Â Â ÙØµØ§Ø­Øª Ùˆ Ø¨Ù„Ø§ØºØª Ø¯Ø± Ú¯ÙØªØ§Ø±\nÂ·Â Â Â Â Â Â Ø¢Ø´Ù†Ø§Ø¦ÛŒ Ø¨Ù‡ Ù‚ÙˆØ§Ù†ÛŒÙ† Ùˆ Ù…Ù‚Ø±Ø±Ø§Øª Ø¨Ø§Ù†Ú©ÛŒ\nÂ·Â Â Â Â Â Â ØªÙˆØ§Ù†Ø§Ø¦ÛŒ Ø¯Ø± ØªØ­Ø±ÛŒØ± Ù…Ú©Ø§ØªÛŒØ¨ØŒ Ù¾ÛŒØ´Ù†Ù‡Ø§Ø¯Ø§Øª Ùˆ Ú¯Ø²Ø§Ø±Ø´Ø§Øª Ú©Ø§Ø±ÛŒ\nÂ·Â Â Â Â Â Â Ø¢Ø´Ù†Ø§ÛŒÛŒ Ø¨Ø§ Ø³ÛŒØ³ØªÙ… Ù‡Ø§ÛŒ Ø¨Ø§Ù†Ú©ÛŒ\nÂ·Â Â Â Â Â Â ÙÙ‡Ù… Ùˆ Ø¯Ø±Ú© Ù…Ø³Ø¦ÙˆÙ„ÛŒØª Ú©Ø§Ø±ÛŒ Ùˆ ØªØ´Ø®ÛŒØµ Ù…Ø´Ú©Ù„Ø§Øª Ø¯Ø± Ø³Ø§Ø­Û€ Ú©Ø§Ø±ÛŒ\nÂ·Â Â Â Â Â Â Ø­ÙØ¸ Ù…Ø­Ø±Ù…ÛŒØª Ùˆ Ø¸ÛŒÙÙˆÛŒ\nÂ·Â Â Â Â Â Â Ø¢Ú¯Ø§Ù‡ÛŒ Ø§Ø² ÙˆØ¸Ø§ÛŒÙ Ùˆ Ø§Ù‡Ø¯Ø§Ù Ø¯ Ø§ÙØºØ§Ù†Ø³ØªØ§Ù† Ø¨Ø§Ù†Ú©\nÂ·Â Â Â Â Â Â Â Â Ø¨Ù„Ø¯ÛŒØª Ø¨Ø§ Ù†ÛŒØªÙˆØ±Ú© Ù…Ø§Ù†ÛŒØªÙˆØ±Ù†Ú¯ Ùˆ Ø³Ø±ÙˆØ± Ù…Ø§Ù†ÛŒØªÙˆØ±Ù†Ú¯ ØªÙˆÙ„Ø²\nÂ·Â Â Â Â Â Â Ø¢Ø´Ù†Ø§Ø¦ÛŒ Ø¨Ø§ Ø¨Ø±Ù†Ø§Ù…Ù‡ Ù‡Ø§ÛŒ Ú©Ù…Ù¾ÛŒÙˆØªØ±ÛŒ Ùˆ Ø³Ø§ÛŒØ± Ø§Ø¬Ø²Ø§ÛŒ ØªÚ©Ù†Ø§Ù„ÙˆÚ˜ÛŒÚ©ÛŒ CCNP, CCNA,N+ AVAYA IP Phone,ØŒ Cyber roam Firewall\nØµÙØ§Øª Ùˆ Ø§Ø±Ø²Ø´ Ù‡Ø§ÛŒ Ø´Ø®ØµÛŒ\nÂ·\nØµØ§Ø¯Ù‚ØŒ Ø¯Ø§Ø±Ø§ÛŒ Ø¨Ø±Ø®ÙˆØ±Ø¯ Ù†ÛŒÚ©ØŒ Ø­Ø§Ù…ÛŒ Ø§Ø­ØªØ±Ø§Ù… Ù…ØªÙ‚Ø§Ø¨Ù„ØŒ Ù…Ø¨ØªÚ©Ø±ØŒ Ø¨Ø§ Ø¯Ø³Ù¾Ù„ÛŒÙ†ØŒ Ù¾Ø§Ø¨Ù†Ø¯ Ø¨Ù‡ ÙˆØ¸ÛŒÙÙ‡ Ùˆ ÙˆÙ‚ØªØŒ Ø¹Ù„Ø§Ù‚Ù…Ù†Ø¯ Ø¨Ù‡ Ú©Ø§Ø± Ú¯Ø±ÙˆÙ¾ÛŒØŒ Ù‡Ù…Ú©Ø§Ø±ØŒ Ù…Ø³Ø¦ÙˆÙ„ÛŒØª Ù¾Ø°ÛŒØ±ØŒ ØªØµÙ…ÛŒÙ…Ú¯ÛŒØ± Ùˆ Ù…Ø³Ù„Ú©ÛŒ Ø¯Ø± Ø¨Ø®Ø´ Ú©Ø§Ø±ÛŒ\nSubmission Guideline\nÙ†Ú©Ø§Øª:\nÂ·Â Â Â Â Ø¹Ù„Ø§Ù‚Ù‡ Ù…Ù†Ø¯Ø§Ù† Ù…ÛŒØªÙˆØ§Ù†Ù†Ø¯ Ù†Ø®Ø³Øª Ø¯Ø± ÙˆÛŒØ¨ Ø³Ø§ÛŒØª\njobs.dab.gov.af\nØ¨Ø±Ø§ÛŒ Ø®ÙˆØ¯ ÛŒÙˆØ²Ø± Ø§ÛŒØ¬Ø§Ø¯ Ù†Ù…ÙˆØ¯Ù‡ Ùˆ Ø¨Ø¹Ø¯Ø§ Ø¨Ø³Øª Ù…ÙˆØ±Ø¯ Ù†Ø¸Ø± Ø±Ø§ Ø§Ù†ØªØ®Ø§Ø¨ Ù†Ù…ÙˆØ¯Ù‡ Ùˆ Ø§Ø³Ù†Ø§Ø¯ Ø®ÙˆØ§Ø³ØªÙ‡ Ø´Ø¯Ù‡ Ø±Ø§ Ø¨Ù‡ ÙØ§Ø±Ù…Øª PDF Ø¢Ù¾Ù„ÙˆØ¯ Ù†Ù…Ø§ÛŒÛŒØ¯.\nÂ·Â Â Â Â Ø¬Ù‡Øª Ø§Ø®Ø° Ø§Ù…ØªØ­Ø§Ù† ÙÙ‚Ø· Ø¨Ø§ Ù…ØªÙ‚Ø§Ø¶ÛŒØ§Ù† Ù…Ù†ØªØ®Ø¨ ØªÙ…Ø§Ø³ Ú¯Ø±ÙØªÙ‡ Ù…ÛŒØ´ÙˆØ¯.\nÂ·Â Â Â Â ØªØ§Ø±ÛŒØ® Ø§Ù…ØªØ­Ø§Ù† Ø¨Ø¹Ø¯Ø§Ù‹ Ø¨Ù‡ Ø§Ø·Ù„Ø§Ø¹ Ø±Ø³Ø§Ù†ÛŒØ¯Ù‡ Ù…ÛŒØ´ÙˆØ¯.\nFunctional Area\nInformation Technology\nComputer Science\nNetworking\nCountries\nAfghanistan\nProvinces\nKabul\nApply Now\nPost Date\nJan 10, 2026\nClosing Date\nJan 24, 2026\nReference\nDAB1446052\nNumber of Vacancies\n1\nSalary Range\nAs per company salary scale\nYears of Experience\n2 years\nProbation Period\n3 month\nContract Type\nPermanent\nContract Duration\nNot specified\nContract Extensible\nYes\nMinimum Education\nBachelor's Degree\nGender\nMale\nRelated Jobs\nNETLINKS Plaza | Shahr-e-Naw,\nLane 3, Kabul, Afghanistan\nQuick Links\nAbout Us\nAdvertise with Us\nPrivacy Policy\nFor Companies\nPost a Job\nPost a Job\nPost a Job\nPost a Job\nPost RFP\nPost RFP\nPost RFP\nPost RFP\nPost Training\nPost Training\nPost Training\nPost Training\nFor Jobseekers\nBrowse Jobs\nBrowse Companies\nBuild Resume\nContact\ninfo@jobs.af\nContact Us\nÂ© 2012 - 2026 Jobs.af | All Rights Reserved\nPowered by:\nNETLINKS Ltd",
      "details": {
        "Post Date": "Jan 10, 2026",
        "Closing Date": "Jan 24, 2026",
        "Reference": "DAB1446052",
        "Number Of Vacancies": "1",
        "Salary Range": "As per company salary scale",
        "Years Of Experience": "2 years",
        "Probation Period": "3 month",
        "Contract Type": "Permanent",
        "Contract Duration": "Not specified",
        "Contract Extensible": "Yes",
        "Minimum Education": "Bachelor's Degree",
        "Functional Area": "Information Technology",
        "Countries": "Afghanistan",
        "Provinces": "Kabul"
      },
      "scraped_at": "2026-01-21T05:00:22Z",
      "apply_emails": [],
      "apply_method": "unknown"
    },
    {
      "url": "https://jobs.af/jobs/adhw-ankshaf-mhswlat",
      "title": "Ø¹Ø¶Ùˆ Ø§Ù†Ú©Ø´Ø§Ù Ù…Ø­ØµÙˆÙ„Ø§Øª",
      "company": null,
      "location": "Kabul",
      "closing_date": "2026-01-24",
      "closing_date_raw": "Jan 24, 2026",
      "apply_url": null,
      "description": "ğŸš€\nComing Soon The Jobs.af Freelancer Portal\nConnect with top clients and freelancers across Afghanistan all in one place!\nStay Tuned\nJobs\nProcurement Opportunities\nCompanies\nFreelancers\nServices\nProcurement Opportunities\nTrainings\nScholarships\nLogin\nRegister\nØ¹Ø¶Ùˆ Ø§Ù†Ú©Ø´Ø§Ù Ù…Ø­ØµÙˆÙ„Ø§Øª\nDa Afghanistan Bank\nApply Now\nSee all jobs\nØ¹Ø¶Ùˆ Ø§Ù†Ú©Ø´Ø§Ù Ù…Ø­ØµÙˆÙ„Ø§Øª\nDa Afghanistan Bank,\n                                        Kabul, Afghanistan\nApply Now\nBachelor's Degree\nKabul, Afghanistan\n(Kabul)\nFull Time\n2981\n144\nAbout\n                                            Da Afghanistan Bank\nØ¯ Ø§ÙØºØ§Ù†Ø³ØªØ§Ù† Ø¨Ø§Ù†Ú© Ù‚Ø±Ø§Ø± ØªØµÙˆÛŒØ¨ Ø´Ù…Ø§Ø±Ù‡ 152 Ù…ÙˆØ±Ø® 3/2/1318 Ù…Ø¬Ù„Ø³ ÙˆØ²Ø±Ø§ØŒ ØªØµÙˆÛŒØ¨ Ø´Ù…Ø§Ø±Ù‡ 11 Ù…ÙˆØ±Ø® 19/6/1318 Ø´ÙˆØ±Ø§ÛŒ Ù…Ù„ÛŒØŒ ØªØµÙˆÛŒØ¨ ØªØ§Ø±ÛŒØ®ÛŒ 12/6/1318 Ù…Ø¬Ù„Ø³ Ø§Ø¹ÛŒØ§Ù† Ùˆ Ù…Ù†Ø¸ÙˆØ±ÛŒ 5280/1317 ØªØ§Ø±ÛŒØ®ÛŒ 17/11/1318 Ø­Ø¶ÙˆØ± Ø´Ø§Ù‡Ø§Ù†Ù‡ Ø¨Ù‡ Ø³Ø±Ù…Ø§ÛŒÙ‡ Ø§Ø¨ØªØ¯Ø§Ø¦ÛŒ Ù…Ø¨Ù„Øº ÛŒÚ©ØµØ¯ Ùˆ Ø¨ÛŒØ³Øª Ù…Ù„ÛŒÙˆÙ† Ø§ÙØºØ§Ù†ÛŒ Ø¯Ø± Ù¾Ø§ÛŒØªØ®Øª Ú©Ø´ÙˆØ± Ø´Ù‡Ø± Ú©Ø§Ø¨Ù„ Ø§ÙØªØªØ§Ø­ Ø´Ø¯ Ú©Ù‡ Ø¯Ø± Ø¯Ø§Ø®Ù„ Ùˆ Ø®Ø§Ø±Ø¬ Ú©Ø´ÙˆØ± Ø¨Ø§ Ø§Ø®ØªÛŒØ§Ø±Ø§Øª Ùˆ ÙˆØ¸Ø§ÛŒÙ Ù„Ø§Ø²Ù… Ù…ÛŒØªÙˆØ§Ù†Ø³Øª Ù†Ù…Ø§ÛŒÙ†Ø¯Ú¯ÛŒ Ùˆ ÙØ±ÙˆØ¹ Ø®ÙˆØ¯ Ø±Ø§ ØªØ£Ø³ÛŒØ³ Ùˆ Ø¨Ø§Ù†Ú©Ù‡Ø§ÛŒ Ø³Ú©ØªÙˆØ±ÛŒ Ø±Ø§ ØªØ¹ÛŒÛŒÙ† Ù†Ù…Ø§ÛŒØ¯. Ù†Ø¸Ø§Ù… Ø¨Ø§Ù†Ú©Ø¯Ø§Ø±ÛŒ Ø§ÙØºØ§Ù†Ø³ØªØ§Ù† Ø¨Ø§ ØªØ£Ø³ÛŒØ³ Ø¨Ø§Ù†Ú© Ù…Ù„ÛŒ Ø§ÙØºØ§Ù† Ø¯Ø± Ø³Ø§Ù„ 1312 Ù‡Ø¬Ø±ÛŒ Ø´Ù…Ø³ÛŒ Ù¾Ø§ Ø¨Ù‡ Ø¹Ø±ØµÙ‡ ÙˆØ¬ÙˆØ¯ Ú¯Ø°Ø§Ø´Øª Ùˆ Ù‚Ø¨Ù„ Ø§Ø² ØªØ£Ø³ÛŒØ³ Ø¯ Ø§ÙØºØ§Ù†Ø³ØªØ§Ù† Ø¨Ø§Ù†Ú©ØŒ Ø§Ù…ÙˆØ± Ø¨Ø§Ù†Ú©Ø¯Ø§Ø±ÛŒ Ø¯ÙˆÙ„ØªÛŒ Ø±Ø§ Ø§ÛŒÙ† Ø¨Ø§Ù†Ú© Ø¨Ù‡ Ù¾ÛŒØ´ Ù…ÛŒØ¨Ø±Ø¯. Ø¨Ø¹Ø¯ Ø§Ø² ØªØ£Ø³ÛŒØ³ Ø¯ Ø§ÙØºØ§Ù†Ø³ØªØ§Ù† Ø¨Ø§Ù†Ú© ÙˆØ¸Ø§ÛŒÙ Ø¨Ø§Ù†Ú©Ø¯Ø§Ø±ÛŒ Ø¯ÙˆÙ„ØªÛŒ Ø¨Ù‡ Ø´Ù…ÙˆÙ„ Ú†Ø§Ù¾ Ùˆ Ù†Ø´Ø± Ù¾ÙˆÙ„ Ø§ÙØºØ§Ù†ÛŒ Ø¨Ù‡ Ø§ÛŒÙ† Ø¨Ø§Ù†Ú© Ù…Ù†ØªÙ‚Ù„ Ú¯Ø±Ø¯ÛŒØ¯. Ø¯ Ø§ÙØºØ§Ù†Ø³ØªØ§Ù† Ø¨Ø§Ù†Ú© Ø¨Ø­ÛŒØ« Ø¨Ø§Ù†Ú©Ø¯Ø§Ø± Ø¯ÙˆÙ„Øª Ùˆ Ø¨Ø§Ù†Ú© ØªØ¬Ø§Ø±ØªÛŒ ØªÙˆØ§Ù†Ø³Øª ØªØ­ÙˆÙ„Ø§Øª Ùˆ Ø§Ù†Ú©Ø´Ø§ÙØ§Øª Ú†Ø´Ù…Ú¯ÛŒØ± Ùˆ Ø¨Ø²Ø±Ú¯ÛŒ Ø±Ø§ Ù‡Ù… Ø¯Ø± Ø±Ø§Ø¨Ø·Ù‡ Ø¨Ù‡ Ú†Ø§Ù¾ Ùˆ Ù†Ø´Ø± Ù¾ÙˆÙ„ Ø§ÙØºØ§Ù†ÛŒ Ø¨Ù‡ ÙˆØ¬ÙˆØ¯ Ø¢ÙˆØ±Ø¯ Ùˆ Ù‡Ù… Ø¯Ø± Ø³Ù…Øª Ùˆ Ø³ÙˆÛŒ Ù†Ø¸Ø§Ù… Ø¨Ø§Ù†Ú©ÛŒ Ø¨Ù‡ Ø¯Ø³ØªØ§ÙˆØ±Ø¯ Ù‡Ø§ÛŒ Ù†Ø§Ø¦Ù„ Ú¯Ø±Ø¯Ø¯. ÙØ¹Ø§Ù„ÛŒØª Ø¯ Ø§ÙØºØ§Ù†Ø³ØªØ§Ù† Ø¨Ø§Ù†Ú© Ø±Ø§ Ù…ÛŒ ØªÙˆØ§Ù† Ø¨Ù‡ Ø¯Ùˆ Ù…Ø±Ø­Ù„Ù‡ ØªÙ‚Ø³ÛŒÙ… Ø¨Ù†Ø¯ÛŒ Ú©Ø±Ø¯: Ø¯Ø± Ù…Ø±Ø­Ù„Ù‡ Ø§ÙˆÙ„ Ú©Ù‡ Ø§Ø² Ø³Ø§Ù„ 1318 Ø§Ù„ÛŒ Ø³Ø§Ù„ 1380 Ø±Ø§ Ø§Ø­ØªÙˆØ§ Ù…ÛŒ Ù†Ù…Ø§ÛŒØ¯Ø› Ø¯ Ø§ÙØºØ§Ù†Ø³ØªØ§Ù† Ø¨Ø§Ù†Ú© Ø¯Ø± Ù‚Ø³Ù…Øª Ú†Ø§Ù¾ØŒ Ø¶Ø±Ø¨ Ùˆ Ù†Ø´Ø± Ù¾ÙˆÙ„ Ø§ÙØºØ§Ù†ÛŒ Ù…Ø·Ø§Ø¨Ù‚ Ø¨Ù‡ ØªÙ‚Ø§Ø¶Ø§ÛŒ Ø¨Ø§Ø²Ø§Ø±ØŒ Ø­ÙØ¸ Ø§Ø±Ø²Ø´ Ù¾ÙˆÙ„ Ùˆ Ø§Ù…ÙˆØ± Ø¨Ø§Ù†Ú©Ø¯Ø§Ø±ÛŒ Ø¯ÙˆÙ„ØªÛŒ Ù…ØµØ±ÙˆÙ Ø¨ÙˆØ¯ Ú©Ù‡ Ø¯Ø± Ù¾Ù‡Ù„ÙˆÛŒ Ø§ÛŒÙ† ÙˆØ¸Ø§ÛŒÙØŒ Ø§Ù…ÙˆØ± ØªØ¬Ø§Ø±ØªÛŒ Ø±Ø§ Ù†ÛŒØ² Ø·Ø¨Ù‚ ÙØ¹Ø§Ù„ÛŒØª Ù‡Ø§ÛŒ Ø³Ø§ÛŒØ± Ø¨Ø§Ù†Ú©Ù‡Ø§ÛŒ ØªØ¬Ø§Ø±ÛŒ Ø§ÙØºØ§Ù†Ø³ØªØ§Ù† Ø§Ù†Ø¬Ø§Ù… Ù…ÛŒØ¯Ø§Ø¯ Ú©Ù‡ Ù…ÛŒ ØªÙˆØ§Ù† Ø§Ø² Ø§ÙØªØªØ§Ø­ Ø­Ø³Ø§Ø¨Ø§Øª Ù¾Ø³ Ø§Ù†Ø¯Ø§Ø²ØŒ Ø¬Ø§Ø±ÛŒØŒ Ù…ÛŒØ¹Ø§Ø¯ÛŒØŒ Ø§Ø¬Ø±Ø§ÛŒ Ù‚Ø±ÙˆØ¶ Ø¨Ù‡ Ù…Ù†Ø¸ÙˆØ± ØªÙ‚ÙˆÛŒÙ‡ Ø³Ø±Ù…Ø§ÛŒÙ‡ Ú¯Ø°Ø§Ø±ÛŒ Ù‡Ø§ Ùˆ Ø§Ø¬Ø±Ø§ÛŒ Ø³Ø§ÛŒØ± Ù‚Ø±ÙˆØ¶ Ø¯Ø± Ø¨Ø®Ø´ Ù‡Ø§ÛŒ ØªØ¬Ø§Ø±ÛŒ ÛŒØ§Ø¯ Ø¢ÙˆØ±ÛŒ Ú©Ø±Ø¯. Ù…Ø±Ø­Ù„Ù‡ Ø¯ÙˆÙ… Ø§Ø² Ø³Ø§Ù„ 1381 Ø¢ØºØ§Ø² Ù…ÛŒ Ø´ÙˆØ¯. Ø¨Ø¹Ø¯ Ø§Ø² ØªØµÙˆÛŒØ¨ Ù‚Ø§Ù†ÙˆÙ† Ø§Ø³Ø§Ø³ÛŒ Ø§ÙØºØ§Ù†Ø³ØªØ§Ù†ØŒ Ø¨Ø§Ù†Ú© Ù…Ø±Ú©Ø²ÛŒ Ø¨Ø± Ø§Ø³Ø§Ø³ Ù…Ø§Ø¯Ù‡ Ø¯ÙˆØ§Ø²Ø¯Ù‡Ù… Ø§ÛŒÙ† Ù‚Ø§Ù†ÙˆÙ†ØŒ Ù…Ù†Ø­ÛŒØ« ÛŒÚ© Ø¨Ø§Ù†Ú© Ù…Ø³ØªÙ‚Ù„ ØªØ³Ø¬ÛŒÙ„ Ú¯Ø±Ø¯ÛŒØ¯ Ùˆ Ø¨Ø§ ØµÙ„Ø§Ø­ÛŒØª Ù‡Ø§ÛŒÛŒ Ú©Ù‡ Ø¨Ù‡ Ø¢Ù† ØªÙÙˆÛŒØ¶ Ø´Ø¯ Ø¨Ù‡ Ø¯Ø³ØªØ§ÙˆØ±Ø¯ Ù‡Ø§ÛŒ Ù‚Ø§Ø¨Ù„ ØªÙˆØ¬Ù‡ÛŒ Ø¯Ø± Ø¹Ø±ØµÙ‡ Ù‡Ø§ÛŒ Ú¯ÙˆÙ†Ø§Ú¯ÙˆÙ† Ø¯Ø³Øª ÛŒØ§ÙØª. Ø¯ Ø§ÙØºØ§Ù†Ø³ØªØ§Ù† Ø¨Ø§Ù†Ú© Ø¨Ø± Ø§Ø³Ø§Ø³ Ù‚ÙˆØ§Ù†ÛŒÙ† Ø¬Ø¯ÛŒØ¯ Ø¨Ø§Ù†Ú©ÛŒ Ùˆ Ù…Ø§Ù„ÛŒ ØªÙ…Ø§Ù… Ø§Ù…ÙˆØ± ØªØ¬Ø§Ø±ØªÛŒ Ø±Ø§ Ø¨Ù‡ Ø¨Ø§Ù†Ú©Ù‡Ø§ÛŒ Ø¯ÙˆÙ„ØªÛŒ Ùˆ Ø®ØµÙˆØµÛŒ ÙˆØ§Ú¯Ø°Ø§Ø± Ù†Ù…ÙˆØ¯ Ùˆ Ù…Ø³ÙˆÙˆÙ„ÛŒØª Ø§Ø¹Ø·Ø§ÛŒ Ø¬ÙˆØ§Ø² ÙØ¹Ø§Ù„ÛŒØª Ùˆ Ù†Ø¸Ø§Ø±Øª Ø§Ø² Ù…Ø¤Ø³Ø³Ø§Øª Ø¨Ø§Ù†Ú©ÛŒ Ùˆ Ù…Ø§Ù„ÛŒ Ø±Ø§ Ø¨Ø¹Ù‡Ø¯Ù‡ Ú¯Ø±ÙØª. Ø¨Ø± Ø§Ø³Ø§Ø³ Ù‚Ø§Ù†ÙˆÙ† Ø¯ Ø§ÙØºØ§Ù†Ø³ØªØ§Ù† Ø¨Ø§Ù†Ú©ØŒ Ø«Ø¨Ø§Øª Ù‚ÛŒÙ… Ù‡Ø¯Ù Ø§ÙˆÙ„ÛŒÙ‡ Ùˆ Ø§Ø³Ø§Ø³ÛŒ Ø¯ Ø§ÙØºØ§Ù†Ø³ØªØ§Ù† Ø¨Ø§Ù†Ú© Ù…ÛŒ Ø¨Ø§Ø´Ø¯ Ùˆ Ø¨Ù‡ Ø§ÛŒÙ† Ù…Ù†Ø¸ÙˆØ± Ø·Ø±Ø­ØŒ ØªØ·Ø¨ÛŒÙ‚ Ùˆ Ø§ØªØ®Ø§Ø° Ø³ÛŒØ§Ø³Øª Ù‡Ø§ÛŒ Ù¾ÙˆÙ„ÛŒØŒ Ø³ÛŒØ§Ø³Øª Ø§Ø±Ø² Ùˆ ØªØ±ØªÛŒØ¨Ø§Øª Ø§Ø³Ø¹Ø§Ø±ØŒ Ú†Ø§Ù¾ Ø¨Ø§Ù†Ú©Ù†ÙˆØª Ùˆ Ø¶Ø±Ø¨ Ù…Ø³Ú©ÙˆÚ©Ø§Øª Ø§Ø² ÙˆØ¸Ø§ÛŒÙ Ø¨Ø§Ù†Ú© Ù…Ø±Ú©Ø²ÛŒ ØªØ¹ÛŒÛŒÙ† Ú¯Ø±Ø¯ÛŒØ¯ Ú©Ù‡ Ø¯Ø± Ú©Ù†Ø§Ø± Ø¢Ù† Ø·Ø¨Ù‚ Ù‚Ø§Ù†ÙˆÙ† Ø¨Ù‡ Ø­ÛŒØ« Ø¨Ø§Ù†Ú©Ø¯Ø§Ø± Ùˆ Ù†Ù…Ø§ÛŒÙ†Ø¯Ù‡ Ù…Ø§Ù„ÛŒ Ø¯ÙˆÙ„ØªØŒ Ù†Ù‡Ø§Ø¯ ØµØ¯ÙˆØ± Ùˆ Ø«Ø¨Øª Ø¬ÙˆØ§Ø² ÙØ¹Ø§Ù„ÛŒØª Ø¨Ø§Ù†Ú©Ù‡Ø§ØŒ ØµØ±Ø§ÙØ§Ù† Ùˆ Ø¹Ø±Ø¶Ù‡ Ú©Ù†Ù†Ø¯Ú¯Ø§Ù† Ø®Ø¯Ù…Ø§Øª Ù¾ÙˆÙ„ÛŒ Ùˆ Ø§Ø³Ù†Ø§Ø¯ Ø¨Ù‡Ø§Ø¯Ø§Ø± Ùˆ Ø³ÛŒØ³ØªÙ… Ù¾Ø±Ø¯Ø§Ø®Øª Ù…ØµÙˆÙ† Ùˆ Ø³Ø§Ù„Ù… Ù†ÛŒØ² ÙØ¹Ø§Ù„ÛŒØª Ù…ÛŒ Ù†Ù…Ø§ÛŒØ¯.\nJob Summary\nØ¹Ù†ÙˆØ§Ù† ÙˆØ¸ÛŒÙÙ‡\n: Ø¹Ø¶Ùˆ Ø§Ù†Ú©Ø´Ø§Ù Ù…Ø­ØµÙˆÙ„Ø§Øª\nØ¢Ù…Ø±ÛŒØª\n:\nØ¢Ù…Ø±ÛŒØª Ø¹Ù…ÙˆÙ…ÛŒ Ù†Ø¸Ø§Ø±Øª Ø¨Ø§Ù†Ú©ÛŒ Ùˆ Ø®Ø¯Ù…Ø§Øª Ù…Ø§Ù„ÛŒ\nÚ¯Ø±ÛŒØ¯\n: Ù‡Ø´ØªÙ… (\nÛ¸\n)\nØªØ¹Ø¯Ø§Ø¯ Ø¨Ø³Øª\n: ÛŒÚ© (\nÛ±\n)\nØªØ§Ø±ÛŒØ® Ø¢ØºØ§Ø²\n: Û±Û´Û°Û´/Û±Û°/Û²Û°\nØªØ§Ø±ÛŒØ® Ø®ØªÙ…:\nÛ±Û´Û°Û´/Û±Û±/Û°Û´\nÙ†ÙˆØ¹ Ø§Ø¹Ù„Ø§Ù†\n:\nØ¯Ø§Ø®Ù„ÛŒ Ùˆ Ø®Ø§Ø±Ø¬ÛŒ\nÙ†ÙˆØ¹ Ø§Ø³ØªØ®Ø¯Ø§Ù…\n:\nØ¯Ø§Ø¦Ù…ÛŒ\nDuties & Responsibilities\nÙˆØ¸Ø§ÛŒÙ Ùˆ Ù…Ø³Ø¦ÙˆÙ„ÛŒØª Ù‡Ø§\nØªØ·Ø¨ÛŒÙ‚ Ù¾Ù„Ø§Ù† Ú©Ø§Ø±ÛŒØŒ Ù…Ø§Ù‡ÙˆØ§Ø±ØŒ Ø±Ø¨Ø¹ÙˆØ§Ø± Ùˆ Ø³Ø§Ù„Ø§Ù†Ù‡ Ø·Ø¨Ù‚ Ù¾Ù„Ø§Ù† Ø¹Ù…ÙˆÙ…ÛŒ Ùˆ Ù‡Ù…Ú©Ø§Ø±ÛŒ Ø¯Ø± ØªØ¹Ø¯ÛŒÙ„ Ø§Ø³Ù†Ø§Ø¯ Ø§Ø¯Ø§Ø±ÛŒ Ùˆ ØªÙ‚Ù†ÛŒÙ†ÛŒ Ù…Ø±Ø¨ÙˆØ· Ø¨Ø§ Ù…Ø¯ÛŒØ± Ù…Ø³ØªÙ‚ÛŒÙ…\nÙ…Ø¯ÛŒØ±ÛŒØª Ù…Ù†Ø§Ø¨Ø¹ØŒ ÙØ¹Ø§Ù„ÛŒØª Ù‡Ø§ Ùˆ Ø¹Ù…Ù„Ú©Ø±Ø¯ Ù‡Ø§ÛŒ ØªØ­Øª Ú©Ù†ØªØ±ÙˆÙ„ Ø¯Ø± Ù…Ø·Ø§Ø¨Ù‚Øª Ø¨Ø§ Ù‚ÙˆØ§Ù†ÛŒÙ†ØŒ Ù…Ù‚Ø±Ø±Ø§ØªØŒ Ù¾Ø§Ù„ÛŒØ³ÛŒ Ù‡Ø§ Ùˆ Ø·Ø±Ø²Ø§Ù„Ø¹Ù…Ù„ Ù‡Ø§ Ø¬Ù‡Øª Ø¹Ø±Ø¶Û€ Ø®Ø¯Ù…Ø§Øª Ù…Ø·Ø§Ø¨Ù‚ Ø¨Ù‡ Ù¾Ù„Ø§Ù† Ú©Ø§Ø±ÛŒ\nØ­ÛŒÙ† Ø´Ù†Ø§Ø³Ø§Ø¦ÛŒ Ùˆ Ø¯Ø±ÛŒØ§ÙØª Ø§Ø´ØªØ¨Ø§Ù‡Ø§ØªØŒ Ø§Ù‚Ø¯Ø§Ù… Ø¨Ù‡ Ø§Ø³Ø±Ø¹ ÙˆÙ‚Øª Ø¯Ø± ØªØµØ­ÛŒØ­ Ø¢Ù† Ùˆ Ù‡Ù…Ú©Ø§Ø±ÛŒ Ø¨Ø§ Ø³Ø§ÛŒØ± Ø´Ø¹Ø¨Ø§Øª Ø°ÛŒØ±Ø¨Ø· Ø¯Ø± Ø±Ø§Ø¨Ø·Ù‡ Ø¨Ù‡ Ø­Ù„ Ù…Ø´Ú©Ù„Ø§Øª Ù…Ø±Ø¨ÙˆØ·\nØ­ØµÙˆÙ„ Ø§Ø·Ù…ÛŒÙ†Ø§Ù† Ø§Ø² ØªØ·Ø¨ÛŒÙ‚ ØªØµØ§ÙˆÛŒØ¨ Ù‡ÛŒØ¦Øª Ø¹Ø§Ù…Ù„ Ùˆ Ø´ÙˆØ±Ø§ÛŒ Ø¹Ø§Ù„ÛŒ Ø¯ Ø§ÙØºØ§Ù†Ø³ØªØ§Ù† Ø¨Ø§Ù†Ú© Ø¯Ø± Ù…Ø·Ø§Ø¨Ù‚Øª Ø¨Ù‡ Ø§Ø³Ù†Ø§Ø¯ ØªÙ‚Ù†ÛŒÙ†ÛŒ\nØ·Ø±Ø­ØŒ ØªØ±ØªÛŒØ¨ Ùˆ ØªØ·Ø¨ÛŒÙ‚ Ù¾Ø§Ù„ÛŒØ³ÛŒ Ù‡Ø§ØŒ Ù¾Ù„Ø§Ù† Ù‡Ø§ÛŒ Ú©Ø§Ø±ÛŒ Ø·Ø¨Ù‚ Ù¾Ù„Ø§Ù† Ø¹Ù…ÙˆÙ…ÛŒ Ùˆ Ù‡Ù…Ú©Ø§Ø±ÛŒ Ø¯Ø± ØªØ¹Ø¯ÛŒÙ„ Ø§Ø³Ù†Ø§Ø¯ ØªÙ‚Ù†ÛŒÙ†ÛŒØŒ Ù…Ù‚Ø±Ø±Ø§ØªØŒ Ø·Ø±Ø²Ø§Ù„Ø¹Ù…Ù„ Ù‡Ø§ Ùˆ Ù…Ø­ØµÙˆÙ„Ø§Øª Ù…Ø±Ø¨ÙˆØ·\nØ¬Ù…Ø¹ Ø¢ÙˆØ±ÛŒ Ù¾ÛŒØ´Ù†Ù‡Ø§Ø¯Ø§Øª Ùˆ Ø¯Ø± Ø®ÙˆØ§Ø³Øª Ù‡Ø§ÛŒ Ø¨Ø§Ù†Ú© Ù‡Ø§ÛŒ ØªØ¬Ø§Ø±ÛŒ Ùˆ Ù†Ù‡Ø§Ø¯ Ù‡Ø§ÛŒ Ù…Ø¬ÙˆØ²ØŒ ØªØ­Ù„ÛŒÙ„ØŒ Ø§Ø±Ø²ÛŒØ§Ø¨ÛŒ Ùˆ Ø¨Ø±Ø±Ø³ÛŒ Ø¢Ù† Ø¯Ø± Ù…Ø·Ø§Ø¨Ù‚Øª Ø¨Ù‡ Ø§Ø³Ù†Ø§Ø¯ ØªÙ‚Ù†ÛŒÙ†ÛŒ Ùˆ Ø¯Ø± ØµÙˆØ±Øª Ù„Ø²ÙˆÙ… Ù‡Ù…Ø¢Ù‡Ù†Ú¯ÛŒ Ø¢Ù† Ø¨Ø§ Ø¢Ù…Ø±ÛŒØª Ù…Ø­ØªØ±Ù… Ø§Ù…ÙˆØ± Ø­Ù‚ÙˆÙ‚ÛŒ Ø¬Ù‡Øª Ø§Ø®Ø° Ù†Ø¸Ø±ÛŒØ§Øª Ø­Ù‚ÙˆÙ‚ÛŒ\nÙ‡Ù…Ú©Ø§Ø±ÛŒ Ø¯Ø± Ù‚Ø³Ù…Øª ØªÙˆØ³Ø¹Û€ Ù¾Ø§Ù„ÛŒØ³ÛŒ Ù‡Ø§ØŒ Ù…Ù‚Ø±Ø±Ø§ØªØŒ Ù„ÙˆØ§ÛŒØ­ØŒ Ø·Ø±Ø² Ø§Ù„Ø¹Ù…Ù„ Ù‡Ø§ØŒ ÙÙˆØ±Ù…Ù‡ Ù‡Ø§ÛŒ Ù…Ø¹ÛŒØ§Ø±ÛŒ Ùˆ Ù¾Ù„Ø§Ù† Ù‡Ø§ÛŒ Ú©ÙˆØªØ§Ù‡ Ù…Ø¯Øª Ùˆ Ø§Ø³ØªØ±Ø§ØªÛŒÚ˜ÛŒÚ© Ø¨Ø§ Ø¯Ø± Ù†Ø¸Ø± Ø¯Ø§Ø´Øª ØªØ®Ø±ÛŒØ¬ Ø´Ø±Ø¹ÛŒ\nØ¬Ù…Ø¹ Ø¢ÙˆØ±ÛŒ Ø¯Ø±ÛŒØ§ÙØª Ù‡Ø§ØŒ ØªØ±ØªÛŒØ¨ØŒ ØªÙˆØ³Ø¹Ù‡ Ùˆ Ø§Ù†Ú©Ø´Ø§Ù Ù…Ø­ØµÙˆÙ„Ø§Øª Ù†ÙˆÛŒÙ† Ø¨Ø§Ù†Ú©ÛŒ Ùˆ Ù…Ù‚Ø±Ø±Ø§Øª Ù…Ø±Ø¨ÙˆØ·\nØªØ¯ÙˆÛŒØ± Ø¬Ù„Ø³Ù‡ Ø¨Ø§ Ø¨Ø§Ù†Ú© Ù‡Ø§ Ø¨Ù‡ Ù…Ù†Ø¸ÙˆØ± Ù‡Ù…Ø¢Ù‡Ù†Ú¯ Ø³Ø§Ø²ÛŒ Ùˆ Ø§Ø±Ø§ÛŒÛ€ ØªÙˆØ¶ÛŒØ­Ø§Øª Ø§Ø² Ø·Ø±Ø² Ø§Ù„Ø¹Ù…Ù„ Ù…Ø­ØµÙˆÙ„Ø§Øª Ø¨Ø§Ù†Ú©Ø¯Ø§Ø±ÛŒ Ø§Ø³Ù„Ø§Ù…ÛŒ\nØ§Ø±Ø§ÛŒÛ€ Ù…Ø¹Ù„ÙˆÙ…Ø§ØªØŒ ØªØ´Ø±ÛŒØ­ Ùˆ ØªÙˆØ¶ÛŒØ­ ØªØ®Ø±ÛŒØ¬ Ù…Ø­ØµÙˆÙ„Ø§Øª Ù†ÙˆÛŒÙ† Ùˆ Ø§Ø³Ù†Ø§Ø¯ ØªÙ‚Ù†ÛŒÙ†ÛŒ Ù…Ø±Ø¨ÙˆØ· Ùˆ ØªØ´Ø±ÛŒÚ© Ø¢Ù† Ø¨Ø§ Ù…Ø±Ø§Ø¬Ø¹ÛŒÙ† Ùˆ Ø¬ÙˆØ§Ù†Ø¨ Ø°ÛŒØ¯Ø®Ù„\nÙ‡Ù…Ú©Ø§Ø±ÛŒ Ùˆ Ù‡Ù…Ø¢Ù‡Ù†Ú¯ÛŒ Ø¨Ø§ Ù…Ø¯ÛŒØ±ÛŒØª Ù‡Ø§ÛŒ Ø°ÛŒØ±Ø¨Ø· Ø¯ Ø§ÙØºØ§Ù†Ø³ØªØ§Ù† Ø¨Ø§Ù†Ú© Ø¨Ù‡ Ù…Ù†Ø¸ÙˆØ± ØªØ¨Ø§Ø¯Ù„ Ù†Ø¸Ø± Ù…Ø³Ù„Ú©ÛŒ Ø¯Ø± Ù‚Ø³Ù…Øª ØªÙˆØ³Ø¹Û€ Ø·Ø±Ø²Ø§Ù„Ø¹Ù…Ù„ Ù‡Ø§ÛŒ Ú©Ø§Ø±ÛŒ Ø§Ø² Ø¨ÙØ¹Ø¯ Ø§Ø³Ù„Ø§Ù…ÛŒ\nÙ‡Ù…Ø¢Ù‡Ù†Ú¯ÛŒ Ùˆ ØªØ£Ù…ÛŒÙ† Ø§Ø±ØªØ¨Ø§Ø· Ø¨Ø§ Ø¨Ø®Ø´ Ù‡Ø§ÛŒ Ø°ÛŒØ±Ø¨Ø· Ø¨Ù‡ Ù…Ù†Ø¸ÙˆØ± ØªÙˆØ³Ø¹Û€ Ù…Ø­ØµÙˆÙ„Ø§Øª Ùˆ ØªØ®Ø±ÛŒØ¬ Ø´Ø±Ø¹ÛŒ Ø¯Ø± Ø±Ø§Ø¨Ø·Ù‡\nØ§Ø´ØªØ±Ø§Ú© Ø¯Ø± Ù…Ø¬Ø§Ù„Ø³ØŒ Ú©Ø§Ù†ÙØ±Ø§Ù†Ø³ Ù‡Ø§ØŒ Ø³Ù…ÛŒÙ†Ø§Ø±Ù‡Ø§ØŒ ÙˆØ±Ú©Ø´Ø§Ù¾ Ù‡Ø§ØŒ Ø¨Ø±Ù†Ø§Ù…Ù‡ Ù‡Ø§ÛŒ Ø¢Ù…ÙˆØ²Ø´ÛŒ Ùˆ Ø³Ø§ÛŒØ± Ø¨Ø±Ù†Ø§Ù…Ù‡ Ù‡Ø§ÛŒ Ø±Ø³Ù…ÛŒ Ø¨Ù‡ Ù†Ù…Ø§ÛŒÙ†Ø¯Ú¯ÛŒ Ø§Ø² Ø¯ Ø§ÙØºØ§Ù†Ø³ØªØ§Ù† Ø¨Ø§Ù†Ú© Ø¯Ø± Ø¯Ø§Ø®Ù„ Ùˆ Ø®Ø§Ø±Ø¬ Ø§Ø² Ú©Ø´ÙˆØ± Ø·Ø¨Ù‚ Ù‡Ø¯Ø§ÛŒØ§Øª\nØªØ­Ø±ÛŒØ± Ù…Ú©Ø§ØªÛŒØ¨ØŒ Ù¾ÛŒØ´Ù†Ù‡Ø§Ø¯Ø§ØªØŒ Ø§Ø³ØªØ¹Ù„Ø§Ù… Ù‡Ø§ Ùˆ Ø³Ø§ÛŒØ± Ù…Ø±Ø§Ø³Ù„Ø§Øª Ø§Ø¯Ø§Ø±ÛŒ Ùˆ Ø·ÛŒ Ù…Ø±Ø§Ø­Ù„ Ø¢Ù† Ø¯Ø± ÙˆÙ‚Øª Ù…Ø¹ÛŒÙ† Ø·Ø¨Ù‚ Ù‡Ø¯Ø§ÛŒØª Ù…Ø¯ÛŒØ± Ù…Ø³ØªÙ‚ÛŒÙ… ÙˆØ¢Ù…Ø± Ø°ÛŒØµÙ„Ø§Ø­\nØªÙ†Ø¸ÛŒÙ… Ùˆ Ø­ÙØ¸ Ù…Ú©Ø§ØªÛŒØ¨ØŒ Ù¾ÛŒØ´Ù†Ù‡Ø§Ø¯Ø§ØªØŒ Ø§Ø³ØªØ¹Ù„Ø§Ù… Ù‡Ø§ Ùˆ Ø³Ø§ÛŒØ± Ù…Ø±Ø§Ø³Ù„Ø§Øª Ø§Ø¯Ø§Ø±ÛŒ Ø¯Ø± Ø¯ÙˆØ³ÛŒÙ‡ Ù‡Ø§ Ùˆ Ú©Ø§Ø±ØªÙ† Ù‡Ø§ Ø·ÙˆØ± Ø¯Ù‚ÛŒÙ‚ Ùˆ Ù…Ù†Ø¸Ù… Ø¨Ù‡ Ø´Ú©Ù„ Ù‡Ø§Ø±Ø¯ Ùˆ Ø³Ø§ÙØª Ú©Ø§Ù¾ÛŒ\nØªØ±ØªÛŒØ¨ Ù¾Ù„Ø§Ù† Ù‡Ø§ÛŒ Ú©Ø§Ø±ÛŒ Ùˆ Ø§Ø±Ø§ÛŒÛ€Ú¯Ø²Ø§Ø±Ø´ Ú©Ø§Ø±ÛŒ Ø¨Ù‡ Ù…Ø¯ÛŒØ± Ù…Ø³ØªÙ‚ÛŒÙ… Ùˆ Ø¢Ù…Ø± Ø°ÛŒØµÙ„Ø§Ø­\nØ§Ù†Ø¬Ø§Ù… Ø³Ø§ÛŒØ± ÙˆØ¸Ø§ÛŒÙ Ùˆ Ù…Ø³Ø¦ÙˆÙ„ÛŒØª Ù‡Ø§ÛŒ Ú©Ù‡ Ø¨ØªØ£Ø³ÛŒ Ø§Ø² Ø·Ø±Ø²Ø§Ù„Ø¹Ù…Ù„ Ù‡Ø§ØŒ Ø¯Ø³ØªÙˆØ±Ø§Ù„Ø¹Ù…Ù„ Ùˆ Ù‡Ø¯Ø§ÛŒØ§Øª Ù…Ù‚Ø§Ù… Ù…Ø§ÙÙˆÙ‚ Ø·Ø¨Ù‚ Ù„Ø§ÛŒØ­Ù‡ Ùˆ Ù…Ù‚Ø±Ø±Ø§Øª Ø§Ø±Ø¬Ø§Ø¹ Ù…ÛŒÚ¯Ø±Ø¯\nJob Requirements\nØ¯Ø±Ø¬Ù‡ ØªØ­ØµÛŒÙ„ÛŒ\nÂ·\nÙ„ÛŒØ³Ø§Ù†Ø³ Ø¯Ø± Ø¨Ø®Ø´ Ù‡Ø§ÛŒ Ø§Ø¯Ø§Ø±Ù‡ Ùˆ ØªØ¬Ø§Ø±ØªØŒ Ø§Ù‚ØªØµØ§Ø¯ØŒ Ø¨Ø§Ù†Ú©Ø¯Ø§Ø±ÛŒ Ø§Ø³Ù„Ø§Ù…ÛŒØŒ Ø­Ù‚ÙˆÙ‚ØŒ Ø´Ø±Ø¹ÛŒØ§ØªØŒ Ø¨Ø§Ù†Ú©Ø¯Ø§Ø±ÛŒ Ùˆ Ù…Ø§Ù„ÛŒ Ùˆ Ø§Ø¯Ø§Ø±Ù‡ Ø¹Ø§Ù…Ù‡ Ùˆ Ø¨Ø¯Ø§Ø´ØªÙ† Ø³Ù†Ø¯ Ù…Ø§Ø³ØªØ±ÛŒ Ø¯Ø± Ø¨Ø®Ø´ Ù‡Ø§ÛŒ ÙÙˆÙ‚ Ø§Ù„Ø°Ú©Ø± Ùˆ Ø¯Ø± ÙÙ‚Ù‡ØŒ ÙÙ‚Ù‡ Ø§Ù„Ù…Ø¹Ø§Ù…Ù„Ø§ØªØŒ Ø§ØµÙˆÙ„ ÙÙ‚Ù‡ ØªØ®ØµØµ ØªØ±Ø¬ÛŒØ­ Ø¯Ø§Ø¯Ù‡ Ù…ÛŒØ´ÙˆØ¯\nØªØ¬Ø±Ø¨Ù‡\nÂ·Â Â Â Â Â Ø³Ù‡ (3) Ø³Ø§Ù„ ØªØ¬Ø±Ø¨Û€ Ú©Ø§Ø±ÛŒ Ù…Ø±ØªØ¨Ø· Ø¨Ù‡ ÙˆØ¸ÛŒÙÙ‡\nÙ…Ù‡Ø§Ø±Øª Ù‡Ø§ Ùˆ ØªÙˆØ§Ù†Ø§Ø¦ÛŒ Ù‡Ø§\nÂ·Â Â Â Â Â Â Ø¨Ù„Ø¯ÛŒØª Ø¨Ù‡ Ø²Ø¨Ø§Ù† Ù‡Ø§ÛŒ Ø±Ø³Ù…ÛŒ Ú©Ø´ÙˆØ± Ùˆ Ø§Ù†Ú¯Ù„ÛŒØ³ÛŒ\nÂ·Â Â Â Â Â Â Ø­ÙØ¸ Ù…Ø­Ø±Ù…ÛŒØª Ùˆ Ø¸ÛŒÙÙˆÛŒ\nÂ·Â Â Â Â Â Â ÙØµØ§Ø­Øª Ùˆ Ø¨Ù„Ø§ØºØª Ø¯Ø± Ú¯ÙØªØ§Ø±\nÂ·Â Â Â Â Â Â Ø¯Ø§Ø´ØªÙ† Ù…Ù‡Ø§Ø±Øª Ù‡Ø§ÛŒ Ù…Ø¯ÛŒØ±ÛŒØªÛŒ\nÂ·Â Â Â Â Â Â Ø¢Ø´Ù†Ø§Ø¦ÛŒ Ø¨Ù‡ Ù‚ÙˆØ§Ù†ÛŒÙ† ÙˆÙ…Ù‚Ø±Ø±Ø§Øª Ø¨Ø§Ù†Ú©ÛŒ\nÂ·Â Â Â Â Â Â ØªÙˆØ§Ù†Ø§Ø¦ÛŒ Ø¯Ø± ØªØ­Ø±ÛŒØ± Ù…Ú©Ø§ØªÛŒØ¨ØŒ Ù¾ÛŒØ´Ù†Ù‡Ø§Ø¯Ø§Øª Ùˆ Ú¯Ø²Ø§Ø±Ø´Ø§Øª Ú©Ø§Ø±ÛŒ\nÂ·Â Â Â Â Â Â ÙÙ‡Ù… Ùˆ Ø¯Ø±Ú© Ù…Ø³Ø¦ÙˆÙ„ÛŒØª Ú©Ø§Ø±ÛŒ Ùˆ ØªØ´Ø®ÛŒØµ Ù…Ø´Ú©Ù„Ø§Øª Ø¯Ø± Ø³Ø§Ø­Û€ Ú©Ø§Ø±ÛŒ\nÂ·Â Â Â Â Â Â Ø¢Ø´Ù†Ø§Ø¦ÛŒ Ø¨Ø§ Ø¨Ø±Ù†Ø§Ù…Ù‡ Ù‡Ø§ÛŒ Ú©Ù…Ù¾ÛŒÙˆØªØ±ÛŒ Ùˆ Ø³ÛŒØ³ØªÙ… Ù‡Ø§ÛŒ Ø¨Ø§Ù†Ú©ÛŒ Ø¨Ø®ØµÙˆØµ Ø¨Ø§Ù†Ú©Ø¯Ø§Ø±ÛŒ Ùˆ Ø®Ø¯Ù…Ø§Øª Ù…Ø§Ù„ÛŒ Ø§Ø³Ù„Ø§Ù…ÛŒ\nØµÙØ§Øª Ùˆ Ø§Ø±Ø²Ø´ Ù‡Ø§ÛŒ Ø´Ø®ØµÛŒ\nÂ·\nØµØ§Ø¯Ù‚ØŒ Ø¯Ø§Ø±Ø§ÛŒ Ø¨Ø±Ø®ÙˆØ±Ø¯ Ù†ÛŒÚ©ØŒ Ø­Ø§Ù…ÛŒ Ø§Ø­ØªØ±Ø§Ù… Ù…ØªÙ‚Ø§Ø¨Ù„ØŒ Ù…Ø¨ØªÚ©Ø±ØŒ Ø¨Ø§ Ø¯Ø³Ù¾Ù„ÛŒÙ†ØŒ Ù¾Ø§Ø¨Ù†Ø¯ Ø¨Ù‡ ÙˆØ¸ÛŒÙÙ‡ Ùˆ ÙˆÙ‚ØªØŒ Ø¹Ù„Ø§Ù‚Ù…Ù†Ø¯ Ø¨Ù‡ Ú©Ø§Ø± Ú¯Ø±ÙˆÙ¾ÛŒØŒ Ù‡Ù…Ú©Ø§Ø±ØŒ Ù…Ø³Ø¦ÙˆÙ„ÛŒØª Ù¾Ø°ÛŒØ±ØŒ ØªØµÙ…ÛŒÙ…Ú¯ÛŒØ± Ùˆ Ù…Ø³Ù„Ú©ÛŒ Ø¯Ø± Ø¨Ø®Ø´ Ú©Ø§Ø±ÛŒ\nSubmission Guideline\nÙ†Ú©Ø§Øª:\nÂ·Â Â Â Â Ø¹Ù„Ø§Ù‚Ù‡ Ù…Ù†Ø¯Ø§Ù† Ù…ÛŒØªÙˆØ§Ù†Ù†Ø¯ Ù†Ø®Ø³Øª Ø¯Ø± ÙˆÛŒØ¨ Ø³Ø§ÛŒØª\njobs.dab.gov.af\nØ¨Ø±Ø§ÛŒ Ø®ÙˆØ¯ ÛŒÙˆØ²Ø± Ø§ÛŒØ¬Ø§Ø¯ Ù†Ù…ÙˆØ¯Ù‡ Ùˆ Ø¨Ø¹Ø¯Ø§ Ø¨Ø³Øª Ù…ÙˆØ±Ø¯ Ù†Ø¸Ø± Ø±Ø§ Ø§Ù†ØªØ®Ø§Ø¨ Ù†Ù…ÙˆØ¯Ù‡ Ùˆ Ø§Ø³Ù†Ø§Ø¯ Ø®ÙˆØ§Ø³ØªÙ‡ Ø´Ø¯Ù‡ Ø±Ø§ Ø¨Ù‡ ÙØ§Ø±Ù…Øª PDF Ø¢Ù¾Ù„ÙˆØ¯ Ù†Ù…Ø§ÛŒÛŒØ¯.\nÂ·Â Â Â Â Ø¬Ù‡Øª Ø§Ø®Ø° Ø§Ù…ØªØ­Ø§Ù† ÙÙ‚Ø· Ø¨Ø§ Ù…ØªÙ‚Ø§Ø¶ÛŒØ§Ù† Ù…Ù†ØªØ®Ø¨ ØªÙ…Ø§Ø³ Ú¯Ø±ÙØªÙ‡ Ù…ÛŒØ´ÙˆØ¯.\nÂ·Â Â Â Â ØªØ§Ø±ÛŒØ® Ø§Ù…ØªØ­Ø§Ù† Ø¨Ø¹Ø¯Ø§Ù‹ Ø¨Ù‡ Ø§Ø·Ù„Ø§Ø¹ Ø±Ø³Ø§Ù†ÛŒØ¯Ù‡ Ù…ÛŒØ´ÙˆØ¯.\nFunctional Area\nBanking\nEconomic Growth\nLaw\nBusiness Administration\nLLB\nComputer Operator\nPublic Administration\nEconomic-Department of Business Administration.\nCountries\nAfghanistan\nProvinces\nKabul\nApply Now\nPost Date\nJan 10, 2026\nClosing Date\nJan 24, 2026\nReference\nDAB1446051\nNumber of Vacancies\n1\nSalary Range\nAs per company salary scale\nYears of Experience\n3 years\nProbation Period\n3 month\nContract Type\nPermanent\nContract Duration\nNot specified\nContract Extensible\nYes\nMinimum Education\nBachelor's Degree\nGender\nMale\nRelated Jobs\nNETLINKS Plaza | Shahr-e-Naw,\nLane 3, Kabul, Afghanistan\nQuick Links\nAbout Us\nAdvertise with Us\nPrivacy Policy\nFor Companies\nPost a Job\nPost a Job\nPost a Job\nPost a Job\nPost RFP\nPost RFP\nPost RFP\nPost RFP\nPost Training\nPost Training\nPost Training\nPost Training\nFor Jobseekers\nBrowse Jobs\nBrowse Companies\nBuild Resume\nContact\ninfo@jobs.af\nContact Us\nÂ© 2012 - 2026 Jobs.af | All Rights Reserved\nPowered by:\nNETLINKS Ltd",
      "details": {
        "Post Date": "Jan 10, 2026",
        "Closing Date": "Jan 24, 2026",
        "Reference": "DAB1446051",
        "Number Of Vacancies": "1",
        "Salary Range": "As per company salary scale",
        "Years Of Experience": "3 years",
        "Probation Period": "3 month",
        "Contract Type": "Permanent",
        "Contract Duration": "Not specified",
        "Contract Extensible": "Yes",
        "Minimum Education": "Bachelor's Degree",
        "Functional Area": "Banking",
        "Countries": "Afghanistan",
        "Provinces": "Kabul"
      },
      "scraped_at": "2026-01-21T05:00:22Z",
      "apply_emails": [],
      "apply_method": "unknown"
    }
  ]
}